Workbook

Sheet 绩效整理表
A1: 2026-05 销售绩效溯源工作簿（精简整理表 + Hub输入）
A2: 第3行=整理表字段（合并）；第4行=源表叶子字段/匹配方式/公式；第5行起填数据。 同工作簿另含 18 张源表（Hub/岗位 + 发薪边表；版式来自 uploads/主账套，公式保留、数值留空）。
A3: 指标汇总部门 | D3: 渠道 | E3: 库存天数 | I3: 订单号 | K3: 车种 | M3: 销售渠道 | O3: 台数 | P3: 订单合计(含税) | R3: VIN码 | T3: 销售顾问 | V3: 部门 | X3: 精品最低价金额 | Z3: 不提成精品 | AB3: 整车节约 | AD3: 经理权限 | AE3: 整车实际节约 | AH3: 盈利性产品按揭权限扣除 | AJ3: 实际整车节约权限 | AK3: 保险返利收入 | AO3: 按揭收入 | AQ3: 爱车宝收入 | AS3: 上户收入 | AU3: 延保收入 | AW3: 单台绩效 | AZ3: 整车超额 | BA3: 加装绩效 | BC3: 保险提成 | BG3: 按揭提成 | BI3: 盈利产品 | BM3: 爱车宝 | BR3: 上户绩效 | BX3: 座位险绩效 | CA3: 玻璃险绩效 | CD3: 特殊车型追加绩效（追加+质损车） | CH3: 二手车置换 | CQ3: 置换服务 | CT3: 延保提成 | CU3: 超期追加 | CV3: 出厂指导价/扣除降价补差 | CX3: 提车现返 | CZ3: 合同履约 | DB3: 项目金额附加费 | DD3: 广告返利 | DF3: 提车奖励当月返 | DH3: 当月返利 | DK3: 促销奖 | DL3: 代交车佣金 | DN3: 裸车毛利 | DO3: 装饰成本 | DQ3: 装饰毛利 | DT3: 主营业务毛利 | DW3: 上户代收代付部分 | DX3: 安心保 | DY3: 爱车保 | DZ3: 上户量
A4: 系统销售毛利-部门（BL列） | B4: 比对表-系统部门（A列）→指标汇总部门（B列） | C4: 通过Vin码匹配 | D4: 表内派生：指标汇总部门+销售渠道→渠道规则 | E4: 系统销售毛利-结算日期（BA列） | F4: 整车成本-结算日期（B列） | G4: 通过Vin码匹配 | H4: 表内派生：INT(订单结算日−成本结算日) | I4: 系统销售毛利-订单号（B列） | J4: 通过Vin码匹配 | K4: 系统销售毛利-车种（D列） | L4: 通过Vin码匹配 | M4: 系统销售毛利-销售渠道（E列） | N4: 通过Vin码匹配 | O4: 表内派生：默认1; supplement_rows可空 | P4: 系统销售毛利-订单合计(含税)（AO列） | Q4: 通过Vin码匹配 | R4: 系统销售毛利-VIN码（BD列） | S4: 通过Vin码匹配 | T4: 系统销售毛利-销售顾问（BJ列） | U4: 通过Vin码匹配 | V4: 系统销售毛利-部门（BL列） | W4: 通过Vin码匹配 | X4: 系统销售毛利-精品最低价金额（BQ列） | Y4: 通过Vin码匹配 | Z4: 装饰台账-最低价含税金额（AR列） | AA4: 按订单号汇总 | AB4: 系统超额-合计超卖金额（P列） | AC4: 通过Vin码匹配 | AD4: 配置：manager_permission_by_vin | AE4: 整车节约 | AF4: 经理权限 | AG4: 整车节约+经理权限 | AH4: 按揭原表-整车超权限（AN列） | AI4: 通过Vin码匹配 | AJ4: 表内派生：盈利性产品按揭权限扣除≠0→0 else 整车实际节约−盈利性产品按揭权限扣除 | AK4: 保险明细-应结算服务费-合计（AN列） | AL4: 保险明细-返利金额（BP列） | AM4: 通过Vin码匹配 | AN4: BP=SUMIF(VIN,AN) | AO4: 按揭明细-服务费合计（Z列） | AP4: 通过Vin码匹配 | AQ4: 爱车保-产品名称（K列） | AR4: 通过Vin码匹配 | AS4: 上户提成-手续费（C列） | AT4: 通过Vin码匹配 | AU4: 延保提成-延保收入（BE列） | AV4: 通过Vin码匹配 | AW4: 提成标准-单台绩效（F列） | AX4: 台数 | AY4: 提成标准F×台数 | AZ4: 表内派生：实际整车节约权限×比例分支 | BA4: 表内派生：台数=0→订单合计×12% | BB4: 表内派生：else (精品最低价金额−不提成精品)×12% | BC4: 保险明细-购买险种-商业险保费（AE列） | BD4: 保险明细-直营店保险额外提成-保险额外提成（BT列） | BE4: 通过Vin码匹配 | BF4: AE*0.03+BT | BG4: 按揭明细-基础绩效（BO列） | BH4: 通过Vin码匹配 | BI4: 按揭原表-盈利性奖励（AF列） | BJ4: 按揭明细-吉致额外追加奖励（BR列） | BK4: 通过Vin码匹配 | BL4: AF+BR | BM4: 爱车保-VIN（F列） | BN4: 爱车保-产品名称（K列） | BO4: 爱车保-实际金额（Z列） | BP4: 通过Vin码匹配 | BQ4: 分段规则(熊猫/畅行保C/置换无忧/悦行保A/金额档) | BR4: 上户提成-手续费（C列） | BS4: 上户提成-福袋（D列） | BT4: 上户提成-VIN码（B列） | BU4: 上户提成-车型（M列） | BV4: 通过Vin码匹配 | BW4: IF(G=0,0,IF(G>=330,G*0.14+53.8,(G-330)*0.14)) | BX4: 保险明细-15/单-座位险提成（BU列） | BY4: 通过Vin码匹配 | BZ4: IF(BF>0,15,0) | CA4: 保险明细-玻璃险-BG（BG列） | CB4: 通过Vin码匹配 | CC4: BG*0.08 | CD4: 重功超期+活动-奖励明细（N列） | CE4: 提成标准-政策追加2月（H列） | CF4: 通过Vin码匹配 | CG4: N+提成标准H×台数 | CH4: 二手置换-公司留存补贴（Y列） | CI4: 二手置换-结余提成（AC列） | CJ4: Y*0.14 | CK4: 二手置换-毛利（O列） | CL4: 二手置换-置换提成（AD列） | CM4: IF(O>=1000,O*0.14,IF(O>=500,100,0)) | CN4: 大客户-销售提成（R列） | CO4: 通过Vin码匹配 | CP4: AC+AD+大客户R | CQ4: 置换服务-服务费金额（AH列） | CR4: 通过Vin码匹配 | CS4: AH*0.14 | CT4: 表内派生：延保收入分段(-200/0/200) | CU4: 表内派生：超期政策×库存天数 | CV4: 整车成本-出厂指导价（R列） | CW4: 通过Vin码匹配 | CX4: 整车成本-提车现返（S列） | CY4: 通过Vin码匹配 | CZ4: 整车成本-合同履约奖（T列） | DA4: 通过Vin码匹配 | DB4: 整车成本-项目金额附加费（U列） | DC4: 通过Vin码匹配 | DD4: 整车成本-广告返利（V列） | DE4: 通过Vin码匹配 | DF4: 整车成本-提车奖励当月返（W列） | DG4: 通过Vin码匹配 | DH4: 终端明细表-金额（P列） | DI4: 通过Vin码匹配 | DJ4: 表内派生：台数≠0时取负SUMIFS | DK4: 需手工填入 | DL4: 系统二手车降价-佣金（去税）（BE列） | DM4: 通过Vin码匹配 | DN4: 表内派生：订单合计(含税)−SUM(出厂指导价:代交车佣金) | DO4: 装饰台账-含税成本价（AK列） | DP4: 按订单号汇总 | DQ4: 精品最低价金额 | DR4: 装饰成本 | DS4: 精品最低价金额−装饰成本 | DT4: 裸车毛利 | DU4: 装饰毛利 | DV4: 裸车毛利+装饰毛利 | DW4: 需手工填入 | DX4: 需手工填入 | DY4: 需手工填入 | DZ4: 需手工填入

Sheet 销售任务及完成率
A1: 西物汽车2016年8月销售任务计划执行计划统计表
A2: 编制部门：2026年05月整理数据 | M2: 拟定时间：
A3: 店名 | B3: 小组 | C3: 姓名 | D3: 西物、超市（合） | G3: 西物、超市（新品）（L网） | J3: 西物、超市（老品）（G网） | M3: 熊猫 | P3: 西物、超市（合） | S3: 西物、超市（合） | V3: 西物、超市（合） | Y3: 西物、超市（总完成率）
D4: 集客(台） | G4: 销量（台） | J4: 销量（台） | P4: *月博越L\博越cool考核 | S4: 武侯店-ICON | V4: 超期/重攻质损 | Y4: 总考核（台）
D5: 考核 | E5: 实际 | F5: 完成率 | G5: 考核 | H5: 实际 | I5: 完成率 | J5: 考核 | K5: 实际 | L5: 完成率 | M5: 考核 | N5: 实际 | O5: 完成率 | P5: 考核 | Q5: 实际 | R5: 完成率 | S5: 考核 | T5: 实际 | U5: 完成率 | V5: 考核 | W5: 实际 | X5: 提成金额 | Y5: 考核 | Z5: 实际 | AA5: 完成率
A6: 总计 | D6: =D7+D40+D55+D78 -> 0 | E6: =E7+E40+E55+E78 -> 0 | F6: =F7+F40+F55+F78 -> 5 | G6: =G7+G40+G55+G78 -> 0 | H6: =H7+H40+H55+H78 -> 0 | I6: =I7+I40+I55+I78 -> 15 | J6: =J7+J40+J55+J78 -> 0 | K6: =K7+K40+K55+K78 -> 0 | ... AA6: =AA7+AA40+AA55+AA78 -> 5 | AB6: 公告车销售量
A7: 武侯店 | B7: 合计 | D7: =D8+D27 -> 0 | E7: =E8+E27 -> 0 | F7: =IF(D7=0,1,E7/D7) -> 1 | G7: =G8+G16+G28 -> 0 | H7: =H8+H16+H28 -> 0 | I7: =I8+I16+I28 -> 12 | J7: =J8+J16+J28 -> 0 | K7: =K8+K16+K28 -> 0 | L7: =L8+L16+L28 -> 13 | M7: =M8+M16+M28 -> 0 | N7: =N8+N16+N28 -> 0 | ... AA7: =AA8+AA16+AA28 -> 2
C8: A组 | D8: =SUM(D9:D15) -> 0 | E8: =SUM(E9:E15) -> 0 | F8: =IF(D8=0,1,E8/D8) -> 1 | G8: =SUM(G9:G15) -> 0 | H8: =SUM(H9:H15) -> 0 | I8: =IF(G8=0,1,H8/G8) -> 1 | J8: =SUM(J9:J15) -> 0 | K8: =SUM(K9:K15) -> 0 | L8: =IF(J8=0,1,K8/J8) -> 1 | M8: =SUM(M9:M15) -> 0 | N8: =SUM(N9:N15) -> 0 | O8: =IF(M8=0,1,N8/M8) -> 1 | P8: =SUM(P9:P15) -> 0 | Q8: =SUM(Q9:Q15) -> 0 | R8: =IF(P8=0,1,Q8/P8) -> 1 | S8: =SUM(S9:S15) -> 0 | T8: =SUM(T9:T15) -> 0 | U8: =IF(S8=0,1,T8/S8) -> 1 | V8: =SUM(V9:V15) -> 0 | W8: =SUM(W9:W15) -> 0 | X8: =IF(V8=0,1,W8/V8) -> 1 | Y8: =SUM(Y9:Y15) -> 0 | Z8: =SUM(Z9:Z15) -> 0 | AA8: =IF(Y8=0,1,Z8/Y8) -> 1
F9: =IF(D9=0,1,E9/D9) -> 1 | I9: =IF(J9=0,1,H9/J9) -> 1 | L9: =IF(J9=0,1,K9/J9) -> 1 | O9: =IF(M9=0,1,N9/M9) -> 1 | R9: =IF(P9=0,1,Q9/P9) -> 1 | Y9: =J9+G9+M9 -> 0 | AA9: =IF(IF(Y9=0,1,Z9/Y9)>1,1,IF(Y9=0,1,Z9/Y9)) -> 1
F10: =IF(D10=0,1,E10/D10) -> 1 | I10: =IF(J10=0,1,H10/J10) -> 1 | L10: =IF(J10=0,1,K10/J10) -> 1 | O10: =IF(M10=0,1,N10/M10) -> 1 | R10: =IF(P10=0,1,Q10/P10) -> 1 | Y10: =J10+G10+M10 -> 0 | AA10: =IF(IF(Y10=0,1,Z10/Y10)>1,1,IF(Y10=0,1,Z10/Y10)) -> 1
F11: =IF(D11=0,1,E11/D11) -> 1 | I11: =IF(J11=0,1,H11/J11) -> 1 | L11: =IF(J11=0,1,K11/J11) -> 1 | O11: =IF(M11=0,1,N11/M11) -> 1 | R11: =IF(P11=0,1,Q11/P11) -> 1 | Y11: =J11+G11+M11 -> 0 | AA11: =IF(IF(Y11=0,1,Z11/Y11)>1,1,IF(Y11=0,1,Z11/Y11)) -> 1
F12: =IF(D12=0,1,E12/D12) -> 1 | I12: =IF(J12=0,1,H12/J12) -> 1 | L12: =IF(J12=0,1,K12/J12) -> 1 | O12: =IF(M12=0,1,N12/M12) -> 1 | R12: =IF(P12=0,1,Q12/P12) -> 1 | Y12: =J12+G12+M12 -> 0 | AA12: =IF(IF(Y12=0,1,Z12/Y12)>1,1,IF(Y12=0,1,Z12/Y12)) -> 1
F13: =IF(D13=0,1,E13/D13) -> 1 | I13: =IF(J13=0,1,H13/J13) -> 1 | L13: =IF(J13=0,1,K13/J13) -> 1 | O13: =IF(M13=0,1,N13/M13) -> 1 | R13: =IF(P13=0,1,Q13/P13) -> 1 | Y13: =J13+G13+M13 -> 0 | AA13: =IF(IF(Y13=0,1,Z13/Y13)>1,1,IF(Y13=0,1,Z13/Y13)) -> 1
F14: =IF(D14=0,1,E14/D14) -> 1 | I14: =IF(J14=0,1,H14/J14) -> 1 | L14: =IF(J14=0,1,K14/J14) -> 1 | O14: =IF(M14=0,1,N14/M14) -> 1 | R14: =IF(P14=0,1,Q14/P14) -> 1 | Y14: =J14+G14+M14 -> 0 | AA14: =IF(IF(Y14=0,1,Z14/Y14)>1,1,IF(Y14=0,1,Z14/Y14)) -> 1
F15: =IF(D15=0,1,E15/D15) -> 1 | I15: =IF(G15=0,1,H15/G15) -> 1 | L15: =IF(J15=0,1,K15/J15) -> 1 | O15: =IF(M15=0,1,N15/M15) -> 1 | R15: =IF(P15=0,1,Q15/P15) -> 1 | Y15: =J15+G15+M15 -> 0 | AA15: =IF(Y15=0,1,Z15/Y15) -> 1
C16: B组 | D16: =SUM(D17:D26) -> 0 | E16: =SUM(E17:E26) -> 0 | F16: =IF(D16=0,1,E16/D16) -> 1 | G16: =SUM(G17:G26) -> 0 | H16: =SUM(H17:H26) -> 0 | J16: =SUM(J17:J26) -> 0 | K16: =SUM(K17:K26) -> 0 | L16: =IF(J16=0,1,K16/J16) -> 1 | M16: =J16*1500 -> 0 | N16: =SUM(N17:N26) -> 0 | O16: =IF(M16=0,1,N16/M16) -> 1 | P16: =SUM(P17:P26) -> 0 | Q16: =SUM(Q17:Q26) -> 0 | R16: =IF(P16=0,1,Q16/P16) -> 1 | S16: =SUM(S17:S26) -> 0 | T16: =SUM(T17:T26) -> 0 | U16: =IF(S16=0,1,T16/S16) -> 1 | V16: =SUM(V17:V26) -> 0 | W16: =SUM(W17:W26) -> 0 | X16: =IF(V16=0,1,W16/V16) -> 1 | Y16: =SUM(Y17:Y26) -> 0 | Z16: =SUM(Z17:Z26) -> 0 | AA16: =IF(Y16=0,1,Z16/Y16) -> 1
B17: 武侯展厅 | C17: 熊杰文 | F17: =IF(D17=0,1,E17/D17) -> 1 | I17: =IF(G17=0,1,H17/G17) -> 1 | L17: =IF(J17=0,1,K17/J17) -> 1 | O17: =IF(M17=0,1,N17/M17) -> 1 | R17: =IF(Q17<P17,-(P17-Q17)*200,0) -> 0 | U17: =IF(T17<S17,-(S17-T17)*200,0) -> 0 | X17: =IF(W17<V17,-(V17-W17)*300,0) -> 0 | Y17: =J17+G17+M17 -> 0 | AA17: =IF(IF(Y17=0,1,Z17/Y17)>1,1,IF(Y17=0,1,Z17/Y17)) -> 1
C18: 易花贞子 | F18: =IF(D18=0,1,E18/D18) -> 1 | I18: =IF(G18=0,1,H18/G18) -> 1 | L18: =IF(J18=0,1,K18/J18) -> 1 | O18: =IF(M18=0,1,N18/M18) -> 1 | R18: =IF(Q18<P18,-(P18-Q18)*200,0) -> 0 | U18: =IF(T18<S18,-(S18-T18)*200,0) -> 0 | X18: =IF(W18<V18,-(V18-W18)*300,0) -> 0 | Y18: =J18+G18+M18 -> 0 | AA18: =IF(IF(Y18=0,1,Z18/Y18)>1,1,IF(Y18=0,1,Z18/Y18)) -> 1
C19: 马攀 | F19: =IF(D19=0,1,E19/D19) -> 1 | I19: =IF(G19=0,1,H19/G19) -> 1 | L19: =IF(J19=0,1,K19/J19) -> 1 | O19: =IF(M19=0,1,N19/M19) -> 1 | R19: =IF(Q19<P19,-(P19-Q19)*200,0) -> 0 | U19: =IF(T19<S19,-(S19-T19)*200,0) -> 0 | X19: =IF(W19<V19,-(V19-W19)*300,0) -> 0 | Y19: =J19+G19+M19 -> 0 | AA19: =IF(IF(Y19=0,1,Z19/Y19)>1,1,IF(Y19=0,1,Z19/Y19)) -> 1
C20: 毛春秀 | F20: =IF(D20=0,1,E20/D20) -> 1 | I20: =IF(G20=0,1,H20/G20) -> 1 | L20: =IF(J20=0,1,K20/J20) -> 1 | O20: =IF(M20=0,1,N20/M20) -> 1 | R20: =IF(Q20<P20,-(P20-Q20)*200,0) -> 0 | U20: =IF(T20<S20,-(S20-T20)*200,0) -> 0 | X20: =IF(W20<V20,-(V20-W20)*300,0) -> 0 | Y20: =J20+G20+M20 -> 0 | AA20: =IF(IF(Y20=0,1,Z20/Y20)>1,1,IF(Y20=0,1,Z20/Y20)) -> 1
C21: 廖晓军 | F21: =IF(D21=0,1,E21/D21) -> 1 | I21: =IF(G21=0,1,H21/G21) -> 1 | L21: =IF(J21=0,1,K21/J21) -> 1 | O21: =IF(M21=0,1,N21/M21) -> 1 | R21: =IF(Q21<P21,-(P21-Q21)*200,0) -> 0 | U21: =IF(T21<S21,-(S21-T21)*200,0) -> 0 | X21: =IF(W21<V21,-(V21-W21)*300,0) -> 0 | Y21: =J21+G21+M21 -> 0 | AA21: =IF(IF(Y21=0,1,Z21/Y21)>1,1,IF(Y21=0,1,Z21/Y21)) -> 1
C22: 康鳞波 | F22: =IF(D22=0,1,E22/D22) -> 1 | O22: =IF(M22=0,1,N22/M22) -> 1 | R22: =IF(Q22<P22,-(P22-Q22)*200,0) -> 0 | U22: =IF(T22<S22,-(S22-T22)*200,0) -> 0 | X22: =IF(W22<V22,-(V22-W22)*300,0) -> 0 | Y22: =J22+G22+M22 -> 0 | AA22: =IF(IF(Y22=0,1,Z22/Y22)>1,1,IF(Y22=0,1,Z22/Y22)) -> 1
C23: 黄利君 | F23: =IF(D23=0,1,E23/D23) -> 1 | I23: =IF(G23=0,1,H23/G23) -> 1 | L23: =IF(J23=0,1,K23/J23) -> 1 | O23: =IF(M23=0,1,N23/M23) -> 1 | R23: =IF(Q23<P23,-(P23-Q23)*200,0) -> 0 | U23: =IF(T23<S23,-(S23-T23)*200,0) -> 0 | X23: =IF(W23<V23,-(V23-W23)*300,0) -> 0 | Y23: =J23+G23+M23 -> 0 | AA23: =IF(IF(Y23=0,1,Z23/Y23)>1,1,IF(Y23=0,1,Z23/Y23)) -> 1
C24: 代力 | F24: =IF(D24=0,1,E24/D24) -> 1 | R24: =IF(Q24<P24,-(P24-Q24)*200,0) -> 0 | U24: =IF(T24<S24,-(S24-T24)*200,0) -> 0 | X24: =IF(W24<V24,-(V24-W24)*300,0) -> 0 | Y24: =J24+G24+M24 -> 0 | AA24: =IF(IF(Y24=0,1,Z24/Y24)>1,1,IF(Y24=0,1,Z24/Y24)) -> 1
R25: =IF(Q25<P25,-(P25-Q25)*200,0) -> 0 | X25: =IF(W25<V25,-(V25-W25)*500,0) -> 0 | Y25: =J25+G25+M25 -> 0 | AA25: =IF(IF(Y25=0,1,Z25/Y25)>1,1,IF(Y25=0,1,Z25/Y25)) -> 1
R26: =IF(Q26<P26,-(P26-Q26)*200,0) -> 0 | X26: =IF(W26<V26,-(V26-W26)*500,0) -> 0 | Y26: =J26+G26+M26 -> 0 | AA26: =IF(IF(Y26=0,1,Z26/Y26)>1,1,IF(Y26=0,1,Z26/Y26)) -> 1
B27: 武侯DCC | D27: =SUM(D29:D39) -> 0 | E27: =SUM(E29:E39) -> 0 | F27: =IF(D27=0,1,E27/D27) -> 1 | G27: =G28 -> 0 | H27: =H28 -> 0 | I27: =I28 -> 11 | J27: =J28 -> 0 | K27: =K28 -> 0 | L27: =L28 -> 11 | Y27: =Y28 -> 0 | Z27: =SUM(Z29:Z39) -> 0 | AA27: =IF(Y27=0,1,Z27/Y27) -> 1
C28: DCCA组 | G28: =SUM(G29:G39) -> 0 | H28: =SUM(H29:H39) -> 0 | I28: =SUM(I29:I39) -> 11 | J28: =SUM(J29:J39) -> 0 | K28: =SUM(K29:K39) -> 0 | L28: =SUM(L29:L39) -> 11 | M28: =SUM(M29:M39) -> 0 | N28: =SUM(N29:N39) -> 0 | ... W28: =SUM(W29:W39) -> 0 | Y28: =SUM(Y29:Y39) -> 0 | Z28: =SUM(Z29:Z39) -> 0
C29: 蒲喜 | F29: =IF(D29=0,1,E29/D29) -> 1 | I29: =IF(G29=0,1,H29/G29) -> 1 | L29: =IF(J29=0,1,K29/J29) -> 1 | O29: =IF(M29=0,1,N29/M29) -> 1 | R29: =IF(Q29<P29,-(P29-Q29)*200,0) -> 0 | U29: =IF(T29<S29,-(S29-T29)*200,0) -> 0 | X29: =IF(W29<V29,-(V29-W29)*300,0) -> 0 | Y29: =J29+G29+M29 -> 0 | AA29: =IF(IF(Y29=0,1,Z29/Y29)>1,1,IF(Y29=0,1,Z29/Y29)) -> 1
C30: 何宇 | F30: =IF(D30=0,1,E30/D30) -> 1 | I30: =IF(G30=0,1,H30/G30) -> 1 | L30: =IF(J30=0,1,K30/J30) -> 1 | O30: =IF(M30=0,1,N30/M30) -> 1 | R30: =IF(Q30<P30,-(P30-Q30)*200,0) -> 0 | U30: =IF(T30<S30,-(S30-T30)*200,0) -> 0 | X30: =IF(W30<V30,-(V30-W30)*300,0) -> 0 | Y30: =J30+G30+M30 -> 0 | AA30: =IF(IF(Y30=0,1,Z30/Y30)>1,1,IF(Y30=0,1,Z30/Y30)) -> 1
C31: 何伟 | F31: =IF(D31=0,1,E31/D31) -> 1 | I31: =IF(G31=0,1,H31/G31) -> 1 | L31: =IF(J31=0,1,K31/J31) -> 1 | O31: =IF(M31=0,1,N31/M31) -> 1 | R31: =IF(Q31<P31,-(P31-Q31)*200,0) -> 0 | U31: =IF(T31<S31,-(S31-T31)*200,0) -> 0 | X31: =IF(W31<V31,-(V31-W31)*300,0) -> 0 | Y31: =J31+G31+M31 -> 0 | AA31: =IF(IF(Y31=0,1,Z31/Y31)>1,1,IF(Y31=0,1,Z31/Y31)) -> 1
C32: 唐操 | F32: =IF(D32=0,1,E32/D32) -> 1 | I32: =IF(G32=0,1,H32/G32) -> 1 | L32: =IF(J32=0,1,K32/J32) -> 1 | O32: =IF(M32=0,1,N32/M32) -> 1 | R32: =IF(Q32<P32,-(P32-Q32)*200,0) -> 0 | U32: =IF(T32<S32,-(S32-T32)*200,0) -> 0 | X32: =IF(W32<V32,-(V32-W32)*300,0) -> 0 | Y32: =J32+G32+M32 -> 0 | AA32: =IF(IF(Y32=0,1,Z32/Y32)>1,1,IF(Y32=0,1,Z32/Y32)) -> 1
C33: 母勇 | F33: =IF(D33=0,1,E33/D33) -> 1 | I33: =IF(G33=0,1,H33/G33) -> 1 | L33: =IF(J33=0,1,K33/J33) -> 1 | O33: =IF(M33=0,1,N33/M33) -> 1 | R33: =IF(Q33<P33,-(P33-Q33)*200,0) -> 0 | U33: =IF(T33<S33,-(S33-T33)*200,0) -> 0 | X33: =IF(W33<V33,-(V33-W33)*300,0) -> 0 | Y33: =J33+G33+M33 -> 0 | AA33: =IF(IF(Y33=0,1,Z33/Y33)>1,1,IF(Y33=0,1,Z33/Y33)) -> 1
C34: 刘飞 | F34: =IF(D34=0,1,E34/D34) -> 1 | I34: =IF(G34=0,1,H34/G34) -> 1 | L34: =IF(J34=0,1,K34/J34) -> 1 | O34: =IF(M34=0,1,N34/M34) -> 1 | R34: =IF(Q34<P34,-(P34-Q34)*200,0) -> 0 | U34: =IF(T34<S34,-(S34-T34)*200,0) -> 0 | X34: =IF(W34<V34,-(V34-W34)*300,0) -> 0 | Y34: =J34+G34+M34 -> 0 | AA34: =IF(IF(Y34=0,1,Z34/Y34)>1,1,IF(Y34=0,1,Z34/Y34)) -> 1
C35: 何剑 | F35: =IF(D35=0,1,E35/D35) -> 1 | I35: =IF(G35=0,1,H35/G35) -> 1 | L35: =IF(J35=0,1,K35/J35) -> 1 | O35: =IF(M35=0,1,N35/M35) -> 1 | R35: =IF(Q35<P35,-(P35-Q35)*200,0) -> 0 | U35: =IF(T35<S35,-(S35-T35)*200,0) -> 0 | X35: =IF(W35<V35,-(V35-W35)*300,0) -> 0 | Y35: =J35+G35+M35 -> 0 | AA35: =IF(IF(Y35=0,1,Z35/Y35)>1,1,IF(Y35=0,1,Z35/Y35)) -> 1
C36: 雷卓远 | F36: =IF(D36=0,1,E36/D36) -> 1 | I36: =IF(G36=0,1,H36/G36) -> 1 | L36: =IF(J36=0,1,K36/J36) -> 1 | O36: =IF(M36=0,1,N36/M36) -> 1 | R36: =IF(Q36<P36,-(P36-Q36)*200,0) -> 0 | X36: =IF(W36<V36,-(V36-W36)*300,0) -> 0 | Y36: =J36+G36+M36 -> 0 | AA36: =IF(IF(Y36=0,1,Z36/Y36)>1,1,IF(Y36=0,1,Z36/Y36)) -> 1
C37: 王泳文 | F37: =IF(D37=0,1,E37/D37) -> 1 | I37: =IF(G37=0,1,H37/G37) -> 1 | L37: =IF(J37=0,1,K37/J37) -> 1 | O37: =IF(M37=0,1,N37/M37) -> 1 | R37: =IF(Q37<P37,-(P37-Q37)*200,0) -> 0 | U37: =IF(T37<S37,-(S37-T37)*200,0) -> 0 | X37: =IF(W37<V37,-(V37-W37)*300,0) -> 0 | Y37: =J37+G37+M37 -> 0 | AA37: =IF(IF(Y37=0,1,Z37/Y37)>1,1,IF(Y37=0,1,Z37/Y37)) -> 1
F38: =IF(D38=0,1,E38/D38) -> 1 | I38: =IF(G38=0,1,H38/G38) -> 1 | L38: =IF(J38=0,1,K38/J38) -> 1 | O38: =IF(M38=0,1,N38/M38) -> 1 | R38: =IF(Q38<P38,-(P38-Q38)*200,0) -> 0 | U38: =IF(T38<S38,-(S38-T38)*200,0) -> 0 | X38: =IF(W38<V38,-(V38-W38)*300,0) -> 0 | Y38: =J38+G38+M38 -> 0 | AA38: =IF(IF(Y38=0,1,Z38/Y38)>1,1,IF(Y38=0,1,Z38/Y38)) -> 1
F39: =IF(D39=0,1,E39/D39) -> 1 | I39: =IF(G39=0,1,H39/G39) -> 1 | L39: =IF(J39=0,1,K39/J39) -> 1 | O39: =IF(M39=0,1,N39/M39) -> 1 | R39: =IF(Q39<P39,-(P39-Q39)*200,0) -> 0 | U39: =IF(T39<S39,-(S39-T39)*200,0) -> 0 | X39: =IF(W39<V39,-(V39-W39)*300,0) -> 0 | Y39: =J39+G39+M39 -> 0 | AA39: =IF(IF(Y39=0,1,Z39/Y39)>1,1,IF(Y39=0,1,Z39/Y39)) -> 1
A40: 机场店 | B40: 展厅 | C40: 合计 | D40: =SUM(D41:D54) -> 0 | E40: =SUM(E41:E54) -> 0 | F40: =IF(D40=0,1,E40/D40) -> 1 | H40: =H54 -> 0 | I40: =I54 -> 0 | K40: =K54 -> 0 | L40: =L54 -> 0 | M40: =SUM(M29:M39) -> 0 | N40: =N54 -> 0 | O40: =O54 -> 1 | P40: =SUM(P41:P53) -> 0 | Q40: =SUM(Q41:Q53) -> 0 | R40: =R54 -> 0 | S40: =S54 -> 0 | T40: =T54 -> 0 | U40: =U54 -> 0 | V40: =V54 -> 0 | W40: =W54 -> 0 | X40: =SUM(X17:X39) -> 0 | Y40: =Y54 -> 0 | Z40: =Z54 -> 0 | AA40: =AA54 -> 0
C41: 姚元利 | F41: =IF(D41=0,1,E41/D41) -> 1 | I41: =IF(G41=0,1,H41/G41) -> 1 | L41: =IF(J41=0,1,K41/J41) -> 1 | O41: =IF(M41=0,1,N41/M41) -> 1 | R41: =IF(Q41<P41,-(P41-Q41)*200,0) -> 0 | U41: =IF(T41<S41,-(S41-T41)*300,0) -> 0 | X41: =IF(W41<V41,-(V41-W41)*300,0) -> 0 | Y41: =J41+G41+M41 -> 0 | AA41: =IF(IF(Y41=0,1,Z41/Y41)>1,1,IF(Y41=0,1,Z41/Y41)) -> 1
C42: 邓戈 | F42: =IF(D42=0,1,E42/D42) -> 1 | I42: =IF(G42=0,1,H42/G42) -> 1 | L42: =IF(J42=0,1,K42/J42) -> 1 | O42: =IF(M42=0,1,N42/M42) -> 1 | R42: =IF(Q42<P42,-(P42-Q42)*200,0) -> 0 | U42: =IF(T42<S42,-(S42-T42)*300,0) -> 0 | X42: =IF(W42<V42,-(V42-W42)*300,0) -> 0 | Y42: =J42+G42+M42 -> 0 | AA42: =IF(IF(Y42=0,1,Z42/Y42)>1,1,IF(Y42=0,1,Z42/Y42)) -> 1
C43: 刘发 | F43: =IF(D43=0,1,E43/D43) -> 1 | I43: =IF(G43=0,1,H43/G43) -> 1 | L43: =IF(J43=0,1,K43/J43) -> 1 | O43: =IF(M43=0,1,N43/M43) -> 1 | R43: =IF(Q43<P43,-(P43-Q43)*200,0) -> 0 | U43: =IF(T43<S43,-(S43-T43)*300,0) -> 0 | X43: =IF(W43<V43,-(V43-W43)*300,0) -> 0 | Y43: =J43+G43+M43 -> 0 | AA43: =IF(IF(Y43=0,1,Z43/Y43)>1,1,IF(Y43=0,1,Z43/Y43)) -> 1
C44: 陈林 | F44: =IF(D44=0,1,E44/D44) -> 1 | I44: =IF(G44=0,1,H44/G44) -> 1 | L44: =IF(J44=0,1,K44/J44) -> 1 | O44: =IF(M44=0,1,N44/M44) -> 1 | R44: =IF(Q44<P44,-(P44-Q44)*200,0) -> 0 | U44: =IF(T44<S44,-(S44-T44)*300,0) -> 0 | X44: =IF(W44<V44,-(V44-W44)*300,0) -> 0 | Y44: =J44+G44+M44 -> 0 | AA44: =IF(IF(Y44=0,1,Z44/Y44)>1,1,IF(Y44=0,1,Z44/Y44)) -> 1
C45: 黄军 | F45: =IF(D45=0,1,E45/D45) -> 1 | I45: =IF(G45=0,1,H45/G45) -> 1 | L45: =IF(J45=0,1,K45/J45) -> 1 | O45: =IF(M45=0,1,N45/M45) -> 1 | R45: =IF(Q45<P45,-(P45-Q45)*200,0) -> 0 | U45: =IF(T45<S45,-(S45-T45)*300,0) -> 0 | X45: =IF(W45<V45,-(V45-W45)*300,0) -> 0 | Y45: =J45+G45+M45 -> 0 | AA45: =IF(IF(Y45=0,1,Z45/Y45)>1,1,IF(Y45=0,1,Z45/Y45)) -> 1
C46: 冯超 | F46: =IF(D46=0,1,E46/D46) -> 1 | I46: =IF(G46=0,1,H46/G46) -> 1 | L46: =IF(J46=0,1,K46/J46) -> 1 | O46: =IF(M46=0,1,N46/M46) -> 1 | R46: =IF(Q46<P46,-(P46-Q46)*200,0) -> 0 | U46: =IF(T46<S46,-(S46-T46)*300,0) -> 0 | X46: =IF(W46<V46,-(V46-W46)*300,0) -> 0 | Y46: =J46+G46+M46 -> 0 | AA46: =IF(IF(Y46=0,1,Z46/Y46)>1,1,IF(Y46=0,1,Z46/Y46)) -> 1
F47: =IF(D47=0,1,E47/D47) -> 1 | I47: =IF(G47=0,1,H47/G47) -> 1 | L47: =IF(J47=0,1,K47/J47) -> 1 | O47: =IF(M47=0,1,N47/M47) -> 1 | R47: =IF(Q47<P47,-(P47-Q47)*200,0) -> 0 | U47: =IF(T47<S47,-(S47-T47)*300,0) -> 0 | X47: =IF(W47<V47,-(V47-W47)*300,0) -> 0 | Y47: =J47+G47+M47 -> 0 | AA47: =IF(IF(Y47=0,1,Z47/Y47)>1,1,IF(Y47=0,1,Z47/Y47)) -> 1
R48: =IF(Q48<P48,-(P48-Q48)*200,0) -> 0 | U48: =IF(T48<S48,-(S48-T48)*300,0) -> 0 | X48: =IF(W48<V48,-(V48-W48)*300,0) -> 0 | Y48: =J48+G48+M48 -> 0 | AA48: =IF(IF(Y48=0,1,Z48/Y48)>1,1,IF(Y48=0,1,Z48/Y48)) -> 1
R49: =IF(Q49<P49,-(P49-Q49)*200,0) -> 0 | U49: =IF(T49<S49,-(S49-T49)*300,0) -> 0 | X49: =IF(W49<V49,-(V49-W49)*300,0) -> 0 | Y49: =J49+G49+M49 -> 0 | AA49: =IF(IF(Y49=0,1,Z49/Y49)>1,1,IF(Y49=0,1,Z49/Y49)) -> 1
R50: =IF(Q50<P50,-(P50-Q50)*200,0) -> 0 | U50: =IF(T50<S50,-(S50-T50)*300,0) -> 0 | X50: =IF(W50<V50,-(V50-W50)*300,0) -> 0 | Y50: =J50+G50+M50 -> 0 | AA50: =IF(IF(Y50=0,1,Z50/Y50)>1,1,IF(Y50=0,1,Z50/Y50)) -> 1
R51: =IF(Q51<P51,-(P51-Q51)*200,0) -> 0 | X51: =IF(W51<V51,-(V51-W51)*500,0) -> 0 | Y51: =J51+G51+M51 -> 0 | AA51: =IF(IF(Y51=0,1,Z51/Y51)>1,1,IF(Y51=0,1,Z51/Y51)) -> 1
R52: =IF(Q52<P52,-(P52-Q52)*200,0) -> 0 | Y52: =J52+G52+M52 -> 0 | AA52: =IF(IF(Y52=0,1,Z52/Y52)>1,1,IF(Y52=0,1,Z52/Y52)) -> 1
R53: =IF(Q53<P53,-(P53-Q53)*200,0) -> 0 | X53: =IF(W53<V53,-(V53-W53)*500,0) -> 0 | Y53: =J53+G53+M53 -> 0 | AA53: =IF(IF(Y53=0,1,Z53/Y53)>1,1,IF(Y53=0,1,Z53/Y53)) -> 1
C54: 小计 | G54: =SUM(G41:G53) -> 0 | J54: =SUM(J41:J53) -> 0 | M54: =SUM(M41:M53) -> 0 | O54: =IF(M54=0,1,N54/M54) -> 1 | S54: =SUM(S41:S53) -> 0 | T54: =SUM(T41:T53) -> 0 | V54: =SUM(V41:V53) -> 0 | W54: =SUM(W41:W53) -> 0 | X54: =SUM(X41:X53) -> 0 | Y54: =SUM(Y41:Y53) -> 0 | Z54: =SUM(Z41:Z53) -> 0
B55: 合计 | D55: =D56+D68 -> 0 | E55: =E56+E68 -> 0 | F55: =F56+F68 -> 2 | G55: =G56+G68 -> 0 | H55: =H56+H68 -> 0 | I55: =I56+I68 -> 2 | J55: =J56+J68 -> 0 | K55: =K56+K68 -> 0 | ... V55: =V56+V68 -> 0 | X55: =X56+X68 -> 1 | Y55: =Y56+Y68 -> 0 | Z55: =Z56+Z68 -> 0 | AA55: =AA56+AA68 -> 2
B56: 网销 | C56: A组 | D56: =SUM(D57:D67) -> 0 | E56: =SUM(E57:E67) -> 0 | F56: =IF(D56=0,1,E56/D56) -> 1 | G56: =SUM(G57:G67) -> 0 | H56: =SUM(H57:H67) -> 0 | I56: =IF(G56=0,1,H56/G56) -> 1 | J56: =SUM(J57:J67) -> 0 | K56: =SUM(K57:K67) -> 0 | L56: =IF(J56=0,1,K56/J56) -> 1 | M56: =SUM(M57:M67) -> 0 | N56: =SUM(N57:N67) -> 0 | O56: =IF(M56=0,1,N56/M56) -> 1 | P56: =SUM(P57:P67) -> 0 | Q56: =SUM(Q57:Q67) -> 0 | S56: =SUM(S57:S67) -> 0 | T56: =SUM(T57:T67) -> 0 | U56: =IF(S56=0,1,T56/S56) -> 1 | V56: =SUM(V57:V67) -> 0 | W56: =SUM(W57:W67) -> 0 | X56: =IF(V56=0,1,W56/V56) -> 1 | Y56: =SUM(Y57:Y67) -> 0 | Z56: =SUM(Z57:Z67) -> 0 | AA56: =IF(Y56=0,1,Z56/Y56) -> 1
C57: 向兰 | O57: =IF(M57=0,1,N57/M57) -> 1 | R57: =IF(Q57<P57,-(P57-Q57)*200,0) -> 0 | U57: =IF(T57<S57,-(S57-T57)*300,0) -> 0 | X57: =IF(W57<V57,-(V57-W57)*300,0) -> 0 | Y57: =J57+G57+M57 -> 0 | AA57: =IF(IF(Y57=0,1,Z57/Y57)>1,1,IF(Y57=0,1,Z57/Y57)) -> 1
C58: 刘波 | F58: =IF(D58=0,1,E58/D58) -> 1 | I58: =IF(G58=0,1,H58/G58) -> 1 | L58: =IF(J58=0,1,K58/J58) -> 1 | O58: =IF(M58=0,1,N58/M58) -> 1 | R58: =IF(Q58<P58,-(P58-Q58)*200,0) -> 0 | U58: =IF(T58<S58,-(S58-T58)*300,0) -> 0 | X58: =IF(W58<V58,-(V58-W58)*300,0) -> 0 | Y58: =J58+G58+M58 -> 0 | AA58: =IF(IF(Y58=0,1,Z58/Y58)>1,1,IF(Y58=0,1,Z58/Y58)) -> 1
C59: 王熙鸿 | F59: =IF(D59=0,1,E59/D59) -> 1 | I59: =IF(G59=0,1,H59/G59) -> 1 | L59: =IF(J59=0,1,K59/J59) -> 1 | O59: =IF(M59=0,1,N59/M59) -> 1 | R59: =IF(Q59<P59,-(P59-Q59)*200,0) -> 0 | U59: =IF(T59<S59,-(S59-T59)*300,0) -> 0 | X59: =IF(W59<V59,-(V59-W59)*300,0) -> 0 | Y59: =J59+G59+M59 -> 0 | AA59: =IF(IF(Y59=0,1,Z59/Y59)>1,1,IF(Y59=0,1,Z59/Y59)) -> 1
C60: 黄婷婷 | F60: =IF(D60=0,1,E60/D60) -> 1 | I60: =IF(G60=0,1,H60/G60) -> 1 | L60: =IF(J60=0,1,K60/J60) -> 1 | O60: =IF(M60=0,1,N60/M60) -> 1 | R60: =IF(Q60<P60,-(P60-Q60)*200,0) -> 0 | U60: =IF(T60<S60,-(S60-T60)*300,0) -> 0 | X60: =IF(W60<V60,-(V60-W60)*300,0) -> 0 | Y60: =J60+G60+M60 -> 0 | AA60: =IF(IF(Y60=0,1,Z60/Y60)>1,1,IF(Y60=0,1,Z60/Y60)) -> 1
C61: 赵强 | F61: =IF(D61=0,1,E61/D61) -> 1 | I61: =IF(G61=0,1,H61/G61) -> 1 | L61: =IF(J61=0,1,K61/J61) -> 1 | O61: =IF(M61=0,1,N61/M61) -> 1 | R61: =IF(Q61<P61,-(P61-Q61)*200,0) -> 0 | U61: =IF(T61<S61,-(S61-T61)*300,0) -> 0 | X61: =IF(W61<V61,-(V61-W61)*300,0) -> 0 | Y61: =J61+G61+M61 -> 0 | AA61: =IF(IF(Y61=0,1,Z61/Y61)>1,1,IF(Y61=0,1,Z61/Y61)) -> 1
C62: 熊俊杰 | F62: =IF(D62=0,1,E62/D62) -> 1 | I62: =IF(G62=0,1,H62/G62) -> 1 | L62: =IF(J62=0,1,K62/J62) -> 1 | O62: =IF(M62=0,1,N62/M62) -> 1 | R62: =IF(Q62<P62,-(P62-Q62)*200,0) -> 0 | U62: =IF(T62<S62,-(S62-T62)*300,0) -> 0 | X62: =IF(W62<V62,-(V62-W62)*300,0) -> 0 | Y62: =J62+G62+M62 -> 0 | AA62: =IF(IF(Y62=0,1,Z62/Y62)>1,1,IF(Y62=0,1,Z62/Y62)) -> 1
C63: 莫晓何 | F63: =IF(D63=0,1,E63/D63) -> 1 | I63: =IF(G63=0,1,H63/G63) -> 1 | L63: =IF(J63=0,1,K63/J63) -> 1 | O63: =IF(M63=0,1,N63/M63) -> 1 | R63: =IF(Q63<P63,-(P63-Q63)*200,0) -> 0 | U63: =IF(T63<S63,-(S63-T63)*300,0) -> 0 | X63: =IF(W63<V63,-(V63-W63)*300,0) -> 0 | Y63: =J63+G63+M63 -> 0 | AA63: =IF(IF(Y63=0,1,Z63/Y63)>1,1,IF(Y63=0,1,Z63/Y63)) -> 1
C64: 邱明杰 | F64: =IF(D64=0,1,E64/D64) -> 1 | I64: =IF(G64=0,1,H64/G64) -> 1 | L64: =IF(J64=0,1,K64/J64) -> 1 | O64: =IF(M64=0,1,N64/M64) -> 1 | R64: =IF(Q64<P64,-(P64-Q64)*200,0) -> 0 | U64: =IF(T64<S64,-(S64-T64)*300,0) -> 0 | X64: =IF(W64<V64,-(V64-W64)*300,0) -> 0 | Y64: =J64+G64+M64 -> 0 | AA64: =IF(IF(Y64=0,1,Z64/Y64)>1,1,IF(Y64=0,1,Z64/Y64)) -> 1
C65: 刘凤英 | F65: =IF(D65=0,1,E65/D65) -> 1 | I65: =IF(G65=0,1,H65/G65) -> 1 | L65: =IF(J65=0,1,K65/J65) -> 1 | O65: =IF(M65=0,1,N65/M65) -> 1 | R65: =IF(Q65<P65,-(P65-Q65)*200,0) -> 0 | U65: =IF(T65<S65,-(S65-T65)*300,0) -> 0 | X65: =IF(W65<V65,-(V65-W65)*300,0) -> 0 | Y65: =J65+G65+M65 -> 0 | AA65: =IF(IF(Y65=0,1,Z65/Y65)>1,1,IF(Y65=0,1,Z65/Y65)) -> 1
C66: 施巍 | F66: =IF(D66=0,1,E66/D66) -> 1 | I66: =IF(G66=0,1,H66/G66) -> 1 | L66: =IF(J66=0,1,K66/J66) -> 1 | O66: =IF(M66=0,1,N66/M66) -> 1 | R66: =IF(Q66<P66,-(P66-Q66)*200,0) -> 0 | U66: =IF(T66<S66,-(S66-T66)*300,0) -> 0 | X66: =IF(W66<V66,-(V66-W66)*300,0) -> 0 | Y66: =J66+G66+M66 -> 0 | AA66: =IF(IF(Y66=0,1,Z66/Y66)>1,1,IF(Y66=0,1,Z66/Y66)) -> 1
F67: =IF(D67=0,1,E67/D67) -> 1 | I67: =IF(G67=0,1,H67/G67) -> 1 | L67: =IF(J67=0,1,K67/J67) -> 1 | O67: =IF(M67=0,1,N67/M67) -> 1 | R67: =IF(Q67<P67,-(P67-Q67)*200,0) -> 0 | U67: =IF(T67<S67,-(S67-T67)*300,0) -> 0 | X67: =IF(W67<V67,-(V67-W67)*300,0) -> 0 | Y67: =J67+G67+M67 -> 0 | AA67: =IF(IF(Y67=0,1,Z67/Y67)>1,1,IF(Y67=0,1,Z67/Y67)) -> 1
C68: B组 | D68: =SUM(D69:D77) -> 0 | E68: =SUM(E69:E77) -> 0 | F68: =IF(D68=0,1,E68/D68) -> 1 | G68: =SUM(G69:G77) -> 0 | H68: =SUM(H69:H77) -> 0 | I68: =IF(G68=0,1,H68/G68) -> 1 | J68: =SUM(J69:J77) -> 0 | K68: =SUM(K69:K77) -> 0 | L68: =IF(J68=0,1,K68/J68) -> 1 | M68: =SUM(M69:M77) -> 0 | N68: =SUM(N69:N77) -> 0 | O68: =IF(M68=0,1,N68/M68) -> 1 | P68: =SUM(P69:P77) -> 0 | R68: =IF(Q68<P68,-(P68-Q68)*200,0) -> 0 | S68: =SUM(S69:S77) -> 0 | T68: =SUM(T69:T77) -> 0 | U68: =IF(S68=0,1,T68/S68) -> 1 | V68: =SUM(V69:V77) -> 0 | W68: =SUM(W69:W77) -> 0 | Y68: =SUM(Y69:Y77) -> 0 | Z68: =SUM(Z69:Z77) -> 0 | AA68: =IF(Y68=0,1,Z68/Y68) -> 1
B69: 大客户 | C69: 张永强 | F69: =IF(D69=0,1,E69/D69) -> 1 | I69: =IF(G69=0,1,H69/G69) -> 1 | L69: =IF(J69=0,1,K69/J69) -> 1 | O69: =IF(M69=0,1,N69/M69) -> 1 | R69: =IF(P69=0,1,Q69/P69) -> 1 | U69: =IF(S69=0,1,T69/S69) -> 1 | X69: =IF(W69<V69,-(V69-W69)*300,0) -> 0 | Y69: =Z69 -> 0 | AA69: =IF(IF(Y69=0,1,Z69/Y69)>1,1,IF(Y69=0,1,Z69/Y69)) -> 1
F70: =IF(D70=0,1,E70/D70) -> 1 | I70: =IF(G71=0,1,H70/G71) -> 1 | L70: =IF(J70=0,1,K70/J70) -> 1 | O70: =IF(M70=0,1,N70/M70) -> 1 | R70: =IF(P70=0,1,Q70/P70) -> 1 | S70: =Z70 -> 0 | U70: =IF(S70=0,1,T70/S70) -> 1 | X70: =IF(W70<V70,-(V70-W70)*300,0) -> 0 | Y70: =J70+G70+M70 -> 0 | AA70: =IF(IF(Y70=0,1,Z70/Y70)>1,1,IF(Y70=0,1,Z70/Y70)) -> 1
F71: =IF(D71=0,1,E71/D71) -> 1 | I71: =IF(G72=0,1,H71/G72) -> 1 | L71: =IF(J71=0,1,K71/J71) -> 1 | O71: =IF(M71=0,1,N71/M71) -> 1 | R71: =IF(P71=0,1,Q71/P71) -> 1 | S71: =Z71 -> 0 | U71: =IF(S71=0,1,T71/S71) -> 1 | X71: =IF(W71<V71,-(V71-W71)*300,0) -> 0 | Y71: =J71+G71+M71 -> 0 | AA71: =IF(IF(Y71=0,1,Z71/Y71)>1,1,IF(Y71=0,1,Z71/Y71)) -> 1
F72: =IF(D72=0,1,E72/D72) -> 1 | I72: =IF(G73=0,1,H72/G73) -> 1 | L72: =IF(J72=0,1,K72/J72) -> 1 | O72: =IF(M72=0,1,N72/M72) -> 1 | R72: =IF(P72=0,1,Q72/P72) -> 1 | S72: =Z72 -> 0 | U72: =IF(S72=0,1,T72/S72) -> 1 | X72: =IF(W72<V72,-(V72-W72)*300,0) -> 0 | Y72: =J72+G72+M72 -> 0 | AA72: =IF(IF(Y72=0,1,Z72/Y72)>1,1,IF(Y72=0,1,Z72/Y72)) -> 1
F73: =IF(D73=0,1,E73/D73) -> 1 | I73: =IF(G74=0,1,H73/G74) -> 1 | L73: =IF(J73=0,1,K73/J73) -> 1 | O73: =IF(M73=0,1,N73/M73) -> 1 | R73: =IF(P73=0,1,Q73/P73) -> 1 | S73: =Z73 -> 0 | U73: =IF(S73=0,1,T73/S73) -> 1 | X73: =IF(W73<V73,-(V73-W73)*500,0) -> 0 | Y73: =J73+G73+M73 -> 0 | AA73: =IF(IF(Y73=0,1,Z73/Y73)>1,1,IF(Y73=0,1,Z73/Y73)) -> 1
F74: =IF(D74=0,1,E74/D74) -> 1 | I74: =IF(G74=0,1,H74/G74) -> 1 | L74: =IF(J74=0,1,K74/J74) -> 1 | O74: =IF(M74=0,1,N74/M74) -> 1 | R74: =IF(P74=0,1,Q74/P74) -> 1 | U74: =IF(S74=0,1,T74/S74) -> 1 | X74: =IF(W74<V74,-(V74-W74)*500,0) -> 0 | Y74: =J74+G74+M74 -> 0 | AA74: =IF(IF(Y74=0,1,Z74/Y74)>1,1,IF(Y74=0,1,Z74/Y74)) -> 1
F75: =IF(D75=0,1,E75/D75) -> 1 | I75: =IF(G75=0,1,H75/G75) -> 1 | L75: =IF(J75=0,1,K75/J75) -> 1 | O75: =IF(M75=0,1,N75/M75) -> 1 | R75: =IF(P75=0,1,Q75/P75) -> 1 | U75: =IF(S75=0,1,T75/S75) -> 1 | X75: =IF(W75<V75,-(V75-W75)*500,0) -> 0 | Y75: =J75+G75+M75 -> 0 | AA75: =IF(IF(Y75=0,1,Z75/Y75)>1,1,IF(Y75=0,1,Z75/Y75)) -> 1
F76: =IF(D76=0,1,E76/D76) -> 1 | I76: =IF(G76=0,1,H76/G76) -> 1 | L76: =IF(J76=0,1,K76/J76) -> 1 | O76: =IF(M76=0,1,N76/M76) -> 1 | R76: =IF(P76=0,1,Q76/P76) -> 1 | U76: =IF(S76=0,1,T76/S76) -> 1 | X76: =IF(W76<V76,-(V76-W76)*500,0) -> 0 | Y76: =J76+G76+M76 -> 0 | AA76: =IF(IF(Y76=0,1,Z76/Y76)>1,1,IF(Y76=0,1,Z76/Y76)) -> 1
F77: =IF(D77=0,1,E77/D77) -> 1 | I77: =IF(G77=0,1,H77/G77) -> 1 | L77: =IF(J77=0,1,K77/J77) -> 1 | O77: =IF(M77=0,1,N77/M77) -> 1 | R77: =IF(P77=0,1,Q77/P77) -> 1 | U77: =IF(S77=0,1,T77/S77) -> 1 | X77: =IF(W77<V77,-(V77-W77)*500,0) -> 0 | Y77: =J77+G77+M77 -> 0 | AA77: =IF(IF(Y77=0,1,Z77/Y77)>1,1,IF(Y77=0,1,Z77/Y77)) -> 1
A78: 网络部 | C78: 合计 | D78: =SUM(D79:D80) -> 0 | E78: =SUM(E79:E80) -> 0 | F78: =IF(D78=0,1,E78/D78) -> 1 | G78: =SUM(G79:G80) -> 0 | H78: =SUM(H79:H80) -> 0 | I78: =IF(G78=0,1,H78/G78) -> 1 | J78: =SUM(J79:J80) -> 0 | K78: =SUM(K79:K80) -> 0 | L78: =IF(J78=0,1,K78/J78) -> 1 | M78: =SUM(M79:M80) -> 0 | N78: =SUM(N79:N80) -> 0 | O78: =IF(M78=0,1,N78/M78) -> 1 | P78: =SUM(P79:P80) -> 0 | Q78: =SUM(Q79:Q80) -> 0 | S78: =SUM(S79:S80) -> 0 | T78: =SUM(T79:T80) -> 0 | V78: =SUM(V79:V80) -> 0 | W78: =SUM(W79:W80) -> 0 | X78: =IF(V78=0,1,W78/V78) -> 1 | Y78: =SUM(Y79:Y80) -> 0 | Z78: =SUM(Z79:Z80) -> 0 | AA78: =IF(Y78=0,1,Z78/Y78) -> 1
I79: =IF(G79=0,1,H79/G79) -> 1 | O79: =IF(M79=0,1,N79/M79) -> 1 | R79: =IF(Q79<P79,-(P79-Q79)*200,0) -> 0 | U79: =IF(T79<S79,-(S79-T79)*300,0) -> 0 | Y79: =G79+J79 -> 0 | AA79: =IF(IF(Y79=0,1,Z79/Y79)>1,1,IF(Y79=0,1,Z79/Y79)) -> 1
C80: 余才万 | L80: =IF(J80=0,1,K80/J80) -> 1 | O80: =IF(M80=0,1,N80/M80) -> 1 | U80: =IF(T80<S80,-(S80-T80)*300,0) -> 0 | X80: =IF(W80<V80,-(V80-W80)*500,0) -> 0 | Y80: =G80+J80 -> 0 | AA80: =IF(IF(Y80=0,1,Z80/Y80)>1,1,IF(Y80=0,1,Z80/Y80)) -> 1
A81: 营销部 | C81: 合计 | D81: =SUM(D82:D87) -> 0 | E81: =SUM(E82:E87) -> 0 | F81: =IF(D81=0,1,E81/D81) -> 1 | G81: =SUM(G82:G87) -> 0 | H81: =SUM(H82:H87) -> 0 | I81: =IF(G81=0,1,H81/G81) -> 1 | J81: =SUM(J82:J86) -> 0 | K81: =SUM(K82:K86) -> 0 | L81: =IF(J81=0,1,K81/J81) -> 1 | M81: =SUM(M82:M86) -> 0 | N81: =SUM(N82:N86) -> 0 | O81: =IF(M81=0,1,N81/M81) -> 1 | P81: =SUM(P82:P86) -> 0 | Q81: =SUM(Q82:Q86) -> 0 | S81: =SUM(S82:S86) -> 0 | T81: =SUM(T82:T86) -> 0 | V81: =SUM(V82:V86) -> 0 | W81: =SUM(W82:W86) -> 0 | X81: =SUM(X82:X86) -> 0 | Y81: =SUM(Y82:Y86) -> 0 | Z81: =SUM(Z82:Z86) -> 0 | AA81: =IF(Y81=0,1,Z81/Y81) -> 1
B82: 机场 | C82: *** | F82: =IF(D82=0,1,E82/D82) -> 1 | G82: =G7 -> 0 | H82: =H7 -> 0 | I82: =IF(G82=0,1,H82/G82) -> 1 | J82: =J7 -> 0 | K82: =K7 -> 0 | L82: =IF(J82=0,1,K82/J82) -> 1 | M82: =M7 -> 0 | N82: =N7 -> 0 | O82: =IF(M82=0,1,N82/M82) -> 1 | P82: =P7 -> 0 | W82: =W28+W16 -> 0 | X82: =IF(W82<V82,-(V82-W82)*300,0) -> 0 | Y82: =Y7 -> 0 | Z82: =Z7 -> 0 | AA82: =IF(Y82=0,1,Z82/Y82) -> 1
B83: 电销 | C83: 范娜 | D83: =Y56 -> 0 | E83: =Z28 -> 0 | F83: =IF(D83=0,1,E83/D83) -> 1 | O83: =IF(M83=0,1,N83/M83) -> 1 | W83: =SUM(W57:W67) -> 0 | X83: =IF(W83<V83,-(V83-W83)*300,0) -> 0 | Y83: =Y54 -> 0 | Z83: =Z54 -> 0 | AA83: =IF(Y83=0,1,Z83/Y83) -> 1
C84: 钟小莉 | D84: =Y28 -> 0 | E84: =Z28 -> 0 | F84: =IF(D84=0,1,E84/D84) -> 1 | O84: =IF(M84=0,1,N84/M84) -> 1 | W84: =SUM(W41:W53) -> 0 | X84: =IF(W84<V84,-(V84-W84)*300,0) -> 0 | Y84: =Y143 -> 0 | Z84: =Z143 -> 0 | AA84: =IF(Y84=0,1,Z84/Y84) -> 1
B85: 武侯 | C85: *** | D85: =D40 -> 0 | E85: =E40 -> 0 | F85: =IF(D85=0,1,E85/D85) -> 1 | G85: =G40 -> 0 | H85: =H55 -> 0 | I85: =IF(G85=0,1,H85/G85) -> 1 | J85: =J40 -> 0 | K85: =K55 -> 0 | L85: =IF(J85=0,1,K85/J85) -> 1 | M85: =M55 -> 0 | N85: =N55 -> 0 | O85: =IF(M85=0,1,N85/M85) -> 1 | P85: =P40 -> 0 | W85: =SUM(W17:W26) -> 0 | X85: =IF(W85<V85,-(V85-W85)*300,0) -> 0 | Y85: =Y56 -> 0 | Z85: =Z56 -> 0 | AA85: =IF(Y85=0,1,Z85/Y85) -> 1
B86: 武侯DCC | C86: 陈文虎 | I86: =IF(G86=0,1,H86/G86) -> 1 | R86: =IF(Q86<P86,-(P86-Q86)*200,0) -> 0 | X86: =IF(W86<V86,-(V86-W86)*300,0) -> 0
D87: =D7 -> 0 | E87: =E7 -> 0 | R87: =IF(Q87<P87,-(P87-Q87)*200,0) -> 0
R88: =IF(Q88<P88,-(P88-Q88)*200,0) -> 0
R89: =IF(Q89<P89,-(P89-Q89)*200,0) -> 0
R90: =IF(Q90<P90,-(P90-Q90)*200,0) -> 0
R91: =IF(Q91<P91,-(P91-Q91)*200,0) -> 0
D92: 集客(台） | G92: 订单（台） | J92: 销量（台） | M92: B网任务 | S92: A网 | V92: 超期（台） | Y92: 西物、超市（总完成率）
A93: 店名 | B93: 岗位 | C93: 姓名 | D93: 考核 | E93: 实际 | F93: 完成率 | G93: 考核 | H93: 实际 | I93: 完成率 | J93: 考核 | K93: 实际 | L93: 完成率 | M93: 考核 | N93: 实际 | O93: 完成率 | P93: 考核 | Q93: 实际 | R93: 完成率 | S93: 考核 | T93: 实际 | U93: 完成率 | V93: 考核 | W93: 实际 | X93: 完成率 | Y93: 考核 | Z93: 实际 | AA93: 完成率
A94: 直营店总计 | D94: =+D104+D113+D122+D131+D142 -> 0 | E94: =+E104+E113+E122+E131+E142 -> 0 | F94: =IF(D94=0,1,E94/D94) -> 1 | G94: =+G104+G113+G122+G131+G142 -> 0 | H94: =+H104+H113+H122+H131+H142 -> 0 | I94: =+I104+I113+I122+I131+I142 -> 10 | J94: =+J104+J113+J122+J131+J142 -> 0 | K94: =+K104+K113+K122+K131+K142 -> 0 | L94: =IF(J94=0,1,K94/J94) -> 1 | M94: =+M104+M113+M122+M131+M142 -> 0 | N94: =+N104+N113+N122+N131+N142 -> 0 | O94: =IF(M94=0,1,N94/M94) -> 1 | P94: =+P104+P113+P122+P131+P142 -> 0 | Q94: =+Q104+Q113+Q122+Q131+Q142 -> 0 | R94: =IF(P94=0,1,Q94/P94) -> 1 | S94: =+S104+S113+S122+S131+S142 -> 0 | T94: =+T104+T113+T122+T131+T142 -> 0 | U94: =IF(S94=0,1,T94/S94) -> 1 | V94: =+V104+V113+V122+V131+V142 -> 0 | X94: =IF(V94=0,1,W94/V94) -> 1 | Y94: =+Y104+Y113+Y122+Y131+Y142 -> 0 | Z94: =+Z104+Z113+Z122+Z131+Z142 -> 0 | AA94: =IF(Y94=0,1,Z94/Y94) -> 1 | AB94: A+B任务量 | AC94: 合并总任务量 | AD94: A网实际量 | AE94: B网实际量 | AF94: 合并总完成量 | AG94: 总完成率
A95: 崇州 直营店 | B95: 销售顾问 | C95: 唐鹏 | F95: =IF(D95=0,1,E95/D95) -> 1 | I95: =IF(G95=0,1,H95/G95) -> 1 | L95: =IF(J95=0,1,K95/J95) -> 1 | O95: =IF(M95=0,1,N95/M95) -> 1 | U95: =IF(T95<S95,-(S95-T95)*200,0) -> 0 | X95: =IF(W95<V95,-(V95-W95)*200,0) -> 0 | Y95: =G95+J95 -> 0 | AA95: =IF(IF(Y95=0,1,Z95/Y95)>1,1,IF(Y95=0,1,Z95/Y95)) -> 1 | AB95: =M95+S95 -> 0 | AC95: =Y95+AB95 -> 0 | AF95: =Z95+AD95+AE95 -> 0 | AG95: =IF(AC95<>0,IF(AF95/AC95>120%,120%,AF95/AC95),0) -> 0
A96: 崇州 直营店 | B96: 销售顾问 | C96: 赵思梵 | F96: =IF(D96=0,1,E96/D96) -> 1 | I96: =IF(G96=0,1,H96/G96) -> 1 | L96: =IF(J96=0,1,K96/J96) -> 1 | O96: =IF(M96=0,1,N96/M96) -> 1 | R96: =IF(Q96<P96,-(P96-Q96)*200,0) -> 0 | U96: =IF(T96<S96,-(S96-T96)*200,0) -> 0 | X96: =IF(W96<V96,-(V96-W96)*200,0) -> 0 | Y96: =G96+J96 -> 0 | AA96: =IF(IF(Y96=0,1,Z96/Y96)>1,1,IF(Y96=0,1,Z96/Y96)) -> 1 | AB96: =M96+S96 -> 0 | AC96: =Y96+AB96 -> 0 | AF96: =Z96+AD96+AE96 -> 0 | AG96: =IF(AC96<>0,IF(AF96/AC96>120%,120%,AF96/AC96),0) -> 0
A97: 崇州 直营店 | B97: 销售顾问 | C97: 陈勇建 | F97: =IF(D97=0,1,E97/D97) -> 1 | I97: =IF(G97=0,1,H97/G97) -> 1 | L97: =IF(J97=0,1,K97/J97) -> 1 | O97: =IF(M97=0,1,N97/M97) -> 1 | R97: =IF(Q97<P97,-(P97-Q97)*200,0) -> 0 | U97: =IF(T97<S97,-(S97-T97)*200,0) -> 0 | X97: =IF(W97<V97,-(V97-W97)*200,0) -> 0 | Y97: =G97+J97 -> 0 | AA97: =IF(IF(Y97=0,1,Z97/Y97)>1,1,IF(Y97=0,1,Z97/Y97)) -> 1 | AB97: =M97+S97 -> 0 | AC97: =Y97+AB97 -> 0 | AF97: =Z97+AD97+AE97 -> 0 | AG97: =IF(AC97<>0,IF(AF97/AC97>120%,120%,AF97/AC97),0) -> 0
A98: 崇州 直营店 | B98: 销售顾问 | C98: 宁袁 | F98: =IF(D98=0,1,E98/D98) -> 1 | I98: =IF(G98=0,1,H98/G98) -> 1 | L98: =IF(J98=0,1,K98/J98) -> 1 | O98: =IF(M98=0,1,N98/M98) -> 1 | R98: =IF(Q98<P98,-(P98-Q98)*200,0) -> 0 | U98: =IF(T98<S98,-(S98-T98)*200,0) -> 0 | X98: =IF(W98<V98,-(V98-W98)*200,0) -> 0 | Y98: =G98+J98 -> 0 | AA98: =IF(IF(Y98=0,1,Z98/Y98)>1,1,IF(Y98=0,1,Z98/Y98)) -> 1 | AB98: =M98+S98 -> 0 | AC98: =Y98+AB98 -> 0 | AF98: =Z98+AD98+AE98 -> 0 | AG98: =IF(AC98<>0,IF(AF98/AC98>120%,120%,AF98/AC98),0) -> 0
A99: 崇州 直营店 | B99: 销售顾问 | C99: 李智洪 | F99: =IF(D99=0,1,E99/D99) -> 1 | I99: =IF(G99=0,1,H99/G99) -> 1 | L99: =IF(J99=0,1,K99/J99) -> 1 | O99: =IF(M99=0,1,N99/M99) -> 1 | R99: =IF(Q99<P99,-(P99-Q99)*200,0) -> 0 | U99: =IF(T99<S99,-(S99-T99)*200,0) -> 0 | X99: =IF(W99<V99,-(V99-W99)*200,0) -> 0 | Y99: =G99+J99 -> 0 | AA99: =IF(IF(Y99=0,1,Z99/Y99)>1,1,IF(Y99=0,1,Z99/Y99)) -> 1 | AB99: =M99+S99 -> 0 | AC99: =Y99+AB99 -> 0 | AF99: =Z99+AD99+AE99 -> 0 | AG99: =IF(AC99<>0,IF(AF99/AC99>120%,120%,AF99/AC99),0) -> 0
A100: 崇州 直营店 | B100: 销售顾问 | C100: 杨婷 | F100: =IF(D100=0,1,E100/D100) -> 1 | I100: =IF(G100=0,1,H100/G100) -> 1 | L100: =IF(J100=0,1,K100/J100) -> 1 | O100: =IF(M100=0,1,N100/M100) -> 1 | R100: =IF(Q100<P100,-(P100-Q100)*200,0) -> 0 | U100: =IF(T100<S100,-(S100-T100)*200,0) -> 0 | X100: =IF(W100<V100,-(V100-W100)*200,0) -> 0 | Y100: =G100+J100 -> 0 | AA100: =IF(IF(Y100=0,1,Z100/Y100)>1,1,IF(Y100=0,1,Z100/Y100)) -> 1 | AB100: =M100+S100 -> 0 | AC100: =Y100+AB100 -> 0 | AF100: =Z100+AD100+AE100 -> 0 | AG100: =IF(AC100<>0,IF(AF100/AC100>120%,120%,AF100/AC100),0) -> 0
...

Sheet 新媒体
B1: 2026年 5月新媒体薪资明细
B2: 岗位 | C2: 项目 | D2: 直播场次 | E2: 直播线索 （仅限 小风车线索、直播复盘数据做参考） | F2: 直播粉丝关注量 （仅限 对应账户） | G2: 视频创作发布量 | H2: 岗位绩效KPI | I2: 岗位绩效 | J2: 终端量提成（仅限 对应公司账户端量） | L2: 线索超额完成奖励 | N2: 直播场次超额奖励 | P2: 基本薪资 | Q2: 绩效薪资 | R2: 合计薪资
J3: 以月度目标制定 | K3: 终端完成 | L3: 超额部分10元/条 （上限1000元） | M3: 当月超额线索数 | N3: 超额部分100元/场 （上限500元） | O3: 直播超额 完成场次 | T3: 新媒体部门人力归属及分配（5月）
T4: 序号 | U4: 网属 | V4: 公司归属 | W4: 执行岗位 | X4: 岗位要求 | Y4: 姓名 | Z4: 负责店面 | AA4: 人力数量 | AB4: 绩效薪资 | AC4: 备注
B5: 直播运维专员 | C5: 月度目标量 | I5: =H9*H5% -> #DIV/0! | J5: 未完成50元/台 完成100元/台 | U5: G网 | V5: 吉星-西物 | W5: 新媒体经理/运营 | X5: 专职 | Y5: 肖廷忠 | Z5: 吉星 | AB5: =Q54 -> #DIV/0!
C6: 实际达成量 | M6: =E6-E5 -> 0 | Q6: =SUM(I5,J8,L8,N8) -> #DIV/0! | R6: =SUM(I5,J8,L8,N8,P6) -> #DIV/0! | U6: G网 | V6: 吉星-西物 | W6: 视频运营专员 | X6: 专职 | Y6: 黄凤 | Z6: 吉星 | AB6: =Q46 -> #DIV/0!
B7: 吉星G-西物 | C7: 实际达成率 | D7: =D6/D5 -> #DIV/0! | E7: =E6/E5 -> #DIV/0! | F7: =F6/F5 -> #DIV/0! | G7: =G6/G5 -> #DIV/0! | U7: G网 | V7: 吉星-西物 | W7: 新媒体主播 | X7: 专职 | Y7: 曾子乂 | Z7: 西物 | AB7: =Q6 -> #DIV/0!
C8: 考核分值数 | H8: =SUM(D8:G8) -> 0 | J8: =J6*K6 -> 0 | L8: =_xlfn.IFS(M6>=100,1000,M6<=100,M6*L6) -> 0 | N8: =_xlfn.IFS(O6>=5,500,O6<=5,O6*N6) -> 0 | U8: L网 | V8: 吉星-超市 | W8: 新媒体主播 | X8: 专职 | Y8: 王芝婕 | Z8: 超市 | AB8: =Q25 -> #DIV/0!
B9: 曾子乂 | C9: 考核得分数 | D9: =IF(D7>=100%,D8*1,D8*D7) -> #DIV/0! | E9: =IF(E7>=100%,E8*1,E8*E7) -> #DIV/0! | F9: =IF(F7>=100%,F8*1,F8*F7) -> #DIV/0! | G9: =IF(G7>=100%,G8*1,G8*G7) -> #DIV/0! | H9: =SUM(D9:G9) -> #DIV/0! | U9: L网 | V9: 吉星-超市 | W9: 新媒体主播 | X9: 专职 | Y9: 蓝仁楷 | Z9: 超市 | AB9: =Q34 -> #DIV/0!
U10: G网 | V10: 吉星-西物 | W10: 新媒体主播 | X10: 专职 | Y10: 何玉 | Z10: 西物G | AB10: =Q15 -> #DIV/0!
B11: 岗位 | C11: 项目 | D11: 直播场次 | E11: 直播线索 （仅限 小风车线索、直播复盘数据做参考） | F11: 直播粉丝关注量 （仅限 对应账户） | G11: 视频创作发布量 视频：40 小红书：20 | H11: 岗位绩效KPI | I11: 岗位绩效 | J11: 终端量提成（仅限 对应公司账户端量） | L11: 线索超额完成奖励 | N11: 直播场次超额奖励 | P11: 基本薪资 | Q11: 绩效薪资 | R11: 合计薪资 | U11: G网 | W11: 新媒体运营 | X11: 兼职 | Y11: 赵金秀 | Z11: 吉星
J12: 以月度目标制定 | K12: 终端完成 | L12: 超额部分10元/条 （上限1000元） | M12: 当月超额线索数 | N12: 超额部分100元/场 （上限500元） | O12: 直播超额 完成场次
B14: 直播运维专员 | C14: 月度目标量 | I14: =H18*H14% -> #DIV/0! | J14: 完成100元/台； 未完成50元/台
C15: 实际达成量 | M15: =E15-E14 -> 0 | Q15: =SUM(I14,J17,L17,N17) -> #DIV/0! | R15: =SUM(I14,J17,L17,N17,P15) -> #DIV/0!
B16: 吉星G-西物 | C16: 实际达成率 | D16: =D15/D14 -> #DIV/0! | E16: =E15/E14 -> #DIV/0! | F16: =F15/F14 -> #DIV/0! | G16: =G15/G14 -> #DIV/0!
C17: 考核分值数 | H17: =SUM(D17:G17) -> 0 | J17: =J15*K15 -> 0 | L17: =_xlfn.IFS(M15>=100,1000,M15<=100,M15*L15) -> 0 | N17: =_xlfn.IFS(O15>=5,500,O15<=5,O15*N15) -> 0
B18: 何玉 | C18: 考核得分数 | D18: =IF(D16>=100%,D17*1,D17*D16) -> #DIV/0! | E18: =IF(E16>=100%,E17*1,E17*E16) -> #DIV/0! | F18: =IF(F16>=100%,F17*1,F17*F16) -> #DIV/0! | G18: =IF(G16>=100%,G17*1,G17*G16) -> #DIV/0! | H18: =SUM(D18:G18) -> #DIV/0!
B21: 岗位 | C21: 项目 | D21: 直播场次 | E21: 直播线索 （仅限 小风车线索、直播复盘数据做参考） | F21: 直播粉丝关注量 （仅限 对应账户） | G21: 视频创作发布量 | H21: 岗位绩效KPI | I21: 岗位绩效 | J21: 终端量提成（仅限 对应公司账户端量） | L21: 线索超额完成奖励 | N21: 直播场次超额奖励 | P21: 基本薪资 | Q21: 绩效薪资 | R21: 合计薪资
J22: 以月度目标制定 | K22: 终端完成 | L22: 超额部分10元/条 （上限1000元） | M22: 当月超额线索数 | N22: 超额部分100元/场 （上限500元） | O22: 直播超额 完成场次
B24: 直播运维专员 | C24: 月度目标量 | I24: =H28*H24% -> #DIV/0! | J24: 未完成50元/台 完成100元/台
C25: 实际达成量 | M25: =E25-E24 -> 0 | O25: =D25-D24 -> 0 | Q25: =SUM(I24,J27,L27,N27) -> #DIV/0! | R25: =SUM(I24,J27,L27,N27,P25) -> #DIV/0!
B26: 吉星L-超市 | C26: 实际达成率 | D26: =D25/D24 -> #DIV/0! | E26: =E25/E24 -> #DIV/0! | F26: =F25/F24 -> #DIV/0! | G26: =G25/G24 -> #DIV/0!
C27: 考核分值数 | H27: =SUM(D27:G27) -> 0 | J27: =J25*K25 -> 0 | L27: =_xlfn.IFS(M25>=100,1000,M25<=100,M25*L25) -> 0 | N27: =_xlfn.IFS(O25>=5,500,O25<=5,O25*N25) -> 0
B28: 王芝婕 | C28: 考核得分数 | D28: =IF(D26>=100%,D27*1,D27*D26) -> #DIV/0! | E28: =IF(E26>=100%,E27*1,E27*E26) -> #DIV/0! | F28: =IF(F26>=100%,F27*1,F27*F26) -> #DIV/0! | G28: =IF(G26>=100%,G27*1,G27*G26) -> #DIV/0! | H28: =SUM(D28:G28) -> #DIV/0!
B30: 岗位 | C30: 项目 | D30: 直播场次 | E30: 直播线索 （仅限 小风车线索、直播复盘数据做参考） | F30: 直播粉丝关注量 （仅限 对应账户） | G30: 视频创作发布量 | H30: 岗位绩效KPI | I30: 岗位绩效 | J30: 终端量提成（仅限 对应公司账户端量） | L30: 线索超额完成奖励 | N30: 直播场次超额奖励 | P30: 基本薪资 | Q30: 绩效薪资 | R30: 合计薪资
J31: 以月度目标制定 | K31: 终端完成 | L31: 超额部分10元/条 （上限1000元） | M31: 当月超额线索数 | N31: 超额部分100元/场 （上限500元） | O31: 直播超额 完成场次
B33: 直播运维专员 | C33: 月度目标量 | I33: =H37*H33% -> #DIV/0! | J33: 未完成50元/台 完成100元/台
C34: 实际达成量 | O34: =D34-D33 -> 0 | Q34: =SUM(I33,J36,L36,N36) -> #DIV/0! | R34: =SUM(I33,J36,L36,N36,P34) -> #DIV/0!
B35: 吉星L—超市 | C35: 实际达成率 | D35: =D34/D33 -> #DIV/0! | E35: =E34/E33 -> #DIV/0! | F35: =F34/F33 -> #DIV/0! | G35: =G34/G33 -> #DIV/0!
C36: 考核分值数 | H36: =SUM(D36:G36) -> 0 | J36: =J34*K34 -> 0 | L36: =_xlfn.IFS(M34>=100,1000,M34<=100,M34*L34) -> 0 | N36: =_xlfn.IFS(O34>=5,500,O34<=5,O34*N34) -> 0
B37: 蓝仁楷 | C37: 考核得分数 | D37: =IF(D35>=100%,D36*1,D36*D35) -> #DIV/0! | E37: =IF(E35>=100%,E36*1,E36*E35) -> #DIV/0! | F37: =IF(F35>=100%,F36*1,F36*F35) -> #DIV/0! | G37: =IF(G35>=100%,G36*1,G36*G35) -> #DIV/0! | H37: =SUM(D37:G37) -> #DIV/0!
B42: 岗位 | C42: 项目 | D42: 视频创作发布数 | E42: 播放量 | F42: 短视频粉丝关注量 | G42: 小红书笔记发布 | H42: 岗位绩效KPI | I42: 岗位绩效 | J42: 终端量提成（双账户合计量） | L42: 优质视频视频奖励≥30000播放量 | N42: 视频创作超额完成奖励 | P42: 基本薪资 | Q42: 绩效薪资 | R42: 合计薪资
J43: 以月度目标制定 | K43: 终端完成 | L43: 优质视频50元/条 （上限500元） | M43: 优质视频数量 | N43: 超额部分50元/条 (上限500元) | O43: 视频超额完成数
E44: 播放量≥3000
B45: 视频运维专员 超市+西物视频 | C45: 月度目标量 | I45: =H49*H45% -> #DIV/0! | J45: 未完成20元/台； 完成30元/台
C46: 实际达成量 | O46: =D46-D45 -> 0 | Q46: =SUM(I45,J48,L48,N48) -> #DIV/0! | R46: =SUM(I45,J48,L48,N48,P46) -> #DIV/0!
B47: 吉星G-西物 | C47: 实际达成率 | D47: =D46/D45 -> #DIV/0! | E47: =E46/E45 -> #DIV/0! | F47: =F46/F45 -> #DIV/0! | G47: =G46/G45 -> #DIV/0!
C48: 考核分值数 | H48: =SUM(D48:G48) -> 0 | J48: =J46*K46 -> 0 | L48: =L46*M46 -> 0
B49: 黄凤 | C49: 考核得分数 | D49: =IF(D47>=100%,D48*1,D48*D47) -> #DIV/0! | E49: =IF(E47>=100%,E48*1,E48*E47) -> #DIV/0! | F49: =IF(F47>=100%,F48*1,F48*F47) -> #DIV/0! | G49: =IF(G47>=100%,G48*1,G48*G47) -> #DIV/0! | H49: =SUM(D49:G49) -> #DIV/0!
B52: 岗位 | C52: 项目 | D52: 直播场次数 | E52: 视频创作数 | F52: 线索量 （月度目标制定） | G52: 邀约到店数 （月度目标制定） | H52: 岗位绩效KPI | I52: 岗位绩效 | J52: 终端量提成 | L52: 底薪薪资 | M52: 无 | N52: 无 | O52: 无 | P52: 无 | Q52: 绩效薪资 | R52: 合计薪资
J53: 40元/台 （不设限） | K53: 终端目标台
B54: 运维主管 | C54: 月度目标量 | I54: =H54*H58% -> #DIV/0! | Q54: =SUM(I54,J57) -> #DIV/0! | R54: =L54+J57+I54 -> #DIV/0!
C55: 实际达成量
B56: 吉星G-西物 | C56: 实际达成率 | D56: =D55/D54 -> #DIV/0! | E56: =E55/E54 -> #DIV/0! | F56: =F55/F54 -> #DIV/0! | G56: =G55/G54 -> #DIV/0! | M56: 无 | N56: 无 | O56: 无 | P56: 无
C57: 考核分值数 | H57: =SUM(D57:G57) -> 0 | J57: =40*K55 -> 0
B58: 肖廷忠 | C58: 考核得分数 | D58: =IF(D56>=100%,D57*1,D57*D56) -> #DIV/0! | E58: =IF(E56>=100%,E57*1,E57*E56) -> #DIV/0! | F58: =IF(F56>=100%,F57*1,F57*F56) -> #DIV/0! | G58: =IF(G56>=100%,G57*1,G57*G56) -> #DIV/0! | H58: =SUM(D58:G58) -> #DIV/0!
B62: 岗位 | C62: 项目 | D62: 私信开口数 | E62: 私信会话开口率 | F62: 私信线索转化率 | G62: 线索完成率 | H62: 岗位绩效KPI | I62: 岗位绩效 | J62: 终端量提成 （双账户合计量、超市+西物） | L62: 线索超额完成奖励 | N62: 基本薪资 | O62: 其它 | P62: 其它 | Q62: 绩效薪资 | R62: 合计薪资
J63: 以月度目标制定 | K63: 终端完成 （负责店面总量） | L63: 超额部分5元/条 （上限500元） | M63: 当月超额线索数
M64: =G65 -> 0
B65: 中国星 线索运维专员 | C65: 月度目标量 | I65: =H69*H65% -> #DIV/0! | J65: 5元/条 | M65: =G66 -> 0
C66: 实际达成量 | Q66: =SUM(I65,J68,N68,Q68,L68) -> #DIV/0! | R66: =N66+O66+P66+Q66 -> #DIV/0!
B67: G网西物+L网超市挖手 | C67: 实际达成率 | D67: =D66/D65 -> #DIV/0! | E67: =E66/E65 -> #DIV/0! | F67: =F66/F65 -> #DIV/0! | G67: =G66/G65 -> #DIV/0!
C68: 考核分值数 | H68: =SUM(D68:G68) -> 0 | J68: =J66*K66 -> 0 | L68: =_xlfn.IFS(M66>=100,500,M66<=100,M66*L66) -> 0
B69: 赵金秀 | C69: 考核得分数 | D69: =IF(D67>=100%,D68*1,D68*D67) -> #DIV/0! | E69: =IF(E67>=100%,E68*1,E68*E67) -> #DIV/0! | F69: =IF(F67>=100%,F68*1,F68*F67) -> #DIV/0! | G69: =IF(G67>=100%,G68*1,G68*G67) -> #DIV/0! | H69: =SUM(D69:G69) -> #DIV/0!

Sheet 邀约专员提成
B1: 05月 | C1: 人员 | D1: 人员 | AE1: 总绩效 | AF1: 发放金额
E2: 标准 | F2: 是否达成 | G2: 考核 | H2: 标准 | I2: 实际得分 | J2: 绩效 | K2: 单台绩效 | L2: 到店量 | M2: 绩效 | N2: 单台绩效 | O2: 成交台次 | P2: 绩效 | Q2: 计划线索分配量 | R2: 线索分配量 | S2: 邀约率 | T2: 单组追加 | U2: 奖励提成 | V2: 成交率 | W2: 单台追加 | X2: 奖励提成 | Y2: 单组追加 | Z2: 重攻台次 | AA2: 奖励 | AB2: 邀约任务 | AC2: 完成率
B3: 西物 | C3: 金玉梅 | G3: 六项标准均达成 | L3: =K3*J3 -> 0 | O3: =M3*N3 -> 0 | R3: =IFERROR(K3/Q3,"") | T3: =S3*K3 -> 0 | U3: =IFERROR(N3/K3,"") | W3: =N3*V3 -> 0 | Z3: =X3*Y3 -> 0 | AB3: =IFERROR(K3/AA3,"") | AD3: =I3+L3+O3+T3+W3+Z3+AC3+F3 -> 0 | AE3: 金玉梅 | AF3: =AD3 -> 0
B4: 西物 | C4: 周思雨 | L4: =K4*J4 -> 0 | O4: =M4*N4 -> 0 | R4: =IFERROR(K4/Q4,"") | T4: =S4*K4 -> 0 | U4: =IFERROR(N4/K4,"") | W4: =N4*V4 -> 0 | Z4: =X4*Y4 -> 0 | AB4: =IFERROR(K4/AA4,"") | AD4: =I4+L4+O4+T4+W4+Z4+AC4+F4 -> 0 | AE4: 周思雨 | AF4: =AD4 -> 0
B5: 西物 | C5: 陈文霜 | L5: =K5*J5 -> 0 | O5: =M5*N5 -> 0 | R5: =IFERROR(K5/Q5,"") | T5: =S5*K5 -> 0 | U5: =IFERROR(N5/K5,"") | W5: =N5*V5 -> 0 | Z5: =X5*Y5 -> 0 | AB5: =IFERROR(K5/AA5,"") | AD5: =I5+L5+O5+T5+W5+Z5+AC5+F5 -> 0 | AE5: 陈文霜 | AF5: =AD5 -> 0
B6: 西物 | C6: 杜小红 | L6: =K6*J6 -> 0 | O6: =M6*N6 -> 0 | R6: =IFERROR(K6/Q6,"") | T6: =S6*K6 -> 0 | U6: =IFERROR(N6/K6,"") | W6: =N6*V6 -> 0 | Z6: =X6*Y6 -> 0 | AB6: =IFERROR(K6/AA6,"") | AD6: =I6+L6+O6+T6+W6+Z6+AC6+F6 -> 0 | AE6: 杜小红 | AF6: =AD6 -> 0
B7: 西物 | C7: 周梅 | L7: =K7*J7 -> 0 | O7: =M7*N7 -> 0 | R7: =IFERROR(K7/Q7,"") | T7: =S7*K7 -> 0 | U7: =IFERROR(N7/K7,"") | W7: =N7*V7 -> 0 | Z7: =X7*Y7 -> 0 | AB7: =IFERROR(K7/AA7,"") | AD7: =I7+L7+O7+T7+W7+Z7+AC7+F7 -> 0 | AE7: 周梅 | AF7: =AD7 -> 0
B9: 05月 | C9: 人员 | D9: 400接起率 | G9: DMS指标六维度 | J9: 邀约绩效60元/组 | M9: 成交绩效40元/台 | P9: 缤越COOL、博越COOL、缤瑞COOL | S9: 成交率奖励 | V9: 任务考核 | Y9: 总绩效
D10: 标准 | E10: 是否达成 | F10: 考核 | G10: 标准 | H10: 实际得分 | I10: 绩效 | J10: 单台绩效 | K10: 到店量 | L10: 绩效 | M10: 单台绩效 | O10: 绩效 | P10: 达成邀约量 | Q10: 单组到店追加 | R10: 奖励提成 | S10: 成交率 | T10: 单台追加 | U10: 奖励提成 | V10: 邀约任务 | W10: 完成率 | X10: 考核金额
B11: 超市 | C11: 李春梅 | G11: 六项标准均达成 | AE11: =C11 -> 李春梅 | AF11: =Y11 -> 0
B12: 超市 | C12: 魏艳 | AE12: =C12 -> 魏艳 | AF12: =Y12 -> 0
B13: 超市 | C13: 谷雨 | AE13: =C13 -> 谷雨 | AF13: =Y13 -> 0
B15: 05月 | C15: 人员 | D15: 400接起率 | G15: DMS指标六维度 | J15: 邀约绩效60元/组 | M15: 成交绩效40元/台 | P15: 过程KPI奖励 | X15: 重攻奖励： | AA15: 任务考核 | AD15: 总绩效 | AE15: 杨婷 | AF15: =AD17 -> 0
D16: 标准 | E16: 是否达成 | F16: 考核 | G16: 标准 | H16: 实际得分 | I16: 绩效 | J16: 单台绩效 | K16: 到店量 | L16: 绩效 | M16: 单台绩效 | N16: 成交台次 | O16: 绩效 | P16: 计划线索分配量 | Q16: 线索分配量 | R16: 邀约率 | S16: 单组追加 | T16: 奖励提成 | U16: 成交率 | V16: 单台追加 | W16: 奖励提成 | X16: 单组追加 | Y16: 重攻台次 | Z16: 奖励 | AA16: 邀约任务 | AB16: 完成率 | AC16: 考核金额 | AE16: 陈子逸 | AF16: =W32 -> 0
B17: 崇州 | C17: 杨婷 | G17: 六项标准均达成 | L17: =K17*J17 -> 0 | O17: =M17*N17 -> 0 | R17: =IFERROR(K17/Q17,"") | T17: =S17*K17 -> 0 | U17: =IFERROR(N17/K17,"") | W17: =N17*V17 -> 0 | Z17: =X17*Y17 -> 0 | AB17: =IFERROR(K17/AA17,"") | AD17: =I17+L17+O17+T17+W17+Z17-AC17-F17 -> 0
B18: 1.400接起率出现未接起考核500元
B19: 2.DMS六维度指标：1.线索有效率70% 2.响应及时率100% 3.及时跟进率100% 4.邀约到店率15% 5.到店成交率35% 6.线索成交率4% 7.战败率90%以下，每项达成按100元计提，7项指标均达成追加100元。
B20: 3.邀约基础绩效：基础绩效60元一组
B21: 4.邀约到店率≥15%追加10元一组，未达标不奖励
B22: 5.成交基础绩效：基础绩效40元/台
B23: 6.成交率30-＜35%，追加20元/台成交；成交率≥35%，追加30元/台成交
B24: 7.有重攻车型时可设立重攻车型，重攻车型客户到店额外追加10元/组
B25: 8.任务考核：设立当月邀约到店目标量，未达成按照比例进行计提邀约绩效，上限100%
B26: 9.薪资方案由网销经理填报，销售总监/副总审核，总经理签字确认，承报财务/行政纳入当月绩效。
B27: 备注：1.到店率及成交率随市场变化，合理设定及上浮邀约专员追加指标。 2.店内过程指标需真实有效，DMS指标可手段提升
L30: 任务达成
C31: 员工 | D31: 店面 | E31: 基本工资 | F31: 岗位工资 | G31: DMS指标绩效/70元/项 | H31: 自媒体绩效(含内部员工转发率） | I31: 线索提成标准 | J31: 终端提成标准（月计算完成率） | K31: 线索任务 | L31: 销售任务 | M31: 线索数 | N31: 线索达成率 | O31: 终端达成 | P31: 终端达成率 | Q31: 线索绩效 | R31: 终端绩效 | S31: 新车上市4月内线索激励减半量 | T31: 线索减半金额 | U31: 考核 | V31: 绩效提成 | W31: 实际发放 | X31: 薪酬总额
C32: 陈子逸 | D32: 机场网销

Sheet 客户部提成
A1: 05月客户关系部 | AO1: A | AP1: B | AQ1: C=B-A | AR1: D | AS1: E | AT1: F=D*E
A2: 值 | B2: 项 | C2: 达成率 | D2: 系数 | E2: 邓芳 | G2: 张保珍 | I2: 备注 | K2: 05月 | L2: 潜客回访 | M2: 5天新车回访 | N2: 30天新车回访 | O2: 潜客战败回访 | P2: 新车回访绩效 | Q2: 面访量 | R2: 面访（6元/个） | S2: 多对一群聊建立量 | T2: 多对一群聊建立及维护（5元） | U2: 生日关怀接通量 | V2: 生日关怀绩效提成（2元/个） | W2: 口碑/发帖量 | X2: 口碑发帖绩效（X/个） | Y2: 投诉处理 | Z2: 销售满意度得分 | AA2: 销售满意度绩效 | AB2: 保客营销 | AD2: 合计薪资 | AE2: 备注 | AH2: 保客营销挖掘与转化绩效 | AN2: 店面——中国星武侯 | AO2: 1-3月数据情况 | AP2: 5月达成情况 | AQ2: 达成提升目标(%) | AR2: 台次(交付数) | AS2: 享受单台 | AT2: 金额
E3: 数量 | F3: 小计 | G3: 数量 | H3: 小计 | K3: 周舟 | P3: =SUM(L3:O3)*2 -> 0 | R3: =Q3*6 -> 0 | T3: =S3*5 -> 0 | V3: =U3*2 -> 0 | X3: =W3*50 -> 0 | AD3: =SUM(P3,R3,T3,V3,X3,Y3,AA3,AB3) -> 0 | AH3: 基盘客户 转介绍 | AI3: 绩效(元/台) | AN3: 电话回访 | AP3: =727+847 -> 1574
A4: 必做 | B4: 3DC一网 | F4: =D4*E4 -> 0 | H4: =G4*D4 -> 0 | K4: 合计 | AI4: 提升目标（%） | AJ4: 提升＜1% | AK4: 1%≤提升＜3% | AL4: 提升≥3% | AN4: 基盘客户转介绍 | AQ4: =+AP4-AO4 -> 0 | AS4: =+IF(AQ4<1%,20,IF(AQ4<3%,30,40)) -> 20 | AT4: =AR4*AS4 -> 0
A5: 必做 | B5: 3DC二网 | F5: =D5*E5 -> 0 | H5: =G5*D5 -> 0 | K5: 1.潜客回访、3天新车回访、30天新车回访、战败客户回访、生日关怀、售后3DC标准提成按电话接通2元/组 2.新车面访6元/个 3.口碑/发帖：＜5篇，30元/帖；≥5帖＜10帖，40元/帖；≥10帖，50元/帖；最高1000元 4.生日关怀，接通1元/个; 5.投诉处理：2小时未响应考核200元/单 3天未闭环考核500元/单，投诉单申述未通过考核200元/单，无异常奖励200元， 6.销售满意度：400得分90分及以下，考核200元；≥93分，奖励300元；≥95分，奖励500元 | AH5: 保客挖掘 置换/增购 | AI5: 绩效(元/台) | AN5: 保客挖掘置换/增购 | AS5: =+IF(AQ5>=3%,50,IF(AQ5>=1%,40,30)) -> 30 | AT5: =AR5*AS5 -> 0
A6: 必做 | B6: 新车5DC回访 | F6: =D6*E6 -> 0 | H6: =G6*D6 -> 0 | AI6: 提升目标（%） | AJ6: 提升＜1% | AK6: 1%≤提升＜3% | AL6: 提升≥3% | AN6: 全员营销 | AQ6: =+AP6-AO6 -> 0 | AS6: =+IF(AQ6<1%,10,IF(AQ6<3%,20,30)) -> 10 | AT6: =AR6*AS6 -> 0
A7: 必做 | B7: 新车30DC回访 | F7: =D7*E7 -> 0 | H7: =G7*D7 -> 0 | AH7: 全员营销 | AI7: 绩效(元/台) | AN7: 绩效合计 | AO7: 邓芳 | AT7: =SUM(AT3:AT6) -> 0
A8: 必做 | B8: 战败回访 | F8: =D8*E8 -> 0 | H8: =G8*D8 -> 0 | AI8: 提升目标（%） | AJ8: 提升＜1% | AK8: 1%≤提升＜3% | AL8: 提升≥3%
A9: 必做 | B9: 潜客回访 | F9: =D9*E9 -> 0 | H9: =G9*D9 -> 0 | AH9: 基本数据要求： | AN9: 店面——银河B武侯 | AO9: 1-3月数据情况 | AP9: 5月达成情况 | AQ9: 达成提升目标(%) | AR9: 台次(交付数) | AS9: 享受单台 | AT9: 金额
A10: 机动 | B10: 其他回访 | F10: =D10*E10 -> 0 | H10: =G10*D10 -> 0 | I10: 其他回访，是指核实老带新，核实债权转让，活动参加等临时事项 | AH10: 1、增加500元固定绩效，要求每日对基盘客户有效回访数＞30批次，单人每月有效回访批次＞900批 2、以上三类别计算基数分母为：当月销量 3、此方案试运行时间为：4月-6月，后续另行调整 | AN10: 电话回访
A11: 必做 | B11: 新车面访 | F11: =D11*E11 -> 0 | H11: =G11*D11 -> 0 | AN11: 基盘客户转介绍 | AQ11: =+AP11-AO11 -> 0 | AS11: =+IF(AQ11<1%,20,IF(AQ11<3%,30,40)) -> 20 | AT11: =AR11*AS11 -> 0
A12: 必做 | B12: 微信维系 | F12: =D12*E12 -> 0 | H12: =G12*D12 -> 0 | AN12: 保客挖掘置换/增购 | AO12: 4月新增项目 | AS12: =+IF(AQ12>=3%,50,IF(AQ12>=1%,40,30)) -> 30 | AT12: =AR12*AS12 -> 0
A13: 必做 | B13: 投诉处理 | F13: =D13*E13 -> 0 | H13: =G13*D13 -> 0 | AN13: 全员营销 | AQ13: =+AP13-AO13 -> 0 | AS13: =+IF(AQ13<1%,10,IF(AQ13<3%,20,30)) -> 10 | AT13: =AR13*AS13 -> 0
A14: 必做 | B14: 微信添加 | F14: =D14*E14 -> 0 | H14: =G14*D14 -> 0 | AN14: 绩效合计 | AO14: 李璐秀 | AT14: =SUM(AT10:AT13) -> 0
A15: 机动 | B15: 满意度 | F15: =D15*E15 -> 0 | H15: =G15*D15 -> 0 | I15: 4月400销售满意度：西物95.65分
A16: 增值 | B16: 口碑 | F16: =D16*E16 -> 0 | H16: =G16*D16 -> 0
A17: 增值 | B17: 发帖 | F17: =D17*E17 -> 0 | H17: =G17*D17 -> 0 | AN17: 店面——银河A武侯 | AO17: 1-3月数据情况 | AP17: 5月达成情况 | AQ17: 达成提升目标(%) | AR17: 台次(交付数) | AS17: 享受单台 | AT17: 金额
A18: 增值 | B18: N-3首保 | F18: =D18*E18 -> 0 | H18: =G18*D18 -> 0 | AN18: 电话回访
A19: 增值 | B19: N-4首保 | F19: =D19*E19 -> 0 | H19: =G19*D19 -> 0 | AN19: 基盘客户转介绍 | AQ19: =+AP19-AO19 -> 0 | AS19: =+IF(AQ19<1%,20,IF(AQ19<3%,30,40)) -> 20 | AT19: =AR19*AS19 -> 0
A20: 增值 | B20: N-5首保 | F20: =D20*E20 -> 0 | H20: =G20*D20 -> 0 | AN20: 保客挖掘置换/增购 | AO20: 4月新增项目 | AS20: =+IF(AQ20>=3%,50,IF(AQ20>=1%,40,30)) -> 30 | AT20: =AR20*AS20 -> 0
A21: 增值 | B21: N-6二保 | F21: =D21*E21 -> 0 | H21: =G21*D21 -> 0 | AN21: 全员营销 | AQ21: =+AP21-AO21 -> 0 | AS21: =+IF(AQ21<1%,10,IF(AQ21<3%,20,30)) -> 10 | AT21: =AR21*AS21 -> 0
A22: 增值 | B22: N-9二保 | F22: =D22*E22 -> 0 | H22: =G22*D22 -> 0 | AN22: 绩效合计 | AO22: 郭静 | AT22: =SUM(AT18:AT21) -> 0
A23: 增值 | B23: N-12二保 | F23: =D23*E23 -> 0 | H23: =G23*D23 -> 0
A24: 增值 | B24: N-6定保 | F24: =D24*E24 -> 0 | H24: =G24*D24 -> 0
A25: 增值 | B25: N-9定保 | F25: =D25*E25 -> 0 | H25: =G25*D25 -> 0 | AN25: 店面——银河B机场 | AO25: 1-3月数据情况 | AP25: 5月达成情况 | AQ25: 达成提升目标(%) | AR25: 台次(交付数) | AS25: 享受单台 | AT25: 金额
A26: 增值 | B26: N-12定保 | F26: =D26*E26 -> 0 | H26: =G26*D26 -> 0 | AN26: 电话回访
A27: 增值 | B27: 外拓 | F27: =D27*E27 -> 0 | H27: =G27*D27 -> 0 | AN27: 基盘客户转介绍 | AQ27: =+AP27-AO27 -> 0 | AS27: =+IF(AQ27<1%,20,IF(AQ27<3%,30,40)) -> 20 | AT27: =AR27*AS27 -> 0
A28: 增值 | B28: N-6其他 | F28: =D28*E28 -> 0 | H28: =G28*D28 -> 0 | AN28: 保客挖掘置换/增购 | AO28: 4月新增项目 | AS28: =+IF(AQ28>=3%,50,IF(AQ28>=1%,40,30)) -> 30 | AT28: =AR28*AS28 -> 0
A29: 增值 | B29: N-9其他 | F29: =D29*E29 -> 0 | H29: =G29*D29 -> 0 | AN29: 全员营销 | AQ29: =+AP29-AO29 -> 0 | AS29: =+IF(AQ29<1%,10,IF(AQ29<3%,20,30)) -> 10 | AT29: =AR29*AS29 -> 0
A30: 增值 | B30: N-12其他 | F30: =D30*E30 -> 0 | H30: =G30*D30 -> 0 | AN30: 绩效合计 | AO30: 古瑞婷 | AT30: =SUM(AT26:AT29) -> 0
A31: 增值 | B31: 无福袋 | F31: =D31*E31 -> 0 | H31: =G31*D31 -> 0
A32: 增值 | B32: 纯电回站 | F32: =D32*E32 -> 0 | H32: =G32*D32 -> 0 | I32: 2023年4月1号起，纯电车型预约回站，按8元/个计算
A33: 增值 | B33: 车机 | F33: =D33*E33 -> 0 | H33: =G33*D33 -> 0 | AN33: 店面——中国星机场 | AO33: 1-3月数据情况 | AP33: 5月达成情况 | AQ33: 达成提升目标(%) | AR33: 台次(交付数) | AS33: 享受单台 | AT33: 金额
A34: 增值 | B34: 福袋 | F34: =D34*E34 -> 0 | H34: =G34*D34 -> 0 | AN34: 电话回访
A35: 增值 | B35: 质保 | F35: =D35*E35 -> 0 | H35: =G35*D35 -> 0 | AN35: 基盘客户转介绍 | AQ35: =+AP35-AO35 -> 0 | AS35: =+IF(AQ35<1%,20,IF(AQ35<3%,30,40)) -> 20 | AT35: =AR35*AS35 -> 0
A36: 增值 | B36: 流失 | F36: =D36*E36 -> 0 | H36: =G36*D36 -> 0 | AN36: 保客挖掘置换/增购 | AO36: 4月新增项目 | AS36: =+IF(AQ36>=3%,50,IF(AQ36>=1%,40,30)) -> 30 | AT36: =AR36*AS36 -> 0
A37: 增值 | B37: 续保 | F37: =D37*E37 -> 0 | H37: =G37*D37 -> 0 | AN37: 全员营销 | AQ37: =+AP37-AO37 -> 0 | AS37: =+IF(AQ37<1%,10,IF(AQ37<3%,20,30)) -> 10 | AT37: =AR37*AS37 -> 0
A38: 增值 | B38: 轮胎 | F38: =D38*E38 -> 0 | H38: =G38*D38 -> 0 | AN38: 绩效合计 | AO38: 周舟 | AT38: =SUM(AT34:AT37) -> 0
A39: 增值 | B39: LED | F39: =D39*E39 -> 0 | H39: =G39*D39 -> 0
A40: 增值 | B40: 盲区 | F40: =D40*E40 -> 0 | H40: =G40*D40 -> 0
A41: 增值 | B41: 星瑞贯穿尾灯 | F41: =D41*E41 -> 0 | H41: =G41*D41 -> 0
A42: 绩效合计 | B42: 绩效合计 | F42: =SUM(F4:F41) -> 0 | G42: =SUM(G4:G41) -> 0 | H42: =SUM(H4:H41) -> 0
A43: 考核绩效
A47: 1.微信维系及时响应，300元；投诉2小时响应率100%，3天内闭环率100%，100元；微信100%添加好友100元；
A48: 2.售后面访65%为达标，未达成提成按产值千分之0.8，达成提成按产值千分之1计算（除去外销）
A49: 3.满意度按照厂家要求执行：销售满意度90分以上，奖励400元； 销售满意度得分90分及以下，考核200元；售后满意度得分92分及以上，奖励400元；售后满意度得分低于91分，考核200元（面访人员减半）；满意度成绩次月出，比如7月绩效按照6月满意计算，以此类推
A50: 6.口碑：＜5篇，30元/帖；≥5帖＜10帖，40元/帖；≥10帖，50元/帖；最高1000元
A51: 7.发帖：当月面访量5%新增发帖为考核标准，达到5%新增发帖100%绩效发放，未达标按80%绩效发放。 首次发帖100元/篇，2次发帖70元/贴；3次及以上50元/贴；
A52: 9.续保25元/单。ETC 10元/单，延保100元/单
A53: 10.车机奖励按照100元/台成交计算
A55: 类别 | B55: 档位 | C55: 3个月(N-3) | E55: 5个月(N-5) | G55: 吉利工厂，首保率，是按N-6来计算的
C56: 目标达成 | D56: 元/个 | E56: 目标达成 | F56: 元/个
A57: 首保 | B57: A | C57: N<75% | E57: N<80%
B58: B | C58: 75%≤N<80% | E58: 80%≤N<85%
B59: C | C59: 80%≤N<85% | E59: 85%≤N<90%
B60: D | C60: N≥85% | E60: N≥90%
A63: 类别 | B63: 档位 | C63: 6个月(N-6) | E63: 12个月(N-12) | G63: 吉利工厂，二保用户保持率，是按N-12来计算的
C64: 目标达成 | D64: 元/个 | E64: 目标达成 | F64: 元/个
A65: 二保 | B65: A | C65: N<35% | E65: N<55%
B66: B | C66: 35%≤N<38% | E66: 55%≤N<60%
B67: C | C67: 38%≤N<41% | E67: 60%≤N<65%
B68: D | C68: N≥41% | E68: N≥65%
A69: 类别 | B69: 档位 | C69: 6个月(N-6) | E69: 12个月(N-12) | G69: 吉利工厂，用户保持率，是按N-12来计算的
C70: 目标达成 | D70: 元/个 | E70: 目标达成 | F70: 元/个
A71: 定保 | B71: A | C71: N<30% | E71: N<60%
B72: B | C72: 30%≤N<33% | E72: 60%≤N<63%
B73: C | C73: 33%≤N<36% | E73: 63%≤N<66%
B74: D | C74: N≥36% | E74: N≥66%
A75: 类别 | B75: 档位 | C75: 6个月(N-6) | E75: 12个月(N-12)
C76: 目标达成 | D76: 元/个 | E76: 目标达成 | F76: 元/个
A77: 其他 | B77: A | C77: N<15% | E77: N<35%
B78: B | C78: 15%≤N<18% | E78: 35%≤N<38%
B79: C | C79: 18%≤N<21% | E79: 38%≤N<41%
B80: D | C80: N≥21% | E80: N≥45%
A84: 备注： | B84: 1、外拓，经主动预约回站的，有不低于50元消费记录，20元/个
B85: 2、预约回站后，对于非福袋客户，单个提成加2元
B86: 3、最终提成系数，DMS的当月预约率/35%，大于35%按35%计算
H89: A | I89: B | J89: C=B-A | K89: D | L89: E | M89: F=D*E
A90: 保客营销挖掘与转化绩效 | G90: 店面——中国星武侯 | H90: 1-3月数据情况 | I90: 4月达成情况 | J90: 达成提升目标(%) | K90: 台次(交付数) | L90: 享受单台 | M90: 金额
A91: 基盘客户 转介绍 | B91: 绩效(元/台) | G91: 电话回访 | M91: =K91*L91 -> 0
B92: 提升目标（%） | C92: 提升＜1% | D92: 1%≤提升＜3% | E92: 提升≥3% | G92: 基盘客户转介绍 | J92: =+I92-H92 -> 0 | L92: =+IF(J92<1%,20,IF(J92<3%,30,40)) -> 20 | M92: =K92*L92 -> 0
A93: 保客挖掘 置换/增购 | B93: 绩效(元/台) | G93: 保客挖掘置换/增购 | H93: 4月新增项目 | J93: -
B94: 提升目标（%） | C94: 提升＜1% | D94: 1%≤提升＜3% | E94: 提升≥3% | G94: 全员营销 | J94: =+I94-H94 -> 0 | L94: =+IF(J94<1%,10,IF(J94<3%,20,30)) -> 10 | M94: =K94*L94 -> 0
A95: 全员营销 | B95: 绩效(元/台) | G95: 绩效合计 | H95: 张保珍 | M95: =SUM(M91:M94) -> 0
B96: 提升目标（%） | C96: 提升＜1% | D96: 1%≤提升＜3% | E96: 提升≥3%
A97: 基本数据要求： | G97: 店面——银河B武侯 | H97: 1-3月数据情况 | I97: 4月达成情况 | J97: 达成提升目标(%) | K97: 台次(交付数) | L97: 享受单台 | M97: 金额
A98: 1、增加500元固定绩效，要求每日对基盘客户有效回访数＞30批次，单人每月有效回访批次＞900批 2、以上三类别计算基数分母为：当月销量 3、此方案试运行时间为：4月-6月，后续另行调整 | G98: 电话回访 | M98: =K98*L98 -> 0
G99: 基盘客户转介绍 | J99: =+I99-H99 -> 0 | L99: =+IF(J99<1%,20,IF(J99<3%,30,40)) -> 20 | M99: =K99*L99 -> 0
G100: 保客挖掘置换/增购 | H100: 4月新增项目 | J100: -
G101: 全员营销 | J101: =+I101-H101 -> 0 | L101: =+IF(J101<1%,10,IF(J101<3%,20,30)) -> 10 | M101: =K101*L101 -> 0
G102: 绩效合计 | H102: 李璐秀 | M102: =SUM(M98:M101) -> 0
G105: 店面——银河A武侯 | H105: 1-3月数据情况 | I105: 4月达成情况 | J105: 达成提升目标(%) | K105: 台次(交付数) | L105: 享受单台 | M105: 金额
G106: 电话回访 | M106: =K106*L106 -> 0
G107: 基盘客户转介绍 | J107: =+I107-H107 -> 0 | L107: =+IF(J107<1%,20,IF(J107<3%,30,40)) -> 20 | M107: =K107*L107 -> 0
G108: 保客挖掘置换/增购 | H108: 4月新增项目 | J108: -
G109: 全员营销 | J109: =+I109-H109 -> 0 | L109: =+IF(J109<1%,10,IF(J109<3%,20,30)) -> 10 | M109: =K109*L109 -> 0
G110: 绩效合计 | H110: 郭静 | M110: =SUM(M106:M109) -> 0

Sheet 直营店经理提成 (财务)
D1: 直营店店面 | J1: 直营店二网
B2: 店别 | C2: 展厅任务销售台次 | D2: 展厅实际销售台次 | E2: 新能源展厅实际销售台次 | F2: 完成率 | G2: 单台提成标准 | H2: 单台提成金额 | I2: 渠道任务销售台次 | J2: 渠道实际销售台次 | K2: 新能源渠道任务销售台次 | L2: 完成率 | M2: 单台提成标准 | N2: 单台提成金额 | O2: 台次提成合计 | P2: 附加收入提成合计 | Q2: 固定绩效 | R2: 提成合计 | S2: 指定车型考核 | T2: 考核金额 | AN2: 序号 | AO2: 出库日期 | AP2: 客户姓名 | AQ2: 电话 | AR2: 按揭信息 | BA2: 贴息信息 | BF2: 上户地 | BG2: 销售部门 | BH2: 直营店经理 | BI2: 车架号 | BJ2: 直营店经理 奖励金额
B3: 崇州直营店 | F3: =IF(C3<>0,IF(D3/C3>110%,110%,D3/C3),0) -> 0 | H3: =D3*F3*G3+E3*G3 -> 0 | L3: =IF(I3<>0,IF(J3/I3>110%,110%,J3/I3),0) -> 0 | N3: =L3*M3*J3+K3*M3 -> 0 | O3: =H3+N3 -> 0 | P3: =V13 -> 0 | Q3: =2500 -> 2500 | R3: =SUM(O3:Q3)+V3 -> 2500 | AR3: 总车价 | AS3: 期数 | AT3: 产品 | AU3: 贷款金额 | AV3: 附加贷 | AW3: 首付金额 | AX3: 首付比例 | AY3: 车型 | AZ3: 金融公司 | BA3: 贴息 | BB3: 工厂贴息 | BC3: 金融公司 贴息 | BD3: 客户补息 | BE3: 我司贴息
B4: 大邑直营店 | F4: =IF(C4<>0,IF(D4/C4>110%,110%,D4/C4),0) -> 0 | H4: =D4*F4*G4+E4*G4 -> 0 | L4: =IF(I4<>0,IF(J4/I4>110%,110%,J4/I4),0) -> 0 | N4: =L4*M4*J4+K4*M4 -> 0 | O4: =H4+N4 -> 0 | P4: =V14 -> 0 | Q4: =2500 -> 2500 | R4: =SUM(O4:Q4)+V4 -> 2500 | AP4: 隆波 | AT4: 60建行三支行(普通) | AY4: 星越L | AZ4: 建行三支行 | BA4: 是 | BF4: A成都 | BG4: 彭州直营店 | BH4: 黎明朗 | BI4: LB37852Z0TS027357
B5: 华阳直营店 | F5: =IF(C5<>0,IF(D5/C5>110%,110%,D5/C5),0) -> 0 | H5: =D5*F5*G5+E5*G5 -> 0 | L5: =IF(I5<>0,IF(J5/I5>110%,110%,J5/I5),0) -> 0 | N5: =L5*M5*J5+K5*M5 -> 0 | O5: =H5+N5 -> 0 | P5: =V15 -> 0 | Q5: =2500 -> 2500 | R5: =SUM(O5:Q5)+V5 -> 2500 | AP5: 刘倩言 | AT5: 60吉致(9.58%标贷) | AY5: 新博越 | AZ5: 吉致 | BA5: 否 | BF5: A成都 | BG5: 邛崃直营店 | BH5: 吴思超 | BI5: LB37722Z6TX316067
B6: 华阳领克 | F6: =IF(C6<>0,IF(D6/C6>110%,110%,D6/C6),0) -> 0 | H6: =D6*F6*G6+E6*G6 -> 0 | L6: =IF(I6<>0,IF(J6/I6>110%,110%,J6/I6),0) -> 0 | N6: =L6*M6*J6+K6*M6 -> 0 | O6: =H6+N6 -> 0 | P6: =V16 -> 0 | R6: =SUM(O6:Q6)+V6 -> 0 | AP6: 肖杨 | AT6: 60吉致(安心宝) | AY6: 第5代帝豪 | AZ6: 吉致 | BA6: 是 | BF6: A成都 | BG6: 崇州直营店 | BH6: 朱剑波 | BI6: LB37824Z1TG026166
B7: 彭州直营店 | F7: =IF(C7<>0,IF(D7/C7>110%,110%,D7/C7),0) -> 0 | H7: =D7*F7*G7+E7*G7 -> 0 | L7: =IF(I7<>0,IF(J7/I7>110%,110%,J7/I7),0) -> 0 | N7: =L7*M7*J7+K7*M7 -> 0 | O7: =H7+N7 -> 0 | P7: =V17 -> 0 | Q7: =2500+750 -> 3250 | R7: =SUM(O7:Q7)+V7 -> 3250 | AP7: 罗利华 | AT7: 60吉致(安心宝) | AY7: 第四代博越L | AZ7: 吉致 | BA7: 是 | BF7: A成都 | BG7: 华阳直营店 | BH7: 钟涛 | BI7: LB37822Z7TB041979
B8: 邛崃直营店 | F8: =IF(C8<>0,IF(D8/C8>110%,110%,D8/C8),0) -> 0 | H8: =D8*F8*G8+E8*G8 -> 0 | L8: =IF(I8<>0,IF(J8/I8>110%,110%,J8/I8),0) -> 0 | N8: =L8*M8*J8+K8*M8 -> 0 | O8: =H8+N8 -> 0 | P8: =V18 -> 0 | Q8: =2500 -> 2500 | R8: =SUM(O8:Q8)+V8 -> 2500 | AP8: 濮寿邦 | AT8: 60吉致(安心宝) | AY8: 星越L | AZ8: 吉致 | BA8: 是 | BF8: A成都 | BG8: 崇州直营店 | BH8: 朱剑波 | BI8: LB37852ZXTS027950
B9: 合计 | C9: =SUM(C3:C8) -> 0 | D9: =SUM(D3:D8) -> 0 | E9: =SUM(E3:E8) -> 0 | I9: =SUM(I3:I8) -> 0 | J9: =SUM(J3:J8) -> 0 | O9: =SUM(O3:O8) -> 0 | P9: =SUM(P3:P8) -> 0 | Q9: =SUM(Q3:Q8) -> 13250 | R9: =SUM(R3:R8) -> 13250 | AP9: 何冉 | AT9: 60吉致(安心宝) | AY9: 豪越L | AZ9: 吉致 | BA9: 是 | BF9: A成都 | BG9: 崇州直营店 | BH9: 朱剑波 | BI9: L6T7922Z0TY871239
AP10: 唐庆 | AT10: 60吉致(安心宝) | AY10: 星越L | AZ10: 吉致 | BA10: 是 | BF10: A成都 | BG10: 华阳直营店 | BH10: 钟涛 | BI10: LB37852Z4TS040239
AP11: 黎智全 | AT11: 60吉致(9.58%标贷) | AY11: 豪越L | AZ11: 吉致 | BA11: 否 | BF11: A成都 | BG11: 彭州直营店 | BH11: 黎明朗 | BI11: L6T7922Z3SY852750
B12: 店别 | C12: 展厅按提台次 | D12: 展厅实际销售台次 | E12: 渠道按提台次 | F12: 渠道实际销售台次 | G12: 展厅手续费实际金额 | H12: 展厅手续费标准金额（考核标准） | I12: 渠道手续费实际金额 | J12: 渠道手续费标准金额（考核标准） | K12: 爱车保毛利 | L12: 爱车保毛利标准 | M12: 上户费合计（扣出库）实际 | N12: 上户费合计（扣出库）标准 | O12: 整车超权限 | P12: 实际附加收入 | Q12: 标准附加收入 | R12: 差异 | S12: 盈利性渗透率 | T12: 盈利性渗透率 | U12: 盈利性提成金额 | V12: 新工资标准 | AP12: 罗新华 | AT12: 60吉致(安心宝) | AY12: 第四代博越L | AZ12: 吉致 | BA12: 是 | BF12: A成都 | BG12: 华阳直营店 | BH12: 钟涛 | BI12: LB37822Z4TB044774
A13: 朱剑波 | B13: 崇州直营店 | D13: =D3 -> 0 | F13: =J3 -> 0 | H13: =D13*0.55*283 -> 0 | J13: =F13*0.3*170 -> 0 | L13: =D13*0.3*1085 -> 0 | N13: =D13*552*1.06 -> 0 | P13: =G13+I13+K13+M13+O13 -> 0 | Q13: =H13+J13+L13+N13 -> 0 | R13: =P13-Q13 -> 0 | U13: =IF(D13>0,ROUND((IF(T13/S13>110%,SUMIF(BH:BH,A13,BJ:BJ)*110%,SUMIF(BH:BH,A13,BJ:BJ)*(T13/S13))),2),0) -> 0 | V13: =IF(R13<=0,(P13+R13)*0.05,P13*0.05)+U13 -> 0 | W13: =P13-Q13 -> 0 | AP13: 张志友 | AT13: 60吉致(安心宝) | AY13: 星瑞(1.5T) | AZ13: 吉致 | BA13: 是 | BF13: A成都 | BG13: 彭州直营店 | BH13: 黎明朗 | BI13: L6T7924Z9TD052802
A14: 孙伟 | B14: 大邑直营店 | D14: =D4 -> 0 | F14: =J4 -> 0 | H14: =D14*0.55*283 -> 0 | J14: =F14*0.3*170 -> 0 | L14: =D14*0.3*1085 -> 0 | N14: =D14*552*1.06 -> 0 | P14: =G14+I14+K14+M14+O14 -> 0 | Q14: =H14+J14+L14+N14 -> 0 | R14: =P14-Q14 -> 0 | U14: =IF(D14>0,ROUND((IF(T14/S14>110%,SUMIF(BH:BH,A14,BJ:BJ)*110%,SUMIF(BH:BH,A14,BJ:BJ)*(T14/S14))),2),0) -> 0 | V14: =IF(R14<=0,(P14+R14)*0.05,P14*0.05)+U14 -> 0 | W14: =P14-Q14 -> 0 | AP14: 陈静 | AT14: 60吉致(安心宝) | AY14: 星瑞(1.5T) | AZ14: 吉致 | BA14: 是 | BF14: A成都 | BG14: 邛崃直营店 | BH14: 吴思超 | BI14: L6T7924Z3TD056019
A15: 钟涛 | B15: 华阳直营店 | D15: =D5 -> 0 | F15: =J5 -> 0 | H15: =D15*0.55*283 -> 0 | J15: =F15*0.3*170 -> 0 | L15: =D15*0.3*1085 -> 0 | N15: =D15*552*1.06 -> 0 | P15: =G15+I15+K15+M15+O15 -> 0 | Q15: =H15+J15+L15+N15 -> 0 | R15: =P15-Q15 -> 0 | U15: =IF(D15>0,ROUND((IF(T15/S15>110%,SUMIF(BH:BH,A15,BJ:BJ)*110%,SUMIF(BH:BH,A15,BJ:BJ)*(T15/S15))),2),0) -> 0 | V15: =IF(R15<=0,(P15+R15)*0.05,P15*0.05)+U15 -> 0 | W15: =P15-Q15 -> 0
B16: 华阳领克 | D16: =D6 -> 0 | F16: =J6 -> 0 | H16: =D16*0.55*283 -> 0 | J16: =F16*0.3*170 -> 0 | L16: =D16*0.3*1085 -> 0 | N16: =D16*552*1.06 -> 0 | P16: =G16+I16+K16+M16+O16 -> 0 | Q16: =H16+J16+L16+N16 -> 0 | U16: =IF(D16>0,ROUND((IF(T16/S16>110%,SUMIF(BH:BH,A16,BJ:BJ)*110%,SUMIF(BH:BH,A16,BJ:BJ)*(T16/S16))),2),0) -> 0 | V16: =IF(R16<=0,(P16+R16)*0.05,P16*0.05)+U16 -> 0 | W16: =P16-Q16 -> 0
A17: 黎明朗 | B17: 彭州直营店 | D17: =D7 -> 0 | F17: =J7 -> 0 | H17: =D17*0.55*283 -> 0 | J17: =F17*0.3*170 -> 0 | L17: =D17*0.3*1085 -> 0 | N17: =D17*552*1.06 -> 0 | P17: =G17+I17+K17+M17+O17 -> 0 | Q17: =H17+J17+L17+N17 -> 0 | R17: =P17-Q17 -> 0 | U17: =IF(D17>0,ROUND((IF(T17/S17>110%,SUMIF(BH:BH,A17,BJ:BJ)*110%,SUMIF(BH:BH,A17,BJ:BJ)*(T17/S17))),2),0) -> 0 | V17: =IF(R17<=0,(P17+R17)*0.05,P17*0.05)+U17 -> 0 | W17: =P17-Q17 -> 0
A18: 吴思超 | B18: 邛崃直营店 | D18: =D8 -> 0 | F18: =J8 -> 0 | H18: =D18*0.55*283 -> 0 | J18: =F18*0.3*170 -> 0 | L18: =D18*0.3*1085 -> 0 | N18: =D18*552*1.06 -> 0 | P18: =G18+I18+K18+M18+O18 -> 0 | Q18: =H18+J18+L18+N18 -> 0 | R18: =P18-Q18 -> 0 | U18: =IF(D18>0,ROUND((IF(T18/S18>110%,SUMIF(BH:BH,A18,BJ:BJ)*110%,SUMIF(BH:BH,A18,BJ:BJ)*(T18/S18))),2),0) -> 0 | V18: =IF(R18<=0,(P18+R18)*0.05,P18*0.05)+U18 -> 0 | W18: =P18-Q18 -> 0
B19: 合计 | C19: =SUM(C13:C18) -> 0 | D19: =SUM(D13:D18) -> 0 | E19: =SUM(E13:E18) -> 0 | F19: =SUM(F13:F18) -> 0 | G19: =SUM(G13:G18) -> 0 | H19: =SUM(H13:H18) -> 0 | I19: =SUM(I13:I18) -> 0 | J19: =SUM(J13:J18) -> 0 | ... O19: =SUM(O13:O18) -> 0 | P19: =G19+I19+K19+M19+O19 -> 0 | Q19: =H19+J19+L19+N19 -> 0 | R19: =SUM(R13:R18) -> 0 | U19: =SUM(U13:U18) -> 0 | V19: =SUM(V13:V18) -> 0 | W19: =SUM(W13:W18) -> 0 | X19: =SUM(X13:X18) -> 0
X20: =IF(V20<=0,(R20+V20)*0.05,R20*0.05) -> 0

Sheet 招聘
A2: 2026年05月招聘报表
A3: 序号 | B3: 日期 | C3: 公司 | D3: 邀约岗位 | E3: 面试者姓名 | F3: 电话 | G3: 部门面试官 | H3: 面试结果 | I3: 预计到岗时间 | J3: 实际到岗时间 | K3: 人数 | L3: 稳岗情况（在岗） | M3: 稳岗情况（离职） | N3: 备注 | O3: 备注 | Q3: 姓名 | R3: 5月岗位需求 | S3: 5月招聘到岗数 | T3: 招聘提成 | U3: 提成金额 | V3: 分配 | W3: 提成金额
B4: 2026.5.10 | C4: 吉利超市 | D4: 续保专员 | E4: 刘尧梅 | G4: 黄意轩 | H4: 建议试用 | Q4: 周小红 | U4: =S4*T4 -> 0 | W4: =$U$4*V4 -> 0
B5: 2026.5.10 | C5: 吉利超市 | D5: 续保专员 | E5: 冯桢 | G5: 黄意轩 | H5: 建议试用 | Q5: 何婷婷 | W5: =$U$4*V5 -> 0
B6: 2026.4.26 | C6: 西物星瑞 | D6: 展厅顾问 | E6: 梁泽煦 | G6: 安洋 | H6: 建议试用 | Q6: 李玲 | W6: =$U$4*V6 -> 0
B7: 2026.5.19 | C7: 成都健行 | D7: 会计助理 | E7: 刘文清 | G7: 刘靖 | H7: 建议试用 | Q7: 刘晓琴 | W7: =$U$4*V7 -> 0
B8: 2026.5.10 | C8: 成都极客 | D8: 机电技师 | E8: 张健涛 | G8: 徐炳涛 | H8: 建议试用 | Q8: 岗位需求 | R8: 需求 | S8: 到岗 | T8: 离职
B9: 2026.5.6 | C9: 成都极客 | D9: 机电技师 | E9: 易佳乐 | F9: 15328215121 | G9: 徐炳涛 | H9: 建议试用 | P9: 武侯售后 | Q9: 续保 | U9: 现有岗位转郫都店补编
B10: 2026.4.30 | C10: 西物精锐 | D10: 展厅顾问 | E10: 张京川 | G10: 刘虹呈 | H10: 建议试用 | P10: 武侯售后 | Q10: 事故接待
B11: 2026.5.1 | C11: 成都健行 | D11: 会计助理 | E11: 淳厚舒 | G11: 刘靖 | H11: 建议试用 | P11: 武侯售后 | Q11: 机电技师
B12: 2026.4.30 | C12: 吉利超市 | D12: 续保专员 | E12: 孙茂梅 | G12: 黄意轩 | H12: 建议试用 | P12: 武侯售后 | Q12: PDI
B13: 2026.5.1 | C13: 吉利超市 | D13: 续保专员 | E13: 王丹 | G13: 黄意轩 | H13: 建议试用 | P13: 超市银河 | Q13: 销售顾问
B14: 2026.5.1 | C14: 成都极客 | D14: 机电技师 | E14: 魏世玉 | G14: 徐炳涛 | H14: 建议试用 | P14: 西物汽车 | Q14: 销售顾问
P15: 西物银河 | Q15: 汽车销售
P16: 西物精锐 | Q16: 汽车销售
P17: 西物精锐 | Q17: 邀约专员
P18: 市场中心 | Q18: 企划
P19: 机场售后 | Q19: 机电技工
P20: 机场售后 | Q20: 服务顾问
P21: 极客 | Q21: 维修技师
P22: 新媒体 | Q22: 主播
P23: 超市 | Q23: 邀约专员
P24: 直营店 | Q24: 销售顾问 | T24: =SUM(T9:T23) -> 0 | U24: =SUM(U9:U23) -> 0 | V24: =SUM(V9:V23) -> 0 | W24: =SUM(W9:W23) -> 0
P25: 西物银河 | Q25: 邀约专员 | T25: =SUM(T9:T24) -> 0
P26: 机场售后 | Q26: 事故接待
P27: 超市吉星 | Q27: 销售顾问 | T27: =SUM(T9:T26) -> 0 | U27: =SUM(U9:U26) -> 0 | V27: =SUM(V9:V26) -> 0 | W27: =SUM(W9:W26) -> 0
P28: 超市吉星 | Q28: 客户专员
P29: 西物星瑞 | Q29: 客户专员
P30: 西物星瑞 | Q30: 销售顾问
P31: 西物星瑞 | Q31: 会计
P32: 西物星瑞 | Q32: 试驾专员
P33: 西物精锐 | Q33: 试驾专员
K34: =SUM(K4:K33) -> 0 | L34: =SUM(L4:L33) -> 0 | M34: =SUM(M4:M33) -> 0 | P34: 健行 | Q34: 会计
M35: =SUM(M4:M34) -> 0 | P35: 西物极客 | Q35: 服务顾问
P36: 西物极客 | Q36: 机电
P37: 健行 | Q37: 销售顾问
R38: =SUM(R9:R37) -> 0 | S38: =SUBTOTAL(9,S9:S37) -> 0

Sheet 综合表
AG1: 武侯店 | AH1: 销售顾问 | AI1: 盈利性产品 | AL1: 渗透率考核 | AO1: 培训考核 | AQ1: 备注
AI2: 任务目标 | AJ2: 完成情况 | AK2: 考核 | AL2: 渗透率 | AM2: 盈利性占比 | AN2: 盈利性产品考核 | AO2: 考试成绩 | AP2: 绩效标准 | AQ2: 实习员工不作考核
A3: 04月 | AG3: 展厅 | AH3: 马攀 | AK3: =IF((AJ3-AI3)>=0,0,IF(AJ3=1,-200,-400)) -> 0 | AN3: =IF(AL3>=0.67,1.1,IF(AL3>=0.6,1,IF(AL3>=0.45,0.9,0.8))) -> 0.8 | AR3: =INDEX(B:B,MATCH(AH3,B:B,0)) -> #N/A
A4: 序号 | B4: 姓名 | C4: 保险及实习员工 | D4: 考核 | E4: 吉致长期考核+培训考核 | F4: 管理考核及特殊车型考核 | G4: 直营店店总盈利性产品考核 | H4: 其它 | I4: 其它 | J4: 安心保(已发并税）+重功+订单+上门服务+转介绍 | L4: 绩效考核进入工资 | AH4: 易花贞子 | AK4: =IF((AJ4-AI4)>=0,0,IF(AJ4=1,-200,-400)) -> 0 | AN4: =IF(AL4>=0.67,1.1,IF(AL4>=0.6,1,IF(AL4>=0.45,0.9,0.8))) -> 0.8 | AR4: =INDEX(B:B,MATCH(AH4,B:B,0)) -> #N/A | BG4: 张永强绩效
E5: =SUMIF(AH:AH,B5,AK:AK) -> 0 | L5: =SUM(C5:K5)-SUM(J5:K5) -> 0 | N5: =INDEX(AK:AK,MATCH(B5,AH:AH,0))-E5 -> #N/A | AH5: 毛春秀 | AK5: =IF((AJ5-AI5)>=0,0,IF(AJ5=1,-200,-400)) -> 0 | AN5: =IF(AL5>=0.67,1.1,IF(AL5>=0.6,1,IF(AL5>=0.45,0.9,0.8))) -> 0.8 | AR5: =INDEX(B:B,MATCH(AH5,B:B,0)) -> #N/A | BH5: 燃油车销量 | BI5: 新能源销量
E6: =SUMIF(AH:AH,B6,AK:AK) -> 0 | L6: =SUM(C6:K6)-SUM(J6:K6) -> 0 | N6: =INDEX(AK:AK,MATCH(B6,AH:AH,0))-E6 -> #N/A | AH6: 廖晓军 | AK6: =IF((AJ6-AI6)>=0,0,IF(AJ6=1,-200,-400)) -> 0 | AN6: =IF(AL6>=0.67,1.1,IF(AL6>=0.6,1,IF(AL6>=0.45,0.9,0.8))) -> 0.8 | AR6: =INDEX(B:B,MATCH(AH6,B:B,0)) -> #N/A | BG6: 大邑直营店
E7: =SUMIF(AH:AH,B7,AK:AK) -> 0 | L7: =SUM(C7:K7)-SUM(J7:K7) -> 0 | N7: =INDEX(AK:AK,MATCH(B7,AH:AH,0))-E7 -> #N/A | AH7: 康鳞波 | AK7: =IF((AJ7-AI7)>=0,0,IF(AJ7=1,-200,-400)) -> 0 | AN7: =IF(AL7>=0.67,1.1,IF(AL7>=0.6,1,IF(AL7>=0.45,0.9,0.8))) -> 0.8 | AR7: =INDEX(B:B,MATCH(AH7,B:B,0)) -> #N/A | BG7: 华阳直营店
E8: =SUMIF(AH:AH,B8,AK:AK) -> 0 | L8: =SUM(C8:K8)-SUM(J8:K8) -> 0 | N8: =INDEX(AK:AK,MATCH(B8,AH:AH,0))-E8 -> #N/A | AH8: 代力 | AK8: =IF((AJ8-AI8)>=0,0,IF(AJ8=1,-200,-400)) -> 0 | AN8: =IF(AL8>=0.67,1.1,IF(AL8>=0.6,1,IF(AL8>=0.45,0.9,0.8))) -> 0.8 | AR8: =INDEX(B:B,MATCH(AH8,B:B,0)) -> #N/A | BG8: 崇州直营店
E9: =SUMIF(AH:AH,B9,AK:AK) -> 0 | L9: =SUM(C9:K9)-SUM(J9:K9) -> 0 | N9: =INDEX(AK:AK,MATCH(B9,AH:AH,0))-E9 -> #N/A | AH9: 熊杰文 | AK9: =IF((AJ9-AI9)>=0,0,IF(AJ9=1,-200,-400)) -> 0 | AN9: =IF(AL9>=0.67,1.1,IF(AL9>=0.6,1,IF(AL9>=0.45,0.9,0.8))) -> 0.8 | AR9: =INDEX(B:B,MATCH(AH9,B:B,0)) -> #N/A | AT9: 2026年04吉利超市售后吧台提成工资明细表 | BG9: 邛崃直营店
E10: =SUMIF(AH:AH,B10,AK:AK) -> 0 | L10: =SUM(C10:K10)-SUM(J10:K10) -> 0 | N10: =INDEX(AK:AK,MATCH(B10,AH:AH,0))-E10 -> #N/A | R10: 2021年4月起市场部薪酬 | V10: 05月绩效核算 | AH10: 黄利君 | AK10: =IF((AJ10-AI10)>=0,0,IF(AJ10=1,-200,-400)) -> 0 | AN10: =IF(AL10>=0.67,1.1,IF(AL10>=0.6,1,IF(AL10>=0.45,0.9,0.8))) -> 0.8 | AR10: =INDEX(B:B,MATCH(AH10,B:B,0)) -> #N/A | AS10: 人数 | AT10: 04月吧台月均营业额 | AU10: 系数 | AV10: 提成金额 | AW10: 2026年04月售后台次 | AX10: 单台比例 | AY10: 提成金额 | AZ10: 固定绩效 | BA10: 考核+其它 | BB10: 分配比例 | BC10: 浮动绩效分配金额 | BD10: 月度薪资合计 | BE10: 出勤天数 | BG10: 彭州直营店
E11: =SUMIF(AH:AH,B11,AK:AK) -> 0 | L11: =SUM(C11:K11)-SUM(J11:K11) -> 0 | N11: =INDEX(AK:AK,MATCH(B11,AH:AH,0))-E11 -> #N/A | P11: 员工 | Q11: 岗位 | R11: 基本工资 | S11: 加班工资 | T11: 考核绩效 | U11: 单台标准 | V11: 提成金额 | W11: 考核绩效 | X11: 销量绩效 | Y11: 其它 | Z11: 绩效总额 | AA11: 当月薪酬总额 | AB11: 人力归属 | AC11: 备注 | AR11: =INDEX(B:B,MATCH(AH11,B:B,0)) -> #N/A | AS11: 白影 | AV11: =AU11*AT11 -> 0 | AY11: =AW11*AX11 -> 0 | BC11: =($AV$11+$AY$11)*BB11 -> 0 | BG11: 新都直营店
E12: =SUMIF(AH:AH,B12,AK:AK) -> 0 | L12: =SUM(C12:K12)-SUM(J12:K12) -> 0 | N12: =INDEX(AK:AK,MATCH(B12,AH:AH,0))-E12 -> #N/A | P12: 谭艳 | Q12: 企划经理 | Z12: =SUM(W12:Y12) -> 0 | AA12: =Z12+R12+S12 -> 0 | AB12: 西物 | AR12: =INDEX(B:B,MATCH(AH12,B:B,0)) -> #N/A | AS12: 曹青 | BC12: =($AV$11+$AY$11)*BB12 -> 0 | BG12: 金堂直营店
E13: =SUMIF(AH:AH,B13,AK:AK) -> 0 | L13: =SUM(C13:K13)-SUM(J13:K13) -> 0 | N13: =INDEX(AK:AK,MATCH(B13,AH:AH,0))-E13 -> #N/A | P13: 孙舒琪 | Q13: 设计专员 | X13: =V13*U13 -> 0 | Z13: =SUM(W13:Y13) -> 0 | AA13: =Z13+R13+S13 -> 0 | AB13: 明睿 | AR13: =INDEX(B:B,MATCH(AH13,B:B,0)) -> #N/A | AS13: 朱开莲 | BC13: =($AV$11+$AY$11)*BB13 -> 0 | BG13: 合计 | BH13: =SUM(BH6:BH12) -> 0 | BI13: =SUM(BI6:BI12) -> 0
E14: =SUMIF(AH:AH,B14,AK:AK) -> 0 | L14: =SUM(C14:K14)-SUM(J14:K14) -> 0 | N14: =INDEX(AK:AK,MATCH(B14,AH:AH,0))-E14 -> #N/A | AR14: =INDEX(B:B,MATCH(AH14,B:B,0)) -> #N/A | AS14: 谢槟羽 | BC14: =($AV$11+$AY$11)*BB14 -> 0
E15: =SUMIF(AH:AH,B15,AK:AK) -> 0 | L15: =SUM(C15:K15)-SUM(J15:K15) -> 0 | N15: =INDEX(AK:AK,MATCH(B15,AH:AH,0))-E15 -> #N/A | P15: 黄思露 | Q15: 核销专员 | X15: =V15*U15 -> 0 | Z15: =SUM(W15:Y15) -> 0 | AA15: =Z15+R15+S15 -> 0 | AB15: 豪明 | AH15: 小计 | AI15: =SUM(AI3:AI14) -> 0 | AJ15: =SUM(AJ3:AJ14) -> 0 | AK15: =SUM(AK3:AK14) -> 0 | AN15: - | AO15: =SUM(AO3:AO14)/13 -> 0 | AP15: - | AR15: =INDEX(B:B,MATCH(AH15,B:B,0)) -> #N/A | AS15: 陶纯玲 | BC15: =($AV$11+$AY$11)*BB15 -> 0
E16: =SUMIF(AH:AH,B16,AK:AK) -> 0 | L16: =SUM(C16:K16)-SUM(J16:K16) -> 0 | N16: =INDEX(AK:AK,MATCH(B16,AH:AH,0))-E16 -> #N/A | P16: 赵若贝 | Q16: 设计专员 | X16: =V16*U16 -> 0 | Z16: =SUM(W16:Y16) -> 0 | AA16: =Z16+R16+S16 -> 0 | AB16: 超市 | AG16: 网销 | AH16: 母勇 | AK16: =IF((AJ16-AI16)>=0,0,IF(AJ16=1,-200,-400)) -> 0 | AN16: =IF(AL16>=0.67,1.1,IF(AL16>=0.6,1,IF(AL16>=0.45,0.9,0.8))) -> 0.8 | AR16: =INDEX(B:B,MATCH(AH16,B:B,0)) -> #N/A
E17: =SUMIF(AH:AH,B17,AK:AK) -> 0 | L17: =SUM(C17:K17)-SUM(J17:K17) -> 0 | N17: =INDEX(AK:AK,MATCH(B17,AH:AH,0))-E17 -> #N/A | P17: 杨兰 | Q17: 企划专员 | X17: =V17*U17 -> 0 | Z17: =SUM(W17:Y17) -> 0 | AA17: =Z17+R17+S17 -> 0 | AB17: 超市 | AH17: 蒲喜 | AK17: =IF((AJ17-AI17)>=0,0,IF(AJ17=1,-200,-400)) -> 0 | AN17: =IF(AL17>=0.67,1.1,IF(AL17>=0.6,1,IF(AL17>=0.45,0.9,0.8))) -> 0.8 | AR17: =INDEX(B:B,MATCH(AH17,B:B,0)) -> #N/A | AS17: 合计 | AT17: =SUM(AT11:AT16) -> 0 | AU17: =SUM(AU11:AU16) -> 0 | AV17: =SUM(AV11:AV16) -> 0 | AW17: =SUM(AW11:AW16) -> 0 | AX17: =SUM(AX11:AX16) -> 0 | AY17: =SUM(AY11:AY16) -> 0 | AZ17: =SUM(AZ11:AZ16) -> 0 | BA17: =SUM(BA11:BA16) -> 0 | ... BE17: =SUM(BE11:BE16) -> 0 | BJ17: =BH17/BI17 -> #DIV/0!
E18: =SUMIF(AH:AH,B18,AK:AK) -> 0 | L18: =SUM(C18:K18)-SUM(J18:K18) -> 0 | N18: =INDEX(AK:AK,MATCH(B18,AH:AH,0))-E18 -> #N/A | P18: 史浩栋 | Q18: 设计专员 | X18: =V18*U18 -> 0 | Z18: =SUM(W18:Y18) -> 0 | AA18: =Z18+R18+S18 -> 0 | AB18: 豪明 | AC18: 9月晋升主管 | AH18: 何伟 | AK18: =IF((AJ18-AI18)>=0,0,IF(AJ18=1,-200,-400)) -> 0 | AN18: =IF(AL18>=0.67,1.1,IF(AL18>=0.6,1,IF(AL18>=0.45,0.9,0.8))) -> 0.8 | AR18: =INDEX(B:B,MATCH(AH18,B:B,0)) -> #N/A | BJ18: =BH18/BI18 -> #DIV/0!
E19: =SUMIF(AH:AH,B19,AK:AK) -> 0 | L19: =SUM(C19:K19)-SUM(J19:K19) -> 0 | N19: =INDEX(AK:AK,MATCH(B19,AH:AH,0))-E19 -> #N/A | P19: 孙小慧 | Q19: 核销专员 | X19: =V19*U19 -> 0 | Z19: =SUM(W19:Y19) -> 0 | AA19: =Z19+R19+S19 -> 0 | AB19: 明睿 | AC19: 9月晋升主管 | AH19: 何宇 | AK19: =IF((AJ19-AI19)>=0,0,IF(AJ19=1,-200,-400)) -> 0 | AN19: =IF(AL19>=0.67,1.1,IF(AL19>=0.6,1,IF(AL19>=0.45,0.9,0.8))) -> 0.8 | AR19: =INDEX(B:B,MATCH(AH19,B:B,0)) -> #N/A | BH19: 基础工资 | BI19: 加班工资 | BJ19: 考核绩效 | BK19: 业绩绩效 | BL19: 月均 | BM19: 单台奖
E20: =SUMIF(AH:AH,B20,AK:AK) -> 0 | L20: =SUM(C20:K20)-SUM(J20:K20) -> 0 | N20: =INDEX(AK:AK,MATCH(B20,AH:AH,0))-E20 -> #N/A | P20: 陈子茜 | Q20: 核销专员 | Z20: =SUM(W20:Y20) -> 0 | AA20: =Z20+R20+S20 -> 0 | AB20: 星瑞 | AH20: 唐操 | AK20: =IF((AJ20-AI20)>=0,0,IF(AJ20=1,-200,-400)) -> 0 | AN20: =IF(AL20>=0.67,1.1,IF(AL20>=0.6,1,IF(AL20>=0.45,0.9,0.8))) -> 0.8 | AR20: =INDEX(B:B,MATCH(AH20,B:B,0)) -> #N/A | BN20: =BK20/BL20 -> #DIV/0!
E21: =SUMIF(AH:AH,B21,AK:AK) -> 0 | L21: =SUM(C21:K21)-SUM(J21:K21) -> 0 | N21: =INDEX(AK:AK,MATCH(B21,AH:AH,0))-E21 -> #N/A | P21: 李中婷 | Q21: 设计专员 | Z21: =SUM(W21:Y21) -> 0 | AA21: =Z21+R21+S21 -> 0 | AB21: 明睿银河 | AH21: 刘飞 | AK21: =IF((AJ21-AI21)>=0,0,IF(AJ21=1,-200,-400)) -> 0 | AN21: =IF(AL21>=0.67,1.1,IF(AL21>=0.6,1,IF(AL21>=0.45,0.9,0.8))) -> 0.8 | AR21: =INDEX(B:B,MATCH(AH21,B:B,0)) -> #N/A | BK21: =BJ18-BJ21-BI21-BH21 -> #DIV/0! | BN21: =BK21/BL21 -> #DIV/0!
E22: =SUMIF(AH:AH,B22,AK:AK) -> 0 | L22: =SUM(C22:K22)-SUM(J22:K22) -> 0 | N22: =INDEX(AK:AK,MATCH(B22,AH:AH,0))-E22 -> #N/A | Q22: 设计专员 | AB22: 西物银河 | AH22: 王泳文 | AK22: =IF((AJ22-AI22)>=0,0,IF(AJ22=1,-200,-400)) -> 0 | AN22: =IF(AL22>=0.67,1.1,IF(AL22>=0.6,1,IF(AL22>=0.45,0.9,0.8))) -> 0.8 | AR22: =INDEX(B:B,MATCH(AH22,B:B,0)) -> #N/A | BK22: =BL21*13 -> 0 | BL22: =BH22+BI22+BJ22+BK22 -> 0 | BM22: =290*12*2 -> 6960 | BN22: =BL22*12 -> 0 | BO22: =BM22+BN22 -> 6960
E23: =SUMIF(AH:AH,B23,AK:AK) -> 0 | L23: =SUM(C23:K23)-SUM(J23:K23) -> 0 | N23: =INDEX(AK:AK,MATCH(B23,AH:AH,0))-E23 -> #N/A | P23: 蔡利君 | Q23: 企划专员 | W23: =T23 -> 0 | X23: =V23*U23 -> 0 | Z23: =SUM(W23:Y23) -> 0 | AA23: =Z23+R23+S23 -> 0 | AB23: 慧民 | AC23: 1月29日入职 | AH23: 雷卓远 | AK23: =IF((AJ23-AI23)>=0,0,IF(AJ23=1,-200,-400)) -> 0 | AN23: =IF(AL23>=0.67,1.1,IF(AL23>=0.6,1,IF(AL23>=0.45,0.9,0.8))) -> 0.8 | AR23: =INDEX(B:B,MATCH(AH23,B:B,0)) -> #N/A | BG23: 4000/考核 | BH23: 场次目标量 | BI23: 内训效果 | BJ23: 内训总结 | BK23: 总经理自调项目 | BL23: 合计 | BM23: 绩效 | BN23: 销量绩效
E24: =SUMIF(AH:AH,B24,AK:AK) -> 0 | L24: =SUM(C24:K24)-SUM(J24:K24) -> 0 | N24: =INDEX(AK:AK,MATCH(B24,AH:AH,0))-E24 -> #N/A | AH24: 何剑 | AK24: =IF((AJ24-AI24)>=0,0,IF(AJ24=1,-200,-400)) -> 0 | AN24: =IF(AL24>=0.67,1.1,IF(AL24>=0.6,1,IF(AL24>=0.45,0.9,0.8))) -> 0.8 | AR24: =INDEX(B:B,MATCH(AH24,B:B,0)) -> #N/A | BG24: 考核权重
E25: =SUMIF(AH:AH,B25,AK:AK) -> 0 | L25: =SUM(C25:K25)-SUM(J25:K25) -> 0 | N25: =INDEX(AK:AK,MATCH(B25,AH:AH,0))-E25 -> #N/A | AR25: =INDEX(B:B,MATCH(AH25,B:B,0)) -> #N/A | AS25: 合计 | BG25: 考核标准 | BH25: 按达成率 | BI25: 按达成率 | BJ25: 按达成率 | BK25: 按达成率 | BL25: 按达成率 | BM25: 按达成率 | BN25: 台次
E26: =SUMIF(AH:AH,B26,AK:AK) -> 0 | L26: =SUM(C26:K26)-SUM(J26:K26) -> 0 | N26: =INDEX(AK:AK,MATCH(B26,AH:AH,0))-E26 -> #N/A | AR26: =INDEX(B:B,MATCH(AH26,B:B,0)) -> #N/A | BG26: 目标 （《月度经营设线目标》） | BL26: / | BM26: / | BN26: /
E27: =SUMIF(AH:AH,B27,AK:AK) -> 0 | L27: =SUM(C27:K27)-SUM(J27:K27) -> 0 | N27: =INDEX(AK:AK,MATCH(B27,AH:AH,0))-E27 -> #N/A | AH27: 小计 | AI27: =SUM(AI16:AI26) -> 0 | AJ27: =SUM(AJ16:AJ26) -> 0 | AK27: =SUM(AK16:AK23) -> 0 | AN27: - | AO27: =SUM(AO16:AO24)/11 -> 0 | AP27: - | AR27: =INDEX(B:B,MATCH(AH27,B:B,0)) -> #N/A | BG27: 实绩 （当月实际达成） | BL27: / | BM27: / | BN27: /
E28: =SUMIF(AH:AH,B28,AK:AK) -> 0 | L28: =SUM(C28:K28)-SUM(J28:K28) -> 0 | N28: =INDEX(AK:AK,MATCH(B28,AH:AH,0))-E28 -> #N/A | AG28: 武侯店合计 | AI28: =AI15+AI27 -> 0 | AJ28: =AJ15+AJ27 -> 0 | AK28: =AK15+AK27 -> 0 | AL28: - | AO28: =(SUM(AO3:AO14)+SUM(AO16:AO24))/24 -> 0 | AP28: - | AR28: =INDEX(B:B,MATCH(AH28,B:B,0)) -> #N/A | BG28: 达成率 （实绩/目标，参考考核标准） | BH28: =IF(BH27>0,BH27/BH26,0) -> 0 | BI28: =IF(BI27>0,BI27/BI26,0) -> 0 | BJ28: =IF(BJ27>0,BJ27/BJ26,0) -> 0 | BK28: =IF(BK27>0,BK27/BK26,0) -> 0 | BL28: / | BM28: /
E29: =SUMIF(AH:AH,B29,AK:AK) -> 0 | L29: =SUM(C29:K29)-SUM(J29:K29) -> 0 | N29: =INDEX(AK:AK,MATCH(B29,AH:AH,0))-E29 -> #N/A | AR29: =INDEX(B:B,MATCH(AH29,B:B,0)) -> #N/A | BG29: 考核得分 （考核分值*达成率） | BH29: =IF(BH28>=100%,BH24*100%,BH24*BH28) -> 0 | BI29: =IF(BI28>=100%,BI24*100%,BI24*BI28) -> 0 | BJ29: =IF(BJ28>=100%,BJ24*100%,BJ24*BJ28) -> 0 | BK29: =IF(BK28>=100%,BK24*100%,BK24*BK28) -> 0 | BL29: =SUM(BH29:BK29) -> 0 | BM29: =BM24*BL29 -> 0 | BN29: =BN28*BN24 -> 0
E30: =SUMIF(AH:AH,B30,AK:AK) -> 0 | L30: =SUM(C30:K30)-SUM(J30:K30) -> 0 | N30: =INDEX(AK:AK,MATCH(B30,AH:AH,0))-E30 -> #N/A | AG30: 机场店 | AH30: 销售顾问 | AI30: 盈利性产品 | AL30: 渗透率考核 | AO30: 培训考核 | AR30: =INDEX(B:B,MATCH(AH30,B:B,0)) -> #N/A
E31: =SUMIF(AH:AH,B31,AK:AK) -> 0 | L31: =SUM(C31:K31)-SUM(J31:K31) -> 0 | N31: =INDEX(AK:AK,MATCH(B31,AH:AH,0))-E31 -> #N/A | AI31: 任务目标 | AJ31: 完成情况 | AK31: 考核 | AL31: 渗透率 | AM31: 盈利性占比 | AN31: 盈利性产品考核 | AO31: 考试成绩 | AP31: 绩效标准 | AR31: =INDEX(B:B,MATCH(AH31,B:B,0)) -> #N/A
E32: =SUMIF(AH:AH,B32,AK:AK) -> 0 | L32: =SUM(C32:K32)-SUM(J32:K32) -> 0 | N32: =INDEX(AK:AK,MATCH(B32,AH:AH,0))-E32 -> #N/A | AG32: 展厅 | AH32: 邓戈 | AK32: =IF((AJ32-AI32)>=0,0,IF(AJ32=1,-200,-400)) -> 0 | AN32: =IF(AL32>=0.67,1.1,IF(AL32>=0.6,1,IF(AL32>=0.45,0.9,0.8))) -> 0.8 | AR32: =INDEX(B:B,MATCH(AH32,B:B,0)) -> #N/A
E33: =SUMIF(AH:AH,B33,AK:AK) -> 0 | L33: =SUM(C33:K33)-SUM(J33:K33) -> 0 | N33: =INDEX(AK:AK,MATCH(B33,AH:AH,0))-E33 -> #N/A | AH33: 刘发 | AK33: =IF((AJ33-AI33)>=0,0,IF(AJ33=1,-200,-400)) -> 0 | AN33: =IF(AL33>=0.67,1.1,IF(AL33>=0.6,1,IF(AL33>=0.45,0.9,0.8))) -> 0.8 | AR33: =INDEX(B:B,MATCH(AH33,B:B,0)) -> #N/A
E34: =SUMIF(AH:AH,B34,AK:AK) -> 0 | L34: =SUM(C34:K34)-SUM(J34:K34) -> 0 | N34: =INDEX(AK:AK,MATCH(B34,AH:AH,0))-E34 -> #N/A | AH34: 黄军 | AK34: =IF((AJ34-AI34)>=0,0,IF(AJ34=1,-200,-400)) -> 0 | AN34: =IF(AL34>=0.67,1.1,IF(AL34>=0.6,1,IF(AL34>=0.45,0.9,0.8))) -> 0.8 | AR34: =INDEX(B:B,MATCH(AH34,B:B,0)) -> #N/A
E35: =SUMIF(AH:AH,B35,AK:AK) -> 0 | L35: =SUM(C35:K35)-SUM(J35:K35) -> 0 | N35: =INDEX(AK:AK,MATCH(B35,AH:AH,0))-E35 -> #N/A | AH35: 姚元利 | AK35: =IF((AJ35-AI35)>=0,0,IF(AJ35=1,-200,-400)) -> 0 | AN35: =IF(AL35>=0.67,1.1,IF(AL35>=0.6,1,IF(AL35>=0.45,0.9,0.8))) -> 0.8 | AR35: =INDEX(B:B,MATCH(AH35,B:B,0)) -> #N/A
E36: =SUMIF(AH:AH,B36,AK:AK) -> 0 | L36: =SUM(C36:K36)-SUM(J36:K36) -> 0 | N36: =INDEX(AK:AK,MATCH(B36,AH:AH,0))-E36 -> #N/A | AH36: 陈林 | AK36: =IF((AJ36-AI36)>=0,0,IF(AJ36=1,-200,-400)) -> 0 | AN36: =IF(AL36>=0.67,1.1,IF(AL36>=0.6,1,IF(AL36>=0.45,0.9,0.8))) -> 0.8 | AR36: =INDEX(B:B,MATCH(AH36,B:B,0)) -> #N/A
E37: =SUMIF(AH:AH,B37,AK:AK) -> 0 | L37: =SUM(C37:K37)-SUM(J37:K37) -> 0 | N37: =INDEX(AK:AK,MATCH(B37,AH:AH,0))-E37 -> #N/A | AH37: 冯超 | AK37: =IF((AJ37-AI37)>=0,0,IF(AJ37=1,-200,-400)) -> 0 | AN37: =IF(AL37>=0.67,1.1,IF(AL37>=0.6,1,IF(AL37>=0.45,0.9,0.8))) -> 0.8 | AR37: =INDEX(B:B,MATCH(AH37,B:B,0)) -> #N/A
E38: =SUMIF(AH:AH,B38,AK:AK) -> 0 | L38: =SUM(C38:K38)-SUM(J38:K38) -> 0 | N38: =INDEX(AK:AK,MATCH(B38,AH:AH,0))-E38 -> #N/A | AR38: =INDEX(B:B,MATCH(AH38,B:B,0)) -> #N/A
E39: =SUMIF(AH:AH,B39,AK:AK) -> 0 | L39: =SUM(C39:K39)-SUM(J39:K39) -> 0 | N39: =INDEX(AK:AK,MATCH(B39,AH:AH,0))-E39 -> #N/A | AR39: =INDEX(B:B,MATCH(AH39,B:B,0)) -> #N/A
E40: =SUMIF(AH:AH,B40,AK:AK) -> 0 | L40: =SUM(C40:K40)-SUM(J40:K40) -> 0 | N40: =INDEX(AK:AK,MATCH(B40,AH:AH,0))-E40 -> #N/A | AR40: =INDEX(B:B,MATCH(AH40,B:B,0)) -> #N/A
E41: =SUMIF(AH:AH,B41,AK:AK) -> 0 | L41: =SUM(C41:K41)-SUM(J41:K41) -> 0 | N41: =INDEX(AK:AK,MATCH(B41,AH:AH,0))-E41 -> #N/A | AH41: 小计 | AI41: =SUM(AI32:AI40) -> 0 | AJ41: =SUM(AJ32:AJ40) -> 0 | AK41: =SUM(AK32:AK40) -> 0 | AN41: - | AR41: =INDEX(B:B,MATCH(AH41,B:B,0)) -> #N/A
E42: =SUMIF(AH:AH,B42,AK:AK) -> 0 | L42: =SUM(C42:K42)-SUM(J42:K42) -> 0 | N42: =INDEX(AK:AK,MATCH(B42,AH:AH,0))-E42 -> #N/A | AG42: 网销 | AH42: 赵强 | AK42: =IF((AJ42-AI42)>=0,0,IF(AJ42=1,-200,-400)) -> 0 | AN42: =IF(AL42>=0.67,1.1,IF(AL42>=0.6,1,IF(AL42>=0.45,0.9,0.8))) -> 0.8 | AR42: =INDEX(B:B,MATCH(AH42,B:B,0)) -> #N/A
E43: =SUMIF(AH:AH,B43,AK:AK) -> 0 | L43: =SUM(C43:K43)-SUM(J43:K43) -> 0 | N43: =INDEX(AK:AK,MATCH(B43,AH:AH,0))-E43 -> #N/A | AH43: 黄婷婷 | AK43: =IF((AJ43-AI43)>=0,0,IF(AJ43=1,-200,-400)) -> 0 | AN43: =IF(AL43>=0.67,1.1,IF(AL43>=0.6,1,IF(AL43>=0.45,0.9,0.8))) -> 0.8 | AR43: =INDEX(B:B,MATCH(AH43,B:B,0)) -> #N/A
E44: =SUMIF(AH:AH,B44,AK:AK) -> 0 | L44: =SUM(C44:K44)-SUM(J44:K44) -> 0 | N44: =INDEX(AK:AK,MATCH(B44,AH:AH,0))-E44 -> #N/A | AH44: 刘波 | AK44: =IF((AJ44-AI44)>=0,0,IF(AJ44=1,-200,-400)) -> 0 | AN44: =IF(AL44>=0.67,1.1,IF(AL44>=0.6,1,IF(AL44>=0.45,0.9,0.8))) -> 0.8 | AR44: =INDEX(B:B,MATCH(AH44,B:B,0)) -> #N/A
E45: =SUMIF(AH:AH,B45,AK:AK) -> 0 | L45: =SUM(C45:K45)-SUM(J45:K45) -> 0 | N45: =INDEX(AK:AK,MATCH(B45,AH:AH,0))-E45 -> #N/A | AH45: 向兰 | AK45: =IF((AJ45-AI45)>=0,0,IF(AJ45=1,-200,-400)) -> 0 | AN45: =IF(AL45>=0.67,1.1,IF(AL45>=0.6,1,IF(AL45>=0.45,0.9,0.8))) -> 0.8 | AR45: =INDEX(B:B,MATCH(AH45,B:B,0)) -> #N/A
E46: =SUMIF(AH:AH,B46,AK:AK) -> 0 | L46: =SUM(C46:K46)-SUM(J46:K46) -> 0 | N46: =INDEX(AK:AK,MATCH(B46,AH:AH,0))-E46 -> #N/A | AH46: 熊俊杰 | AK46: =IF((AJ46-AI46)>=0,0,IF(AJ46=1,-200,-400)) -> 0 | AN46: =IF(AL46>=0.67,1.1,IF(AL46>=0.6,1,IF(AL46>=0.45,0.9,0.8))) -> 0.8 | AR46: =INDEX(B:B,MATCH(AH46,B:B,0)) -> #N/A
E47: =SUMIF(AH:AH,B47,AK:AK) -> 0 | L47: =SUM(C47:K47)-SUM(J47:K47) -> 0 | N47: =INDEX(AK:AK,MATCH(B47,AH:AH,0))-E47 -> #N/A | AH47: 莫晓何 | AK47: =IF((AJ47-AI47)>=0,0,IF(AJ47=1,-200,-400)) -> 0 | AN47: =IF(AL47>=0.67,1.1,IF(AL47>=0.6,1,IF(AL47>=0.45,0.9,0.8))) -> 0.8 | AR47: =INDEX(B:B,MATCH(AH47,B:B,0)) -> #N/A
E48: =SUMIF(AH:AH,B48,AK:AK) -> 0 | L48: =SUM(C48:K48)-SUM(J48:K48) -> 0 | N48: =INDEX(AK:AK,MATCH(B48,AH:AH,0))-E48 -> #N/A | AH48: 刘凤英 | AK48: =IF((AJ48-AI48)>=0,0,IF(AJ48=1,-200,-400)) -> 0 | AN48: =IF(AL48>=0.67,1.1,IF(AL48>=0.6,1,IF(AL48>=0.45,0.9,0.8))) -> 0.8 | AR48: =INDEX(B:B,MATCH(AH48,B:B,0)) -> #N/A
E49: =SUMIF(AH:AH,B49,AK:AK) -> 0 | L49: =SUM(C49:K49)-SUM(J49:K49) -> 0 | N49: =INDEX(AK:AK,MATCH(B49,AH:AH,0))-E49 -> #N/A | AH49: 邱明杰 | AK49: =IF((AJ49-AI49)>=0,0,IF(AJ49=1,-200,-400)) -> 0 | AN49: =IF(AL49>=0.67,1.1,IF(AL49>=0.6,1,IF(AL49>=0.45,0.9,0.8))) -> 0.8 | AR49: =INDEX(B:B,MATCH(AH49,B:B,0)) -> #N/A
N50: =INDEX(AK:AK,MATCH(B50,AH:AH,0))-E50 -> #N/A | AH50: 王熙鸿 | AK50: =IF((AJ50-AI50)>=0,0,IF(AJ50=1,-200,-400)) -> 0 | AN50: =IF(AL50>=0.67,1.1,IF(AL50>=0.6,1,IF(AL50>=0.45,0.9,0.8))) -> 0.8 | AR50: =INDEX(B:B,MATCH(AH50,B:B,0)) -> #N/A
E51: =SUMIF(AH:AH,B51,AK:AK) -> 0 | L51: =SUM(C51:K51)-SUM(J51:K51) -> 0 | N51: =INDEX(AK:AK,MATCH(B51,AH:AH,0))-E51 -> #N/A | AH51: 施巍 | AK51: =IF((AJ51-AI51)>=0,0,IF(AJ51=1,-200,-400)) -> 0 | AN51: =IF(AL51>=0.67,1.1,IF(AL51>=0.6,1,IF(AL51>=0.45,0.9,0.8))) -> 0.8 | AR51: =INDEX(B:B,MATCH(AH51,B:B,0)) -> #N/A
E52: =SUMIF(AH:AH,B52,AK:AK) -> 0 | L52: =SUM(C52:K52)-SUM(J52:K52) -> 0 | N52: =INDEX(AK:AK,MATCH(B52,AH:AH,0))-E52 -> #N/A | AR52: =INDEX(B:B,MATCH(AH52,B:B,0)) -> #N/A
E53: =SUMIF(AH:AH,B53,AK:AK) -> 0 | L53: =SUM(C53:K53)-SUM(J53:K53) -> 0 | N53: =INDEX(AK:AK,MATCH(B53,AH:AH,0))-E53 -> #N/A | AR53: =INDEX(B:B,MATCH(AH53,B:B,0)) -> #N/A
E54: =SUMIF(AH:AH,B54,AK:AK) -> 0 | L54: =SUM(C54:K54)-SUM(J54:K54) -> 0 | N54: =INDEX(AK:AK,MATCH(B54,AH:AH,0))-E54 -> #N/A | AH54: 小计 | AI54: =SUM(AI42:AI53) -> 0 | AJ54: =SUM(AJ42:AJ53) -> 0 | AK54: =SUM(AK42:AK53) -> 0 | AN54: - | AR54: =INDEX(B:B,MATCH(AH54,B:B,0)) -> #N/A
E55: =SUMIF(AH:AH,B55,AK:AK) -> 0 | L55: =SUM(C55:K55)-SUM(J55:K55) -> 0 | N55: =INDEX(AK:AK,MATCH(B55,AH:AH,0))-E55 -> #N/A | AG55: 机场店合计 | AI55: =AI41+AI54 -> 0 | AJ55: =AJ41+AJ54 -> 0 | AK55: =AK41+AK54 -> 0 | AL55: - | AN55: - | AO55: =(SUM(AO32:AO39)+SUM(AO41:AO53))/17 -> 0 | AP55: - | AR55: =INDEX(B:B,MATCH(AH55,B:B,0)) -> #N/A
E56: =SUMIF(AH:AH,B56,AK:AK) -> 0 | L56: =SUM(C56:K56)-SUM(J56:K56) -> 0 | N56: =INDEX(AK:AK,MATCH(B56,AH:AH,0))-E56 -> #N/A | AR56: =INDEX(B:B,MATCH(AH56,B:B,0)) -> #N/A
E57: =SUMIF(AH:AH,B57,AK:AK) -> 0 | L57: =SUM(C57:K57)-SUM(J57:K57) -> 0 | N57: =INDEX(AK:AK,MATCH(B57,AH:AH,0))-E57 -> #N/A | AG57: 直营店 | AH57: 销售顾问 | AI57: 盈利性产品 | AL57: 渗透率考核 | AO57: 培训考核 | AR57: =INDEX(B:B,MATCH(AH57,B:B,0)) -> #N/A
E58: =SUMIF(AH:AH,B58,AK:AK) -> 0 | L58: =SUM(C58:K58)-SUM(J58:K58) -> 0 | N58: =INDEX(AK:AK,MATCH(B58,AH:AH,0))-E58 -> #N/A | AI58: 任务目标 | AJ58: 完成情况 | AK58: 考核 | AL58: 渗透率 | AM58: 盈利性占比 | AN58: 盈利性产品考核 | AO58: 考试成绩 | AP58: 绩效标准 | AR58: =INDEX(B:B,MATCH(AH58,B:B,0)) -> #N/A
E59: =SUMIF(AH:AH,B59,AK:AK) -> 0 | L59: =SUM(C59:K59)-SUM(J59:K59) -> 0 | N59: =INDEX(AK:AK,MATCH(B59,AH:AH,0))-E59 -> #N/A | AG59: 华阳 | AH59: 丁小玲 | AK59: =IF((AJ59-AI59)>=0,0,IF(AJ59=1,-200,-400)) -> 0 | AN59: =IF(AL59>=0.67,1.1,IF(AL59>=0.6,1,IF(AL59>=0.45,0.9,0.8))) -> 0.8 | AR59: =INDEX(B:B,MATCH(AH59,B:B,0)) -> #N/A
E60: =SUMIF(AH:AH,B60,AK:AK) -> 0 | L60: =SUM(C60:K60)-SUM(J60:K60) -> 0 | N60: =INDEX(AK:AK,MATCH(B60,AH:AH,0))-E60 -> #N/A | AH60: 吴小琴 | AK60: =IF((AJ60-AI60)>=0,0,IF(AJ60=1,-200,-400)) -> 0 | AN60: =IF(AL60>=0.67,1.1,IF(AL60>=0.6,1,IF(AL60>=0.45,0.9,0.8))) -> 0.8 | AR60: =INDEX(B:B,MATCH(AH60,B:B,0)) -> #N/A
E61: =SUMIF(AH:AH,B61,AK:AK) -> 0 | L61: =SUM(C61:K61)-SUM(J61:K61) -> 0 | N61: =INDEX(AK:AK,MATCH(B61,AH:AH,0))-E61 -> #N/A | AH61: 张坤 | AK61: =IF((AJ61-AI61)>=0,0,IF(AJ61=1,-200,-400)) -> 0 | AN61: =IF(AL61>=0.67,1.1,IF(AL61>=0.6,1,IF(AL61>=0.45,0.9,0.8))) -> 0.8 | AR61: =INDEX(B:B,MATCH(AH61,B:B,0)) -> #N/A
E62: =SUMIF(AH:AH,B62,AK:AK) -> 0 | L62: =SUM(C62:K62)-SUM(J62:K62) -> 0 | N62: =INDEX(AK:AK,MATCH(B62,AH:AH,0))-E62 -> #N/A | AH62: 刘华 | AK62: =IF((AJ62-AI62)>=0,0,IF(AJ62=1,-200,-400)) -> 0 | AN62: =IF(AL62>=0.67,1.1,IF(AL62>=0.6,1,IF(AL62>=0.45,0.9,0.8))) -> 0.8 | AR62: =INDEX(B:B,MATCH(AH62,B:B,0)) -> #N/A
E63: =SUMIF(AH:AH,B63,AK:AK) -> 0 | L63: =SUM(C63:K63)-SUM(J63:K63) -> 0 | N63: =INDEX(AK:AK,MATCH(B63,AH:AH,0))-E63 -> #N/A | AR63: =INDEX(B:B,MATCH(AH63,B:B,0)) -> #N/A
E64: =SUMIF(AH:AH,B64,AK:AK) -> 0 | L64: =SUM(C64:K64)-SUM(J64:K64) -> 0 | N64: =INDEX(AK:AK,MATCH(B64,AH:AH,0))-E64 -> #N/A | AR64: =INDEX(B:B,MATCH(AH64,B:B,0)) -> #N/A | AS64: 2025年12月陈总免考核盈利性产品
E65: =SUMIF(AH:AH,B65,AK:AK) -> 0 | L65: =SUM(C65:K65)-SUM(J65:K65) -> 0 | N65: =INDEX(AK:AK,MATCH(B65,AH:AH,0))-E65 -> #N/A | AR65: =INDEX(B:B,MATCH(AH65,B:B,0)) -> #N/A
E66: =SUMIF(AH:AH,B66,AK:AK) -> 0 | L66: =SUM(C66:K66)-SUM(J66:K66) -> 0 | N66: =INDEX(AK:AK,MATCH(B66,AH:AH,0))-E66 -> #N/A | AH66: 小计 | AI66: =SUM(AI59:AI65) -> 0 | AK66: =SUM(AK59:AK65) -> 0 | AR66: =INDEX(B:B,MATCH(AH66,B:B,0)) -> #N/A
E67: =SUMIF(AH:AH,B67,AK:AK) -> 0 | L67: =SUM(C67:K67)-SUM(J67:K67) -> 0 | N67: =INDEX(AK:AK,MATCH(B67,AH:AH,0))-E67 -> #N/A | AG67: 都江堰 | AR67: =INDEX(B:B,MATCH(AH67,B:B,0)) -> #N/A
L68: =SUM(C68:K68)-SUM(J68:K68) -> 0 | N68: =INDEX(AK:AK,MATCH(B68,AH:AH,0))-E68 -> #N/A | AR68: =INDEX(B:B,MATCH(AH68,B:B,0)) -> #N/A
E69: =SUMIF(AH:AH,B69,AK:AK) -> 0 | L69: =SUM(C69:K69)-SUM(J69:K69) -> 0 | N69: =INDEX(AK:AK,MATCH(B69,AH:AH,0))-E69 -> #N/A | AR69: =INDEX(B:B,MATCH(AH69,B:B,0)) -> #N/A
E70: =SUMIF(AH:AH,B70,AK:AK) -> 0 | L70: =SUM(C70:K70)-SUM(J70:K70) -> 0 | N70: =INDEX(AK:AK,MATCH(B70,AH:AH,0))-E70 -> #N/A | AR70: =INDEX(B:B,MATCH(AH70,B:B,0)) -> #N/A
E71: =SUMIF(AH:AH,B71,AK:AK) -> 0 | L71: =SUM(C71:K71)-SUM(J71:K71) -> 0 | N71: =INDEX(AK:AK,MATCH(B71,AH:AH,0))-E71 -> #N/A | AH71: 小计 | AR71: =INDEX(B:B,MATCH(AH71,B:B,0)) -> #N/A
E72: =SUMIF(AH:AH,B72,AK:AK) -> 0 | L72: =SUM(C72:K72)-SUM(J72:K72) -> 0 | N72: =INDEX(AK:AK,MATCH(B72,AH:AH,0))-E72 -> #N/A | AG72: 彭州 | AH72: 钟家林 | AK72: =IF((AJ72-AI72)>=0,0,IF(AJ72=1,-200,-400)) -> 0 | AN72: =IF(AL72>=0.67,1.1,IF(AL72>=0.6,1,IF(AL72>=0.45,0.9,0.8))) -> 0.8 | AR72: =INDEX(B:B,MATCH(AH72,B:B,0)) -> #N/A
E73: =SUMIF(AH:AH,B73,AK:AK) -> 0 | L73: =SUM(C73:K73)-SUM(J73:K73) -> 0 | N73: =INDEX(AK:AK,MATCH(B73,AH:AH,0))-E73 -> #N/A | AH73: 任和奎 | AK73: =IF((AJ73-AI73)>=0,0,IF(AJ73=1,-200,-400)) -> 0 | AN73: =IF(AL73>=0.67,1.1,IF(AL73>=0.6,1,IF(AL73>=0.45,0.9,0.8))) -> 0.8 | AR73: =INDEX(B:B,MATCH(AH73,B:B,0)) -> #N/A
E74: =SUMIF(AH:AH,B74,AK:AK) -> 0 | L74: =SUM(C74:K74)-SUM(J74:K74) -> 0 | N74: =INDEX(AK:AK,MATCH(B74,AH:AH,0))-E74 -> #N/A | AH74: 兰代全 | AK74: =IF((AJ74-AI74)>=0,0,IF(AJ74=1,-200,-400)) -> 0 | AN74: =IF(AL74>=0.67,1.1,IF(AL74>=0.6,1,IF(AL74>=0.45,0.9,0.8))) -> 0.8 | AR74: =INDEX(B:B,MATCH(AH74,B:B,0)) -> #N/A
E75: =SUMIF(AH:AH,B75,AK:AK) -> 0 | L75: =SUM(C75:K75)-SUM(J75:K75) -> 0 | N75: =INDEX(AK:AK,MATCH(B75,AH:AH,0))-E75 -> #N/A | AH75: 刘娅 | AK75: =IF((AJ75-AI75)>=0,0,IF(AJ75=1,-200,-400)) -> 0 | AN75: =IF(AL75>=0.67,1.1,IF(AL75>=0.6,1,IF(AL75>=0.45,0.9,0.8))) -> 0.8 | AR75: =INDEX(B:B,MATCH(AH75,B:B,0)) -> #N/A
E76: =SUMIF(AH:AH,B76,AK:AK) -> 0 | L76: =SUM(C76:K76)-SUM(J76:K76) -> 0 | N76: =INDEX(AK:AK,MATCH(B76,AH:AH,0))-E76 -> #N/A | AH76: 陈莉 | AN76: =IF(AL76>=0.67,1.1,IF(AL76>=0.6,1,IF(AL76>=0.45,0.9,0.8))) -> 0.8 | AR76: =INDEX(B:B,MATCH(AH76,B:B,0)) -> #N/A
E77: =SUMIF(AH:AH,B77,AK:AK) -> 0 | L77: =SUM(C77:K77)-SUM(J77:K77) -> 0 | N77: =INDEX(AK:AK,MATCH(B77,AH:AH,0))-E77 -> #N/A | AR77: =INDEX(B:B,MATCH(AH77,B:B,0)) -> #N/A
E78: =SUMIF(AH:AH,B78,AK:AK) -> 0 | L78: =SUM(C78:K78)-SUM(J78:K78) -> 0 | N78: =INDEX(AK:AK,MATCH(B78,AH:AH,0))-E78 -> #N/A | AH78: 小计 | AI78: =SUM(AI72:AI74) -> 0 | AK78: =SUM(AK72:AK77) -> 0 | AN78: =IF(AL78>=0.65,1.1,IF(AL78>=0.6,1,IF(AL78>=0.45,0.8,0.6))) -> 0.6 | AR78: =INDEX(B:B,MATCH(AH78,B:B,0)) -> #N/A
E79: =SUMIF(AH:AH,B79,AK:AK) -> 0 | L79: =SUM(C79:K79)-SUM(J79:K79) -> 0 | N79: =INDEX(AK:AK,MATCH(B79,AH:AH,0))-E79 -> #N/A | AG79: 邛崃 | AH79: 叶荣鹏 | AK79: =IF((AJ79-AI79)>=0,0,IF(AJ79=1,-200,-400)) -> 0 | AN79: =IF(AL79>=0.67,1.1,IF(AL79>=0.6,1,IF(AL79>=0.45,0.9,0.8))) -> 0.8 | AR79: =INDEX(B:B,MATCH(AH79,B:B,0)) -> #N/A
E80: =SUMIF(AH:AH,B80,AK:AK) -> 0 | L80: =SUM(C80:K80)-SUM(J80:K80) -> 0 | N80: =INDEX(AK:AK,MATCH(B80,AH:AH,0))-E80 -> #N/A | AH80: 马勇 | AK80: =IF((AJ80-AI80)>=0,0,IF(AJ80=1,-200,-400)) -> 0 | AN80: =IF(AL80>=0.67,1.1,IF(AL80>=0.6,1,IF(AL80>=0.45,0.9,0.8))) -> 0.8 | AR80: =INDEX(B:B,MATCH(AH80,B:B,0)) -> #N/A
E81: =SUMIF(AH:AH,B81,AK:AK) -> 0 | L81: =SUM(C81:K81)-SUM(J81:K81) -> 0 | N81: =INDEX(AK:AK,MATCH(B81,AH:AH,0))-E81 -> #N/A | AH81: 高东琴 | AK81: =IF((AJ81-AI81)>=0,0,IF(AJ81=1,-200,-400)) -> 0 | AN81: =IF(AL81>=0.67,1.1,IF(AL81>=0.6,1,IF(AL81>=0.45,0.9,0.8))) -> 0.8 | AR81: =INDEX(B:B,MATCH(AH81,B:B,0)) -> #N/A
E82: =SUMIF(AH:AH,B82,AK:AK) -> 0 | L82: =SUM(C82:K82)-SUM(J82:K82) -> 0 | N82: =INDEX(AK:AK,MATCH(B82,AH:AH,0))-E82 -> #N/A | AN82: =IF(AL82>=0.67,1.1,IF(AL82>=0.6,1,IF(AL82>=0.45,0.9,0.8))) -> 0.8 | AR82: =INDEX(B:B,MATCH(AH82,B:B,0)) -> #N/A
E83: =SUMIF(AH:AH,B83,AK:AK) -> 0 | L83: =SUM(C83:K83)-SUM(J83:K83) -> 0 | N83: =INDEX(AK:AK,MATCH(B83,AH:AH,0))-E83 -> #N/A | AR83: =INDEX(B:B,MATCH(AH83,B:B,0)) -> #N/A
E84: =SUMIF(AH:AH,B84,AK:AK) -> 0 | L84: =SUM(C84:K84)-SUM(J84:K84) -> 0 | N84: =INDEX(AK:AK,MATCH(B84,AH:AH,0))-E84 -> #N/A | AH84: 小计 | AI84: =SUM(AI79:AI83) -> 0 | AK84: =SUM(AK79:AK83) -> 0 | AR84: =INDEX(B:B,MATCH(AH84,B:B,0)) -> #N/A
E85: =SUMIF(AH:AH,B85,AK:AK) -> 0 | L85: =SUM(C85:K85)-SUM(J85:K85) -> 0 | N85: =INDEX(AK:AK,MATCH(B85,AH:AH,0))-E85 -> #N/A | AG85: 大邑 | AH85: 程羊 | AN85: =IF(AL85>=0.67,1.1,IF(AL85>=0.6,1,IF(AL85>=0.45,0.9,0.8))) -> 0.8 | AR85: =INDEX(B:B,MATCH(AH85,B:B,0)) -> #N/A
E86: =SUMIF(AH:AH,B86,AK:AK) -> 0 | L86: =SUM(C86:K86)-SUM(J86:K86) -> 0 | N86: =INDEX(AK:AK,MATCH(B86,AH:AH,0))-E86 -> #N/A | AH86: 常涛 | AK86: =IF((AJ86-AI86)>=0,0,IF(AJ86=1,-200,-400)) -> 0 | AN86: =IF(AL86>=0.67,1.1,IF(AL86>=0.6,1,IF(AL86>=0.45,0.9,0.8))) -> 0.8 | AR86: =INDEX(B:B,MATCH(AH86,B:B,0)) -> #N/A
E87: =SUMIF(AH:AH,B87,AK:AK) -> 0 | L87: =SUM(C87:K87)-SUM(J87:K87) -> 0 | N87: =INDEX(AK:AK,MATCH(B87,AH:AH,0))-E87 -> #N/A | AH87: 王海 | AK87: =IF((AJ87-AI87)>=0,0,IF(AJ87=1,-200,-400)) -> 0 | AN87: =IF(AL87>=0.67,1.1,IF(AL87>=0.6,1,IF(AL87>=0.45,0.9,0.8))) -> 0.8 | AR87: =INDEX(B:B,MATCH(AH87,B:B,0)) -> #N/A
E88: =SUMIF(AH:AH,B88,AK:AK) -> 0 | L88: =SUM(C88:K88)-SUM(J88:K88) -> 0 | N88: =INDEX(AK:AK,MATCH(B88,AH:AH,0))-E88 -> #N/A | AN88: =IF(AL88>=0.67,1.1,IF(AL88>=0.6,1,IF(AL88>=0.45,0.9,0.8))) -> 0.8 | AR88: =INDEX(B:B,MATCH(AH88,B:B,0)) -> #N/A
E89: =SUMIF(AH:AH,B89,AK:AK) -> 0 | L89: =SUM(C89:K89)-SUM(J89:K89) -> 0 | N89: =INDEX(AK:AK,MATCH(B89,AH:AH,0))-E89 -> #N/A | AR89: =INDEX(B:B,MATCH(AH89,B:B,0)) -> #N/A
E90: =SUMIF(AH:AH,B90,AK:AK) -> 0 | L90: =SUM(C90:K90)-SUM(J90:K90) -> 0 | N90: =INDEX(AK:AK,MATCH(B90,AH:AH,0))-E90 -> #N/A | AH90: 小计 | AI90: =SUM(AI85:AI89) -> 0 | AK90: =SUM(AK85:AK89) -> 0 | AR90: =INDEX(B:B,MATCH(AH90,B:B,0)) -> #N/A
E91: =SUMIF(AH:AH,B91,AK:AK) -> 0 | L91: =SUM(C91:K91)-SUM(J91:K91) -> 0 | N91: =INDEX(AK:AK,MATCH(B91,AH:AH,0))-E91 -> #N/A | AG91: 崇州 | AH91: 唐鹏 | AK91: =IF((AJ91-AI91)>=0,0,IF(AJ91=1,-200,-400)) -> 0 | AN91: =IF(AL91>=0.67,1.1,IF(AL91>=0.6,1,IF(AL91>=0.45,0.9,0.8))) -> 0.8 | AR91: =INDEX(B:B,MATCH(AH91,B:B,0)) -> #N/A
E92: =SUMIF(AH:AH,B92,AK:AK) -> 0 | L92: =SUM(C92:K92)-SUM(J92:K92) -> 0 | N92: =INDEX(AK:AK,MATCH(B92,AH:AH,0))-E92 -> #N/A | AH92: 陈勇建 | AK92: =IF((AJ92-AI92)>=0,0,IF(AJ92=1,-200,-400)) -> 0 | AN92: =IF(AL92>=0.67,1.1,IF(AL92>=0.6,1,IF(AL92>=0.45,0.9,0.8))) -> 0.8 | AR92: =INDEX(B:B,MATCH(AH92,B:B,0)) -> #N/A
E93: =SUMIF(AH:AH,B93,AK:AK) -> 0 | L93: =SUM(C93:K93)-SUM(J93:K93) -> 0 | N93: =INDEX(AK:AK,MATCH(B93,AH:AH,0))-E93 -> #N/A | AH93: 赵思梵 | AK93: =IF((AJ93-AI93)>=0,0,IF(AJ93=1,-200,-400)) -> 0 | AN93: =IF(AL93>=0.67,1.1,IF(AL93>=0.6,1,IF(AL93>=0.45,0.9,0.8))) -> 0.8 | AR93: =INDEX(B:B,MATCH(AH93,B:B,0)) -> #N/A
E94: =SUMIF(AH:AH,B94,AK:AK) -> 0 | L94: =SUM(C94:K94)-SUM(J94:K94) -> 0 | N94: =INDEX(AK:AK,MATCH(B94,AH:AH,0))-E94 -> #N/A | AH94: 宁袁 | AK94: =IF((AJ94-AI94)>=0,0,IF(AJ94=1,-300,-600)) -> 0 | AN94: =IF(AL94>=0.67,1.1,IF(AL94>=0.6,1,IF(AL94>=0.45,0.9,0.8))) -> 0.8 | AR94: =INDEX(B:B,MATCH(AH94,B:B,0)) -> #N/A
E95: =SUMIF(AH:AH,B95,AK:AK) -> 0 | L95: =SUM(C95:K95)-SUM(J95:K95) -> 0 | N95: =INDEX(AK:AK,MATCH(B95,AH:AH,0))-E95 -> #N/A | AR95: =INDEX(B:B,MATCH(AH95,B:B,0)) -> #N/A
E96: =SUMIF(AH:AH,B96,AK:AK) -> 0 | L96: =SUM(C96:K96)-SUM(J96:K96) -> 0 | N96: =INDEX(AK:AK,MATCH(B96,AH:AH,0))-E96 -> #N/A | AR96: =INDEX(B:B,MATCH(AH96,B:B,0)) -> #N/A
E97: =SUMIF(AH:AH,B97,AK:AK) -> 0 | L97: =SUM(C97:K97)-SUM(J97:K97) -> 0 | N97: =INDEX(AK:AK,MATCH(B97,AH:AH,0))-E97 -> #N/A | AR97: =INDEX(B:B,MATCH(AH97,B:B,0)) -> #N/A
E98: =SUMIF(AH:AH,B98,AK:AK) -> 0 | L98: =SUM(C98:K98)-SUM(J98:K98) -> 0 | N98: =INDEX(AK:AK,MATCH(B98,AH:AH,0))-E98 -> #N/A | AH98: 小计 | AI98: =SUM(AI91:AI96) -> 0 | AJ98: =SUM(AJ91:AJ96) -> 0 | AK98: =SUM(AK91:AK95) -> 0 | AR98: =INDEX(B:B,MATCH(AH98,B:B,0)) -> #N/A
E99: =SUMIF(AH:AH,B99,AK:AK) -> 0 | L99: =SUM(C99:K99)-SUM(J99:K99) -> 0 | N99: =INDEX(AK:AK,MATCH(B99,AH:AH,0))-E99 -> #N/A | AG99: 直营店合计 | AI99: =AI66+AI71+AI78+AI84+AI90+AI98 -> 0 | AJ99: =AJ66+AJ71+AJ78+AJ84+AJ90+AJ98 -> 0 | AK99: =AK66+AK71+AK78+AK84+AK90+AK98 -> 0 | AL99: - | AR99: =INDEX(B:B,MATCH(AH99,B:B,0)) -> #N/A | AS99: 离职
E100: =SUMIF(AH:AH,B100,AK:AK) -> 0 | L100: =SUM(C100:K100)-SUM(J100:K100) -> 0 | N100: =INDEX(AK:AK,MATCH(B100,AH:AH,0))-E100 -> #N/A | AR100: =INDEX(B:B,MATCH(AH100,B:B,0)) -> #N/A
...

Sheet 重功超期+活动
P1: 3月团购活动任务（活动周期3.7-3.15）
A2: 归属公司 | B2: 车种 | C2: 采购日期 | D2: 颜色 | E2: VIN号 | F2: 统一零售价 | G2: 库龄 | H2: 区域 | I2: 库别 | J2: 装饰情况 | K2: 物流补偿 | L2: 质损降价 | M2: 销售追加奖励 | N2: =M2 -> 销售追加奖励 | Z2: =COUNTIF(Q:Q,Q2) -> 0 | AA2: 500/台 | AB2: 200≥2 台 | AC2: 100≥2 台 | AF2: 500/台 | AG2: 200≥2 台 | AH2: 100≥2 台
A3: 西物明睿 | B3: 星瑞 | C3: 2026-01-05 | D3: 紫 | E3: L6T7954Z2TD009890 | H3: 自有店 | I3: 电子厂库房 | J3: 前保险杠下部装饰条更换，需告知客户，降价1000 | N3: =M3 -> 0 | O3: 眉山销售 | P3: 部门 | Q3: 人员 | R3: 24号 | S3: 25号 | T3: 26号 | U3: 奖励明细 | V3: 重攻考核 | W3: 合计实发 | X3: 合计实发 | Z3: =COUNTIF(Q:Q,Q3) -> 3 | AA3: 奖励明细 | AB3: 奖励明细 | AC3: 奖励明细 | AD3: 合计实发 | AF3: 奖励明细 | AG3: 奖励明细 | AH3: 奖励明细 | AI3: 合计实发
A4: 西物明睿 | B4: 博越REV | C4: 2026-03-19 | D4: 白 | E4: L6T78XCZ2TY781363 | H4: 自有店 | I4: 网销 | J4: 天窗损坏跟换 | N4: =M4 -> 0 | X4: =SUM(U4:W4) -> 0 | Z4: =COUNTIF(Q:Q,Q4) -> 0 | AD4: =SUM(AA4:AC4) -> 0 | AF4: =SUMIFS(O:O,I:I,'重功超期+活动'!Q4,B:B,"豪越L") -> 0 | AG4: =SUMIFS(O:O,I:I,'重功超期+活动'!Q4,B:B,"第4代帝豪") -> 0 | AH4: =SUMIFS(O:O,I:I,'重功超期+活动'!Q4,B:B,"第5代帝豪") -> 0 | AI4: =SUM(AF4:AH4) -> 0
A5: 成都西物 | B5: 博越L | C5: 2026-02-25 | D5: 黑 | E5: LB37822Z0TB034100 | H5: 自有店 | I5: 西部智谷A区 | J5: 发动机下护板被猫抓坏-保险承担降价金额请示总经理 | N5: =M5 -> 0 | X5: =SUM(U5:W5) -> 0 | Z5: =COUNTIF(Q:Q,Q5) -> 0 | AD5: =SUM(AA5:AC5) -> 0 | AF5: =SUMIFS(O:O,I:I,'重功超期+活动'!Q5,B:B,"豪越L") -> 0 | AG5: =SUMIFS(O:O,I:I,'重功超期+活动'!Q5,B:B,"第4代帝豪") -> 0 | AH5: =SUMIFS(O:O,I:I,'重功超期+活动'!Q5,B:B,"第5代帝豪") -> 0 | AI5: =SUM(AF5:AH5) -> 0
A6: 成都西物 | B6: 豪越L | C6: 2026-03-03 | D6: 白 | E6: L6T7922Z0TY871189 | H6: 自有店 | I6: 电子营销 | J6: 更换贯穿式背门灯-需告知客户-具体降价补偿销售时请示总经理 | N6: =M6 -> 0 | X6: =SUM(U6:W6) -> 0 | Z6: =COUNTIF(Q:Q,Q6) -> 0 | AD6: =SUM(AA6:AC6) -> 0 | AF6: =SUMIFS(O:O,I:I,'重功超期+活动'!Q6,B:B,"豪越L") -> 0 | AG6: =SUMIFS(O:O,I:I,'重功超期+活动'!Q6,B:B,"第4代帝豪") -> 0 | AH6: =SUMIFS(O:O,I:I,'重功超期+活动'!Q6,B:B,"第5代帝豪") -> 0 | AI6: =SUM(AF6:AH6) -> 0
A7: 成都西物 | B7: 博越L | C7: 2026-03-19 | D7: 银 | E7: LB37822Z6TB045859 | H7: 自有店 | I7: 西部智谷B区 | J7: 车底挡板被猫抓坏待处理 | N7: =M7 -> 0 | X7: =SUM(U7:W7) -> 0 | Z7: =COUNTIF(Q:Q,Q7) -> 0 | AD7: =SUM(AA7:AC7) -> 0 | AF7: =SUMIFS(O:O,I:I,'重功超期+活动'!Q7,B:B,"豪越L") -> 0 | AG7: =SUMIFS(O:O,I:I,'重功超期+活动'!Q7,B:B,"第4代帝豪") -> 0 | AH7: =SUMIFS(O:O,I:I,'重功超期+活动'!Q7,B:B,"第5代帝豪") -> 0 | AI7: =SUM(AF7:AH7) -> 0
A8: 成都西物 | B8: 缤越L | C8: 2026-04-09 | D8: 白 | E8: LB37622Z8TX621220 | H8: 自有店 | I8: 售后维修 | J8: 更换右前右后门等装饰条及右后视镜总成-售后三包-告知客户降价金额待定 | N8: =M8 -> 0 | X8: =SUM(U8:W8) -> 0 | Z8: =COUNTIF(Q:Q,Q8) -> 0 | AD8: =SUM(AA8:AC8) -> 0 | AF8: =SUMIFS(O:O,I:I,'重功超期+活动'!Q8,B:B,"豪越L") -> 0 | AG8: =SUMIFS(O:O,I:I,'重功超期+活动'!Q8,B:B,"第4代帝豪") -> 0 | AH8: =SUMIFS(O:O,I:I,'重功超期+活动'!Q8,B:B,"第5代帝豪") -> 0 | AI8: =SUM(AF8:AH8) -> 0
A9: 成都西物 | B9: 缤越L | C9: 2026-04-09 | D9: 白 | E9: LB37622Z2TX621214 | H9: 自有店 | I9: 售后维修 | J9: 更换右前右后门等装饰条-售后三包-告知客户降价金额待定 | N9: =M9 -> 0 | X9: =SUM(U9:W9) -> 0 | Z9: =COUNTIF(Q:Q,Q9) -> 0 | AD9: =SUM(AA9:AC9) -> 0 | AF9: =SUMIFS(O:O,I:I,'重功超期+活动'!Q9,B:B,"豪越L") -> 0 | AG9: =SUMIFS(O:O,I:I,'重功超期+活动'!Q9,B:B,"第4代帝豪") -> 0 | AH9: =SUMIFS(O:O,I:I,'重功超期+活动'!Q9,B:B,"第5代帝豪") -> 0 | AI9: =SUM(AF9:AH9) -> 0
A10: 成都西物 | B10: 博越L | C10: 2026-03-19 | D10: 黑 | E10: LB37822Z6TB048261 | H10: 自有店 | I10: 售后 | J10: 底盘护板被抓坏，更换油钱轮眉，右前杠做漆待处理 | N10: =M10 -> 0 | X10: =SUM(U10:W10) -> 0 | Z10: =COUNTIF(Q:Q,Q10) -> 0 | AD10: =SUM(AA10:AC10) -> 0 | AF10: =SUMIFS(O:O,I:I,'重功超期+活动'!Q10,B:B,"豪越L") -> 0 | AG10: =SUMIFS(O:O,I:I,'重功超期+活动'!Q10,B:B,"第4代帝豪") -> 0 | AH10: =SUMIFS(O:O,I:I,'重功超期+活动'!Q10,B:B,"第5代帝豪") -> 0 | AI10: =SUM(AF10:AH10) -> 0
A11: 成都西物 | B11: 博越L | C11: 2026-01-20 | D11: 青 | E11: LB37822Z8TB021028 | H11: 自有店 | I11: 西部智谷C区 | J11: 右前杠右前叶子板被抓坏待保险处理 | N11: =M11 -> 0 | X11: =SUM(U11:W11) -> 0 | Z11: =COUNTIF(Q:Q,Q11) -> 0 | AD11: =SUM(AA11:AC11) -> 0 | AF11: =SUMIFS(O:O,I:I,'重功超期+活动'!Q11,B:B,"豪越L") -> 0 | AG11: =SUMIFS(O:O,I:I,'重功超期+活动'!Q11,B:B,"第4代帝豪") -> 0 | AH11: =SUMIFS(O:O,I:I,'重功超期+活动'!Q11,B:B,"第5代帝豪") -> 0 | AI11: =SUM(AF11:AH11) -> 0
A12: 成都西物 | B12: 博越L | C12: 2026-03-19 | D12: 银 | E12: LB37822Z9TB045144 | H12: 自有店 | I12: 售后 | J12: 车底挡板被猫抓坏待处理 | N12: =M12 -> 0 | X12: =SUM(U12:W12) -> 0 | Z12: =COUNTIF(Q:Q,Q12) -> 0 | AD12: =SUM(AA12:AC12) -> 0 | AF12: =SUMIFS(O:O,I:I,'重功超期+活动'!Q12,B:B,"豪越L") -> 0 | AG12: =SUMIFS(O:O,I:I,'重功超期+活动'!Q12,B:B,"第4代帝豪") -> 0 | AH12: =SUMIFS(O:O,I:I,'重功超期+活动'!Q12,B:B,"第5代帝豪") -> 0 | AI12: =SUM(AF12:AH12) -> 0
A13: 吉利超市 | B13: 星越L | C13: 2025-11-20 | D13: 白 | E13: LB37852Z0SS260105 | H13: 自有店 | I13: 华阳直营店 | J13: 右前轮轮毂轻微擦伤-华阳承担需要告知客户降价金额500元 | N13: =M13 -> 0 | X13: =SUM(U13:W13) -> 0 | Z13: =COUNTIF(Q:Q,Q13) -> 0 | AD13: =SUM(AB13:AC13) -> 0 | AI13: =SUM(AG13:AH13) -> 0
A14: 吉利超市 | B14: 缤越超能版 | C14: 2026-04-09 | D14: 白 | E14: LB37622Z0TX812503 | H14: 自有店 | I14: 售后维修 | J14: 更换右前B柱右后C柱右后门等装饰条-售后三包-告知客户降价金额待定 | N14: =M14 -> 0 | X14: =SUM(U14:W14) -> 0 | Z14: =COUNTIF(Q:Q,Q14) -> 0 | AD14: =SUM(AA14:AC14) -> 0 | AF14: =SUMIFS(O:O,I:I,'重功超期+活动'!Q14,B:B,"豪越L") -> 0 | AG14: =SUMIFS(O:O,I:I,'重功超期+活动'!Q14,B:B,"第4代帝豪") -> 0 | AH14: =SUMIFS(O:O,I:I,'重功超期+活动'!Q14,B:B,"第5代帝豪") -> 0 | AI14: =SUM(AF14:AH14) -> 0
A15: 吉利超市 | B15: 第5代帝豪 | C15: 2025-12-05 | D15: 蓝 | E15: LB37824Z4SG148390 | H15: 自有店 | I15: 机场展厅 | J15: 车顶划痕掉漆-公司承担告知客户降价金额800元 | N15: =M15 -> 0 | X15: =SUM(U15:W15) -> 0 | Z15: =COUNTIF(Q:Q,Q15) -> 0 | AD15: =SUM(AA15:AC15) -> 0 | AF15: =SUMIFS(O:O,I:I,'重功超期+活动'!Q15,B:B,"豪越L") -> 0 | AG15: =SUMIFS(O:O,I:I,'重功超期+活动'!Q15,B:B,"第4代帝豪") -> 0 | AH15: =SUMIFS(O:O,I:I,'重功超期+活动'!Q15,B:B,"第5代帝豪") -> 0 | AI15: =SUM(AF15:AH15) -> 0
A16: 成都豪明 | B16: 星越L | C16: 2025-09-12 | D16: 莫高蓝 | E16: LB37852Z7SS238487 | H16: 自有店 | I16: 龙潭展厅 | J16: 前保险杠有伤，新都直营店负责，降价3000 | N16: =M16 -> 0 | X16: =SUM(U16:W16) -> 0 | Z16: =COUNTIF(Q:Q,Q16) -> 0 | AD16: =SUM(AA16:AC16) -> 0 | AF16: =SUMIFS(O:O,I:I,'重功超期+活动'!Q16,B:B,"豪越L") -> 0 | AG16: =SUMIFS(O:O,I:I,'重功超期+活动'!Q16,B:B,"第4代帝豪") -> 0 | AH16: =SUMIFS(O:O,I:I,'重功超期+活动'!Q16,B:B,"第5代帝豪") -> 0 | AI16: =SUM(AF16:AH16) -> 0
A17: 成都豪明 | B17: 星越L | C17: 2025-12-18 | D17: 玄武灰KX | E17: LB37852Z9SS262046 | H17: 自有店 | I17: 华冠库 | J17: 前保险杠左侧有伤（刘尚勇） | N17: =M17 -> 0 | X17: =SUM(U17:W17) -> 0 | Z17: =COUNTIF(Q:Q,Q17) -> 0 | AD17: =SUM(AA17:AC17) -> 0 | AF17: =SUMIFS(O:O,I:I,'重功超期+活动'!Q17,B:B,"豪越L") -> 0 | AG17: =SUMIFS(O:O,I:I,'重功超期+活动'!Q17,B:B,"第4代帝豪") -> 0 | AH17: =SUMIFS(O:O,I:I,'重功超期+活动'!Q17,B:B,"第5代帝豪") -> 0 | AI17: =SUM(AF17:AH17) -> 0
A18: 成都豪明 | B18: 星越L | C18: 2025-11-20 | E18: LB37852Z9SS265027 | H18: 自有店 | I18: 华冠库 | J18: 后档风玻璃有伤，需更换。可降价3000 | N18: =M18 -> 0 | X18: =SUM(U18:W18) -> 0 | Z18: =COUNTIF(Q:Q,Q18) -> 0 | AD18: =SUM(AA18:AC18) -> 0 | AF18: =SUMIFS(O:O,I:I,'重功超期+活动'!Q18,B:B,"豪越L") -> 0 | AG18: =SUMIFS(O:O,I:I,'重功超期+活动'!Q18,B:B,"第4代帝豪") -> 0 | AH18: =SUMIFS(O:O,I:I,'重功超期+活动'!Q18,B:B,"第5代帝豪") -> 0 | AI18: =SUM(AF18:AH18) -> 0
A19: 绵阳西物 | B19: 星瑞 | D19: 月牙青 | E19: L6T7924Z5TD024186 | H19: 自有店 | I19: 绵阳西物 | J19: 左后玻璃更换 | N19: =M19 -> 0 | X19: =SUM(U19:W19) -> 0 | Z19: =COUNTIF(Q:Q,Q19) -> 0 | AD19: =SUM(AA19:AC19) -> 0 | AF19: =SUMIFS(O:O,I:I,'重功超期+活动'!Q19,B:B,"豪越L") -> 0 | AG19: =SUMIFS(O:O,I:I,'重功超期+活动'!Q19,B:B,"第4代帝豪") -> 0 | AH19: =SUMIFS(O:O,I:I,'重功超期+活动'!Q19,B:B,"第5代帝豪") -> 0 | AI19: =SUM(AF19:AH19) -> 0
A20: 西物慧生 | B20: 第4代博越L | D20: 白色 | E20: LB37822Z0SB204521 | H20: 锦江区 | I20: 展厅 | J20: 1、前保险杠刮擦，进行漆面修补，已完成修复 2、中网受损，需要进行更换，已完成修复 | N20: =M20 -> 0 | X20: =SUM(U20:W20) -> 0 | Z20: =COUNTIF(Q:Q,Q20) -> 0 | AD20: =SUM(AA20:AC20) -> 0 | AF20: =SUMIFS(O:O,I:I,'重功超期+活动'!Q20,B:B,"豪越L") -> 0 | AG20: =SUMIFS(O:O,I:I,'重功超期+活动'!Q20,B:B,"第4代帝豪") -> 0 | AH20: =SUMIFS(O:O,I:I,'重功超期+活动'!Q20,B:B,"第5代帝豪") -> 0 | AI20: =SUM(AF20:AH20) -> 0
A21: 西物慧生 | B21: 星瑞 | D21: 紫色 | E21: L6T7954Z3SD167797 | H21: 锦江区 | I21: 展厅 | J21: 后保险杠受损，进行更换，已完成修复 | N21: =M21 -> 0 | X21: =SUM(U21:W21) -> 0 | Z21: =COUNTIF(Q:Q,Q21) -> 0 | AD21: =SUM(AA21:AC21) -> 0 | AF21: =SUMIFS(O:O,I:I,'重功超期+活动'!Q21,B:B,"豪越L") -> 0 | AG21: =SUMIFS(O:O,I:I,'重功超期+活动'!Q21,B:B,"第4代帝豪") -> 0 | AH21: =SUMIFS(O:O,I:I,'重功超期+活动'!Q21,B:B,"第5代帝豪") -> 0 | AI21: =SUM(AF21:AH21) -> 0
A22: 西物慧生 | B22: 星瑞 | D22: 紫色 | E22: L6T7924Z4SD170948 | H22: 金牛区 | I22: 明睿 | J22: 轮胎受损，已经修复 | N22: =M22 -> 0 | X22: =SUM(U22:W22) -> 0 | Z22: =COUNTIF(Q:Q,Q22) -> 0 | AD22: =SUM(AA22:AC22) -> 0 | AF22: =SUMIFS(O:O,I:I,'重功超期+活动'!Q22,B:B,"豪越L") -> 0 | AG22: =SUMIFS(O:O,I:I,'重功超期+活动'!Q22,B:B,"第4代帝豪") -> 0 | AH22: =SUMIFS(O:O,I:I,'重功超期+活动'!Q22,B:B,"第5代帝豪") -> 0 | AI22: =SUM(AF22:AH22) -> 0
X23: =SUM(U23:W23) -> 0 | Z23: =COUNTIF(Q:Q,Q23) -> 0 | AD23: =SUM(AA23:AC23) -> 0 | AF23: =SUMIFS(O:O,I:I,'重功超期+活动'!Q23,B:B,"豪越L") -> 0 | AG23: =SUMIFS(O:O,I:I,'重功超期+活动'!Q23,B:B,"第4代帝豪") -> 0 | AH23: =SUMIFS(O:O,I:I,'重功超期+活动'!Q23,B:B,"第5代帝豪") -> 0 | AI23: =SUM(AF23:AH23) -> 0
X24: =SUM(U24:W24) -> 0 | Z24: =COUNTIF(Q:Q,Q24) -> 0 | AD24: =SUM(AA24:AC24) -> 0 | AF24: =SUMIFS(O:O,I:I,'重功超期+活动'!Q24,B:B,"豪越L") -> 0 | AG24: =SUMIFS(O:O,I:I,'重功超期+活动'!Q24,B:B,"第4代帝豪") -> 0 | AH24: =SUMIFS(O:O,I:I,'重功超期+活动'!Q24,B:B,"第5代帝豪") -> 0 | AI24: =SUM(AF24:AH24) -> 0
A25: 5月特殊奖励 | V25: =SUM(V15:V24) -> 0 | X25: =SUM(X14:X24) -> 0 | Z25: =COUNTIF(Q:Q,Q25) -> 0 | AD25: =SUM(AD14:AD24) -> 0 | AI25: =SUM(AI14:AI24) -> 0
A26: 双星展厅 | B26: 第4代帝豪 | E26: LB37824Z0SG170127 | I26: 双星展厅 | J26: 康鳞波 | P26: 合计 | V26: =V13+V25 -> 0 | X26: =X25+X13 -> 0 | Z26: =COUNTIF(Q:Q,Q26) -> 0 | AD26: =AD25+AD13 -> 0 | AI26: =AI25+AI13 -> 0
A27: 双星展厅 | B27: 第4代帝豪 | E27: LB37824S4SG178525 | I27: 双星展厅 | J27: 何宇 | Z27: =COUNTIF(Q:Q,Q27) -> 0
A28: 机场店新媒体 | B28: 第4代帝豪 | E28: LB37824Z1SG163283 | I28: 机场店新媒体 | J28: 黄婷婷 | P28: 3月团购活动任务 | Z28: =COUNTIF(Q:Q,Q28) -> 0
A29: 机场店新媒体 | B29: 星瑞 | E29: L6T79PEZ1TD059366 | I29: 机场店新媒体 | J29: 赵强 | X29: =SUM(U29:W29) -> 0 | Z29: =COUNTIF(Q:Q,Q29) -> 0 | AD29: =SUM(AB29:AC29) -> 0 | AI29: =SUM(AG29:AH29) -> 0
A30: 华阳直营店 | B30: 星瑞 | E30: L6T79PEZ5TD067194 | I30: 华阳直营店 | J30: 张坤 | P30: 部门 | Q30: 人员 | R30: 3.14任务 | S30: 订车 | T30: 交车 | U30: 激励 | V30: 重攻考核 | W30: 合计实发 | X30: 合计实发 | Z30: =COUNTIF(Q:Q,Q30) -> 3 | AA30: 豪越 | AB30: 第四帝豪 | AC30: 第五帝豪 | AD30: =AD3 -> 合计实发 | AF30: 豪越 | AG30: 第四帝豪 | AH30: 第五帝豪 | AI30: =AI3 -> 合计实发
A31: 机场展厅 | B31: 星瑞 | E31: L6T79PEZ5TD069527 | I31: 机场展厅 | J31: 冯超 | X31: =U31 -> 0 | Z31: =COUNTIF(Q:Q,Q31) -> 0 | AD31: =SUM(AA31:AC31) -> 0 | AF31: =SUMIFS(O:O,I:I,'重功超期+活动'!Q31,B:B,"豪越L") -> 0 | AG31: =SUMIFS(O:O,I:I,'重功超期+活动'!Q31,B:B,"第4代帝豪") -> 0 | AH31: =SUMIFS(O:O,I:I,'重功超期+活动'!Q31,B:B,"第5代帝豪") -> 0 | AI31: =SUM(AF31:AH31) -> 0
A32: 机场店网销 | B32: 星越L | E32: LB3781NZXTS079664 | I32: 机场店网销 | J32: 向兰 | X32: =U32 -> 0 | Z32: =COUNTIF(Q:Q,Q32) -> 0 | AD32: =SUM(AA32:AC32) -> 0 | AF32: =SUMIFS(O:O,I:I,'重功超期+活动'!Q32,B:B,"豪越L") -> 0 | AG32: =SUMIFS(O:O,I:I,'重功超期+活动'!Q32,B:B,"第4代帝豪") -> 0 | AH32: =SUMIFS(O:O,I:I,'重功超期+活动'!Q32,B:B,"第5代帝豪") -> 0 | AI32: =SUM(AF32:AH32) -> 0
A33: 电子营销 | B33: 星越L | E33: LB3781NZ3TS079487 | I33: 电子营销 | J33: 何宇 | X33: =U33 -> 0 | Z33: =COUNTIF(Q:Q,Q33) -> 0 | AD33: =SUM(AA33:AC33) -> 0 | AF33: =SUMIFS(O:O,I:I,'重功超期+活动'!Q33,B:B,"豪越L") -> 0 | AG33: =SUMIFS(O:O,I:I,'重功超期+活动'!Q33,B:B,"第4代帝豪") -> 0 | AH33: =SUMIFS(O:O,I:I,'重功超期+活动'!Q33,B:B,"第5代帝豪") -> 0 | AI33: =SUM(AF33:AH33) -> 0
A34: 邛崃直营店 | B34: 星越L | E34: LB3781NZ6TS079905 | I34: 邛崃直营店 | J34: 马勇 | X34: =U34 -> 0 | Z34: =COUNTIF(Q:Q,Q34) -> 0 | AD34: =SUM(AA34:AC34) -> 0 | AF34: =SUMIFS(O:O,I:I,'重功超期+活动'!Q34,B:B,"豪越L") -> 0 | AG34: =SUMIFS(O:O,I:I,'重功超期+活动'!Q34,B:B,"第4代帝豪") -> 0 | AH34: =SUMIFS(O:O,I:I,'重功超期+活动'!Q34,B:B,"第5代帝豪") -> 0 | AI34: =SUM(AF34:AH34) -> 0
A35: 机场店网销 | B35: 星越L | E35: LB3781NZ2TS084308 | I35: 机场店网销 | J35: 黄婷婷 | X35: =U35 -> 0 | Z35: =COUNTIF(Q:Q,Q35) -> 0 | AD35: =SUM(AA35:AC35) -> 0 | AF35: =SUMIFS(O:O,I:I,'重功超期+活动'!Q35,B:B,"豪越L") -> 0 | AG35: =SUMIFS(O:O,I:I,'重功超期+活动'!Q35,B:B,"第4代帝豪") -> 0 | AH35: =SUMIFS(O:O,I:I,'重功超期+活动'!Q35,B:B,"第5代帝豪") -> 0 | AI35: =SUM(AF35:AH35) -> 0
A36: 大邑直营店 | B36: 星越L | E36: LB3781NZ7TS079878 | I36: 大邑直营店 | J36: 王海 | X36: =U36 -> 0 | Z36: =COUNTIF(Q:Q,Q36) -> 0 | AD36: =SUM(AA36:AC36) -> 0 | AF36: =SUMIFS(O:O,I:I,'重功超期+活动'!Q36,B:B,"豪越L") -> 0 | AG36: =SUMIFS(O:O,I:I,'重功超期+活动'!Q36,B:B,"第4代帝豪") -> 0 | AH36: =SUMIFS(O:O,I:I,'重功超期+活动'!Q36,B:B,"第5代帝豪") -> 0 | AI36: =SUM(AF36:AH36) -> 0
A37: 电子营销 | B37: 星越L | E37: LB3781NZ3TS087170 | I37: 电子营销 | J37: 王泳文 | X37: =U37 -> 0 | Z37: =COUNTIF(Q:Q,Q37) -> 0 | AD37: =SUM(AA37:AC37) -> 0 | AF37: =SUMIFS(O:O,I:I,'重功超期+活动'!Q37,B:B,"豪越L") -> 0 | AG37: =SUMIFS(O:O,I:I,'重功超期+活动'!Q37,B:B,"第4代帝豪") -> 0 | AH37: =SUMIFS(O:O,I:I,'重功超期+活动'!Q37,B:B,"第5代帝豪") -> 0 | AI37: =SUM(AF37:AH37) -> 0
A38: 机场展厅 | B38: 星越L | E38: LB3781NZ9TS089912 | I38: 机场展厅 | J38: 冯超 | X38: =U38 -> 0 | Z38: =COUNTIF(Q:Q,Q38) -> 0 | AD38: =SUM(AA38:AC38) -> 0 | AF38: =SUMIFS(O:O,I:I,'重功超期+活动'!Q38,B:B,"豪越L") -> 0 | AG38: =SUMIFS(O:O,I:I,'重功超期+活动'!Q38,B:B,"第4代帝豪") -> 0 | AH38: =SUMIFS(O:O,I:I,'重功超期+活动'!Q38,B:B,"第5代帝豪") -> 0 | AI38: =SUM(AF38:AH38) -> 0
A39: 机场店网销 | B39: 星越L | E39: LB3781NZ3TS079652 | I39: 机场店网销 | J39: 赵强 | W39: =SUM(W31:W38) -> 0 | X39: =SUM(X31:X38) -> 0 | Z39: =COUNTIF(Q:Q,Q39) -> 0 | AA39: =SUM(AA31:AA38) -> 0 | AB39: =SUM(AB31:AB38) -> 0 | AC39: =SUM(AC31:AC38) -> 0 | AD39: =SUM(AD31:AD38) -> 0 | AF39: =SUM(AF31:AF38) -> 0 | AG39: =SUM(AG31:AG38) -> 0 | AH39: =SUM(AH31:AH38) -> 0 | AI39: =SUM(AI31:AI38) -> 0
P40: 网销 | X40: =U40 -> 0 | Z40: =COUNTIF(Q:Q,Q40) -> 0 | AD40: =SUM(AA40:AC40) -> 0 | AF40: =SUMIFS(O:O,I:I,'重功超期+活动'!Q40,B:B,"豪越L") -> 0 | AG40: =SUMIFS(O:O,I:I,'重功超期+活动'!Q40,B:B,"第4代帝豪") -> 0 | AH40: =SUMIFS(O:O,I:I,'重功超期+活动'!Q40,B:B,"第5代帝豪") -> 0 | AI40: =SUM(AF40:AH40) -> 0
A41: 机场展厅 | B41: 新博越 | E41: LB37722Z3SX720488 | I41: 机场展厅 | J41: 冯超 | X41: =U41 -> 0 | Z41: =COUNTIF(Q:Q,Q41) -> 0 | AD41: =SUM(AA41:AC41) -> 0 | AF41: =SUMIFS(O:O,I:I,'重功超期+活动'!Q41,B:B,"豪越L") -> 0 | AG41: =SUMIFS(O:O,I:I,'重功超期+活动'!Q41,B:B,"第4代帝豪") -> 0 | AH41: =SUMIFS(O:O,I:I,'重功超期+活动'!Q41,B:B,"第5代帝豪") -> 0 | AI41: =SUM(AF41:AH41) -> 0
A42: 机场店新媒体 | B42: 第5代帝豪 | E42: LB37824Z9SG160986 | I42: 机场店新媒体 | J42: 刘波 | X42: =U42 -> 0 | Z42: =COUNTIF(Q:Q,Q42) -> 0 | AD42: =SUM(AA42:AC42) -> 0 | AF42: =SUMIFS(O:O,I:I,'重功超期+活动'!Q42,B:B,"豪越L") -> 0 | AG42: =SUMIFS(O:O,I:I,'重功超期+活动'!Q42,B:B,"第4代帝豪") -> 0 | AH42: =SUMIFS(O:O,I:I,'重功超期+活动'!Q42,B:B,"第5代帝豪") -> 0 | AI42: =SUM(AF42:AH42) -> 0
X43: =U43 -> 0 | Z43: =COUNTIF(Q:Q,Q43) -> 0 | AD43: =SUM(AA43:AC43) -> 0 | AF43: =SUMIFS(O:O,I:I,'重功超期+活动'!Q43,B:B,"豪越L") -> 0 | AG43: =SUMIFS(O:O,I:I,'重功超期+活动'!Q43,B:B,"第4代帝豪") -> 0 | AH43: =SUMIFS(O:O,I:I,'重功超期+活动'!Q43,B:B,"第5代帝豪") -> 0 | AI43: =SUM(AF43:AH43) -> 0
X44: =U44 -> 0 | Z44: =COUNTIF(Q:Q,Q44) -> 0 | AD44: =SUM(AA44:AC44) -> 0 | AF44: =SUMIFS(O:O,I:I,'重功超期+活动'!Q44,B:B,"豪越L") -> 0 | AG44: =SUMIFS(O:O,I:I,'重功超期+活动'!Q44,B:B,"第4代帝豪") -> 0 | AH44: =SUMIFS(O:O,I:I,'重功超期+活动'!Q44,B:B,"第5代帝豪") -> 0 | AI44: =SUM(AF44:AH44) -> 0
X45: =U45 -> 0 | Z45: =COUNTIF(Q:Q,Q45) -> 0 | AD45: =SUM(AA45:AC45) -> 0 | AF45: =SUMIFS(O:O,I:I,'重功超期+活动'!Q45,B:B,"豪越L") -> 0 | AG45: =SUMIFS(O:O,I:I,'重功超期+活动'!Q45,B:B,"第4代帝豪") -> 0 | AH45: =SUMIFS(O:O,I:I,'重功超期+活动'!Q45,B:B,"第5代帝豪") -> 0 | AI45: =SUM(AF45:AH45) -> 0
X46: =U46 -> 0 | Z46: =COUNTIF(Q:Q,Q46) -> 0 | AD46: =SUM(AA46:AC46) -> 0 | AF46: =SUMIFS(O:O,I:I,'重功超期+活动'!Q46,B:B,"豪越L") -> 0 | AG46: =SUMIFS(O:O,I:I,'重功超期+活动'!Q46,B:B,"第4代帝豪") -> 0 | AH46: =SUMIFS(O:O,I:I,'重功超期+活动'!Q46,B:B,"第5代帝豪") -> 0 | AI46: =SUM(AF46:AH46) -> 0
X47: =U47 -> 0 | Z47: =COUNTIF(Q:Q,Q47) -> 0 | AD47: =SUM(AA47:AC47) -> 0 | AF47: =SUMIFS(O:O,I:I,'重功超期+活动'!Q47,B:B,"豪越L") -> 0 | AG47: =SUMIFS(O:O,I:I,'重功超期+活动'!Q47,B:B,"第4代帝豪") -> 0 | AH47: =SUMIFS(O:O,I:I,'重功超期+活动'!Q47,B:B,"第5代帝豪") -> 0 | AI47: =SUM(AF47:AH47) -> 0
X48: =U48 -> 0 | Z48: =COUNTIF(Q:Q,Q48) -> 0 | AD48: =SUM(AA48:AC48) -> 0 | AF48: =SUMIFS(O:O,I:I,'重功超期+活动'!Q48,B:B,"豪越L") -> 0 | AG48: =SUMIFS(O:O,I:I,'重功超期+活动'!Q48,B:B,"第4代帝豪") -> 0 | AH48: =SUMIFS(O:O,I:I,'重功超期+活动'!Q48,B:B,"第5代帝豪") -> 0 | AI48: =SUM(AF48:AH48) -> 0
V49: =SUM(V40:V48) -> 0 | W49: =SUM(W40:W48) -> 0 | X49: =SUM(X40:X48) -> 0 | Z49: =COUNTIF(Q:Q,Q49) -> 0 | AA49: =SUM(AA40:AA48) -> 0 | AB49: =SUM(AB40:AB48) -> 0 | AC49: =SUM(AC40:AC48) -> 0 | AD49: =SUM(AD40:AD48) -> 0 | AF49: =SUM(AF40:AF48) -> 0 | AG49: =SUM(AG40:AG48) -> 0 | AH49: =SUM(AH40:AH48) -> 0 | AI49: =SUM(AI40:AI48) -> 0
X50: =SUM(X49) -> 0 | Z50: =COUNTIF(Q:Q,Q50) -> 0
P51: 合计 | X51: =X49+X39 -> 0 | Z51: =COUNTIF(Q:Q,Q51) -> 0 | AD51: =AD49+AD39 -> 0 | AI51: =AI49+AI39 -> 0
P53: 3月
P54: 部门 | Q54: 人员 | R54: 任务量 | S54: 订车 | T54: 订单进度 | U54: 交车 | V54: 重攻考核 | W54: 合计实发 | X54: 合计实发 | Z54: =COUNTIF(Q:Q,Q54) -> 3 | AA54: 豪越 | AB54: 第四帝豪 | AC54: 第五帝豪 | AD54: =AD3 -> 合计实发 | AF54: 豪越 | AG54: 第四帝豪 | AH54: 第五帝豪 | AI54: =AI3 -> 合计实发
W55: =SUM(U55:V55) -> 0 | X55: =V55+W55 -> 0 | Z55: =COUNTIF(Q:Q,Q55) -> 0 | AD55: =SUM(AA55:AC55) -> 0 | AF55: =SUMIFS(O:O,I:I,'重功超期+活动'!Q55,B:B,"豪越L") -> 0 | AG55: =SUMIFS(O:O,I:I,'重功超期+活动'!Q55,B:B,"第4代帝豪") -> 0 | AH55: =SUMIFS(O:O,I:I,'重功超期+活动'!Q55,B:B,"第5代帝豪") -> 0 | AI55: =SUM(AF55:AH55) -> 0
W56: =SUM(U56:V56) -> 0 | X56: =V56+W56 -> 0 | Z56: =COUNTIF(Q:Q,Q56) -> 0 | AD56: =SUM(AA56:AC56) -> 0 | AF56: =SUMIFS(O:O,I:I,'重功超期+活动'!Q56,B:B,"豪越L") -> 0 | AG56: =SUMIFS(O:O,I:I,'重功超期+活动'!Q56,B:B,"第4代帝豪") -> 0 | AH56: =SUMIFS(O:O,I:I,'重功超期+活动'!Q56,B:B,"第5代帝豪") -> 0 | AI56: =SUM(AF56:AH56) -> 0
W57: =SUM(U57:V57) -> 0 | X57: =V57+W57 -> 0 | Z57: =COUNTIF(Q:Q,Q57) -> 0 | AD57: =SUM(AA57:AC57) -> 0 | AF57: =SUMIFS(O:O,I:I,'重功超期+活动'!Q57,B:B,"豪越L") -> 0 | AG57: =SUMIFS(O:O,I:I,'重功超期+活动'!Q57,B:B,"第4代帝豪") -> 0 | AH57: =SUMIFS(O:O,I:I,'重功超期+活动'!Q57,B:B,"第5代帝豪") -> 0 | AI57: =SUM(AF57:AH57) -> 0
W58: =SUM(U58:V58) -> 0 | X58: =V58+W58 -> 0 | Z58: =COUNTIF(Q:Q,Q58) -> 0 | AD58: =SUM(AA58:AC58) -> 0 | AF58: =SUMIFS(O:O,I:I,'重功超期+活动'!Q58,B:B,"豪越L") -> 0 | AG58: =SUMIFS(O:O,I:I,'重功超期+活动'!Q58,B:B,"第4代帝豪") -> 0 | AH58: =SUMIFS(O:O,I:I,'重功超期+活动'!Q58,B:B,"第5代帝豪") -> 0 | AI58: =SUM(AF58:AH58) -> 0
W59: =SUM(U59:V59) -> 0 | X59: =V59+W59 -> 0 | Z59: =COUNTIF(Q:Q,Q59) -> 0 | AD59: =SUM(AA59:AC59) -> 0 | AF59: =SUMIFS(O:O,I:I,'重功超期+活动'!Q59,B:B,"豪越L") -> 0 | AG59: =SUMIFS(O:O,I:I,'重功超期+活动'!Q59,B:B,"第4代帝豪") -> 0 | AH59: =SUMIFS(O:O,I:I,'重功超期+活动'!Q59,B:B,"第5代帝豪") -> 0 | AI59: =SUM(AF59:AH59) -> 0
W60: =SUM(U60:V60) -> 0 | X60: =V60+W60 -> 0 | Z60: =COUNTIF(Q:Q,Q60) -> 0 | AD60: =SUM(AA60:AC60) -> 0 | AF60: =SUMIFS(O:O,I:I,'重功超期+活动'!Q60,B:B,"豪越L") -> 0 | AG60: =SUMIFS(O:O,I:I,'重功超期+活动'!Q60,B:B,"第4代帝豪") -> 0 | AH60: =SUMIFS(O:O,I:I,'重功超期+活动'!Q60,B:B,"第5代帝豪") -> 0 | AI60: =SUM(AF60:AH60) -> 0
W61: =SUM(U61:V61) -> 0 | X61: =V61+W61 -> 0 | Z61: =COUNTIF(Q:Q,Q61) -> 0 | AD61: =SUM(AA61:AC61) -> 0 | AF61: =SUMIFS(O:O,I:I,'重功超期+活动'!Q61,B:B,"豪越L") -> 0 | AG61: =SUMIFS(O:O,I:I,'重功超期+活动'!Q61,B:B,"第4代帝豪") -> 0 | AH61: =SUMIFS(O:O,I:I,'重功超期+活动'!Q61,B:B,"第5代帝豪") -> 0 | AI61: =SUM(AF61:AH61) -> 0
W62: =SUM(U62:V62) -> 0 | X62: =V62+W62 -> 0 | Z62: =COUNTIF(Q:Q,Q62) -> 0 | AD62: =SUM(AA62:AC62) -> 0 | AF62: =SUMIFS(O:O,I:I,'重功超期+活动'!Q62,B:B,"豪越L") -> 0 | AG62: =SUMIFS(O:O,I:I,'重功超期+活动'!Q62,B:B,"第4代帝豪") -> 0 | AH62: =SUMIFS(O:O,I:I,'重功超期+活动'!Q62,B:B,"第5代帝豪") -> 0 | AI62: =SUM(AF62:AH62) -> 0
W63: =SUM(U63:V63) -> 0 | X63: =V63+W63 -> 0 | Z63: =COUNTIF(Q:Q,Q63) -> 0 | AD63: =SUM(AA63:AC63) -> 0 | AF63: =SUMIFS(O:O,I:I,'重功超期+活动'!Q63,B:B,"豪越L") -> 0 | AG63: =SUMIFS(O:O,I:I,'重功超期+活动'!Q63,B:B,"第4代帝豪") -> 0 | AH63: =SUMIFS(O:O,I:I,'重功超期+活动'!Q63,B:B,"第5代帝豪") -> 0 | AI63: =SUM(AF63:AH63) -> 0
W64: =SUM(U64:V64) -> 0 | X64: =V64+W64 -> 0 | Z64: =COUNTIF(Q:Q,Q64) -> 0 | AD64: =SUM(AA64:AC64) -> 0 | AF64: =SUMIFS(O:O,I:I,'重功超期+活动'!Q64,B:B,"豪越L") -> 0 | AG64: =SUMIFS(O:O,I:I,'重功超期+活动'!Q64,B:B,"第4代帝豪") -> 0 | AH64: =SUMIFS(O:O,I:I,'重功超期+活动'!Q64,B:B,"第5代帝豪") -> 0 | AI64: =SUM(AF64:AH64) -> 0
W65: =SUM(U65:V65) -> 0 | X65: =V65+W65 -> 0 | Z65: =COUNTIF(Q:Q,Q65) -> 0 | AD65: =SUM(AA65:AC65) -> 0 | AF65: =SUMIFS(O:O,I:I,'重功超期+活动'!Q65,B:B,"豪越L") -> 0 | AG65: =SUMIFS(O:O,I:I,'重功超期+活动'!Q65,B:B,"第4代帝豪") -> 0 | AH65: =SUMIFS(O:O,I:I,'重功超期+活动'!Q65,B:B,"第5代帝豪") -> 0 | AI65: =SUM(AF65:AH65) -> 0
W66: =SUM(U66:V66) -> 0 | X66: =V66+W66 -> 0 | Z66: =COUNTIF(Q:Q,Q66) -> 0 | AD66: =SUM(AA66:AC66) -> 0 | AF66: =SUMIFS(O:O,I:I,'重功超期+活动'!Q66,B:B,"豪越L") -> 0 | AG66: =SUMIFS(O:O,I:I,'重功超期+活动'!Q66,B:B,"第4代帝豪") -> 0 | AH66: =SUMIFS(O:O,I:I,'重功超期+活动'!Q66,B:B,"第5代帝豪") -> 0 | AI66: =SUM(AF66:AH66) -> 0
... W79: =SUM(U79:V79) -> 0 | X79: =V79+W79 -> 0 | Z79: =COUNTIF(Q:Q,Q79) -> 0 | AD79: =SUM(AA79:AC79) -> 0 | AF79: =SUMIFS(O:O,I:I,'重功超期+活动'!Q79,B:B,"豪越L") -> 0 | AG79: =SUMIFS(O:O,I:I,'重功超期+活动'!Q79,B:B,"第4代帝豪") -> 0 | AH79: =SUMIFS(O:O,I:I,'重功超期+活动'!Q79,B:B,"第5代帝豪") -> 0 | AI79: =SUM(AF79:AH79) -> 0
X80: =V80+W80 -> 0 | Z80: =COUNTIF(Q:Q,Q80) -> 0 | AD80: =SUM(AA80:AC80) -> 0 | AF80: =SUMIFS(O:O,I:I,'重功超期+活动'!Q80,B:B,"豪越L") -> 0 | AG80: =SUMIFS(O:O,I:I,'重功超期+活动'!Q80,B:B,"第4代帝豪") -> 0 | AH80: =SUMIFS(O:O,I:I,'重功超期+活动'!Q80,B:B,"第5代帝豪") -> 0 | AI80: =SUM(AF80:AH80) -> 0
P81: 合计 | V81: =SUM(V55:V80) -> 0 | X81: =SUM(X55:X80) -> 0 | Z81: =COUNTIF(Q:Q,Q81) -> 0 | AD81: =SUM(AD55:AD80) -> 0 | AI81: =SUM(AI55:AI80) -> 0

Sheet 保客考核明细
A1: 公司 | B1: 大部 | C1: 分部 | D1: 店别 | E1: 姓名 | F1: 岗位 | G1: 入职日期 | H1: 1季度目标任务量 | I1: 1季度实际达成量 | J1: 考核
A2: 西物汽车 | B2: 管理人员 | C2: 管理部 | D2: 武侯店 | E2: 陈俊霖 | F2: 总经理
A3: 西物汽车 | B3: 管理人员 | C3: 销售财务部 | D3: 武侯店 | E3: 顾雪梅 | F3: 财务经理
A4: 西物汽车 | B4: 销售后勤二线 | C4: 销售财务部 | D4: 武侯店 | E4: 丁红 | F4: 财务主管
A5: 吉利超市 | B5: 销售后勤二线 | C5: 销售财务部 | D5: 武侯店 | E5: 沈燕 | F5: 销售财务收银
A6: 吉利超市 | B6: 销售后勤二线 | C6: 销售财务部 | D6: 机场店 | E6: 高敏 | F6: 销售财务收银
A7: 西物汽车 | B7: 销售后勤二线 | C7: 销售财务部 | D7: 武侯店 | E7: 罗涵 | F7: 销售财务会计
A8: 吉利超市 | B8: 销售后勤二线 | C8: 销售财务部 | D8: 武侯店 | E8: 唐梁英 | F8: 销售财务收银
A9: 吉利超市 | B9: 销售后勤二线 | C9: 销售财务部 | D9: 武侯店 | E9: 李芳 | F9: 销售财务出纳
A10: 西物汽车 | B10: 销售后勤二线 | C10: 销售财务部 | D10: 武侯店 | E10: 邓琦琪 | F10: 销售财务会计助理
A11: 西物汽车 | B11: 销售后勤二线 | C11: 销售财务部 | D11: 武侯店 | E11: 李佳乐 | F11: 销售财务会计助理
A12: 西物汽车 | B12: 管理人员 | C12: 行政人事部 | D12: 武侯店 | E12: 林琼 | F12: 行政人事总监
A13: 西物汽车 | B13: 销售后勤二线 | C13: 行政人事部 | D13: 武侯店 | E13: 周小红 | F13: 行政人事主管
... A88: 吉利超市 | B88: 销售一线 | C88: 销售部直营店 | D88: 崇州直营店 | E88: 杨婷 | F88: 销售邀约专员
A89: 吉利超市 | B89: 管理人员 | C89: 管理部 | D89: 武侯店 | E89: 曾吉斌
A90: 吉利超市 | B90: 管理人员 | C90: 管理部 | D90: 武侯店 | E90: 曹磊
A91: 吉利超市 | B91: 管理人员 | C91: 售后业务部 | D91: 武侯店 | E91: 谢尧江
A92: 吉利超市 | B92: 售后二线 | C92: 售后财务部 | D92: 武侯店 | E92: 张敏
A93: 吉利超市 | B93: 售后二线 | C93: 售后财务部 | D93: 武侯店 | E93: 邱小艳
A94: 吉利超市 | B94: 售后二线 | C94: 售后财务部 | D94: 武侯店 | E94: 潘倩
A95: 吉利超市 | B95: 售后二线 | C95: 售后续保部 | D95: 武侯店 | E95: 黄意轩
A96: 吉利超市 | B96: 售后二线 | C96: 售后续保部 | D96: 武侯店 | E96: 赵水仙
A97: 吉利超市 | B97: 售后二线 | C97: 售后续保部 | D97: 武侯店 | E97: 张琴
A98: 吉利超市 | B98: 售后二线 | C98: 售后续保部 | D98: 武侯店 | E98: 唐芳兰
A99: 吉利超市 | B99: 售后二线 | C99: 售后续保部 | D99: 武侯店 | E99: 罗文琦
A100: 吉利超市 | B100: 售后二线 | C100: 售后续保部 | D100: 武侯店 | E100: 高梓绮
... A120: 西物汽车 | B120: 售后二线 | C120: 售后客服部 | D120: 机场店 | E120: 况婷婷
A121: 西物汽车 | B121: 管理人员 | C121: 管理部 | D121: 武侯店 | E121: 刘伟生 | F121: 事业部总经理
A122: 西物汽车 | B122: 管理人员 | C122: 管理部 | D122: 武侯店 | E122: 代蓓 | F122: 事业部油车总经理
A123: 西物汽车 | B123: 管理人员 | C123: 管理部 | D123: 武侯店 | E123: 齐坤忠 | F123: 事业部副总经理
A124: 西物汽车 | B124: 管理人员 | C124: 管理部 | D124: 武侯店 | E124: 汤小明 | F124: 事业部水平业务总监
A125: 西物汽车 | B125: 管理人员 | C125: 管理部 | D125: 武侯店 | E125: 唐玲 | F125: 事业部内勤
A126: 西物汽车 | B126: 管理人员 | C126: 管理部 | D126: 武侯店 | E126: 冯岚 | F126: 保客营销总监

Sheet 直营店交车
A1: 序号 | B1: 销售区域 | C1: 车型 | D1: 车架号 | E1: 客户姓名 | F1: 销售顾问 | H1: 交车日期
B2: 直营店-彭州 | C2: 星瑞 | D2: L6T7924Z1TD052132 | E2: 张长建 | F2: 兰代全 | H2: 2026.5.1
B3: 直营店-崇州 | C3: 吉利星愿 | D3: L6T75MNN4TF357776 | E3: 宣静 | F3: 唐鹏 | H3: 2026.5.1
B4: 直营店-崇州 | C4: 吉利星愿 | D4: LB375HNN5TX412905 | E4: 吴小鹏 | F4: 赵思梵 | H4: 2026.5.2
B5: 直营店-邛崃 | C5: 吉利星愿 | D5: L6T75LNN8TF354678 | E5: 王丽0629 | F5: 马勇 | H5: 2026.5.2
B6: 直营店-崇州 | C6: 新博越 | D6: LB37722Z0TX312032X | E6: 唐亮1310 | F6: 赵思梵 | H6: 2026.5.2
B7: 直营店-崇州 | C7: 博越L | D7: LB37822Z4TB045200 | E7: 王菲菲 | F7: 唐鹏 | H7: 2026.5.2
B8: 直营店-彭州 | C8: 星瑞 | D8: L6T7924Z9TD010145 | E8: 李祥1011 | F8: 钟家林 | H8: 2026.5.3
B9: 直营店-彭州 | C9: 星越L | D9: LB37852Z3TS057422 | E9: 刘永强0711 | F9: 兰代全 | H9: 2026.5.3
B10: 直营店-彭州 | C10: 星越L | D10: LB37852Z5TS063755 | E10: 周建483X | F10: 钟家林 | H10: 2026.5.3
B11: 直营店-崇州 | C11: 吉利星愿 | D11: L6T75MNN3TF358837 | E11: 焦影 | F11: 陈勇建 | H11: 2026.5.3
B12: 直营店-邛崃 | C12: 吉利星愿 | D12: L6T75MNNXTF359144 | E12: 熊建成 | F12: 叶荣鹏 | H12: 2026.5.4
B13: 直营店-大邑 | C13: 熊猫卡丁 | D13: LB370ADN4TJ103453 | E13: 张玲6120 | F13: 程羊 | H13: 2026.5.4
... B57: 直营店-华阳 | C57: 银河A7 EV | D57: L6T79NBW7TY457107 | E57: 丁应 | F57: 张坤 | H57: 2026.5.7
B58: 直营店-崇州 | C58: 吉利星愿 | D58: L6T75LNN3TF356080 | E58: 李晓艳 | F58: 宁袁 | H58: 2026.5.8 | J58: 雅安车
B59: 直营店-彭州 | C59: 五代帝豪 | D59: LB37824Z2TG026841 | E59: 杨作英 | F59: 任和奎 | H59: 2026.5.8
B60: 直营店-邛崃 | C60: 吉利星愿 | D60: L6T75LNN3TF352868 | E60: 赵德兵 | F60: 叶荣鹏 | H60: 2026.5.8
B61: 直营店-邛崃 | C61: 博越L | D61: LB37822Z4TB021124 | E61: 赵伟005 | F61: 马勇 | H61: 2026.5.8
B62: 直营店-邛崃 | C62: 银河E5 | D62: L6T78CNW6SY216690 | E62: 李玉巧 | F62: 马勇 | H62: 2026.5.8
B63: 直营店-彭州 | C63: 吉利星愿 | D63: L6T75MNN8TF362091 | E63: 蒋晨 | F63: 刘娅 | H63: 2026.5.9
B64: 直营店-彭州 | C64: 银河A7 | D64: L6T791RZ5SY537531 | E64: 彭浩岚 | F64: 刘娅 | H64: 2026.5.10
B65: 直营店-崇州 | C65: 新博越 | D65: LB37722Z5TX314522 | E65: 黄鑫6335 | F65: 赵思梵 | H65: 2026.5.10
B66: 直营店-崇州 | C66: 星瑞 | D66: L6T7924Z3TD048728 | E66: 魏宇 | F66: 唐鹏 | H66: 2026.5.10
B67: 直营店-崇州 | C67: 博越L | D67: LB37822Z1TB034705 | E67: 邓定海 | F67: 赵思梵 | H67: 2026.5.11
B68: 直营店-大邑 | C68: 缤越超能版 | D68: LB37622Z0TX812517X | E68: 张华杰 | F68: 王海 | H68: 2026.5.11
B69: 直营店-彭州 | C69: 博越L | D69: LB37822Z1TB034056 | E69: 涂国华 | F69: 钟家林 | H69: 2026.5.11
B70: 直营店-崇州 | C70: 五代帝豪 | D70: LB37824Z1TG026166X | E70: 肖杨4878 | F70: 赵思梵 | H70: 2026.5.11
... B168: 直营店-华阳 | C168: 银河A7 | D168: L6T791RZ1SY537929 | E168: 雷华勇 | F168: 吴小琴 | H168: 2026.5.27
B169: 直营店-崇州 | C169: 吉利星愿 | D169: L6T75LNN6TF357515 | E169: 胡建洪 | F169: 宁袁 | H169: 2026.5.27 | J169: 绵阳车
B170: 直营店-彭州 | C170: 熊猫卡丁 | D170: LB370ADN3TJ106070 | E170: 岳倩 | F170: 钟家林 | H170: 2026.5.27
B171: 直营店二网-大邑 | C171: 博越L | D171: LB37822Z4TB021026X | E171: 鄢淑芳 | F171: 余才万1 | H171: 2026.5.27
B172: 直营店-华阳 | C172: 星越L | D172: LB37852Z9TS050801 | E172: 贾勇7318 | F172: 丁小玲 | H172: 2026.5.27
B173: 直营店-彭州 | C173: 星瑞 | D173: L6T7924Z9TD052802X | E173: 张志友2222 | F173: 刘娅 | H173: 2026.5.27
B174: 直营店-华阳 | C174: 星越L | D174: LB37852ZXTS028581 | E174: 齐晚霞 | F174: 张坤 | H174: 2026.5.27
B175: 直营店-邛崃 | C175: 星瑞 | D175: L6T7924Z3TD056019X | E175: 陈静5120 | F175: 马勇 | H175: 2026.5.27
B176: 直营店-邛崃 | C176: 豪越L | D176: L6T7922Z6TY871603X | E176: 王志康 | F176: 高东琴 | H176: 2026.5.27
B177: 直营店-崇州 | C177: 博越L | D177: LB37822ZXSB207636 | E177: 雷杰9236 | F177: 赵思梵 | H177: 2026.5.28
B178: 直营店-金堂 | C178: 博越L | D178: LB37822Z1TB043856X | E178: 蒲佳赓 | F178: 文科 | H178: 2026.5.29
B179: 直营店-崇州 | C179: 星瑞 | D179: L6T7924Z1TD010009X | E179: 杨建伟5812 | F179: 陈勇建 | H179: 2026.5.30
B180: 直营店-彭州 | C180: 银河星舰7 | D180: LB3781NZ3SH151932 | E180: 晏光燕 | F180: 钟家林 | H180: 2026.5.30
B181: 直营店-大邑 | C181: 星越L | D181: LB37852Z4TS067456 | E181: 刘光才5832 | F181: 王海 | H181: 2026.5.31
B182: 直营店-大邑 | C182: 银河A7 | D182: L6T791RZ7SY529592 | E182: 刘姗 | F182: 王海 | H182: 2026.5.31 | J182: 绵阳车
B183: 直营店-彭州 | C183: 博越L | D183: LB37822Z4TB045181X | E183: 李思宇0234 | F183: 兰代全 | H183: 2026.5.31
B184: 直营店-彭州 | C184: 星越L | D184: LB37852Z6SS265065 | E184: 刘丛鑫 | F184: 陈莉 | H184: 2026.5.31
B185: 直营店-彭州 | C185: 博越L | D185: LB37822Z5TB045223 | E185: 王伊婷 | F185: 兰代全 | H185: 2026.5.31
B186: 直营店-华阳 | C186: 新博越 | D186: LB37722Z3TX307553 | E186: 刘芳3721 | F186: 张坤 | H186: 2026.5.31
B187: 直营店-崇州 | C187: 银河星耀8 | D187: L6T791RZ1SU027846 | E187: 高燕红 | F187: 陈勇建 | H187: 2026.5.31
B188: 直营店-彭州 | C188: 星瑞 | D188: L6T7924Z4TD055770X | E188: 孟银花1123 | F188: 任和奎 | H188: 2026.5.31
B189: 直营店-彭州 | C189: 星越L | D189: LB37852Z9TS067243 | E189: 倪邦洪 | F189: 兰代全 | H189: 2026.5.31
B190: 直营店-崇州 | C190: 吉利星愿 | D190: LB375GNN3TX009970 | E190: 阳文松 | F190: 赵思梵 | H190: 2026.5.31

Sheet 翼真考核
A1: 翼真考核数据统计表-5月
D2: 集客-600 | H2: 邀约进店率-600 | L2: 试驾率-800 | P2: 任务达成率-600 | T2: 垂媒发帖率-200 | X2: 直播率-200 | AB2: 有责底薪合计 | AC2: 发放金额
A3: 店名 | B3: 岗位 | C3: 姓名 | D3: 任务目标 | E3: 实际达成 | F3: 达成率 | G3: 提成金额 | H3: 任务目标 | I3: 实际达成 | J3: 达成率 | K3: 提成金额 | L3: 任务目标 | M3: 实际达成 | N3: 达成率 | O3: 提成金额 | P3: 任务目标 | Q3: 实际达成 | R3: 达成率 | S3: 提成金额 | T3: 任务目标 | U3: 实际达成 | V3: 达成率 | W3: 提成金额 | X3: 任务目标 | Y3: 实际达成 | Z3: 达成率 | AA3: 提成金额
A4: 分配比例
A5: 翼真-销售 | B5: 销售总监 | C5: 薛祥建 | D5: / | E5: / | F5: / | G5: / | H5: / | I5: / | J5: / | K5: / | L5: / | M5: / | N5: / | O5: / | P5: / | Q5: / | R5: / | S5: / | T5: / | U5: / | V5: / | W5: / | X5: / | Y5: / | Z5: / | AA5: / | AB5: =SUM(G5,K5,O5,S5,W5,AA5) -> 0
B6: 销售顾问 | C6: 韩柏成 | F6: =E6/D6 -> #DIV/0! | G6: =IF(F6>=1,$G$4,IF(F6<1,F6*$G$4)) -> #DIV/0! | J6: =I6/H6 -> #DIV/0! | K6: =IF(J6>=1,$K$4,IF(J6<1,J6*$K$4)) -> #DIV/0! | N6: =M6/L6 -> #DIV/0! | O6: =IF(N6>=1,$O$4,IF(N6<1,N6*$O$4)) -> #DIV/0! | P6: / | R6: / | V6: =U6/T6 -> #DIV/0! | W6: =IF(V6>=1,$W$4,IF(V6<1,V6*$W$4)) -> #DIV/0! | Z6: =Y6/X6 -> #DIV/0! | AA6: =IF(Z6>=1,$AA$4,IF(Z6<1,Z6*$W$4)) -> #DIV/0! | AB6: =SUM(G6,K6,O6,S6,W6,AA6) -> #DIV/0! | AC6: =AB6 -> #DIV/0!
B7: 销售顾问 | C7: 沈燕1 | F7: =E7/D7 -> #DIV/0! | G7: =IF(F7>=1,$G$4,IF(F7<1,F7*$G$4)) -> #DIV/0! | J7: =I7/H7 -> #DIV/0! | K7: =IF(J7>=1,$K$4,IF(J7<1,J7*$K$4)) -> #DIV/0! | N7: =M7/L7 -> #DIV/0! | O7: =IF(N7>=1,$O$4,IF(N7<1,N7*$O$4)) -> #DIV/0! | P7: / | R7: / | V7: =U7/T7 -> #DIV/0! | W7: =IF(V7>=1,$W$4,IF(V7<1,V7*$W$4)) -> #DIV/0! | Z7: =Y7/X7 -> #DIV/0! | AA7: =IF(Z7>=1,$AA$4,IF(Z7<1,Z7*$W$4)) -> #DIV/0! | AB7: =SUM(G7,K7,O7,S7,W7,AA7) -> #DIV/0! | AC7: =AB7 -> #DIV/0!
B8: 兼职销售 | C8: 吴嘉敏 | F8: =E8/D8 -> #DIV/0! | G8: =IF(F8>=1,$G$4,IF(F8<1,F8*$G$4)) -> #DIV/0! | J8: =I8/H8 -> #DIV/0! | K8: =IF(J8>=1,$K$4,IF(J8<1,J8*$K$4)) -> #DIV/0! | N8: =M8/L8 -> #DIV/0! | O8: =IF(N8>=1,$O$4,IF(N8<1,N8*$O$4)) -> #DIV/0! | P8: / | R8: / | V8: =U8/T8 -> #DIV/0! | W8: =IF(V8>=1,$W$4,IF(V8<1,V8*$W$4)) -> #DIV/0! | Z8: =Y8/X8 -> #DIV/0! | AA8: =IF(Z8>=1,$AA$4,IF(Z8<1,Z8*$W$4)) -> #DIV/0! | AB8: =SUM(G8,K8,O8,S8,W8,AA8) -> #DIV/0! | AC8: =AB8 -> #DIV/0!
B9: 小计 | AB9: =SUM(G9,K9,O9,S9,W9,AA9) -> 0 | AC9: =SUM(AC3:AC8) -> #DIV/0!
A14: 新媒体考核数据 | B14: 岗位 | D14: 直播任务（月/场） | E14: 提成标准（实习期80/场） | F14: 实际播放场次 | G14: 实际提成金额 | H14: 视频（月/条） | I14: 提成标准（元）40 | J14: 实际视频量 | K14: 实际提成金额 | L14: 线索量（月/条） | M14: 提成标准（元） | N14: 线索量 | O14: 提成金额 | P14: 自行邀约量 | Q14: 提成标准 | R14: 提成金额 | S14: 他人邀约量 | T14: 提成标准 | U14: 提成金额 | V14: 大定成交量 | W14: 提成标准 | X14: 提成金额 | Y14: 交付量 | Z14: 提成标准 | AA14: 提成金额 | AC14: 合计金额
A15: 翼真-新媒体 | B15: 直播专员 | C15: 蒋利 | G15: =IF(F15>=D15,E15,IF(F15<D15,E15/D15*F15)) -> 0 | K15: =IF(J15>=H15,I15,IF(J15<H15,I15/H15*J15)) -> 0 | O15: =IF(N15<=L15,N15*M15,IF(N15>L15,1500)) -> 0 | R15: =P15*Q15 -> 0 | U15: =S15*T15 -> 0 | X15: =V15*W15 -> 0 | AA15: =Y15*Z15 -> 0 | AC15: =SUM(G15,K15,O15,R15,U15,X15,AA15) -> 0

Sheet 二手置换 
A1: 序号 | B1: 交易类型 | C1: 新车出库日期 | D1: 旧车车主 | E1: 车主电话 | F1: 旧车上户日期 | G1: 车型名称 | H1: 车架号 | I1: 车牌号 | J1: 购进日期 | K1: 购进金额 | L1: 处置日期 | M1: 二手车商名称 | N1: 处置金额 | O1: 毛利 | P1: 新客户姓名 | Q1: 联系电话 | R1: 销售公司 | S1: 车型 | T1: 车架号 | U1: 整车开票金额 | V1: 厂家置换政策 | W1: 客户置换补贴 | X1: 押金金额 | Y1: 公司留存补贴 | Z1: 部门 | AA1: 业务员 | AB1: 旧车处置人员 | AC1: 结余提成 | AD1: 置换提成 | AE1: 合计 | AF1: 备注 | AG1: 比对信息 | AH1: 情况说明
A2: =ROW()-1 -> 1 | B2: 置换 | D2: 张长建 | G2: 雪佛兰牌 | H2: LSGHD52H2FY302833 | I2: 川AV8M25 | P2: 张长建 | R2: 西物 | S2: 星瑞(1.5T) | T2: L6T7924Z1TD052132 | Z2: 彭州直营店 | AA2: 兰代全 | AC2: =Y2*0.14 -> 0 | AD2: =IF(O2>=1000,O2*0.14,IF(O2>=500,100,0)) -> 0 | AE2: =SUM(AC2:AD2) -> 0 | AI2: 5月 | AJ2: 二手车合计情况
A3: =ROW()-1 -> 2 | B3: 置换 | D3: 黄鹏 | F3: 2016.08.41 | G3: 长安 | H3: LS5A2BBR8GH004621 | I3: 渝BHP571 | M3: 和信汇二手车 | P3: 黄鹏 | R3: 超市 | S3: 3代豪越L | T3: L6T7922Z8TY871196 | Z3: 双星展厅 | AA3: 熊杰文 | AB3: 张龙 | AC3: =Y3*0.14 -> 0 | AD3: =IF(O3>=1000,O3*0.14,IF(O3>=500,100,0)) -> 0 | AE3: =SUM(AC3:AD3) -> 0 | AJ3: 完成情况 | AK3: 成交率考核标准 | AN3: 总毛利
A4: =ROW()-1 -> 3 | B4: 置换 | D4: 王超 | G4: 大众 | H4: LFV2A11K6D4227521 | I4: 浙BK2G86 | P4: 王超 | R4: 超市 | S4: 星越L | T4: LB37852Z5TS032506 | Z4: 机场网销 | AA4: 熊俊杰 | AC4: =Y4*0.14 -> 0 | AD4: =IF(O4>=1000,O4*0.14,IF(O4>=500,100,0)) -> 0 | AE4: =SUM(AC4:AD4) -> 0 | AI4: 店面销量(除熊猫) | AJ4: =AJ11 -> 0 | AK4: 50%以上(含) | AN4: =AJ13 -> 0
A5: =ROW()-1 -> 4 | B5: 置换 | D5: 叶文冰 | G5: 大众 | H5: LFV2A2154G3055127 | I5: 冀TL8P01 | M5: 和信汇二手车 | P5: 叶文冰 | R5: 超市 | S5: 星越L | T5: LB37852Z5TS031596 | Z5: 机场展厅 | AA5: 陈林 | AC5: =Y5*0.14 -> 0 | AD5: =IF(O5>=1000,O5*0.14,IF(O5>=500,100,0)) -> 0 | AE5: =SUM(AC5:AD5) -> 0 | AI5: 置换台次 | AJ5: =AL12 -> 0 | AK5: 30%(含)至50%
A6: =ROW()-1 -> 5 | B6: 置换 | D6: 邱思维 | G6: 东风标致 | H6: LDC633T24K3001150 | I6: 川M0233T | M6: 锦栖汇二手车 | P6: 邱思维 | R6: 超市 | S6: 星越L | T6: LB37852Z0TS057572 | Z6: 机场网销 | AA6: 施巍 | AC6: =Y6*0.14 -> 0 | AD6: =IF(O6>=1000,O6*0.14,IF(O6>=500,100,0)) -> 0 | AE6: =SUM(AC6:AD6) -> 0 | AI6: 置换率 | AJ6: =AJ5/AJ4 -> #DIV/0! | AK6: 低于30%
A7: =ROW()-1 -> 6 | B7: 置换 | D7: 曹世华 | G7: 帝豪牌 | H7: LB37824Z7SG012710 | I7: 川F7L0T0 | P7: 曹世华 | R7: 西物 | S7: 星瑞(1.5T) | T7: L6T7924Z5TD018081 | Z7: 机场网销 | AA7: 莫晓何 | AC7: =Y7*0.14 -> 0 | AD7: =IF(O7>=1000,O7*0.14,IF(O7>=500,100,0)) -> 0 | AE7: =SUM(AC7:AD7) -> 0 | AI7: 认证二手车台次 | AJ7: =AJ16+AN16+AJ26 -> 0 | AK7: 奖励(台/元) | AN7: -
A8: =ROW()-1 -> 7 | B8: 报废 | D8: 张燕 | G8: 东风牌D | H8: LDC613P2990950642 | I8: 川A0G84L | P8: 张燕 | R8: 西物 | S8: 第四代博越L | T8: LB37822Z4TB046993 | Z8: 网络部 | AA8: 余才万 | AC8: =Y8*0.14 -> 0 | AD8: =IF(O8>=1000,O8*0.14,IF(O8>=500,100,0)) -> 0 | AE8: =SUM(AC8:AD8) -> 0 | AI8: 二手车按揭台次 | AK8: 奖励 | AL8: 按新车销售顾问方式 | AN8: =AJ17+AN17+AJ27 -> 0
A9: =ROW()-1 -> 8 | B9: 报废 | D9: 王钰萱 | G9: 荣威 | H9: LSJA16E35CG064357 | I9: 川AT1142 | M9: 锦栖汇二手车 | P9: 王钰萱 | R9: 西物 | S9: 星瑞(1.5T) | T9: L6T7954Z9TD054437 | Z9: 双星展厅 | AA9: 毛春秀 | AB9: 张龙 | AC9: =Y9*0.14 -> 0 | AD9: =IF(O9>=1000,O9*0.14,IF(O9>=500,100,0)) -> 0 | AE9: =SUM(AC9:AD9) -> 0
A10: =ROW()-1 -> 9 | B10: 置换 | D10: 黄欠 | F10: 2014.12.14 | G10: 吉利英伦 | H10: LB37824S4EX044568 | I10: 川A7J239 | M10: 八千熊猫二手车 | P10: 黄欠 | R10: 西物 | S10: 第四代博越L | T10: LB37822Z6TB045151 | Z10: 双星新媒体 | AA10: 何伟 | AB10: 张龙 | AC10: =Y10*0.14 -> 0 | AD10: =IF(O10>=1000,O10*0.14,IF(O10>=500,100,0)) -> 0 | AE10: =SUM(AC10:AD10) -> 0 | AI10: 张龙（武侯店+精锐店+超市银河A） | AM10: 白林（机场店+星瑞店+西物银河A）
A11: =ROW()-1 -> 10 | B11: 置换 | D11: 李祥 | G11: 雪佛兰牌 | H11: LSGGJ5456JS195529 | I11: 川A21LF0 | M11: 锦栖汇二手车 | P11: 李祥 | R11: 西物 | S11: 星瑞(1.5T) | T11: L6T7924Z9TD010145 | Z11: 彭州直营店 | AA11: 钟家林 | AC11: =Y11*0.14 -> 0 | AD11: =IF(O11>=1000,O11*0.14,IF(O11>=500,100,0)) -> 0 | AE11: =SUM(AC11:AD11) -> 0 | AI11: 店面销量(除熊猫) | AK11: 收购台次 | AM11: 评估台次 | AO11: 收购台次
A12: =ROW()-1 -> 11 | B12: 置换 | D12: 袁静 | G12: 名爵 | H12: LSJZ14E60CS102186 | I12: 川G9C9H0 | M12: 锦栖汇二手车 | P12: 袁静 | R12: 西物 | S12: ICON | T12: L6T7622Z2TV010719 | Z12: 机场展厅 | AA12: 冯超 | AC12: =Y12*0.14 -> 0 | AD12: =IF(O12>=1000,O12*0.14,IF(O12>=500,100,0)) -> 0 | AE12: =SUM(AC12:AD12) -> 0 | AI12: 置换率 | AJ12: =AL11/AJ11 -> #DIV/0! | AK12: 置换台次 | AM12: 成交率 | AN12: =AP11/AN11 -> #DIV/0! | AO12: 置换台次
A13: =ROW()-1 -> 12 | B13: 置换 | D13: 刘永强 | G13: 帝豪牌 | H13: LB37722Z9JH152000 | I13: 川AS04F9 | P13: 刘永强 | R13: 超市 | S13: 星越L | T13: LB37852Z3TS057422 | Z13: 彭州直营店 | AA13: 兰代全 | AC13: =Y13*0.14 -> 0 | AD13: =IF(O13>=1000,O13*0.14,IF(O13>=500,100,0)) -> 0 | AE13: =SUM(AC13:AD13) -> 0 | AI13: 置换毛利 | AK13: 绩效毛利 | AL13: =IF((AJ13-(2000*AL12))<0,(AJ13-(2000*AL12)),AJ13-(2000*AL12)) -> 0 | AM13: 置换毛利 | AO13: 绩效毛利 | AP13: =IF((AN13-(2000*AP12))<0,(AN13-(2000*AP12)),AN13-(2000*AP12)) -> 0
A14: =ROW()-1 -> 13 | B14: 置换 | D14: 徐高平 | F14: 2016.11.16 | G14: 长安 | H14: LS5A3DBE3GA083386 | I14: 陕A66CP1 | M14: 八千熊猫二手车 | P14: 徐高平 | R14: 超市 | S14: 星越L | T14: LB37852Z7TS038503 | Z14: 双星网销 | AA14: 母勇 | AB14: 张龙 | AC14: =Y14*0.14 -> 0 | AD14: =IF(O14>=1000,O14*0.14,IF(O14>=500,100,0)) -> 0 | AE14: =SUM(AC14:AD14) -> 0 | AI14: 毛利提成标准 | AK14: 考核执行标准 | AM14: 毛利提成标准 | AO14: 考核执行标准
A15: =ROW()-1 -> 14 | B15: 置换 | D15: 朱晓攀 | F15: 2017.5.16 | G15: 吉利 | H15: L6T7824S4HN183370 | I15: 川MMJ885 | P15: 朱晓攀 | R15: 超市 | S15: 星越L | T15: LB37852Z1TS064711 | Z15: 双星展厅 | AA15: 熊杰文 | AC15: =Y15*0.14 -> 0 | AD15: =IF(O15>=1000,O15*0.14,IF(O15>=500,100,0)) -> 0 | AE15: =SUM(AC15:AD15) -> 0 | AI15: 台次提成 | AJ15: =AL12*120 -> 0 | AK15: 毛利提成 | AL15: =IF(AL13>0,AL13*AJ14*AL14,AL13*0.1) -> 0 | AM15: 台次提成 | AN15: =AP12*120 -> 0 | AO15: 毛利提成 | AP15: =IF(AP13>0,AP13*AN14*AP14,AP13*0.1) -> 0
A16: =ROW()-1 -> 15 | B16: 置换 | D16: 周建 | G16: 起亚牌 | H16: LJDLAA29700277597 | I16: 川A0G631 | M16: 许航 | P16: 周建 | R16: 超市 | S16: 星越L | T16: LB37852Z5TS063755 | Z16: 彭州直营店 | AA16: 钟家林 | AC16: =Y16*0.14 -> 0 | AD16: =IF(O16>=1000,O16*0.14,IF(O16>=500,100,0)) -> 0 | AE16: =SUM(AC16:AD16) -> 0 | AI16: 认证二手车台次 | AK16: 认证二手车提成 | AL16: =AJ16*AL7 -> 0 | AM16: 认证二手车台次 | AO16: 认证二手车提成 | AP16: =AN16*AL7 -> 0
A17: =ROW()-1 -> 16 | B17: 置换 | D17: 杨金良 | G17: 大众牌 | H17: LSVAA4BR5EN050100 | I17: 川A9VB58 | M17: 锦栖汇二手车 | P17: 杨金良 | R17: 超市 | S17: 星越L | T17: LB37852Z7SS272252 | Z17: 机场新媒体 | AA17: 邱明杰 | AC17: =Y17*0.14 -> 0 | AD17: =IF(O17>=1000,O17*0.14,IF(O17>=500,100,0)) -> 0 | AE17: =SUM(AC17:AD17) -> 0 | AI17: 按揭服务费 | AK17: 按揭服务费提成 | AL17: =AJ17*0.12 -> 0 | AM17: 按揭服务费 | AO17: 按揭服务费提成 | AP17: =AN17*0.12 -> 0
A18: =ROW()-1 -> 17 | B18: 报废 | D18: 周祥甫 | G18: 吉利牌 | H18: LB37824S8AX048228 | I18: 川A4L60F | P18: 周祥甫 | R18: 超市 | S18: 全新博越 | T18: LB37722ZXTX314905 | Z18: 网络部 | AA18: 余才万 | AC18: =Y18*0.14 -> 0 | AD18: =IF(O18>=1000,O18*0.14,IF(O18>=500,100,0)) -> 0 | AE18: =SUM(AC18:AD18) -> 0 | AI18: 合计 | AJ18: =AJ15+AL15+AL16+AL17 -> 0 | AM18: 合计 | AN18: =AN15+AP15+AP16+AP17 -> 0
A19: =ROW()-1 -> 18 | B19: 报废 | D19: 罗廷芳 | G19: 北京现代牌 | H19: LBERCACB4CX204570 | I19: 川A198KG | P19: 罗廷芳 | R19: 超市 | S19: 星越L | T19: LB37852Z7TS065233 | Z19: 网络部 | AA19: 余才万 | AC19: =Y19*0.14 -> 0 | AD19: =IF(O19>=1000,O19*0.14,IF(O19>=500,100,0)) -> 0 | AE19: =SUM(AC19:AD19) -> 0
A20: =ROW()-1 -> 19 | B20: 报废 | D20: 杨世全 | G20: 昂科雷 | H20: 5GALVCED0AJ241498 | I20: 川1A30G91 | P20: 杨世全 | R20: 西物 | S20: 第四代博越L | T20: LB37822Z5TB045917 | Z20: 彭州直营店 | AA20: 兰代全 | AC20: =Y20*0.14 -> 0 | AD20: =IF(O20>=1000,O20*0.14,IF(O20>=500,100,0)) -> 0 | AE20: =SUM(AC20:AD20) -> 0 | AI20: 张龙（精锐） | AM20: 白林（星瑞）
A21: =ROW()-1 -> 20 | B21: 置换 | D21: 董罗潇 | G21: 猎豹汽车 | H21: LN86GABF8HB024049 | I21: 川S139J1 | P21: 董罗潇 | R21: 西物 | S21: 星瑞(1.5T) | T21: L6T7924Z5TD051663 | Z21: 崇州直营店 | AA21: 赵思梵 | AC21: =Y21*0.14 -> 0 | AD21: =IF(O21>=1000,O21*0.14,IF(O21>=500,100,0)) -> 0 | AE21: =SUM(AC21:AD21) -> 0 | AI21: 店面销量(除熊猫) | AK21: 收购台次 | AM21: 店面销量(除熊猫) | AO21: 收购台次
A22: =ROW()-1 -> 21 | B22: 报废 | D22: 潘云鑫 | G22: 别克牌 | H22: LSGJA52U5CH010628 | I22: 川GN1U51 | P22: 潘云鑫 | R22: 超市 | S22: 星越L | T22: LB37852Z5TS057440 | Z22: 彭州直营店 | AA22: 钟家林 | AC22: =Y22*0.14 -> 0 | AD22: =IF(O22>=1000,O22*0.14,IF(O22>=500,100,0)) -> 0 | AE22: =SUM(AC22:AD22) -> 0 | AI22: 置换率 | AJ22: =AL21/AJ21 -> #DIV/0! | AK22: 置换台次 | AM22: 置换率 | AN22: =AP21/AN21 -> #DIV/0! | AO22: 置换台次
A23: =ROW()-1 -> 22 | B23: 置换 | D23: 付崇阳 | G23: 大众 | H23: LSVFD26R4B2718347 | I23: 川1A1H4C9 | P23: 付崇阳 | R23: 超市 | S23: 星越L | T23: LB37852Z5TS028259 | Z23: 彭州直营店 | AA23: 陈莉 | AC23: =Y23*0.14 -> 0 | AD23: =IF(O23>=1000,O23*0.14,IF(O23>=500,100,0)) -> 0 | AE23: =SUM(AC23:AD23) -> 0 | AI23: 置换毛利 | AK23: 绩效毛利 | AL23: =IF((AJ23-(2000*AL22))<0,(AJ23-(2000*AL22)),AJ23-(2000*AL22)) -> 0 | AM23: 置换毛利 | AO23: 绩效毛利 | AP23: =IF((AN23-(2000*AP22))<0,0,(AN23-(2000*AP22))) -> 0
A24: =ROW()-1 -> 23 | B24: 置换 | D24: 何超杰 | G24: 大众捷达 | H24: LFV2A2BS1C4002216 | I24: 川A9V3C9 | M24: 和信汇二手车 | P24: 何超杰 | R24: 超市 | S24: 星越L | T24: LB37852Z2SS272207 | Z24: 机场新媒体 | AA24: 熊俊杰 | AC24: =Y24*0.14 -> 0 | AD24: =IF(O24>=1000,O24*0.14,IF(O24>=500,100,0)) -> 0 | AE24: =SUM(AC24:AD24) -> 0 | AI24: 毛利提成标准 | AK24: 考核执行标准 | AL24: =AL14 -> 0 | AM24: 毛利提成标准 | AO24: 考核执行标准 | AP24: =AL14 -> 0
A25: =ROW()-1 -> 24 | B25: 置换 | D25: 李昌洪 | G25: 吉利 | H25: L6T7824Z1RD014508 | I25: 川E033G7 | M25: 锦栖汇二手车 | P25: 李昌洪 | R25: 超市 | S25: 星越L | T25: LB37852Z5TS027063 | Z25: 机场新媒体 | AA25: 刘波 | AC25: =Y25*0.14 -> 0 | AD25: =IF(O25>=1000,O25*0.14,IF(O25>=500,100,0)) -> 0 | AE25: =SUM(AC25:AD25) -> 0 | AI25: 台次提成 | AJ25: =AL22*120 -> 0 | AK25: 毛利提成 | AL25: =IF(AL23>0,AL23*AJ24*AL24,AL23*0.1) -> 0 | AM25: 台次提成 | AN25: =AP22*120 -> 0 | AO25: 毛利提成 | AP25: =AP23*AN24*AP24 -> 0
A26: =ROW()-1 -> 25 | B26: 置换 | D26: 何继武 | G26: 吉利牌 | H26: LB37752Z8FC256225 | I26: 川DUG686 | M26: 和信汇二手车 | P26: 何继武 | R26: 超市 | S26: 星越L | T26: LB37852D7TS072297 | Z26: 机场网销 | AA26: 邱明杰 | AC26: =Y26*0.14 -> 0 | AD26: =IF(O26>=1000,O26*0.14,IF(O26>=500,100,0)) -> 0 | AE26: =SUM(AC26:AD26) -> 0 | AI26: 认证二手车台次 | AK26: 认证二手车提成 | AM26: 认证二手车台次 | AO26: 认证二手车提成
A27: =ROW()-1 -> 26 | B27: 置换 | D27: 隆波 | G27: 别克 | H27: LSGER5354NW165302 | I27: 川A804RM | M27: 锦栖汇二手车 | P27: 隆波 | R27: 超市 | S27: 星越L | T27: LB37852Z0TS027357 | Z27: 彭州直营店 | AA27: 陈莉 | AC27: =Y27*0.14 -> 0 | AD27: =IF(O27>=1000,O27*0.14,IF(O27>=500,100,0)) -> 0 | AE27: =SUM(AC27:AD27) -> 0 | AI27: 按揭服务费 | AK27: 按揭服务费提成 | AL27: =AJ27*0.12 -> 0 | AM27: 按揭服务费 | AO27: 按揭服务费提成 | AP27: =AN27*0.12 -> 0
A28: =ROW()-1 -> 27 | B28: 置换 | D28: 李征 | G28: 江淮 | H28: LJ12EKS43G4755762 | I28: 川A4X35F | M28: 八千熊猫二手车 | P28: 李征 | R28: 西物 | S28: 第四代博越L | T28: LB37822Z6TB028513 | Z28: 双星新媒体 | AA28: 雷卓远 | AB28: 张龙 | AC28: =Y28*0.14 -> 0 | AD28: =IF(O28>=1000,O28*0.14,IF(O28>=500,100,0)) -> 0 | AE28: =SUM(AC28:AD28) -> 0 | AI28: 合计 | AJ28: =AJ25+AL25+AL26+AL27 -> 0 | AM28: 合计 | AN28: =AN25+AP25+AP26+AP27 -> 0
A29: =ROW()-1 -> 28 | B29: 置换 | D29: 黄军 | G29: 吉利牌 | H29: LB37724S4FX098005 | I29: 川A5H02J | P29: 黄军 | R29: 超市 | S29: 3代豪越L | T29: L6T7922Z2SY000681 | Z29: 双星新媒体 | AA29: 刘飞 | AC29: =Y29*0.14 -> 0 | AD29: =IF(O29>=1000,O29*0.14,IF(O29>=500,100,0)) -> 0 | AE29: =SUM(AC29:AD29) -> 0
A30: =ROW()-1 -> 29 | B30: 置换 | D30: 杜镜鹏 | G30: 东风雪铁龙牌 | H30: LDCC13T28E1123423 | I30: 川A3K926 | P30: 杜镜鹏 | R30: 超市 | S30: 缤越超能版 | T30: LB37622Z5TX812173 | Z30: 网络部 | AA30: 余才万 | AC30: =Y30*0.14 -> 0 | AD30: =IF(O30>=1000,O30*0.14,IF(O30>=500,100,0)) -> 0 | AE30: =SUM(AC30:AD30) -> 0 | AI30: 张龙（超市银河A网） | AM30: 白林（西物银河A网）
A31: =ROW()-1 -> 30 | B31: 报废 | D31: 夏永章 | G31: 海马牌 | H31: LH17C2JFXBH330320 | I31: 川A485EU | M31: 锦栖汇二手车 | P31: 夏永章 | R31: 超市 | S31: 第四代博越L | T31: LB37822Z5TB034108 | Z31: 双星网销 | AA31: 王泳文 | AB31: 张龙 | AC31: =Y31*0.14 -> 0 | AD31: =IF(O31>=1000,O31*0.14,IF(O31>=500,100,0)) -> 0 | AE31: =SUM(AC31:AD31) -> 0 | AI31: 店面销量(除熊猫) | AK31: 收购台次 | AM31: 店面销量(除熊猫) | AO31: 收购台次
A32: =ROW()-1 -> 31 | B32: 置换 | D32: 张毅强 | G32: 观致牌 | H32: LLNCKACB8GA002433 | I32: 川A14Q9L | P32: 张毅强 | R32: 西物 | S32: 第四代博越L | T32: LB37822Z3TB028484 | Z32: 崇州直营店 | AA32: 赵思梵 | AC32: =Y32*0.14 -> 0 | AD32: =IF(O32>=1000,O32*0.14,IF(O32>=500,100,0)) -> 0 | AE32: =SUM(AC32:AD32) -> 0 | AI32: 置换率 | AJ32: =AL31/AJ31 -> #DIV/0! | AK32: 置换台次 | AM32: 置换率 | AN32: =AP31/AN31 -> #DIV/0! | AO32: 置换台次
A33: =ROW()-1 -> 32 | B33: 置换 | D33: 罗红 | F33: 2017.8.7 | G33: 长安牌 | H33: LS5A3ABE8HA013785 | I33: 川K23E36 | M33: 锦栖汇二手车 | P33: 罗红 | R33: 超市 | S33: 缤越L | T33: LB37622Z2TX618622 | Z33: 华阳直营店 | AA33: 丁小玲 | AC33: =Y33*0.14 -> 0 | AD33: =IF(O33>=1000,O33*0.14,IF(O33>=500,100,0)) -> 0 | AE33: =SUM(AC33:AD33) -> 0 | AI33: 置换毛利 | AK33: 绩效毛利 | AL33: =IF((AJ33-(2000*AL32))<0,(AJ33-(2000*AL32)),AJ33-(2000*AL32)) -> 0 | AM33: 置换毛利 | AO33: 绩效毛利 | AP33: =IF((AN33-(2000*AP32))<0,0,(AN33-(2000*AP32))) -> 0
A34: =ROW()-1 -> 33 | B34: 置换 | D34: 李勇祥 | F34: 2016.2.22 | G34: 哈佛牌 | H34: LGWEF4A55GF021821 | I34: 川H6389E | P34: 李勇祥 | R34: 超市 | S34: 星瑞(1.5T) | T34: L6T7924Z2TD052267 | Z34: 华阳直营店 | AA34: 吴小琴 | AC34: =Y34*0.14 -> 0 | AD34: =IF(O34>=1000,O34*0.14,IF(O34>=500,100,0)) -> 0 | AE34: =SUM(AC34:AD34) -> 0 | AI34: 毛利提成标准 | AK34: 考核执行标准 | AL34: =AL24 -> 0 | AM34: 毛利提成标准 | AO34: 考核执行标准 | AP34: =AL24 -> 0
A35: =ROW()-1 -> 34 | B35: 报废 | D35: 杨梅 | F35: 2012.11.27 | G35: 东南 | H35: LDNB43AZ3C0449272 | I35: 川AU373V | M35: 锦栖汇二手车 | P35: 杨梅 | R35: 超市 | S35: 全新博越 | T35: LB37722Z5TX312995 | Z35: 大邑直营店 | AA35: 袁萍 | AC35: =Y35*0.14 -> 0 | AD35: =IF(O35>=1000,O35*0.14,IF(O35>=500,100,0)) -> 0 | AE35: =SUM(AC35:AD35) -> 0 | AI35: 台次提成 | AJ35: =AL32*120 -> 0 | AK35: 毛利提成 | AL35: =IF(AL33>0,AL33*AJ34*AL34,AL33*0.1) -> 0 | AM35: 台次提成 | AN35: =AP32*120 -> 0 | AO35: 毛利提成 | AP35: =AP33*AN34*AP34 -> 0
A36: =ROW()-1 -> 35 | B36: 报废 | D36: 辜小琴 | G36: 奇瑞牌 | H36: LVVDA11A4AD436510 | I36: 川A50LN6 | M36: 锦栖汇二手车 | P36: 辜小琴 | R36: 超市 | S36: 全新博越 | T36: LB37722ZXTX310479 | Z36: 崇州直营店 | AA36: 陈勇建 | AC36: =Y36*0.14 -> 0 | AD36: =IF(O36>=1000,O36*0.14,IF(O36>=500,100,0)) -> 0 | AE36: =SUM(AC36:AD36) -> 0 | AI36: 认证二手车台次 | AK36: 认证二手车提成 | AM36: 认证二手车台次 | AO36: 认证二手车提成
A37: =ROW()-1 -> 36 | B37: 置换 | D37: 刘庭 | G37: 帝豪牌 | H37: LB37742S7JA014852 | I37: 川A48YC1 | M37: 八千熊猫二手车 | P37: 刘庭 | R37: 西物 | S37: 星瑞(1.5T) | T37: L6T7924Z8TD052130 | Z37: 双星新媒体 | AA37: 何剑 | AB37: 张龙 | AC37: =Y37*0.14 -> 0 | AD37: =IF(O37>=1000,O37*0.14,IF(O37>=500,100,0)) -> 0 | AE37: =SUM(AC37:AD37) -> 0 | AI37: 按揭服务费 | AK37: 按揭服务费提成 | AL37: =AJ37*0.12 -> 0 | AM37: 按揭服务费 | AO37: 按揭服务费提成 | AP37: =AN37*0.12 -> 0
A38: =ROW()-1 -> 37 | B38: 置换 | D38: 谭霞 | F38: 2016.7.4 | G38: 中华牌 | H38: LSYYDACB5GC033501 | I38: 川J9671D | M38: 八千熊猫二手车 | P38: 谭霞 | R38: 西物 | S38: 4代帝豪 | T38: LB37824Z0SG170127 | Z38: 双星展厅 | AA38: 康鳞波 | AB38: 张龙 | AC38: =Y38*0.14 -> 0 | AD38: =IF(O38>=1000,O38*0.14,IF(O38>=500,100,0)) -> 0 | AE38: =SUM(AC38:AD38) -> 0 | AI38: 合计 | AJ38: =AJ35+AL35+AL36+AL37 -> 0 | AM38: 合计 | AN38: =AN35+AP35+AP36+AP37 -> 0
A39: =ROW()-1 -> 38 | B39: 置换 | D39: 李大平 | G39: 大众 | H39: LSVGX46R4E2128435 | I39: 陕F1967K | M39: 和信汇二手车 | P39: 李大平 | R39: 超市 | S39: 星越L | T39: LB37852Z4SS262178 | Z39: 双星展厅 | AA39: 毛春秀 | AB39: 张龙 | AC39: =Y39*0.14 -> 0 | AD39: =IF(O39>=1000,O39*0.14,IF(O39>=500,100,0)) -> 0 | AE39: =SUM(AC39:AD39) -> 0
A40: =ROW()-1 -> 39 | B40: 置换 | D40: 辜玉容 | G40: 比亚迪牌 | H40: LGXCG6CF9G0034382 | I40: 川CG7829 | M40: 锦栖汇二手车 | P40: 辜玉容 | R40: 西物 | S40: 第四代博越L | T40: LB37822Z1TB069339 | Z40: 机场展厅 | AA40: 姚元利 | AC40: =Y40*0.14 -> 0 | AD40: =IF(O40>=1000,O40*0.14,IF(O40>=500,100,0)) -> 0 | AE40: =SUM(AC40:AD40) -> 0
A41: =ROW()-1 -> 40 | B41: 置换 | D41: 刘国华 | G41: 博越 | H41: LB37852ZXRS075361 | I41: 川Q20G91 | P41: 刘国华 | R41: 超市 | S41: 星越L | T41: LB37852D9TS072298 | Z41: 机场网销 | AA41: 施巍 | AC41: =Y41*0.14 -> 0 | AD41: =IF(O41>=1000,O41*0.14,IF(O41>=500,100,0)) -> 0 | AE41: =SUM(AC41:AD41) -> 0
A42: =ROW()-1 -> 41 | B42: 报废 | D42: 刘显平 | G42: 大众波罗 | H42: LSVFB66R8B2061100 | I42: 川AT8A78 | M42: 锦栖汇二手车 | P42: 刘显平 | R42: 超市 | S42: 星越L | T42: LB37852Z2TS063812 | Z42: 机场展厅 | AA42: 刘发 | AC42: =Y42*0.14 -> 0 | AD42: =IF(O42>=1000,O42*0.14,IF(O42>=500,100,0)) -> 0 | AE42: =SUM(AC42:AD42) -> 0
A43: =ROW()-1 -> 42 | B43: 置换 | D43: 王寿刚 | G43: 宝马5系 | H43: LBV21AF08NS319206 | I43: 川A0C3B4 | P43: 王寿刚 | R43: 超市 | S43: 星越L | T43: LB37852Z9TS065234 | Z43: 机场新媒体 | AA43: 刘波 | AC43: =Y43*0.14 -> 0 | AD43: =IF(O43>=1000,O43*0.14,IF(O43>=500,100,0)) -> 0 | AE43: =SUM(AC43:AD43) -> 0
A44: =ROW()-1 -> 43 | B44: 置换 | D44: 王小兰 | F44: 2015.11.25 | G44: 吉利美日牌 | H44: L6T7824S1FN199345 | I44: 川A8K95T | M44: 锦栖汇二手车 | P44: 王小兰 | R44: 超市 | S44: 星越L | T44: LB37852Z4TS057445 | Z44: 华阳直营店 | AA44: 吴小琴 | AC44: =Y44*0.14 -> 0 | AD44: =IF(O44>=1000,O44*0.14,IF(O44>=500,100,0)) -> 0 | AE44: =SUM(AC44:AD44) -> 0
A45: =ROW()-1 -> 44 | B45: 报废 | D45: 连志玮 | G45: 福克斯 | H45: LVSHCFAE4CF255438 | I45: 贵AX8U17 | M45: 锦栖汇二手车 | P45: 连志玮 | R45: 西物 | S45: 星瑞(1.5T) | T45: L6T7924Z4TD054442 | Z45: 双星展厅 | AA45: 代力 | AB45: 张龙 | AC45: =Y45*0.14 -> 0 | AD45: =IF(O45>=1000,O45*0.14,IF(O45>=500,100,0)) -> 0 | AE45: =SUM(AC45:AD45) -> 0
A46: =ROW()-1 -> 45 | B46: 置换 | D46: 蒋凯 | E46: 1878414 0316 | G46: 帝豪牌 | H46: LB37722Z2JA029759 | I46: 川Q988G6 | P46: 蒋凯 | Q46: 1878414 0316 | R46: 西物 | S46: 第四代博越L | T46: LB37822Z3TB046967 | Z46: 网络部 | AA46: 余才万 | AC46: =Y46*0.14 -> 0 | AD46: =IF(O46>=1000,O46*0.14,IF(O46>=500,100,0)) -> 0 | AE46: =SUM(AC46:AD46) -> 0
A47: =ROW()-1 -> 46 | B47: 置换 | D47: 许红 | G47: 吉利美日牌 | H47: L6T7722S2HN014857 | I47: 川A03G1Q | P47: 许红 | R47: 超市 | S47: 星越L | T47: LB37852Z1TS038514 | Z47: 彭州直营店 | AA47: 刘娅 | AC47: =Y47*0.14 -> 0 | AD47: =IF(O47>=1000,O47*0.14,IF(O47>=500,100,0)) -> 0 | AE47: =SUM(AC47:AD47) -> 0
A48: =ROW()-1 -> 47 | B48: 置换 | D48: 李文英 | F48: 2015.06.23 | G48: 奇瑞 | H48: LVVDC11B0EC088462 | I48: 川A5L0E0 | M48: 锦栖汇二手车 | P48: 李文英 | R48: 西物 | S48: 第四代博越L | T48: LB37822Z5TB022038 | Z48: 大邑直营店 | AA48: 常涛 | AC48: =Y48*0.14 -> 0 | AD48: =IF(O48>=1000,O48*0.14,IF(O48>=500,100,0)) -> 0 | AE48: =SUM(AC48:AD48) -> 0
A49: =ROW()-1 -> 48 | B49: 置换 | D49: 徐能能 | G49: 吉利美日牌 | H49: L6T7824S3DN105656 | I49: 川GV0383 | P49: 徐能能 | R49: 超市 | S49: 星越L | T49: LB37852Z2TS064748 | Z49: 机场网销 | AA49: 向兰 | AC49: =Y49*0.14 -> 0 | AD49: =IF(O49>=1000,O49*0.14,IF(O49>=500,100,0)) -> 0 | AE49: =SUM(AC49:AD49) -> 0
A50: =ROW()-1 -> 49 | B50: 报废 | D50: 李龙兵 | G50: 雪佛兰 | H50: LSGSA52S4BY073382 | I50: 川AG13B7 | M50: 锦栖汇二手车 | P50: 李龙兵 | R50: 西物 | S50: 第四代博越L | T50: LB37822Z1TB072662 | Z50: 机场展厅 | AA50: 陈林 | AC50: =Y50*0.14 -> 0 | AD50: =IF(O50>=1000,O50*0.14,IF(O50>=500,100,0)) -> 0 | AE50: =SUM(AC50:AD50) -> 0
A51: =ROW()-1 -> 50 | B51: 置换 | D51: 冯波 | G51: 福特嘉年华 | H51: LVRFFFML8DN535655 | I51: 川AL46V3 | P51: 冯波 | R51: 超市 | S51: 星越L | T51: LB37852Z5TS030187 | Z51: 邛崃直营店 | AA51: 马勇 | AC51: =Y51*0.14 -> 0 | AD51: =IF(O51>=1000,O51*0.14,IF(O51>=500,100,0)) -> 0 | AE51: =SUM(AC51:AD51) -> 0
A52: =ROW()-1 -> 51 | B52: 报废 | D52: 刘倩言 | G52: 雪佛兰乐驰 | H52: LSGSA52S9DD241821 | I52: 川AEB803 | P52: 刘倩言 | R52: 超市 | S52: 全新博越 | T52: LB37722Z6TX316067 | Z52: 邛崃直营店 | AA52: 叶荣鹏 | AC52: =Y52*0.14 -> 0 | AD52: =IF(O52>=1000,O52*0.14,IF(O52>=500,100,0)) -> 0 | AE52: =SUM(AC52:AD52) -> 0
A53: =ROW()-1 -> 52 | B53: 置换 | D53: 蒋波 | F53: 2019.01.03 | G53: 五菱牌 | H53: LZWADAGA6JE069404 | I53: 川A14W0Y | M53: 八千熊猫二手车 | P53: 蒋波 | R53: 西物 | S53: 星瑞(1.5T) | T53: L6T7924Z7TD045816 | Z53: 双星网销 | AA53: 唐操 | AB53: 张龙 | AC53: =Y53*0.14 -> 0 | AD53: =IF(O53>=1000,O53*0.14,IF(O53>=500,100,0)) -> 0 | AE53: =SUM(AC53:AD53) -> 0
A54: =ROW()-1 -> 53 | B54: 报废 | D54: 唐炳文 | G54: 起亚牌 | H54: LJDFAA14480030451 | I54: 川G7PG70 | M54: 锦栖汇二手车 | P54: 唐炳文 | R54: 超市 | S54: 星越L | T54: LB37852Z6SS299801 | Z54: 机场展厅 | AA54: 姚元利 | AC54: =Y54*0.14 -> 0 | AD54: =IF(O54>=1000,O54*0.14,IF(O54>=500,100,0)) -> 0 | AE54: =SUM(AC54:AD54) -> 0
A55: =ROW()-1 -> 54 | B55: 报废 | D55: 颜挺 | G55: 中华牌 | H55: LSYYBACAXAC069849 | I55: 川AN913V | M55: 和信汇二手车 | P55: 颜挺 | R55: 超市 | S55: 星越L | T55: LB37852Z2SS242382 | Z55: 机场网销 | AA55: 王熙鸿 | AC55: =Y55*0.14 -> 0 | AD55: =IF(O55>=1000,O55*0.14,IF(O55>=500,100,0)) -> 0 | AE55: =SUM(AC55:AD55) -> 0
A56: =ROW()-1 -> 55 | B56: 置换 | D56: 珍珠 | G56: 五菱 | H56: LZWADAGA4JC512449 | I56: 川VF1583 | M56: 和信汇二手车 | P56: 珍珠 | R56: 超市 | S56: 第四代博越L | T56: LB37822Z1TB051102 | Z56: 机场展厅 | AA56: 陈林 | AC56: =Y56*0.14 -> 0 | AD56: =IF(O56>=1000,O56*0.14,IF(O56>=500,100,0)) -> 0 | AE56: =SUM(AC56:AD56) -> 0
A57: =ROW()-1 -> 56 | B57: 报废 | D57: 冯前军 | G57: 五菱面包车 | H57: LZWACAGA8A7233923 | I57: 川A2AW03 | M57: 锦栖汇二手车 | P57: 冯前军 | R57: 超市 | S57: 3代豪越L | T57: L6T7922Z2TY871694 | Z57: 机场网销 | AA57: 刘波 | AC57: =Y57*0.14 -> 0 | AD57: =IF(O57>=1000,O57*0.14,IF(O57>=500,100,0)) -> 0 | AE57: =SUM(AC57:AD57) -> 0
A58: =ROW()-1 -> 57 | B58: 置换 | D58: 徐国文 | G58: 铃木天语 | H58: LS5A3ABE2EB064477 | I58: 川AB08Y9 | P58: 徐国文 | R58: 西物 | S58: 星瑞(1.5T) | T58: L6T7954Z5TD054385 | Z58: 邛崃直营店 | AA58: 马勇 | AC58: =Y58*0.14 -> 0 | AD58: =IF(O58>=1000,O58*0.14,IF(O58>=500,100,0)) -> 0 | AE58: =SUM(AC58:AD58) -> 0
A59: =ROW()-1 -> 58 | B59: 置换 | D59: 余崇恩 | G59: 现代 | H59: LBEXDAEB66X385757 | I59: 川U31889 | M59: 锦栖汇二手车 | P59: 余崇恩 | R59: 西物 | S59: 星越L | T59: LB37852D4SS256921 | Z59: 机场网销 | AA59: 赵强 | AC59: =Y59*0.14 -> 0 | AD59: =IF(O59>=1000,O59*0.14,IF(O59>=500,100,0)) -> 0 | AE59: =SUM(AC59:AD59) -> 0
A60: =ROW()-1 -> 59 | B60: 置换 | D60: 赵伟 | G60: 大众途观 | H60: LSVXU25N9E2091684 | I60: 川A7Q18X | P60: 赵伟 | R60: 超市 | S60: 第四代博越L | T60: LB37822Z4TB021124 | Z60: 邛崃直营店 | AA60: 马勇 | AC60: =Y60*0.14 -> 0 | AD60: =IF(O60>=1000,O60*0.14,IF(O60>=500,100,0)) -> 0 | AE60: =SUM(AC60:AD60) -> 0
A61: =ROW()-1 -> 60 | B61: 报废 | D61: 陈诗富 | G61: 雪佛兰牌 | H61: LSGSA52M5AY232913 | I61: 川C5T612 | P61: 陈诗富 | R61: 超市 | S61: 缤越L | T61: LB37622Z7TX621239 | Z61: 网络部 | AA61: 余才万 | AC61: =Y61*0.14 -> 0 | AD61: =IF(O61>=1000,O61*0.14,IF(O61>=500,100,0)) -> 0 | AE61: =SUM(AC61:AD61) -> 0
A62: =ROW()-1 -> 61 | B62: 置换 | D62: 陈卓 | F62: 2016.05.26 | G62: 哈弗牌 | H62: LGWED2A41GE012167 | I62: 川A52BH9 | M62: 锦栖汇二手车 | P62: 陈卓 | R62: 超市 | S62: 星越L | T62: LB37852Z5TS051928 | Z62: 双星新媒体 | AA62: 唐操 | AB62: 张龙 | AC62: =Y62*0.14 -> 0 | AD62: =IF(O62>=1000,O62*0.14,IF(O62>=500,100,0)) -> 0 | AE62: =SUM(AC62:AD62) -> 0
A63: =ROW()-1 -> 62 | B63: 置换 | D63: 郭成 | G63: 本田 | H63: LVHFB2546D6024533 | I63: 川AU024G | M63: 和信汇二手车 | P63: 郭成 | R63: 超市 | S63: 星越L | T63: LB37852Z8TS029230 | Z63: 机场展厅 | AA63: 冯超 | AC63: =Y63*0.14 -> 0 | AD63: =IF(O63>=1000,O63*0.14,IF(O63>=500,100,0)) -> 0 | AE63: =SUM(AC63:AD63) -> 0
A64: =ROW()-1 -> 63 | B64: 置换 | D64: 张建丽 | G64: 高尔夫牌 | H64: LFV2B21K4D3550295 | I64: 川A564JL | M64: 锦栖汇二手车 | P64: 张建丽 | R64: 超市 | S64: 星越i-HEV | T64: LB3781NZXTS079664 | Z64: 机场网销 | AA64: 向兰 | AC64: =Y64*0.14 -> 0 | AD64: =IF(O64>=1000,O64*0.14,IF(O64>=500,100,0)) -> 0 | AE64: =SUM(AC64:AD64) -> 0
A65: =ROW()-1 -> 64 | B65: 置换 | D65: 刘志祥 | F65: 2017.06.26 | G65: 长安 | H65: LS4ASJ2E8HA691170 | I65: 川UG6565 | M65: 八千熊猫二手车 | P65: 刘志祥 | R65: 超市 | S65: 星越L | T65: LB37852Z1TS033958 | Z65: 双星展厅 | AA65: 熊杰文 | AB65: 张龙 | AC65: =Y65*0.14 -> 0 | AD65: =IF(O65>=1000,O65*0.14,IF(O65>=500,100,0)) -> 0 | AE65: =SUM(AC65:AD65) -> 0
A66: =ROW()-1 -> 65 | B66: 报废 | D66: 杨波 | G66: 北京现代 | H66: LBEXDAEB78X652634 | I66: 川FC9565 | M66: 八千熊猫二手车 | P66: 杨波 | R66: 西物 | S66: 星瑞(1.5T) | T66: L6T7924Z6TD045810 | Z66: 双星展厅 | AA66: 毛春秀 | AB66: 张龙 | AC66: =Y66*0.14 -> 0 | AD66: =IF(O66>=1000,O66*0.14,IF(O66>=500,100,0)) -> 0 | AE66: =SUM(AC66:AD66) -> 0
A67: =ROW()-1 -> 66 | B67: 置换 | D67: 李祥 | G67: 雪佛兰 | H67: LSGSA52S1EY203168 | I67: 川R19FF3 | P67: 李祥 | R67: 西物 | S67: 4代帝豪 | T67: LB37824S4SG178525 | Z67: 双星网销 | AA67: 何宇 | AC67: =Y67*0.14 -> 0 | AD67: =IF(O67>=1000,O67*0.14,IF(O67>=500,100,0)) -> 0 | AE67: =SUM(AC67:AD67) -> 0
A68: =ROW()-1 -> 67 | B68: 置换 | D68: 魏宇 | G68: 中华牌 | H68: LSYYBACA6EC008794 | I68: 川A7K3J2 | M68: 锦栖汇二手车 | P68: 魏宇 | R68: 西物 | S68: 星瑞(1.5T) | T68: L6T7924Z3TD048728 | Z68: 崇州直营店 | AA68: 唐鹏 | AC68: =Y68*0.14 -> 0 | AD68: =IF(O68>=1000,O68*0.14,IF(O68>=500,100,0)) -> 0 | AE68: =SUM(AC68:AD68) -> 0
A69: =ROW()-1 -> 68 | B69: 置换 | D69: 何春兰 | F69: 2021.4.2 | G69: 帝豪 | H69: LB37622Z4MX604254 | I69: 川F7J9X1 | P69: 何春兰 | R69: 西物 | S69: 星瑞(1.5T) | T69: L6T7924Z9TD045736 | Z69: 双星新媒体 | AA69: 母勇 | AC69: =Y69*0.14 -> 0 | AD69: =IF(O69>=1000,O69*0.14,IF(O69>=500,100,0)) -> 0 | AE69: =SUM(AC69:AD69) -> 0
A70: =ROW()-1 -> 69 | B70: 置换 | D70: 邓定海 | G70: 北京牌 | H70: LNBMDBAF3FU138026 | I70: 川A6F00Q | M70: 锦栖汇二手车 | P70: 邓定海 | R70: 超市 | S70: 第四代博越L | T70: LB37822Z1TB034705 | Z70: 崇州直营店 | AA70: 赵思梵 | AC70: =Y70*0.14 -> 0 | AD70: =IF(O70>=1000,O70*0.14,IF(O70>=500,100,0)) -> 0 | AE70: =SUM(AC70:AD70) -> 0
A71: =ROW()-1 -> 70 | B71: 置换 | D71: 曲卫鹏 | G71: 东风 | H71: LDC953T3XD1760531 | I71: 川F5C3U5 | M71: 和信汇二手车 | P71: 曲卫鹏 | R71: 豪明 | S71: 星瑞(1.5T) | T71: L6T7924Z6TD048710 | Z71: 机场展厅 | AA71: 陈林 | AB71: 白林 | AC71: =Y71*0.14 -> 0 | AD71: =IF(O71>=1000,O71*0.14,IF(O71>=500,100,0)) -> 0 | AE71: =SUM(AC71:AD71) -> 0
A72: =ROW()-1 -> 71 | B72: 置换 | D72: 王胜 | F72: 2021.5.14 | G72: 荣威 | H72: LSJA36E64MZ123747 | I72: 川Z64B63 | M72: 八千熊猫二手车 | P72: 王胜 | R72: 豪明 | S72: 星瑞(1.5T) | T72: L6T7924Z2TD059204 | Z72: 双星展厅 | AA72: 熊杰文 | AB72: 张龙 | AC72: =Y72*0.14 -> 0 | AD72: =IF(O72>=1000,O72*0.14,IF(O72>=500,100,0)) -> 0 | AE72: =SUM(AC72:AD72) -> 0
A73: =ROW()-1 -> 72 | B73: 报废 | D73: 李来亮 | F73: 2013.5.29 | G73: 起亚 | H73: LJDLAA297D0229047 | I73: 川A8JV08 | M73: 锦栖汇二手车 | P73: 李来亮 | R73: 超市 | S73: 星越L | T73: LB37852ZXTS031920 | Z73: 双星新媒体 | AA73: 母勇 | AB73: 张龙 | AC73: =Y73*0.14 -> 0 | AD73: =IF(O73>=1000,O73*0.14,IF(O73>=500,100,0)) -> 0 | AE73: =SUM(AC73:AD73) -> 0
A74: =ROW()-1 -> 73 | B74: 置换 | D74: 王文 | F74: 2014.7.30 | G74: 长安牌 | H74: LS4AAB3R5EG153903 | I74: 川AT79W7 | M74: 八千熊猫二手车 | P74: 王文 | R74: 超市 | S74: 3代豪越L | T74: L6T7922Z3TY871848 | Z74: 双星网销 | AA74: 何剑 | AB74: 张龙 | AC74: =Y74*0.14 -> 0 | AD74: =IF(O74>=1000,O74*0.14,IF(O74>=500,100,0)) -> 0 | AE74: =SUM(AC74:AD74) -> 0
A75: =ROW()-1 -> 74 | B75: 置换 | D75: 段正常 | G75: 长安牌 | H75: LS5A2ABR4DH017338 | I75: 川川LC6K19 | P75: 段正常 | R75: 西物 | S75: 第四代博越L | T75: LB37822Z7TB050858 | Z75: 网络部 | AA75: 余才万 | AC75: =Y75*0.14 -> 0 | AD75: =IF(O75>=1000,O75*0.14,IF(O75>=500,100,0)) -> 0 | AE75: =SUM(AC75:AD75) -> 0
A76: =ROW()-1 -> 75 | B76: 置换 | D76: 涂国华 | G76: 长安牌 | H76: LS5A2BBR4FH035184 | I76: 川A3K2T9 | P76: 涂国华 | R76: 西物 | S76: 第四代博越L | T76: LB37822Z1TB034056 | Z76: 彭州直营店 | AA76: 钟家林 | AC76: =Y76*0.14 -> 0 | AD76: =IF(O76>=1000,O76*0.14,IF(O76>=500,100,0)) -> 0 | AE76: =SUM(AC76:AD76) -> 0
A77: =ROW()-1 -> 76 | B77: 置换 | D77: 刘强 | G77: 吉利牌 | H77: LB37622Z4KX637655 | I77: 粤E523LQ | M77: 锦栖汇二手车 | P77: 刘强 | R77: 豪明 | S77: 星越L | T77: LB37852Z4TS065223 | Z77: 机场新媒体 | AA77: 刘凤英 | AC77: =Y77*0.14 -> 0 | AD77: =IF(O77>=1000,O77*0.14,IF(O77>=500,100,0)) -> 0 | AE77: =SUM(AC77:AD77) -> 0
A78: =ROW()-1 -> 77 | B78: 置换 | D78: 杨建茹 | F78: 2017.07.14 | G78: 比亚迪 | H78: LGXC14DF9H0091493 | I78: 川A65T1D | M78: 和信汇二手车 | P78: 杨建茹 | R78: 西物 | S78: 博越REV | T78: L6T78XCZ4TY781977 | Z78: 大邑直营店 | AA78: 常涛 | AC78: =Y78*0.14 -> 0 | AD78: =IF(O78>=1000,O78*0.14,IF(O78>=500,100,0)) -> 0 | AE78: =SUM(AC78:AD78) -> 0
A79: =ROW()-1 -> 78 | B79: 置换 | D79: 四郎志玛 | G79: 黄海皮卡 | H79: LDDC8A305J0002584 | I79: 川VL5757 | P79: 四郎志玛 | R79: 豪明 | S79: 星瑞(2.0T) | T79: L6T7954Z7TD023753 | Z79: 机场新媒体 | AA79: 熊俊杰 | AC79: =Y79*0.14 -> 0 | AD79: =IF(O79>=1000,O79*0.14,IF(O79>=500,100,0)) -> 0 | AE79: =SUM(AC79:AD79) -> 0
A80: =ROW()-1 -> 79 | B80: 报废 | D80: 冯二毛 | G80: 吉利全球鹰 | H80: LB37122Z5AH019168 | I80: 川A423V4 | M80: 锦栖汇二手车 | P80: 冯二毛 | R80: 豪明 | S80: 星越L | T80: LB37852ZXTS033960 | Z80: 机场新媒体 | AA80: 赵强 | AB80: 白林 | AC80: =Y80*0.14 -> 0 | AD80: =IF(O80>=1000,O80*0.14,IF(O80>=500,100,0)) -> 0 | AE80: =SUM(AC80:AD80) -> 0
A81: =ROW()-1 -> 80 | B81: 置换 | D81: 罗兵 | F81: 2015.09.28 | G81: 标志 | H81: LDC953T2XF1272111 | I81: 川A2A65D | P81: 罗兵 | R81: 豪明 | S81: 星越L | T81: LB37852Z2TS067259 | Z81: 彭州直营店 | AA81: 陈莉 | AC81: =Y81*0.14 -> 0 | AD81: =IF(O81>=1000,O81*0.14,IF(O81>=500,100,0)) -> 0 | AE81: =SUM(AC81:AD81) -> 0
A82: =ROW()-1 -> 81 | B82: 置换 | D82: 蒋涛 | G82: 马自达 | H82: LVRHDFML0HN024798 | I82: 川MAJ826 | P82: 蒋涛 | R82: 豪明 | S82: 星瑞(2.0T) | T82: L6T7924Z2TD050339 | Z82: 机场网销 | AA82: 莫晓何 | AC82: =Y82*0.14 -> 0 | AD82: =IF(O82>=1000,O82*0.14,IF(O82>=500,100,0)) -> 0 | AE82: =SUM(AC82:AD82) -> 0
A83: =ROW()-1 -> 82 | B83: 置换 | D83: 张德友 | G83: 长安逸动 | H83: LS5A2ABE4FA026842 | I83: 川ZFM19 | M83: 和信汇二手车 | P83: 张德友 | R83: 豪明 | S83: 星越L | T83: LB37852Z6SS290631 | Z83: 机场展厅 | AA83: 邓戈 | AC83: =Y83*0.14 -> 0 | AD83: =IF(O83>=1000,O83*0.14,IF(O83>=500,100,0)) -> 0 | AE83: =SUM(AC83:AD83) -> 0
A84: =ROW()-1 -> 83 | B84: 置换 | D84: 汪璐 | G84: 日产 | H84: LGBH52E08HY295072 | I84: 川GB9K22 | M84: 锦栖汇二手车 | P84: 汪璐 | R84: 西物 | S84: 第四代博越L | T84: LB37822Z0TB052029 | Z84: 机场展厅 | AA84: 陈林 | AB84: 白林 | AC84: =Y84*0.14 -> 0 | AD84: =IF(O84>=1000,O84*0.14,IF(O84>=500,100,0)) -> 0 | AE84: =SUM(AC84:AD84) -> 0
A85: =ROW()-1 -> 84 | B85: 置换 | D85: 罗利华 | F85: 2017.08.15 | G85: 长安牌 | H85: LS5A33FE2HB329599 | I85: 川R6W522 | M85: 和信汇二手车 | P85: 罗利华 | R85: 西物 | S85: 第四代博越L | T85: LB37822Z7TB041979 | Z85: 华阳直营店 | AA85: 刘华 | AC85: =Y85*0.14 -> 0 | AD85: =IF(O85>=1000,O85*0.14,IF(O85>=500,100,0)) -> 0 | AE85: =SUM(AC85:AD85) -> 0
A86: =ROW()-1 -> 85 | B86: 置换 | D86: 魏天平 | F86: 2021.10.28 | G86: 帝豪牌 | H86: LB37622Z1MX731740 | I86: 川AL5156 | M86: 八千熊猫二手车 | P86: 魏天平 | R86: 西物 | S86: 博越REV | T86: L6T78XCZ5TY782006 | Z86: 双星新媒体 | AA86: 唐操 | AB86: 张龙 | AC86: =Y86*0.14 -> 0 | AD86: =IF(O86>=1000,O86*0.14,IF(O86>=500,100,0)) -> 0 | AE86: =SUM(AC86:AD86) -> 0
A87: =ROW()-1 -> 86 | B87: 报废 | D87: 毛平 | G87: 东风标致牌 | H87: LDC931L23A0151557 | I87: 川A3M59P | M87: 锦栖汇二手车 | P87: 毛平 | R87: 西物 | S87: 第四代博越L | T87: LB37822Z7TB069314 | Z87: 崇州直营店 | AA87: 宁袁 | AC87: =Y87*0.14 -> 0 | AD87: =IF(O87>=1000,O87*0.14,IF(O87>=500,100,0)) -> 0 | AE87: =SUM(AC87:AD87) -> 0
A88: =ROW()-1 -> 87 | B88: 置换 | D88: 吴晓娟 | G88: 长安牌 | H88: LS5A2ABE7FA068518 | I88: 川A6X5M4 | M88: 锦栖汇二手车 | P88: 吴晓娟 | R88: 超市 | S88: 星越L(智擎) | T88: LB3781NZ3TS079487 | Z88: 双星网销 | AA88: 何宇 | AB88: 张龙 | AC88: =Y88*0.14 -> 0 | AD88: =IF(O88>=1000,O88*0.14,IF(O88>=500,100,0)) -> 0 | AE88: =SUM(AC88:AD88) -> 0
A89: =ROW()-1 -> 88 | B89: 置换 | D89: 宋霞 | G89: 别克 | H89: LSGJB84J3EY051375 | I89: 川A7QT62 | P89: 宋霞 | R89: 超市 | S89: 星越L | T89: LB37852D2TS069484 | Z89: 双星展厅 | AA89: 廖晓军 | AC89: =Y89*0.14 -> 0 | AD89: =IF(O89>=1000,O89*0.14,IF(O89>=500,100,0)) -> 0 | AE89: =SUM(AC89:AD89) -> 0
A90: =ROW()-1 -> 89 | B90: 报废 | D90: 王玉 | F90: 2012.6.14 | G90: 雪佛兰 | H90: LSGSA52S6CY295116 | I90: 川GLP521 | M90: 和信汇二手车 | P90: 王玉 | R90: 西物 | S90: 星瑞(1.5T) | T90: L6T7954Z9TD032759 | Z90: 双星网销 | AA90: 母勇 | AB90: 张龙 | AC90: =Y90*0.14 -> 0 | AD90: =IF(O90>=1000,O90*0.14,IF(O90>=500,100,0)) -> 0 | AE90: =SUM(AC90:AD90) -> 0
A91: =ROW()-1 -> 90 | B91: 置换 | D91: 尹秀珍 | G91: 东风标致 | H91: LDC633T20F3294776 | I91: 川AL606B | M91: 锦栖汇二手车 | P91: 尹秀珍 | R91: 超市 | S91: 星越L | T91: LB37852Z0TS057457 | Z91: 双星新媒体 | AA91: 王泳文 | AB91: 张龙 | AC91: =Y91*0.14 -> 0 | AD91: =IF(O91>=1000,O91*0.14,IF(O91>=500,100,0)) -> 0 | AE91: =SUM(AC91:AD91) -> 0
A92: =ROW()-1 -> 91 | B92: 置换 | D92: 廖容 | G92: 吉利 | H92: L6T7824S7FN010553 | I92: 川GY5E77 | M92: 八千熊猫二手车 | P92: 廖容 | R92: 西物 | S92: 星瑞(1.5T) | T92: L6T7924Z2TD010052 | Z92: 双星网销 | AA92: 雷卓远 | AB92: 张龙 | AC92: =Y92*0.14 -> 0 | AD92: =IF(O92>=1000,O92*0.14,IF(O92>=500,100,0)) -> 0 | AE92: =SUM(AC92:AD92) -> 0
A93: =ROW()-1 -> 92 | B93: 置换 | D93: 陈涛 | G93: 吉利 | H93: L6T7824S0HN078079 | I93: 川Y7J761 | M93: 锦栖汇二手车 | P93: 陈涛 | R93: 慧生 | S93: 星瑞(1.5T) | T93: L6T7924Z2TD050406 | Z93: 机场网销 | AA93: 赵强 | AB93: 白林 | AC93: =Y93*0.14 -> 0 | AD93: =IF(O93>=1000,O93*0.14,IF(O93>=500,100,0)) -> 0 | AE93: =SUM(AC93:AD93) -> 0
A94: =ROW()-1 -> 93 | B94: 报废 | D94: 杨华猛 | G94: 大众朗逸 | H94: LSVAH2184B2318320 | I94: 川A3G75Q | M94: 锦栖汇二手车 | P94: 杨华猛 | R94: 超市 | S94: 5代帝豪1.5L | T94: LB37824ZXTG035433 | Z94: 机场展厅 | AA94: 邓戈 | AB94: 白林 | AC94: =Y94*0.14 -> 0 | AD94: =IF(O94>=1000,O94*0.14,IF(O94>=500,100,0)) -> 0 | AE94: =SUM(AC94:AD94) -> 0
A95: =ROW()-1 -> 94 | B95: 置换 | D95: 黄俊芳 | G95: 帝豪牌 | H95: LB37824Z1NG149985 | I95: 川G0BG50 | P95: 黄俊芳 | R95: 西物 | S95: 星瑞(1.5T) | T95: L6T7924Z6TD056032 | Z95: 网络部 | AA95: 余才万 | AC95: =Y95*0.14 -> 0 | AD95: =IF(O95>=1000,O95*0.14,IF(O95>=500,100,0)) -> 0 | AE95: =SUM(AC95:AD95) -> 0
A96: =ROW()-1 -> 95 | B96: 置换 | D96: 刘波 | E96: 135 4005 9461 | G96: 吉利美日牌 | H96: L6T7824S1JN043511 | I96: 川A85E80 | P96: 刘波 | Q96: 135 4005 9461 | R96: 西物 | S96: 第四代博越L | T96: LB37822Z2TB048046 | Z96: 网络部 | AA96: 余才万 | AC96: =Y96*0.14 -> 0 | AD96: =IF(O96>=1000,O96*0.14,IF(O96>=500,100,0)) -> 0 | AE96: =SUM(AC96:AD96) -> 0
A97: =ROW()-1 -> 96 | B97: 置换 | D97: 何冉 | G97: 鑫源牌 | H97: LM6AFABDXMX325730 | I97: 川A37Z1F | M97: 和信汇二手车 | P97: 何冉 | R97: 超市 | S97: 3代豪越L | T97: L6T7922Z0TY871239 | Z97: 崇州直营店 | AA97: 陈勇建 | AC97: =Y97*0.14 -> 0 | AD97: =IF(O97>=1000,O97*0.14,IF(O97>=500,100,0)) -> 0 | AE97: =SUM(AC97:AD97) -> 0
A98: =ROW()-1 -> 97 | B98: 置换 | D98: 潘志建 | G98: 纳智捷 | H98: LUXC71H02GB099402 | I98: 川Z0BE36 | M98: 和信汇二手车 | P98: 潘志建 | R98: 西物 | S98: 星瑞(1.5T) | T98: L6T7924Z2TD050437 | Z98: 双星展厅 | AA98: 黄利君 | AB98: 张龙 | AC98: =Y98*0.14 -> 0 | AD98: =IF(O98>=1000,O98*0.14,IF(O98>=500,100,0)) -> 0 | AE98: =SUM(AC98:AD98) -> 0
A99: =ROW()-1 -> 98 | B99: 报废 | D99: 袁霄庆 | E99: 137 3066 6165 | F99: 2012.1.18 | G99: 大众牌 | H99: LSVFC26R8B2723134 | I99: 川A EF300 | M99: 八千熊猫二手车 | P99: 袁霄庆 | Q99: 137 3066 6165 | R99: 西物 | S99: 第四代博越L | T99: LB37822Z0TB072670 | Z99: 双星展厅 | AA99: 康鳞波 | AB99: 张龙 | AC99: =Y99*0.14 -> 0 | AD99: =IF(O99>=1000,O99*0.14,IF(O99>=500,100,0)) -> 0 | AE99: =SUM(AC99:AD99) -> 0
A100: =ROW()-1 -> 99 | B100: 置换 | D100: 成都咚林怡涛商贸部 | G100: 名爵牌 | H100: LSJZ14E64FS064501 | I100: 川AK683X | P100: 董林涛 | R100: 超市 | S100: 星越L | T100: LB37852Z4TS031606 | Z100: 网络部 | AA100: 余才万 | AC100: =Y100*0.14 -> 0 | AD100: =IF(O100>=1000,O100*0.14,IF(O100>=500,100,0)) -> 0 | AE100: =SUM(AC100:AD100) -> 0
...

Sheet 按揭绩效
B2: 5月考核 (油车) | C2: 展厅部分 | H2: 二网部分 | J2: 分公司 | L2: 5月绩效(油车) | O2: 展厅部分 | P2: 二网部分 | Q2: 必达项 (扣) | R2: 绩效合计 | S2: 合计金额 （工资卡） | T2: 新保绩效+临牌提成 | U2: 安心宝 | V2: 抵押业务 | W2: 二手车 核销 | X2: 大客户 | Y2: 分公司过票提成 | Z2: 全转按 服务费
C3: 店面熊猫+翼真+雷达 | E3: 武侯店(除熊猫) | F3: 机场店(除熊猫) | G3: 直营店店面(除熊猫) | H3: 直营店二网 | I3: 网络部 | L3: 姓名 | M3: 系数 | N3: 绩效比例
B4: 渗透率考核目标 | C4: - | I4: - | J4: - | L4: 李彦林
B5: 销量 | L5: 熊宇
B6: 按揭量(小计) | L6: 刘彦
B7: 按揭量(部门)
B8: 按揭渗透率 | C8: - | J8: - | L8: 晏彬文
B9: 完成率 | C9: - | D9: - | I9: - | J9: -
B10: 专员提成基础数
B11: 按揭量合计 | L11: 2026年金融考核 | N11: KPI | Q11: 标准 | U11: 提成金额 | X11: 新保提成 | Y11: 48、60期 | Z11: 抵押业务 | AA11: 二手车 | AB11: 大客户 | AC11: 意外险 | AD11: 考核 | AE11: 服务费 | AF11: 实发提成金额 | AG11: 姓名
B12: 熊宇考核武侯店渗透率，刘彦考核机场店，李彦林考核直营店店面，按完成率发放绩效。 | L12: 按揭 | M12: 岗位 | N12: 渠道 | O12: 提成标准（元） | P12: 目标（渗透） | Q12: 目标(公司销售台次） | R12: 达成台次 | S12: 渗透率 | T12: 提成标准（完成率） | U12: 系数分配 | V12: 提成金额 | W12: 合计金额 | X12: 提成金额 | Y12: 提成金额 | Z12: 提成金额 | AA12: 提成金额 | AB12: 提成金额 | AC12: 提成金额 | AD12: 提成金额 | AE12: 提成金额
M13: 专员岗-武侯 | N13: 自有店店面 | AG13: 熊宇
B14: 必达项 | C14: 人员 | E14: 刘彦 | F14: 李彦林 | G14: 熊宇 | H14: 考核金额 | N14: 直营店面 | AG14: 李彦林
C15: 按揭培训 | E15: 完成 | F15: 完成 | G15: 完成 | N15: 直营店网络
C16: 全转按 | M16: 专员岗-机场 | N16: 自有店店面 | AG16: 刘彦
C17: 客户满意度 | E17: 完成 | F17: 完成 | G17: 完成 | N17: 直营店面
B18: 全款转按揭 | C18: 服务费金额 | H18: - | N18: 二网/分公司
B19: GPS专项奖励 | M19: 全转按/二手车 | S19: -
B20: 抵押业务 | D20: 团队合计奖励收益20%的55%。 | M20: 经理 | N20: 自有店店面
B21: 二车手核销 | D21: 团队合计1000元。 | N21: 直营店面 | AG21: 晏彬文
B22: 盈利性产品 | D22: 团队按照盈利性占比提成。 | N22: 二网/直营店网络/分公司
B23: 大客户核销 | D23: 团队合计400元。
B24: 盈利性产品占比 | C24: 盈利性产品 | D24: 按揭量 | E24: 占比
B25: 双星店
B26: 机场店
B27: 直营店店面
B28: 店面合计

Sheet 西物基本
A1: 工资明细表
A2: 编制单位：成都西物汽车有限公司
A3: 所属月份：2026年5月
A4: 部 门：西物营销部 | AH4: 金额单位：元
A5: 序号 | B5: 部门 | C5: 姓名 | D5: 出勤情况 | E5: 职 务 | F5: 应发工资 | Q5: 其他应发 | T5: 单位承担社会保险 | AB5: 代扣款项 | AH5: 实发金额 | AI5: 备注
F6: 基本工资 | G6: 加班工资 | H6: 保密工资 | I6: 津贴补贴 | J6: 车展补贴 | K6: 交通补贴 | L6: 通讯补贴 | M6: 其他补贴 | N6: 减：病假、事假、缺勤、罚款 | O6: 减：未发绩效 | P6: 应发小计 | Q6: 预发 | R6: *月绩效 | S6: 其他小计 | T6: 基本养老保险16％ | U6: 基本医疗保险7.7％ | V6: 失业保险0.6% | W6: 工伤保险0.1% | X6: 大病医疗补充保险0.6% | Y6: *月社保补差 | Z6: 公积金（公司） | AA6: 单位承担小计 | AB6: 社保个人承担 | AC6: 公积金个人承担 | AD6: 其它 | AE6: 爱心基金 | AF6: 代垫社保 | AG6: 代扣合计
B7: 事业部 | C7: 刘伟生 | E7: 事业部总经理
B8: 事业部 | C8: 代蓓 | E8: 燃油车总经理
B9: 事业部 | C9: 齐坤忠 | E9: 综合部副总
B10: 事业部 | C10: 王斌 | E10: 综合部副总
B11: 事业部 | C11: 陈军 | E11: 资金总监
B12: 事业部 | C12: 陶兰 | E12: 财务副总
B13: 事业部 | C13: 汤小明 | E13: 平行业务
B14: 事业部 | C14: 冯岚 | E14: 保客营销总监
B15: 事业部 | C15: 唐玲 | E15: 助理
A16: 小计
B17: 总经办 | C17: 陈俊霖 | E17: 总经理
B18: 电子营销 | C18: 袁顺序 | E18: 实习销售总监
B19: 电子营销 | C19: 钟小丽 | E19: 实习销售经理
B20: 武侯展厅 | C20: 熊杰文 | D20: 丧假2天 | E20: 销售顾问
B21: 武侯展厅 | C21: 马攀 | E21: 销售顾问
B22: 武侯展厅 | C22: 易花贞子 | E22: 销售顾问
B23: 武侯展厅 | C23: 毛春秀 | E23: 销售顾问
B24: 武侯展厅 | C24: 廖晓军 | E24: 销售顾问
B25: 武侯展厅 | C25: 康鳞波 | E25: 销售顾问
B26: 武侯展厅 | C26: 代力 | E26: 销售顾问
B27: 武侯展厅 | C27: 干小楠 | D27: 5月17日离职生效，本月实际出勤16天 | E27: 试驾专员
B28: 电子营销 | C28: 蒲喜 | D28: 迟到1次 | E28: 销售顾问
B29: 电子营销 | C29: 何伟 | E29: 销售顾问
B30: 电子营销 | C30: 唐操 | E30: 销售顾问
B31: 电子营销 | C31: 母勇 | E31: 销售顾问
B32: 电子营销 | C32: 刘飞 | D32: 迟到1次 | E32: 销售顾问
B33: 电子营销 | C33: 黄利君 | E33: 销售助理
B34: 电子营销 | C34: 何剑 | E34: 销售助理
B35: 电子营销 | C35: 雷卓远 | E35: 销售顾问
B36: 电子营销 | C36: 何宇 | D36: 事假0.15天 | E36: 销售顾问
B37: 电子营销 | C37: 王泳文 | E37: 销售顾问
B38: 电子营销 | C38: 周思雨 | D38: 年假1天 | E38: 后台维护
B39: 电子营销 | C39: 杜小红 | E39: 邀约专员
B40: 电子营销 | C40: 陈文霜 | E40: 邀约专员
B41: 电子营销 | C41: 周梅 | E41: 邀约专员
B42: 电子营销 | C42: 金玉梅 | E42: 邀约专员
B43: 网络部 | C43: 邱勇 | E43: 交车专员
B44: 增值业务部 | C44: 晏彬文 | D44: 出差3天 | E44: 按揭经理
B45: 增值业务部 | C45: 张龙 | E45: 二手车置换
B46: 增值业务部 | C46: 熊宇 | E46: 按揭专员
B47: 增值业务部 | C47: 张春燕 | E47: 保险出单员
B48: 增值业务部 | C48: 邓小军 | E48: 上户专员
B49: 财务部 | C49: 顾雪梅 | E49: 财务经理
B50: 财务部 | C50: 丁红 | E50: 会计审计
B51: 财务部 | C51: 邓琦琪 | E51: 主办会计
B52: 财务部 | C52: 李佳乐 | D52: 年休1天 | E52: 主办会计
B53: 财务部 | C53: 罗涵 | E53: 会计助理
B54: 市场部 | C54: 谭艳 | D54: 年休3天 | E54: 市场总监
B55: 市场部 | C55: 李青洋 | E55: 市场专员
B56: 市场部 | C56: 何莉 | E56: 设计主管
B57: 市场部 | C57: 邓娟 | D57: 事假3小时 | E57: 前台接待
B58: 新媒体 | C58: 肖廷忠 | E58: 新媒体主管
B59: 新媒体 | C59: 黄凤 | D59: 年休1天 | E59: 新媒体专员
B60: 新媒体 | C60: 曾子乂 | E60: 新媒体主播
B61: 综合部 | C61: 刘菁妍 | E61: 专员
B62: 行政人事部 | C62: 林琼 | D62: 年休1天 | E62: 行政人事经理
B63: 行政人事部 | C63: 周小红 | E63: 行政主管
B64: 行政人事部 | C64: 何婷婷 | E64: 行政专员
B65: 销售辅助 | C65: 谢槟羽 | E65: 吧员
B66: 物流部 | C66: 陈凌 | D66: 出差5天 | E66: 物流总监
B67: 物流部 | C67: 周德芳 | D67: 年休1天 | E67: 物流专员
B68: 物流部 | C68: 杨英 | E68: 主管
B69: 物流部 | C69: 唐中华 | E69: 库管
B70: 客户关系部 | C70: 张保珍 | E70: 回访经理
B71: 客户关系部 | C71: 邓芳 | D71: 年休1天 | E71: 回访专员
A72: 小计
A73: 总计
B74: 总经理： | G74: 审批： | M74: 复核： | T74: 财务审核： | AA74: 直属主管： | AH74: 制表：
A76: 说明：应发工资填列计入个人所得税基数的内容；其他应发填列不计入个人所得税基数的内容；单位和个人所承担的五险一金与有权部门实际收取金额不一致的，请以本表格式为模板单独列表；
B77: 代扣款项中的员工基金和其他代扣款项系指不能在个人所得税税前扣除的集团代垫款项或借款，需在备注栏中说明。
B79: 代扣款项中的员工基金和其他代扣款项系指不能在个人所得税税前扣除的集团代垫款项或借款，需在备注栏中说明。

Sheet 直营店基本
A1: 工资明细表
A2: 编制单位：成都吉利汽车超市连锁有限公司
A3: 所属月份：2026年5月
A4: 部 门：各直营店（超市） | AH4: 金额单位：元
A5: 序号 | B5: 部门 | C5: 姓名 | D5: 出勤情况 | E5: 职 务 | F5: 应发工资 | Q5: 其他应发 | T5: 单位承担社会保险 | AB5: 代扣款项 | AH5: 实发金额 | AI5: 备注 | AJ5: 签名
F6: 基本工资 | G6: 加班工资 | H6: 保密工资 | I6: 社保补贴 | J6: 车展补贴 | K6: 交通补贴 | L6: 通讯补贴 | M6: 其他补贴 | N6: 减：病假、事假、缺勤、罚款 | O6: 减：未发绩效 | P6: 应发小计 | Q6: 其它 | S6: 其他小计 | T6: 基本养老保险16％ | U6: 基本医疗保险7.7％ | V6: 失业保险0.6% | W6: 工伤保险0.1% | X6: 大病医疗补充保险0.6% | Y6: *月社保补差 | Z6: 公积金公司承担 | AA6: 单位承担小计 | AB6: 社保个人承担 | AC6: 公积金个人承担 | AD6: 服装 | AE6: 爱心基金 | AF6: 其他代扣款项 | AG6: 代扣合计
B7: 直营店网络 | C7: 余才万 | E7: 渠道经理
C8: 孙杰 | D8: 病假23天，年休冲抵8天，病假15天 | E8: 直营店交车支持
B9: 直营店管理 | C9: 王茂林 | E9: 直营店总监
B10: 彭州直营店 | C10: 黎明朗 | E10: 彭州实习店长
C11: 牟春柳 | E11: 销售内勤
C12: 钟家林 | E12: 销售顾问
C13: 任和奎 | E13: 销售顾问
C14: 刘娅 | E14: 销售顾问
C15: 兰代全 | E15: 销售顾问
C16: 陈莉 | E16: 销售顾问
B17: 大邑直营店 | C17: 孙伟 | E17: 大邑店长
C18: 程羊 | E18: 销售顾问
C19: 常涛 | E19: 销售顾问
C20: 王海 | E20: 销售顾问
C21: 袁萍 | E21: 销售顾问
B22: 邛崃直营店 | C22: 吴思超 | D22: 迟到1次 | E22: 邛崃店长
C23: 叶荣鹏 | D23: 迟到1次 | E23: 销售顾问
C24: 马勇 | D24: 迟到1次 | E24: 销售顾问
C25: 高东琴 | D25: 迟到1次 | E25: 销售顾问
C26: 王巧巧 | E26: 内勤
B27: 崇州直营店 | C27: 朱剑波 | E27: 崇州实习店长
C28: 李良英 | E28: 出纳
C29: 唐鹏 | D29: 迟到1次 | E29: 销售顾问
C30: 赵思梵 | E30: 销售顾问
C31: 陈勇建 | E31: 销售顾问
C32: 宁袁 | E32: 销售顾问
C33: 杨婷 | E33: 销售顾问
B34: 华阳直营店 | C34: 钟涛 | E34: 华阳店长
C35: 毛婷婷 | E35: 内勤
C36: 吴小琴 | E36: 销售顾问
C37: 张坤 | E37: 销售顾问
C38: 丁小玲 | E38: 销售顾问
C39: 刘华 | E39: 销售顾问
C40: 蒋云 | E40: 销售顾问
B42: 总经理： | E42: 车部总： | L42: 审批： | R42: 复核： | T42: 财务审核： | AA42: 直属主管： | AH42: 制表：
A45: 代扣款项中的员工基金和其他代扣款项系指不能在个人所得税税前扣除的集团代垫款项或借款，需在备注栏中说明。

Sheet 超市基本
A1: 工资明细表
A2: 编制单位：成都吉利汽车超市连锁有限公司
A3: 所属月份：2026年5月
A4: 部 门：吉利超市 | AH4: 金额单位：元
A5: 序号 | B5: 部门 | C5: 姓名 | D5: 出勤情况 | E5: 职 务 | F5: 应发工资 | Q5: 其他应发 | T5: 单位承担社会保险 | AB5: 代扣款项 | AH5: 实发金额 | AI5: 备注
F6: 基本工资 | G6: 加班工资 | H6: 保密工资 | I6: 津贴补贴 | J6: 车展补贴 | K6: 交通补贴 | L6: 通讯补贴 | M6: 其它 | N6: 减：病假、事假、缺勤、罚款 | O6: 减：未发绩效 | P6: 应发小计 | Q6: 预发 | S6: 其他小计 | T6: 基本养老保险16％ | U6: 基本医疗保险7.7％ | V6: 失业保险0.6% | W6: 工伤保险0.1% | X6: 大病医疗补充保险0.6% | Y6: *月社保补差 | Z6: 公积金公司承担 | AA6: 单位承担小计 | AB6: 社保个人承担 | AC6: 公积金个人承担 | AD6: 服装 | AE6: 爱心基金 | AF6: 其他代扣款项 | AG6: 代扣合计
B7: 总经办 | C7: 张嘉唯 | E7: 总经理
B8: 销售管理 | C8: 王欢 | E8: 实习销售总监
B9: 销售管理 | C9: 范娜 | E9: 网销经理
B10: 市场部 | C10: 黄思路 | E10: 市场专员
B11: 市场部 | C11: 付国晓 | E11: 前台接待
B12: 新媒体 | C12: 王芝婕 | E12: 主播
B13: 新媒体 | C13: 何玉 | E13: 主播
B14: 新媒体 | C14: 蓝仁楷 | E14: 主播
B15: 增值业务部 | C15: 刘彦 | E15: 金融专员
B16: 增值业务部 | C16: 李彦林 | E16: 金融专员
B17: 增值业务部 | C17: 白林 | E17: 二手车置换
B18: 财务部 | C18: 沈燕 | D18: 年休3天 | E18: 财务外勤
B19: 财务部 | C19: 李芳 | D19: 年休0.5天 | E19: 出纳
B20: 财务部 | C20: 唐梁英 | E20: 出纳
B21: 财务部 | C21: 高敏 | E21: 收银
B22: 行政人事部 | C22: 刘晓琴 | E22: 行政专员
B23: 销售支持 | C23: 刘玉兰 | E23: 吧员
B24: 客户关系部 | C24: 周舟 | E24: 回访专员
B25: 保客营销 | C25: 李姣 | E25: 保险出单员
B26: 物流部 | C26: 李燕 | E26: 物流内勤
B27: 物流部 | C27: 罗良清 | D27: 年休1天 | E27: 库管
B28: 综合部 | C28: 康忠伦 | E28: 司机
B29: 机场店（展厅） | C29: 邓戈 | E29: 销售顾问
B30: 机场店（展厅） | C30: 黄军 | E30: 销售顾问
B31: 机场店（展厅） | C31: 刘发 | E31: 销售顾问
B32: 机场店（展厅） | C32: 刘波 | E32: 销售顾问
B33: 机场店（展厅） | C33: 姚元利 | E33: 销售顾问
B34: 机场店（展厅） | C34: 王熙鸿 | D34: 5月25日离职生效，本月实际出勤24天 | E34: 销售顾问
B35: 机场店（展厅） | C35: 王秋望 | E35: 试驾专员
B36: 机场店（展厅） | C36: 冯超 | E36: 销售顾问
B37: 机场店（网销） | C37: 苟松柏 | E37: 上户专员
B38: 机场店（网销） | C38: 刘凤英 | D38: 年休5天 | E38: 销售顾问
B39: 机场店（网销） | C39: 莫晓何 | D39: 迟到1次 | E39: 销售顾问
B40: 机场店（网销） | C40: 赵强 | D40: 迟到1次 | E40: 销售顾问
B41: 机场店（网销） | C41: 黄婷婷 | E41: 销售顾问
B42: 机场店（网销） | C42: 向兰 | E42: 销售顾问
B43: 机场店（网销） | C43: 熊俊杰 | E43: 销售顾问
B44: 机场店（网销） | C44: 邱明杰 | D44: 5月28日离职生效，本月实际出勤27天 | E44: 销售顾问
B45: 机场店（网销） | C45: 陈林 | E45: 销售顾问
B46: 机场店（网销） | C46: 施巍 | E46: 销售顾问
B47: 机场店（网销） | C47: 陈子逸 | D47: 病假1天，迟到1次 | E47: 后台维护
B48: 机场店（网销） | C48: 李春梅 | D48: 事假0.5天 | E48: 邀约专员
B49: 机场店（网销） | C49: 魏艳 | E49: 邀约专员
B50: 机场店（网销） | C50: 谷雨 | E50: 邀约专员
B51: 上户部 | C51: 王艳 | E51: 上户主管
B52: 上户部 | C52: 刘珣 | E52: 上户专员
B53: 上户部 | C53: 王俊茹 | E53: 上户专员
B54: 上户部 | C54: 贾名伟 | E54: 查验员
B55: 上户部 | C55: 王泽文 | E55: 查验员
A56: 机场销售合计
B57: 机场总计
B58: 总经理： | E58: 车部总： | L58: 审批： | R58: 复核： | U58: 财务审核： | AB58: 直属主管： | AH58: 制表：
A61: 代扣款项中的员工基金和其他代扣款项系指不能在个人所得税税前扣除的集团代垫款项或借款，需在备注栏中说明。

Sheet 银河B直营店提成
C2: 2026年05月提成工资发放表 编制单位：直营店 所属月份：2026年05月份
A3: 发放公司 | B3: 挂账公司 | C3: 序号 | D3: 店别 | E3: 职务 | F3: 姓名 | G3: 人数 | H3: 考核量 | I3: 销售数量 | J3: 整车绩效 | K3: 权限结余绩效 | L3: 附加1绩效 | M3: 附加2绩效 | N3: 附加3绩效 | O3: 附加4绩效 | P3: 上户绩效 | Q3: 专项提成 | R3: 其他 | S3: 超期绩效 | T3: 大客户 | U3: 附加 | V3: 提成合计 | W3: 整车完成考核 | X3: 附加1考核 | Y3: 综合 | Z3: 已发绩效 | AA3: 其它1 | AB3: 活动内促奖励 | AC3: 交车支出 | AD3: 其它 | AE3: 特殊车型 | AF3: 考核小计 | AG3: 应发放合计 | AH3: 代发放绩效 | AI3: 实际发放=AE-X | AJ3: 基本工资（含补助） | AK3: 其它 | AL3: 其它 | AM3: 社保个人 | AN3: 应纳税所得额 | AO3: 个人所得税 | AP3: 已交个税 | AQ3: 本次扣税 | AR3: 基本代扣款 | AS3: 服装代扣 | AT3: 实际发放 | AU3: 年终标准 | AV3: 年终绩效 | AZ3: 核对
A4: 成都西物 | B4: 西物精锐 | D4: 直营店渠道 | E4: 销售顾问 | F4: 余才万 | V4: =SUM(J4:U4) -> 0 | AF4: =SUM(W4:AE4) -> 0 | AG4: =V4+AF4 -> 0 | AI4: =IF(Z4>0,AG4-Z4,AG4) -> 0 | AN4: =AG4+AJ4-AM4+AL4+AK4 -> 0 | AQ4: =AO4-AP4 -> 0 | AT4: =AI4-AQ4-AS4 -> 0 | AV4: =AU4*I4 -> 0 | AW4: =I4*AU4-AV4 -> 0 | AX4: =SUM(J4:U4)+SUM(W4:AC4)-AG4 -> 0 | AY4: =AT4-AI4 -> 0 | BB4: 王秀梅
A5: 成都西物 | B5: 西物精锐 | E5: 销售顾问 | V5: =SUM(J5:U5) -> 0 | AF5: =SUM(W5:AE5) -> 0 | AG5: =V5+AF5 -> 0 | AI5: =IF(Z5>0,AG5-Z5,AG5) -> 0 | AN5: =AG5+AJ5-AM5+AL5+AK5 -> 0 | AQ5: =AO5-AP5 -> 0 | AT5: =AI5-AQ5-AS5 -> 0 | AW5: =I5*AU5-AV5 -> 0 | AX5: =SUM(J5:U5)+SUM(W5:AC5)-AG5 -> 0 | AY5: =AT5-AI5 -> 0 | BB5: 陶小忠
A6: 吉利超市 | B6: 西物精锐 | E6: 小计 | G6: =SUM(G4:G5) -> 0 | H6: =SUM(H4:H5) -> 0 | I6: =SUM(I4:I5) -> 0 | J6: =SUM(J4:J5) -> 0 | K6: =SUM(K4:K5) -> 0 | L6: =SUM(L4:L5) -> 0 | M6: =SUM(M4:M5) -> 0 | N6: =SUM(N4:N5) -> 0 | ... AV6: =SUM(AV4:AV5) -> 0 | AX6: =SUM(J6:U6)+SUM(W6:AC6)-AG6 -> 0 | BB6: 杨婷
A7: 吉利超市 | B7: 西物精锐 | D7: 崇州直营店 | E7: 销售顾问 | F7: 杨婷 | V7: =SUM(J7:U7) -> 0 | AF7: =SUM(W7:AE7) -> 0 | AG7: =V7+AF7 -> 0 | AI7: =IF(Z7>0,AG7-Z7,AG7) -> 0 | AN7: =AG7+AJ7+AL7+AK7 -> 0 | AO7: =INDEX(BC:BC,MATCH(F7,BB:BB,0)) -> 0 | AQ7: =AO7-AP7 -> 0 | AT7: =AI7-AQ7-AS7 -> 0 | AW7: =I7*AU7-AV7 -> 0 | AX7: =SUM(J7:U7)+SUM(W7:AC7)-AG7 -> 0 | AY7: =AT7-AI7 -> 0 | BB7: 李智洪
A8: 吉利超市 | B8: 西物精锐 | E8: 销售助理 | F8: 唐鹏 | V8: =SUM(J8:U8) -> 0 | AF8: =SUM(W8:AE8) -> 0 | AG8: =V8+AF8 -> 0 | AI8: =IF(Z8>0,AG8-Z8,AG8) -> 0 | AN8: =AG8+AJ8+AL8+AK8 -> 0 | AO8: =INDEX(BC:BC,MATCH(F8,BB:BB,0)) -> 0 | AQ8: =AO8-AP8 -> 0 | AT8: =AI8-AQ8-AS8 -> 0 | AW8: =I8*AU8-AV8 -> 0 | AX8: =SUM(J8:U8)+SUM(W8:AC8)-AG8 -> 0 | AY8: =AT8-AI8 -> 0 | BB8: 朱剑波
A9: 吉利超市 | B9: 西物精锐 | E9: 销售顾问 | F9: 宁袁 | V9: =SUM(J9:U9) -> 0 | AF9: =SUM(W9:AE9) -> 0 | AG9: =V9+AF9 -> 0 | AI9: =IF(Z9>0,AG9-Z9,AG9) -> 0 | AN9: =AG9+AJ9+AL9+AK9 -> 0 | AQ9: =AO9-AP9 -> 0 | AT9: =AI9-AQ9-AS9 -> 0 | AW9: =I9*AU9-AV9 -> 0 | AX9: =SUM(J9:U9)+SUM(W9:AC9)-AG9 -> 0 | AY9: =AT9-AI9 -> 0 | BB9: 杨丽
A10: 吉利超市 | B10: 西物精锐 | E10: 销售顾问 | F10: 赵思梵 | V10: =SUM(J10:U10) -> 0 | AF10: =SUM(W10:AE10) -> 0 | AG10: =V10+AF10 -> 0 | AI10: =IF(Z10>0,AG10-Z10,AG10) -> 0 | AN10: =AG10+AJ10+AL10+AK10 -> 0 | AO10: =INDEX(BC:BC,MATCH(F10,BB:BB,0)) -> 0 | AQ10: =AO10-AP10 -> 0 | AT10: =AI10-AQ10-AS10 -> 0 | AW10: =I10*AU10-AV10 -> 0 | AX10: =SUM(J10:U10)+SUM(W10:AC10)-AG10 -> 0 | AY10: =AT10-AI10 -> 0 | BB10: 赵思梵
A11: 吉利超市 | B11: 西物精锐 | E11: 销售顾问 | F11: 李智洪 | V11: =SUM(J11:U11) -> 0 | AF11: =SUM(W11:AE11) -> 0 | AG11: =V11+AF11 -> 0 | AI11: =IF(Z11>0,AG11-Z11,AG11) -> 0 | AN11: =AG11+AJ11+AL11+AK11 -> 0 | AO11: =INDEX(BC:BC,MATCH(F11,BB:BB,0)) -> 0 | AQ11: =AO11-AP11 -> 0 | AT11: =AI11-AQ11-AS11 -> 0 | AW11: =I11*AU11-AV11 -> 0 | AX11: =SUM(J11:U11)+SUM(W11:AC11)-AG11 -> 0 | AY11: =AT11-AI11 -> 0 | BB11: 唐鹏
A12: 吉利超市 | B12: 西物精锐 | E12: 销售顾问 | F12: 陈勇建 | V12: =SUM(J12:U12) -> 0 | AF12: =SUM(W12:AE12) -> 0 | AG12: =V12+AF12 -> 0 | AI12: =IF(Z12>0,AG12-Z12,AG12) -> 0 | AN12: =AG12+AJ12+AL12+AK12 -> 0 | AO12: =INDEX(BC:BC,MATCH(F12,BB:BB,0)) -> 0 | AQ12: =AO12-AP12 -> 0 | AT12: =AI12-AQ12-AS12 -> 0 | AW12: =I12*AU12-AV12 -> 0 | AX12: =SUM(J12:U12)+SUM(W12:AC12)-AG12 -> 0 | AY12: =AT12-AI12 -> 0 | BB12: 赵思梵
A13: 吉利超市 | B13: 西物精锐 | E13: 销售顾问 | F13: 空白 | V13: =SUM(J13:U13) -> 0 | AF13: =SUM(W13:AE13) -> 0 | AG13: =V13+AF13 -> 0 | AI13: =IF(Z13>0,AG13-Z13,AG13) -> 0 | AN13: =AG13+AJ13+AL13+AK13 -> 0 | AO13: =INDEX(BC:BC,MATCH(F13,BB:BB,0)) -> 0 | AQ13: =AO13-AP13 -> 0 | AT13: =AI13-AQ13-AS13 -> 0 | AW13: =I13*AU13-AV13 -> 0 | AX13: =SUM(J13:U13)+SUM(W13:AC13)-AG13 -> 0 | AY13: =AT13-AI13 -> 0 | BB13: 唐鹏
A14: 吉利超市 | B14: 西物精锐 | E14: 内勤 | F14: 李良英 | V14: =SUM(J14:U14) -> 0 | AF14: =SUM(W14:AE14) -> 0 | AG14: =V14+AF14 -> 0 | AI14: =IF(Z14>0,AG14-Z14,AG14) -> 0 | AN14: =AG14+AJ14+AL14+AK14 -> 0 | AO14: =INDEX(BC:BC,MATCH(F14,BB:BB,0)) -> 0 | AQ14: =AO14-AP14 -> 0 | AT14: =AI14-AQ14-AS14 -> 0 | AW14: =I14*AU14-AV14 -> 0 | AX14: =SUM(J14:U14)+SUM(W14:AC14)-AG14 -> 0 | AY14: =AT14-AI14 -> 0 | BB14: 赵思梵
A15: 吉利超市 | B15: 西物精锐 | F15: 空白 | V15: =SUM(J15:U15) -> 0 | AF15: =SUM(W15:AE15) -> 0 | AG15: =V15+AF15 -> 0 | AI15: =IF(Z15>0,AG15-Z15,AG15) -> 0 | AN15: =AG15+AJ15+AL15+AK15 -> 0 | AQ15: =AO15-AP15 -> 0 | AT15: =AI15-AQ15-AS15 -> 0 | AW15: =I15*AU15-AV15 -> 0 | AX15: =SUM(J15:U15)+SUM(W15:AC15)-AG15 -> 0 | AY15: =AT15-AI15 -> 0 | BB15: 唐鹏
A16: 吉利超市 | B16: 西物精锐 | F16: 空白 | V16: =SUM(J16:U16) -> 0 | AF16: =SUM(W16:AE16) -> 0 | AG16: =V16+AF16 -> 0 | AI16: =IF(Z16>0,AG16-Z16,AG16) -> 0 | AN16: =AG16+AJ16+AL16+AK16 -> 0 | AQ16: =AO16-AP16 -> 0 | AT16: =AI16-AQ16-AS16 -> 0 | AW16: =I16*AU16-AV16 -> 0 | AX16: =SUM(J16:U16)+SUM(W16:AC16)-AG16 -> 0 | AY16: =AT16-AI16 -> 0 | BB16: 李良英
A17: 吉利超市 | B17: 西物精锐 | E17: 销售经理 | F17: 朱剑波 | V17: =SUM(J17:U17) -> 0 | AF17: =SUM(W17:AE17) -> 0 | AG17: =V17+AF17 -> 0 | AI17: =IF(Z17>0,AG17-Z17,AG17)+AH17 -> 0 | AN17: =AG17+AJ17+AL17+AK17 -> 0 | AQ17: =AO17-AP17 -> 0 | AT17: =AI17-AQ17-AS17 -> 0 | BB17: 何松
A18: 吉利超市 | B18: 西物精锐 | E18: 小计 | G18: =SUM(G7:G17) -> 0 | H18: =SUM(H7:H17) -> 0 | I18: =SUM(I7:I17) -> 0 | J18: =SUM(J7:J17) -> 0 | K18: =SUM(K7:K17) -> 0 | L18: =SUM(L7:L17) -> 0 | M18: =SUM(M7:M17) -> 0 | N18: =SUM(N7:N17) -> 0 | ... AJ18: =SUM(AJ7:AJ17) -> 0 | AK18: =SUM(AK7:AK16) -> 0 | AL18: =SUM(AL7:AL16) -> 0 | AM18: =SUM(AM7:AM16) -> 0 | AN18: =SUM(AN7:AN17) -> 0 | AO18: =SUM(AO7:AO17) -> 0 | AP18: =SUM(AP7:AP17) -> 0 | AQ18: =SUM(AQ7:AQ17) -> 0 | AR18: =SUM(AR7:AR17) -> 0 | AS18: =SUM(AS7:AS17) -> 0 | AT18: =SUM(AT7:AT17) -> 0 | AU18: =SUM(AU7:AU17) -> 0 | AV18: =SUM(AV7:AV17) -> 0 | AX18: =SUM(J18:U18)+SUM(W18:AC18)-AG18 -> 0 | BB18: 李容
A19: 吉利超市 | B19: 西物精锐 | D19: 邛崃直营店 | E19: 内勤 | F19: 王巧巧 | V19: =SUM(J19:U19) -> 0 | AF19: =SUM(W19:AE19) -> 0 | AG19: =V19+AF19 -> 0 | AI19: =IF(Z19>0,AG19-Z19,AG19) -> 0 | AN19: =AG19+AJ19+AL19+AK19 -> 0 | AO19: =INDEX(BC:BC,MATCH(F19,BB:BB,0)) -> 0 | AQ19: =AO19-AP19 -> 0 | AT19: =AI19-AQ19-AS19 -> 0 | AW19: =I19*AU19-AV19 -> 0 | AX19: =SUM(J19:U19)+SUM(W19:AC19)-AG19 -> 0 | AY19: =AT19-AI19 -> 0 | BB19: 王巧巧
A20: 吉利超市 | B20: 西物精锐 | E20: 销售顾问 | F20: 叶荣鹏 | V20: =SUM(J20:U20) -> 0 | AF20: =SUM(W20:AE20) -> 0 | AG20: =V20+AF20 -> 0 | AI20: =IF(Z20>0,AG20-Z20,AG20) -> 0 | AN20: =AG20+AJ20+AL20+AK20 -> 0 | AO20: =INDEX(BC:BC,MATCH(F20,BB:BB,0)) -> 0 | AQ20: =AO20-AP20 -> 0 | AT20: =AI20-AQ20-AS20 -> 0 | AW20: =I20*AU20-AV20 -> 0 | AX20: =SUM(J20:U20)+SUM(W20:AC20)-AG20 -> 0 | AY20: =AT20-AI20 -> 0 | BB20: 叶荣鹏
A21: 吉利超市 | B21: 西物精锐 | E21: 销售顾问 | F21: 马勇 | V21: =SUM(J21:U21) -> 0 | AF21: =SUM(W21:AE21) -> 0 | AG21: =V21+AF21 -> 0 | AI21: =IF(Z21>0,AG21-Z21,AG21) -> 0 | AN21: =AG21+AJ21+AL21+AK21 -> 0 | AO21: =INDEX(BC:BC,MATCH(F21,BB:BB,0)) -> 0 | AQ21: =AO21-AP21 -> 0 | AT21: =AI21-AQ21-AS21 -> 0 | AW21: =I21*AU21-AV21 -> 0 | AX21: =SUM(J21:U21)+SUM(W21:AC21)-AG21 -> 0 | AY21: =AT21-AI21 -> 0 | BB21: 马勇
A22: 吉利超市 | B22: 西物精锐 | E22: 销售顾问 | F22: 高东琴 | V22: =SUM(J22:U22) -> 0 | AF22: =SUM(W22:AE22) -> 0 | AG22: =V22+AF22 -> 0 | AI22: =IF(Z22>0,AG22-Z22,AG22) -> 0 | AN22: =AG22+AJ22+AL22+AK22 -> 0 | AO22: =INDEX(BC:BC,MATCH(F22,BB:BB,0)) -> 0 | AQ22: =AO22-AP22 -> 0 | AT22: =AI22-AQ22-AS22 -> 0 | AW22: =I22*AU22-AV22 -> 0 | AX22: =SUM(J22:U22)+SUM(W22:AC22)-AG22 -> 0 | AY22: =AT22-AI22 -> 0 | BB22: 高东琴
A23: 吉利超市 | B23: 西物精锐 | E23: 销售顾问 | F23: 空白 | V23: =SUM(J23:U23) -> 0 | AF23: =SUM(W23:AE23) -> 0 | AG23: =V23+AF23 -> 0 | AI23: =IF(Z23>0,AG23-Z23,AG23) -> 0 | AN23: =AG23+AJ23+AL23+AK23 -> 0 | AO23: =INDEX(BC:BC,MATCH(F23,BB:BB,0)) -> 0 | AQ23: =AO23-AP23 -> 0 | AT23: =AI23-AQ23-AS23 -> 0 | AW23: =I23*AU23-AV23 -> 0 | AX23: =SUM(J23:U23)+SUM(W23:AC23)-AG23 -> 0 | AY23: =AT23-AI23 -> 0 | BB23: 王渔浩
A24: 吉利超市 | B24: 西物精锐 | E24: 销售经理 | F24: 吴思超 | V24: =SUM(J24:U24) -> 0 | AF24: =SUM(W24:AE24) -> 0 | AG24: =V24+AF24 -> 0 | AI24: =IF(Z24>0,AG24-Z24,AG24) -> 0 | AN24: =AG24+AJ24+AL24+AK24 -> 0 | AO24: =INDEX(BC:BC,MATCH(F24,BB:BB,0)) -> 0 | AQ24: =AO24-AP24 -> 0 | AT24: =AI24-AQ24-AS24 -> 0 | AW24: =I24*AU24-AV24 -> 0 | AX24: =SUM(J24:U24)+SUM(W24:AC24)-AG24 -> 0 | AY24: =AT24-AI24 -> 0 | BB24: 吴思超
A25: 吉利超市 | B25: 西物精锐 | E25: 小计 | G25: =SUM(G19:G24) -> 0 | H25: =SUM(H19:H24) -> 0 | I25: =SUM(I19:I24) -> 0 | J25: =SUM(J19:J24) -> 0 | K25: =SUM(K19:K24) -> 0 | L25: =SUM(L19:L24) -> 0 | M25: =SUM(M19:M24) -> 0 | N25: =SUM(N19:N24) -> 0 | ... AV25: =SUM(AV19:AV24) -> 0 | AX25: =SUM(J25:U25)+SUM(W25:AC25)-AG25 -> 0 | BB25: 杨念慈
A26: 吉利超市 | B26: 西物精锐 | D26: 大邑直营店 | E26: 销售内勤 | F26: 杨念慈 | V26: =SUM(J26:U26) -> 0 | AF26: =SUM(W26:AE26) -> 0 | AG26: =V26+AF26 -> 0 | AI26: =IF(Z26>0,AG26-Z26,AG26) -> 0 | AN26: =AG26+AJ26+AL26+AK26 -> 0 | AO26: =INDEX(BC:BC,MATCH(F26,BB:BB,0)) -> 0 | AQ26: =AO26-AP26 -> 0 | AT26: =AI26-AQ26-AS26 -> 0 | AW26: =I26*AU26-AV26 -> 0 | AX26: =SUM(J26:U26)+SUM(W26:AC26)-AG26 -> 0 | AY26: =AT26-AI26 -> 0 | BB26: 空白
A27: 吉利超市 | B27: 西物精锐 | E27: 销售顾问 | F27: 程羊 | V27: =SUM(J27:U27) -> 0 | AF27: =SUM(W27:AE27) -> 0 | AG27: =V27+AF27 -> 0 | AI27: =IF(Z27>0,AG27-Z27,AG27) -> 0 | AN27: =AG27+AJ27+AL27+AK27 -> 0 | AO27: =INDEX(BC:BC,MATCH(F27,BB:BB,0)) -> 0 | AQ27: =AO27-AP27 -> 0 | AT27: =AI27-AQ27-AS27 -> 0 | AW27: =I27*AU27-AV27 -> 0 | AX27: =SUM(J27:U27)+SUM(W27:AC27)-AG27 -> 0 | AY27: =AT27-AI27 -> 0 | BB27: 程羊
A28: 吉利超市 | B28: 西物精锐 | E28: 销售顾问 | F28: 常涛 | V28: =SUM(J28:U28) -> 0 | AF28: =SUM(W28:AE28) -> 0 | AG28: =V28+AF28 -> 0 | AI28: =IF(Z28>0,AG28-Z28,AG28) -> 0 | AN28: =AG28+AJ28+AL28+AK28 -> 0 | AO28: =INDEX(BC:BC,MATCH(F28,BB:BB,0)) -> 0 | AQ28: =AO28-AP28 -> 0 | AT28: =AI28-AQ28-AS28 -> 0 | AW28: =I28*AU28-AV28 -> 0 | AX28: =SUM(J28:U28)+SUM(W28:AC28)-AG28 -> 0 | AY28: =AT28-AI28 -> 0 | BB28: 常涛
A29: 吉利超市 | B29: 西物精锐 | E29: 销售顾问 | F29: 王海 | V29: =SUM(J29:U29) -> 0 | AF29: =SUM(W29:AE29) -> 0 | AG29: =V29+AF29 -> 0 | AI29: =IF(Z29>0,AG29-Z29,AG29) -> 0 | AN29: =AG29+AJ29+AL29+AK29 -> 0 | AO29: =INDEX(BC:BC,MATCH(F29,BB:BB,0)) -> 0 | AQ29: =AO29-AP29 -> 0 | AT29: =AI29-AQ29-AS29 -> 0 | AW29: =I29*AU29-AV29 -> 0 | AX29: =SUM(J29:U29)+SUM(W29:AC29)-AG29 -> 0 | AY29: =AT29-AI29 -> 0 | BB29: 王海
A30: 吉利超市 | B30: 西物精锐 | E30: 销售顾问 | F30: 袁萍 | V30: =SUM(J30:U30) -> 0 | AF30: =SUM(W30:AE30) -> 0 | AG30: =V30+AF30 -> 0 | AI30: =IF(Z30>0,AG30-Z30,AG30) -> 0 | AN30: =AG30+AJ30+AL30+AK30 -> 0 | AQ30: =AO30-AP30 -> 0 | AT30: =AI30-AQ30-AS30 -> 0 | AW30: =I30*AU30-AV30 -> 0 | AX30: =SUM(J30:U30)+SUM(W30:AC30)-AG30 -> 0 | AY30: =AT30-AI30 -> 0 | BB30: 王海
A31: 吉利超市 | B31: 西物精锐 | E31: 销售经理 | F31: 孙伟 | V31: =SUM(J31:U31) -> 0 | AF31: =SUM(W31:AE31) -> 0 | AG31: =V31+AF31 -> 0 | AI31: =IF(Z31>0,AG31-Z31,AG31) -> 0 | AN31: =AG31+AJ31+AL31+AK31 -> 0 | AO31: =INDEX(BC:BC,MATCH(F31,BB:BB,0)) -> 0 | AQ31: =AO31-AP31 -> 0 | AT31: =AI31-AQ31-AS31 -> 0 | AW31: =I31*AU31-AV31 -> 0 | AX31: =SUM(J31:U31)+SUM(W31:AC31)-AG31 -> 0 | AY31: =AT31-AI31 -> 0 | BB31: 孙伟
A32: 吉利超市 | B32: 西物精锐 | E32: 小计 | G32: =SUM(G26:G31) -> 0 | H32: =SUM(H26:H31) -> 0 | I32: =SUM(I26:I31) -> 0 | J32: =SUM(J26:J31) -> 0 | K32: =SUM(K26:K31) -> 0 | L32: =SUM(L26:L31) -> 0 | M32: =SUM(M26:M31) -> 0 | N32: =SUM(N26:N31) -> 0 | ... AV32: =SUM(AV26:AV31) -> 0 | AX32: =SUM(J32:U32)+SUM(W32:AC32)-AG32 -> 0 | BB32: 刘娅
A33: 吉利超市 | B33: 西物精锐 | D33: 彭州直营店 | E33: 出纳+内勤 | F33: 牟春柳 | V33: =SUM(J33:U33) -> 0 | AF33: =SUM(W33:AE33) -> 0 | AG33: =V33+AF33 -> 0 | AI33: =IF(Z33>0,AG33-Z33,AG33) -> 0 | AN33: =AG33+AJ33+AL33+AK33 -> 0 | AO33: =INDEX(BC:BC,MATCH(F33,BB:BB,0)) -> 0 | AQ33: =AO33-AP33 -> 0 | AT33: =AI33-AQ33-AS33 -> 0 | AW33: =I33*AU33-AV33 -> 0 | AX33: =SUM(J33:U33)+SUM(W33:AC33)-AG33 -> 0 | AY33: =AT33-AI33 -> 0 | BB33: 牟春柳
A34: 吉利超市 | B34: 西物精锐 | E34: 销售顾问 | F34: 钟家林 | V34: =SUM(J34:U34) -> 0 | AF34: =SUM(W34:AE34) -> 0 | AG34: =V34+AF34 -> 0 | AI34: =IF(Z34>0,AG34-Z34,AG34) -> 0 | AN34: =AG34+AJ34+AL34+AK34 -> 0 | AO34: =INDEX(BC:BC,MATCH(F34,BB:BB,0)) -> 0 | AQ34: =AO34-AP34 -> 0 | AT34: =AI34-AQ34-AS34 -> 0 | AW34: =I34*AU34-AV34 -> 0 | AX34: =SUM(J34:U34)+SUM(W34:AC34)-AG34 -> 0 | AY34: =AT34-AI34 -> 0 | BB34: 钟家林
A35: 吉利超市 | B35: 西物精锐 | E35: 销售顾问 | F35: 刘娅 | V35: =SUM(J35:U35) -> 0 | AF35: =SUM(W35:AE35) -> 0 | AG35: =V35+AF35 -> 0 | AI35: =IF(Z35>0,AG35-Z35,AG35) -> 0 | AN35: =AG35+AJ35+AL35+AK35 -> 0 | AQ35: =AO35-AP35 -> 0 | AT35: =AI35-AQ35-AS35 -> 0 | AW35: =I35*AU35-AV35 -> 0 | AX35: =SUM(J35:U35)+SUM(W35:AC35)-AG35 -> 0 | AY35: =AT35-AI35 -> 0 | BB35: 黎明朗
A36: 吉利超市 | B36: 西物精锐 | E36: 销售顾问 | F36: 陈莉 | V36: =SUM(J36:U36) -> 0 | AF36: =SUM(W36:AE36) -> 0 | AG36: =V36+AF36 -> 0 | AI36: =IF(Z36>0,AG36-Z36,AG36) -> 0 | AN36: =AG36+AJ36+AL36+AK36 -> 0 | AO36: =INDEX(BC:BC,MATCH(F36,BB:BB,0)) -> 0 | AQ36: =AO36-AP36 -> 0 | AT36: =AI36-AQ36-AS36 -> 0 | AW36: =I36*AU36-AV36 -> 0 | AX36: =SUM(J36:U36)+SUM(W36:AC36)-AG36 -> 0 | AY36: =AT36-AI36 -> 0 | BB36: 任和奎
A37: 吉利超市 | B37: 西物精锐 | E37: 销售助理 | F37: 任和奎 | V37: =SUM(J37:U37) -> 0 | AF37: =SUM(W37:AE37) -> 0 | AG37: =V37+AF37 -> 0 | AI37: =IF(Z37>0,AG37-Z37,AG37) -> 0 | AN37: =AG37+AJ37+AL37+AK37 -> 0 | AQ37: =AO37-AP37 -> 0 | AT37: =AI37-AQ37-AS37 -> 0 | AW37: =I37*AU37-AV37 -> 0 | AX37: =SUM(J37:U37)+SUM(W37:AC37)-AG37 -> 0 | AY37: =AT37-AI37 -> 0 | BB37: 王伟
A38: 吉利超市 | B38: 西物精锐 | E38: 销售顾问 | F38: 兰代全 | V38: =SUM(J38:U38) -> 0 | AF38: =SUM(W38:AE38) -> 0 | AG38: =V38+AF38 -> 0 | AI38: =IF(Z38>0,AG38-Z38,AG38) -> 0 | AN38: =AG38+AJ38+AL38+AK38 -> 0 | AO38: =INDEX(BC:BC,MATCH(F38,BB:BB,0)) -> 0 | AQ38: =AO38-AP38 -> 0 | AT38: =AI38-AQ38-AS38 -> 0 | AW38: =I38*AU38-AV38 -> 0 | AX38: =SUM(J38:U38)+SUM(W38:AC38)-AG38 -> 0 | AY38: =AT38-AI38 -> 0 | BB38: 任和奎
A39: 吉利超市 | B39: 西物精锐 | F39: 空白 | V39: =SUM(J39:U39) -> 0 | AF39: =SUM(W39:AE39) -> 0 | AG39: =V39+AF39 -> 0 | AI39: =IF(Z39>0,AG39-Z39,AG39) -> 0 | AN39: =AG39+AJ39+AL39+AK39 -> 0 | AQ39: =AO39-AP39 -> 0 | AT39: =AI39-AQ39-AS39 -> 0 | AW39: =I39*AU39-AV39 -> 0 | AX39: =SUM(J39:U39)+SUM(W39:AC39)-AG39 -> 0 | AY39: =AT39-AI39 -> 0 | BB39: 王伟
A40: 吉利超市 | B40: 西物精锐 | F40: 空白 | V40: =SUM(J40:U40) -> 0 | AF40: =SUM(W40:AE40) -> 0 | AG40: =V40+AF40 -> 0 | AI40: =IF(Z40>0,AG40-Z40,AG40) -> 0 | AN40: =AG40+AJ40+AL40+AK40 -> 0 | AO40: =INDEX(BC:BC,MATCH(F40,BB:BB,0)) -> 0 | AQ40: =AO40-AP40 -> 0 | AT40: =AI40-AQ40-AS40 -> 0 | AW40: =I40*AU40-AV40 -> 0 | AX40: =SUM(J40:U40)+SUM(W40:AC40)-AG40 -> 0 | AY40: =AT40-AI40 -> 0 | BB40: 王伟
A41: 吉利超市 | B41: 西物精锐 | E41: 销售经理 | F41: 黎明朗 | V41: =SUM(J41:U41) -> 0 | AF41: =SUM(W41:AE41) -> 0 | AG41: =V41+AF41 -> 0 | AI41: =IF(Z41>0,AG41-Z41,AG41) -> 0 | AN41: =AG41+AJ41+AL41+AK41 -> 0 | AO41: =INDEX(BC:BC,MATCH(F41,BB:BB,0)) -> 0 | AQ41: =AO41-AP41 -> 0 | AT41: =AI41-AQ41-AS41 -> 0 | AW41: =I41*AU41-AV41 -> 0 | AX41: =SUM(J41:U41)+SUM(W41:AC41)-AG41 -> 0 | AY41: =AT41-AI41 -> 0 | BB41: 王茂林
A42: 吉利超市 | B42: 西物精锐 | E42: 小计 | G42: =SUM(G33:G41) -> 0 | H42: =SUM(H33:H41) -> 0 | I42: =SUM(I33:I41) -> 0 | J42: =SUM(J33:J41) -> 0 | K42: =SUM(K33:K41) -> 0 | L42: =SUM(L33:L41) -> 0 | M42: =SUM(M33:M41) -> 0 | N42: =SUM(N33:N41) -> 0 | ... AV42: =SUM(AV33:AV41) -> 0 | AX42: =SUM(J42:U42)+SUM(W42:AC42)-AG42 -> 0 | BB42: 胡刚
A43: 吉利超市 | B43: 西物精锐 | D43: 华阳直营店 | E43: 出纳+内勤 | F43: 毛婷婷 | V43: =SUM(J43:U43) -> 0 | AF43: =SUM(W43:AE43) -> 0 | AG43: =V43+AF43 -> 0 | AI43: =IF(Z43>0,AG43-Z43,AG43) -> 0 | AN43: =AG43+AJ43+AL43+AK43 -> 0 | AO43: =INDEX(BC:BC,MATCH(F43,BB:BB,0)) -> 0 | AQ43: =AO43-AP43 -> 0 | AT43: =AI43-AQ43-AS43 -> 0 | AW43: =I43*AU43-AV43 -> 0 | AX43: =SUM(J43:U43)+SUM(W43:AC43)-AG43 -> 0 | AY43: =AT43-AI43 -> 0 | BB43: 毛婷婷
A44: 吉利超市 | B44: 西物精锐 | E44: 销售顾问 | F44: 蒋云 | V44: =SUM(J44:U44) -> 0 | AF44: =SUM(W44:AE44) -> 0 | AG44: =V44+AF44 -> 0 | AI44: =IF(Z44>0,AG44-Z44,AG44) -> 0 | AN44: =AG44+AJ44+AL44+AK44 -> 0 | AQ44: =AO44-AP44 -> 0 | AT44: =AI44-AQ44-AS44 -> 0 | AW44: =I44*AU44-AV44 -> 0 | AX44: =SUM(J44:U44)+SUM(W44:AC44)-AG44 -> 0 | AY44: =AT44-AI44 -> 0 | BB44: 袁湘
A45: 吉利超市 | B45: 西物精锐 | E45: 销售顾问 | F45: 张坤 | V45: =SUM(J45:U45) -> 0 | AF45: =SUM(W45:AE45) -> 0 | AG45: =V45+AF45 -> 0 | AI45: =IF(Z45>0,AG45-Z45,AG45) -> 0 | AN45: =AG45+AJ45+AL45+AK45 -> 0 | AO45: =INDEX(BC:BC,MATCH(F45,BB:BB,0)) -> 0 | AQ45: =AO45-AP45 -> 0 | AT45: =AI45-AQ45-AS45 -> 0 | AW45: =I45*AU45-AV45 -> 0 | AX45: =SUM(J45:U45)+SUM(W45:AC45)-AG45 -> 0 | AY45: =AT45-AI45 -> 0 | BB45: 张坤
A46: 吉利超市 | B46: 西物精锐 | E46: 销售顾问 | F46: 向凤 | V46: =SUM(J46:U46) -> 0 | AF46: =SUM(W46:AE46) -> 0 | AG46: =V46+AF46 -> 0 | AI46: =IF(Z46>0,AG46-Z46,AG46) -> 0 | AN46: =AG46+AJ46+AL46+AK46 -> 0 | AO46: =INDEX(BC:BC,MATCH(F46,BB:BB,0)) -> 0 | AQ46: =AO46-AP46 -> 0 | AT46: =AI46-AQ46-AS46 -> 0 | AW46: =I46*AU46-AV46 -> 0 | AX46: =SUM(J46:U46)+SUM(W46:AC46)-AG46 -> 0 | AY46: =AT46-AI46 -> 0 | BB46: 向凤
A47: 吉利超市 | B47: 西物精锐 | E47: 销售顾问 | F47: 吴小琴 | V47: =SUM(J47:U47) -> 0 | AF47: =SUM(W47:AE47) -> 0 | AG47: =V47+AF47 -> 0 | AI47: =IF(Z47>0,AG47-Z47,AG47) -> 0 | AN47: =AG47+AJ47+AL47+AK47 -> 0 | AO47: =INDEX(BC:BC,MATCH(F47,BB:BB,0)) -> 0 | AQ47: =AO47-AP47 -> 0 | AT47: =AI47-AQ47-AS47 -> 0 | AW47: =I47*AU47-AV47 -> 0 | AX47: =SUM(J47:U47)+SUM(W47:AC47)-AG47 -> 0 | AY47: =AT47-AI47 -> 0 | BB47: 向凤
A48: 吉利超市 | B48: 西物精锐 | E48: 销售顾问 | F48: 丁小玲 | V48: =SUM(J48:U48) -> 0 | AF48: =SUM(W48:AE48) -> 0 | AG48: =V48+AF48 -> 0 | AI48: =IF(Z48>0,AG48-Z48,AG48) -> 0 | AN48: =AG48+AJ48+AL48+AK48 -> 0 | AO48: =INDEX(BC:BC,MATCH(F48,BB:BB,0)) -> 0 | AQ48: =AO48-AP48 -> 0 | AT48: =AI48-AQ48-AS48 -> 0 | AW48: =I48*AU48-AV48 -> 0 | AX48: =SUM(J48:U48)+SUM(W48:AC48)-AG48 -> 0 | AY48: =AT48-AI48 -> 0 | BB48: 吴小琴
A49: 吉利超市 | B49: 西物精锐 | E49: 销售顾问 | F49: 刘华 | V49: =SUM(J49:U49) -> 0 | AF49: =SUM(W49:AE49) -> 0 | AG49: =V49+AF49 -> 0 | AI49: =IF(Z49>0,AG49-Z49,AG49) -> 0 | AN49: =AG49+AJ49+AL49+AK49 -> 0 | AO49: =INDEX(BC:BC,MATCH(F49,BB:BB,0)) -> 0 | AQ49: =AO49-AP49 -> 0 | AT49: =AI49-AQ49-AS49 -> 0 | AW49: =I49*AU49-AV49 -> 0 | AX49: =SUM(J49:U49)+SUM(W49:AC49)-AG49 -> 0 | AY49: =AT49-AI49 -> 0 | BB49: 丁小玲
A50: 吉利超市 | B50: 西物精锐 | E50: 销售经理 | F50: 钟涛 | V50: =SUM(J50:U50) -> 0 | AF50: =SUM(W50:AE50) -> 0 | AG50: =V50+AF50 -> 0 | AI50: =IF(Z50>0,AG50-Z50,AG50) -> 0 | AN50: =AG50+AJ50+AL50+AK50 -> 0 | AO50: =INDEX(BC:BC,MATCH(F50,BB:BB,0)) -> 0 | AQ50: =AO50-AP50 -> 0 | AT50: =AI50-AQ50-AS50 -> 0 | AW50: =I50*AU50-AV50 -> 0 | AX50: =SUM(J50:U50)+SUM(W50:AC50)-AG50 -> 0 | AY50: =AT50-AI50 -> 0 | BB50: 钟涛
A51: 吉利超市 | B51: 西物精锐 | E51: 小计 | G51: =SUM(G43:G50) -> 0 | H51: =SUM(H43:H50) -> 0 | I51: =SUM(I43:I50) -> 0 | J51: =SUM(J43:J50) -> 0 | K51: =SUM(K43:K50) -> 0 | L51: =SUM(L43:L50) -> 0 | M51: =SUM(M43:M50) -> 0 | N51: =SUM(N43:N50) -> 0 | ... AV51: =SUM(AV43:AV50) -> 0 | AX51: =SUM(J51:U51)+SUM(W51:AC51)-AG51 -> 0 | BB51: 姚佳秀
A52: 吉利超市 | B52: 西物精锐 | E52: 直营店总计 | G52: =SUM(G6,G18,G25,G32,G42,G51) -> 0 | H52: =SUM(H6,H18,H25,H32,H42,H51) -> 0 | I52: =SUM(I6,I18,I25,I32,I42,I51) -> 0 | J52: =SUM(J6,J18,J25,J32,J42,J51) -> 0 | K52: =SUM(K6,K18,K25,K32,K42,K51) -> 0 | L52: =SUM(L6,L18,L25,L32,L42,L51) -> 0 | M52: =SUM(M6,M18,M25,M32,M42,M51) -> 0 | N52: =SUM(N6,N18,N25,N32,N42,N51) -> 0 | ... AV52: =SUM(AV6,AV18,AV25,AV32,AV42,AV51) -> 0 | AX52: =SUM(J52:U52)+SUM(W52:AC52)-AG52 -> 0 | BB52: 陈勇建
BB53: 杨凤华
I54: =243+230+239 -> 712 | BB54: 张家耀
D55: 事业部总经理审核： | M55: 事业部审核： | V55: 财务审核： | AG55: 主管审核： | AT55: 制表人： | BB55: 赵可
BB56: 陈莉
BB57: 兰代全
BB58: 刘华

Sheet 银河A提成- 渠道+直营店
A2: 发放公司 | B2: 核销公司 | C2: 2026年05月提成工资发放表 编制单位：成都西物汽车有限公司+精锐
C3: 序号 | D3: 店别 | E3: 职务 | F3: 姓名 | G3: 人数 | H3: 考核量 | I3: 销售数量 | J3: 整车绩效 | K3: 权限结余绩效 | L3: 附加1绩效 | M3: 附加2绩效 | N3: 附加3绩效 | O3: 附加4绩效 | P3: 上户绩效 | Q3: 专项提成 | R3: 其他 | S3: 超期绩效 | T3: 大客户 | U3: 附加 | V3: 提成合计 | W3: 整车完成考核 | X3: 附加1考核 | Y3: 综合 | Z3: 台阶奖励 | AA3: 已发合并扣税 | AB3: 满意度考核 | AC3: 交车支出 | AD3: 已发并 | AE3: 考核 | AF3: 考核小计 | AG3: 应发放合计 | AH3: 实际发放 | AI3: 基本工资（含补助） | AJ3: 其它 | AK3: 已发合并扣税项 | AL3: 社保个人 | AM3: 应纳税所得额 | AN3: 个人所得税 | AO3: 已交个税 | AP3: 本次扣税 | AQ3: 基本代扣款 | AR3: 服装代扣 | AS3: 实际发放 | AT3: 年终标准 | AU3: 年终绩效 | AY3: 核对 | AZ3: 税前工资合计
A4: 西物精锐 | B4: 银河 | D4: 银河西物渠道 | E4: 销售顾问 | F4: 徐尊剑 | AH4: =AG4 -> 0 | AM4: =AH4+AI4-AK4-AL4 -> 0 | AS4: =AH4-AN4-AQ4-AR4 -> 0 | AV4: =I4*AT4-AU4 -> 0 | AW4: =SUM(J4:U4)+SUM(W4:AC4)-AG4 -> 0 | AX4: =AS4-AH4 -> 0 | AZ4: =AL4+AM4 -> 0
E5: 小计 | H5: =SUM(H4:H4) -> 0 | I5: =SUM(I4:I4) -> 0 | J5: =SUM(J4:J4) -> 0 | K5: =SUM(K4:K4) -> 0 | L5: =SUM(L4:L4) -> 0 | M5: =SUM(M4:M4) -> 0 | N5: =SUM(N4:N4) -> 0 | O5: =SUM(O4:O4) -> 0 | ... AU5: =SUM(AU4:AU4) -> 0
E6: 小计 | G6: =G5 -> 0 | H6: =H5 -> 0 | I6: =I5 -> 0 | J6: =J5 -> 0 | K6: =K5 -> 0 | L6: =L5 -> 0 | M6: =M5 -> 0 | N6: =N5 -> 0 | ... AU6: =AU5 -> 0
D9: 事业部总经理审核： | M9: 事业部审核： | V9: 财务审核： | AG9: 主管审核： | AS9: 制表人：
C11: 序号 | D11: 店别 | E11: 职务 | F11: 姓名 | G11: 人数 | H11: 考核量 | I11: 销售数量 | J11: 整车绩效 | K11: 权限结余绩效 | L11: 附加1绩效 | M11: 附加2绩效 | N11: 附加3绩效 | O11: 附加4绩效 | P11: 上户绩效 | Q11: 专项提成 | R11: 其他 | S11: 超期绩效 | T11: 大客户 | U11: 附加 | V11: 提成合计 | W11: 整车完成考核 | X11: 附加1考核 | Y11: 综合 | Z11: 台阶奖励 | AA11: 已发合并扣税 | AB11: 满意度考核 | AC11: 交车支出 | AD11: 已发并 | AE11: 考核 | AF11: 考核小计 | AG11: 应发放合计 | AH11: 实际发放 | AI11: 基本工资（含补助） | AJ11: 其它 | AK11: 已发合并扣税项 | AL11: 社保个人 | AM11: 应纳税所得额 | AN11: 个人所得税 | AO11: 已交个税 | AP11: 本次扣税 | AQ11: 基本代扣款 | AR11: 服装代扣 | AS11: 实际发放 | AT11: 年终标准 | AU11: 年终绩效 | AY11: 核对 | AZ11: 税前工资合计
A12: 成都西物 | B12: 西物银河 | E12: 销售经理 | F12: 余才万 | V12: =SUM(J12:U12) -> 0 | AF12: =SUM(W12:AE12) -> 0 | AH12: =AG12 -> 0 | AM12: =AH12+AI12-AK12-AL12 -> 0 | AS12: =AH12-AN12-AQ12-AR12 -> 0
A13: 成都西物 | B13: 西物银河 | E13: 小计 | I13: =SUM(I12:I12) -> 0 | J13: =SUM(J12:J12) -> 0 | K13: =SUM(K12:K12) -> 0 | L13: =SUM(L12:L12) -> 0 | M13: =SUM(M12:M12) -> 0 | N13: =SUM(N12:N12) -> 0 | O13: =SUM(O12:O12) -> 0 | P13: =SUM(P12:P12) -> 0 | ... AU13: =SUM(AU12:AU12) -> 0
A14: 吉利超市 | B14: 西物银河 | D14: 崇州直营店 | E14: 销售顾问 | F14: 杨婷 | V14: =SUM(J14:U14) -> 0 | AF14: =SUM(W14:AE14) -> 0 | AH14: =AG14 -> 0 | AM14: =AH14+AI14-AK14-AL14 -> 0 | AS14: =AH14-AN14-AQ14-AR14 -> 0
A15: 吉利超市 | B15: 西物银河 | E15: 销售顾问 | F15: 何煜佳 | V15: =SUM(J15:U15) -> 0 | AF15: =SUM(W15:AE15) -> 0 | AH15: =AG15 -> 0 | AM15: =AH15+AI15-AK15-AL15 -> 0 | AS15: =AH15-AN15-AQ15-AR15 -> 0
A16: 吉利超市 | B16: 西物银河 | E16: 销售顾问 | F16: 宁袁 | V16: =SUM(J16:U16) -> 0 | AF16: =SUM(W16:AE16) -> 0 | AH16: =AG16 -> 0 | AM16: =AH16+AI16-AK16-AL16 -> 0 | AS16: =AH16-AN16-AQ16-AR16 -> 0
A17: 吉利超市 | B17: 西物银河 | E17: 销售顾问 | F17: 赵思梵 | V17: =SUM(J17:U17) -> 0 | AF17: =SUM(W17:AE17) -> 0 | AH17: =AG17 -> 0 | AM17: =AH17+AI17-AK17-AL17 -> 0 | AS17: =AH17-AN17-AQ17-AR17 -> 0
A18: 吉利超市 | B18: 西物银河 | E18: 销售顾问 | F18: 唐鹏 | V18: =SUM(J18:U18) -> 0 | AF18: =SUM(W18:AE18) -> 0 | AH18: =AG18 -> 0 | AM18: =AH18+AI18-AK18-AL18 -> 0 | AS18: =AH18-AN18-AQ18-AR18 -> 0
A19: 吉利超市 | B19: 西物银河 | E19: 销售顾问 | F19: 陈勇建 | V19: =SUM(J19:U19) -> 0 | AF19: =SUM(W19:AE19) -> 0 | AH19: =AG19 -> 0 | AM19: =AH19+AI19-AK19-AL19 -> 0 | AS19: =AH19-AN19-AQ19-AR19 -> 0
A20: 吉利超市 | B20: 西物银河 | E20: 销售顾问 | F20: 李智洪 | V20: =SUM(J20:U20) -> 0 | AF20: =SUM(W20:AE20) -> 0 | AH20: =AG20 -> 0 | AM20: =AH20+AI20-AK20-AL20 -> 0 | AS20: =AH20-AN20-AQ20-AR20 -> 0
A21: 吉利超市 | B21: 西物银河 | E21: 内勤 | F21: 李良英 | V21: =SUM(J21:U21) -> 0 | AF21: =SUM(W21:AE21) -> 0 | AH21: =AG21 -> 0 | AM21: =AH21+AI21-AK21-AL21 -> 0 | AS21: =AH21-AN21-AQ21-AR21 -> 0
A22: 吉利超市 | B22: 西物银河 | F22: 空白 | V22: =SUM(J22:U22) -> 0 | AF22: =SUM(W22:AE22) -> 0 | AH22: =AG22 -> 0 | AM22: =AH22+AI22-AK22-AL22 -> 0 | AS22: =AH22-AN22-AQ22-AR22 -> 0
A23: 吉利超市 | B23: 西物银河 | F23: 空白 | V23: =SUM(J23:U23) -> 0 | AF23: =SUM(W23:AE23) -> 0 | AH23: =AG23 -> 0 | AM23: =AH23+AI23-AK23-AL23 -> 0 | AS23: =AH23-AN23-AQ23-AR23 -> 0
A24: 吉利超市 | B24: 西物银河 | E24: 销售经理 | F24: 朱剑波 | V24: =SUM(J24:U24) -> 0 | AF24: =SUM(W24:AE24) -> 0 | AH24: =AG24 -> 0 | AM24: =AH24+AI24-AK24-AL24 -> 0 | AS24: =AH24-AN24-AQ24-AR24 -> 0
A25: 吉利超市 | B25: 西物银河 | E25: 小计 | I25: =SUM(I14:I24) -> 0 | J25: =SUM(J14:J24) -> 0 | K25: =SUM(K14:K24) -> 0 | L25: =SUM(L14:L24) -> 0 | M25: =SUM(M14:M24) -> 0 | N25: =SUM(N14:N24) -> 0 | O25: =SUM(O14:O24) -> 0 | P25: =SUM(P14:P24) -> 0 | ... AU25: =SUM(AU14:AU24) -> 0
A26: 吉利超市 | B26: 西物银河 | D26: 大邑直营店 | E26: 销售内勤 | F26: 空白 | AF26: =SUM(W26:AE26) -> 0 | AH26: =AG26 -> 0 | AM26: =AH26+AI26-AK26-AL26 -> 0 | AS26: =AH26-AN26-AQ26-AR26 -> 0
A27: 吉利超市 | B27: 西物银河 | E27: 销售顾问 | F27: 程羊 | AF27: =SUM(W27:AE27) -> 0 | AH27: =AG27 -> 0 | AM27: =AH27+AI27-AK27-AL27 -> 0 | AS27: =AH27-AN27-AQ27-AR27 -> 0
A28: 吉利超市 | B28: 西物银河 | E28: 销售顾问 | F28: 常涛 | AF28: =SUM(W28:AE28) -> 0 | AH28: =AG28 -> 0 | AM28: =AH28+AI28-AK28-AL28 -> 0 | AS28: =AH28-AN28-AQ28-AR28 -> 0
A29: 吉利超市 | B29: 西物银河 | E29: 销售顾问 | F29: 袁萍 | AF29: =SUM(W29:AE29) -> 0 | AH29: =AG29 -> 0 | AM29: =AH29+AI29-AK29-AL29 -> 0 | AS29: =AH29-AN29-AQ29-AR29 -> 0
A30: 吉利超市 | B30: 西物银河 | E30: 销售顾问 | F30: 王海 | AF30: =SUM(W30:AE30) -> 0 | AH30: =AG30 -> 0 | AM30: =AH30+AI30-AK30-AL30 -> 0 | AS30: =AH30-AN30-AQ30-AR30 -> 0
A31: 吉利超市 | B31: 西物银河 | E31: 销售经理 | F31: 孙伟 | AF31: =SUM(W31:AE31) -> 0 | AH31: =AG31 -> 0 | AM31: =AH31+AI31-AK31-AL31 -> 0 | AS31: =AH31-AN31-AQ31-AR31 -> 0
A32: 吉利超市 | B32: 西物银河 | E32: 小计 | I32: =SUM(I26:I31) -> 0 | V32: =SUM(V26:V31) -> 0 | AG32: =SUM(AG26:AG31) -> 0 | AH32: =SUM(AH26:AH31) -> 0 | AI32: =SUM(AI26:AI31) -> 0 | AJ32: =SUM(AJ26:AJ31) -> 0 | AK32: =SUM(AK26:AK31) -> 0 | AL32: =SUM(AL26:AL31) -> 0 | AM32: =SUM(AM26:AM31) -> 0 | AN32: =SUM(AN26:AN31) -> 0 | ... AS32: =SUM(AS26:AS31) -> 0 | AU32: =SUM(AU26:AU31) -> 0
A33: 吉利超市 | B33: 西物银河 | D33: 邛崃直营店 | E33: 内勤 | F33: 王巧巧 | V33: =SUM(J33:U33) -> 0 | AF33: =SUM(W33:AE33) -> 0 | AH33: =AG33 -> 0 | AM33: =AH33+AI33-AK33-AL33 -> 0 | AS33: =AH33-AN33-AQ33-AR33 -> 0
A34: 吉利超市 | B34: 西物银河 | E34: 销售顾问 | F34: 叶荣鹏 | V34: =SUM(J34:U34) -> 0 | AF34: =SUM(W34:AE34) -> 0 | AH34: =AG34 -> 0 | AM34: =AH34+AI34-AK34-AL34 -> 0 | AS34: =AH34-AN34-AQ34-AR34 -> 0
A35: 吉利超市 | B35: 西物银河 | E35: 销售顾问 | F35: 马勇 | V35: =SUM(J35:U35) -> 0 | AF35: =SUM(W35:AE35) -> 0 | AH35: =AG35 -> 0 | AM35: =AH35+AI35-AK35-AL35 -> 0 | AS35: =AH35-AN35-AQ35-AR35 -> 0
A36: 吉利超市 | B36: 西物银河 | E36: 销售顾问 | F36: 高东琴 | V36: =SUM(J36:U36) -> 0 | AF36: =SUM(W36:AE36) -> 0 | AH36: =AG36 -> 0 | AM36: =AH36+AI36-AK36-AL36 -> 0 | AS36: =AH36-AN36-AQ36-AR36 -> 0
A37: 吉利超市 | B37: 西物银河 | F37: 空白 | V37: =SUM(J37:U37) -> 0 | AF37: =SUM(W37:AE37) -> 0 | AH37: =AG37 -> 0 | AM37: =AH37+AI37-AK37-AL37 -> 0 | AS37: =AH37-AN37-AQ37-AR37 -> 0
A38: 吉利超市 | B38: 西物银河 | E38: 销售经理 | F38: 吴思超 | V38: =SUM(J38:U38) -> 0 | AF38: =SUM(W38:AE38) -> 0 | AH38: =AG38 -> 0 | AM38: =AH38+AI38-AK38-AL38 -> 0 | AS38: =AH38-AN38-AQ38-AR38 -> 0
A39: 吉利超市 | B39: 西物银河 | E39: 小计 | F39: =SUM(F33:F38) -> 0 | G39: =SUM(G33:G38) -> 0 | H39: =SUM(H33:H38) -> 0 | I39: =SUM(I33:I38) -> 0 | J39: =SUM(J33:J38) -> 0 | K39: =SUM(K33:K38) -> 0 | L39: =SUM(L33:L38) -> 0 | M39: =SUM(M33:M38) -> 0 | ... W39: =SUM(W33:W38) -> 0 | AF39: =SUM(AF33:AF38) -> 0 | AG39: =SUM(AG33:AG38) -> 0 | AH39: =SUM(AH33:AH38) -> 0 | AI39: =SUM(AI33:AI38) -> 0 | AJ39: =SUM(AJ33:AJ38) -> 0 | AK39: =SUM(AK33:AK38) -> 0 | AL39: =SUM(AL33:AL38) -> 0 | AM39: =SUM(AM33:AM38) -> 0 | ... AS39: =SUM(AS33:AS38) -> 0 | AU39: =SUM(AU33:AU38) -> 0
A40: 吉利超市 | B40: 西物银河 | D40: 彭州直营店 | E40: 出纳+内勤 | F40: 牟春柳 | V40: =SUM(J40:U40) -> 0 | AF40: =SUM(W40:AE40) -> 0 | AH40: =AG40 -> 0 | AM40: =AH40+AI40-AK40-AL40 -> 0 | AS40: =AH40-AN40-AQ40-AR40 -> 0
A41: 吉利超市 | B41: 西物银河 | E41: 销售顾问 | F41: 钟家林 | V41: =SUM(J41:U41) -> 0 | AF41: =SUM(W41:AE41) -> 0 | AH41: =AG41 -> 0 | AM41: =AH41+AI41-AK41-AL41 -> 0 | AS41: =AH41-AN41-AQ41-AR41 -> 0
A42: 吉利超市 | B42: 西物银河 | E42: 销售顾问 | F42: 兰代全 | V42: =SUM(J42:U42) -> 0 | AF42: =SUM(W42:AE42) -> 0 | AH42: =AG42 -> 0 | AM42: =AH42+AI42-AK42-AL42 -> 0 | AS42: =AH42-AN42-AQ42-AR42 -> 0
A43: 吉利超市 | B43: 西物银河 | E43: 销售顾问 | F43: 罗小雄 | V43: =SUM(J43:U43) -> 0 | AF43: =SUM(W43:AE43) -> 0 | AH43: =AG43 -> 0 | AM43: =AH43+AI43-AK43-AL43 -> 0 | AS43: =AH43-AN43-AQ43-AR43 -> 0
A44: 吉利超市 | B44: 西物银河 | E44: 销售顾问 | F44: 陈莉 | V44: =SUM(J44:U44) -> 0 | AF44: =SUM(W44:AE44) -> 0 | AH44: =AG44 -> 0 | AM44: =AH44+AI44-AK44-AL44 -> 0 | AS44: =AH44-AN44-AQ44-AR44 -> 0
A45: 吉利超市 | B45: 西物银河 | E45: 销售顾问 | F45: 任和奎 | V45: =SUM(J45:U45) -> 0 | AF45: =SUM(W45:AE45) -> 0 | AH45: =AG45 -> 0 | AM45: =AH45+AI45-AK45-AL45 -> 0 | AS45: =AH45-AN45-AQ45-AR45 -> 0
A46: 吉利超市 | B46: 西物银河 | F46: 空白 | V46: =SUM(J46:U46) -> 0 | AF46: =SUM(W46:AE46) -> 0 | AH46: =AG46 -> 0 | AM46: =AH46+AI46-AK46-AL46 -> 0 | AS46: =AH46-AN46-AQ46-AR46 -> 0
E47: 销售助理 | F47: 刘娅 | V47: =SUM(J47:U47) -> 0 | AH47: =AG47 -> 0 | AM47: =AH47+AI47-AK47-AL47 -> 0 | AS47: =AH47-AN47-AQ47-AR47 -> 0
A48: 吉利超市 | B48: 西物银河 | E48: 销售经理 | F48: 黎明朗 | V48: =SUM(J48:U48) -> 0 | AF48: =SUM(W48:AE48) -> 0 | AH48: =AG48 -> 0 | AM48: =AH48+AI48-AK48-AL48 -> 0 | AS48: =AH48-AN48-AQ48-AR48 -> 0
A49: 吉利超市 | B49: 西物银河 | E49: 小计 | G49: =SUM(G40:G48) -> 0 | H49: =SUM(H40:H48) -> 0 | I49: =SUM(I40:I48) -> 0 | J49: =SUM(J40:J48) -> 0 | K49: =SUM(K40:K48) -> 0 | L49: =SUM(L40:L48) -> 0 | M49: =SUM(M40:M48) -> 0 | N49: =SUM(N40:N48) -> 0 | ... T49: =SUM(T40:T48) -> 0 | V49: =SUM(V40:V48) -> 0 | W49: =SUM(W40:W48) -> 0 | AF49: =SUM(AF40:AF48) -> 0 | AG49: =SUM(AG40:AG48) -> 0 | AH49: =SUM(AH40:AH48) -> 0 | AI49: =SUM(AI40:AI48) -> 0 | AJ49: =SUM(AJ40:AJ48) -> 0 | AK49: =SUM(AK40:AK48) -> 0 | AL49: =SUM(AL40:AL48) -> 0 | AM49: =SUM(AM40:AM48) -> 0 | ... AS49: =SUM(AS40:AS48) -> 0 | AU49: =SUM(AU40:AU48) -> 0
A50: 吉利超市 | B50: 西物银河 | D50: 华阳直营店 | E50: 出纳+内勤 | F50: 毛婷婷 | V50: =SUM(J50:U50) -> 0 | AF50: =SUM(W50:AE50) -> 0 | AH50: =AG50 -> 0 | AM50: =AH50+AI50-AK50-AL50 -> 0 | AS50: =AH50-AN50-AQ50-AR50 -> 0
A51: 吉利超市 | B51: 西物银河 | E51: 销售顾问 | F51: 袁湘 | V51: =SUM(J51:U51) -> 0 | AF51: =SUM(W51:AE51) -> 0 | AH51: =AG51 -> 0 | AM51: =AH51+AI51-AK51-AL51 -> 0 | AS51: =AH51-AN51-AQ51-AR51 -> 0
A52: 吉利超市 | B52: 西物银河 | E52: 销售顾问 | F52: 张坤 | V52: =SUM(J52:U52) -> 0 | AF52: =SUM(W52:AE52) -> 0 | AH52: =AG52 -> 0 | AM52: =AH52+AI52-AK52-AL52 -> 0 | AS52: =AH52-AN52-AQ52-AR52 -> 0
A53: 吉利超市 | B53: 西物银河 | E53: 销售顾问 | F53: 向凤 | V53: =SUM(J53:U53) -> 0 | AF53: =SUM(W53:AE53) -> 0 | AH53: =AG53 -> 0 | AM53: =AH53+AI53-AK53-AL53 -> 0 | AS53: =AH53-AN53-AQ53-AR53 -> 0
A54: 吉利超市 | B54: 西物银河 | E54: 销售顾问 | F54: 吴小琴 | V54: =SUM(J54:U54) -> 0 | AF54: =SUM(W54:AE54) -> 0 | AH54: =AG54 -> 0 | AM54: =AH54+AI54-AK54-AL54 -> 0 | AS54: =AH54-AN54-AQ54-AR54 -> 0
A55: 吉利超市 | B55: 西物银河 | E55: 销售顾问 | F55: 丁小玲 | V55: =SUM(J55:U55) -> 0 | AF55: =SUM(W55:AE55) -> 0 | AH55: =AG55 -> 0 | AM55: =AH55+AI55-AK55-AL55 -> 0 | AS55: =AH55-AN55-AQ55-AR55 -> 0
A56: 吉利超市 | B56: 西物银河 | E56: 销售顾问 | F56: 刘华 | V56: =SUM(J56:U56) -> 0 | AF56: =SUM(W56:AE56) -> 0 | AH56: =AG56 -> 0 | AM56: =AH56+AI56-AK56-AL56 -> 0 | AS56: =AH56-AN56-AQ56-AR56 -> 0
A57: 吉利超市 | B57: 西物银河 | E57: 销售经理 | F57: 钟涛 | V57: =SUM(J57:U57) -> 0 | AF57: =SUM(W57:AE57) -> 0 | AH57: =AG57 -> 0 | AM57: =AH57+AI57-AK57-AL57 -> 0 | AS57: =AH57-AN57-AQ57-AR57 -> 0
A58: 吉利超市 | B58: 西物银河 | E58: 小计 | I58: =SUM(I50:I57) -> 0 | J58: =SUM(J50:J57) -> 0 | K58: =SUM(K50:K57) -> 0 | L58: =SUM(L50:L57) -> 0 | O58: =SUM(O50:O57) -> 0 | V58: =SUM(V51:V57) -> 0 | W58: =SUM(W50:W57) -> 0 | X58: =SUM(X50:X57) -> 0 | Y58: =SUM(Y50:Y57) -> 0 | Z58: =SUM(Z50:Z57) -> 0 | AA58: =SUM(AA50:AA57) -> 0 | AB58: =SUM(AB50:AB57) -> 0 | AC58: =SUM(AC50:AC57) -> 0 | AD58: =SUM(AD50:AD57) -> 0 | ... AS58: =SUM(AS50:AS57) -> 0 | AU58: =SUM(AU50:AU57) -> 0
