Workbook
Name 备件类: #REF!
Name 服务质量: [1]基础参数勿删!$E$6:$E$14
Name 颜色: [2]菜单!$C$2:$C$15

Sheet 05月提成-武侯售后
A1: 2026年05月成都吉利汽车超市工资明细表（售后）
A2: 编制：人事部
A3: 序号 | B3: 部门 | C3: 姓 名 | D3: 其他补贴 | E3: 单位社保 | F3: 个人社保 | G3: 个人公积金 | H3: 其它 | I3: 基本工资 | J3: 其中： 加班工资 | K3: 当月应计提绩效 | L3: 综合考核/其他 | M3: 应付提 成工资 | N3: 代扣社保 | O3: 实付提成 | P3: 其它 | Q3: 已发并税 | R3: 计税工资 | S3: 代扣个税 | V3: 其他(代扣项) | W3: 实发提成 | X3: 备注 | Y3: 留存 合计 | Z3: 留存1 | AA3: 留存2 | AF3: 其他部门 | AG3: 车间 | AH3: 业务
S4: 应扣税 | T4: 已扣税 | U4: 实际扣税 | Y4: 留存 | Z4: 留存 | AA4: 留存 | AB4: 姓名 | AC4: 累计应补(退)税额 | AF4: =SUMIF('05月其他部门提成'!C:C,'05月提成-武侯售后'!C4,'05月其他部门提成'!Q:Q) -> 0 | AH4: =SUMIF('05月业务提成'!B:B,'05月提成-武侯售后'!C4,'05月业务提成'!BO:BO) -> 0
A5: 1 | B5: 管理部 | C5: 曹磊 | D5: =INDEX('05基本'!I:I,MATCH(C5,'05基本'!C:C,0))+INDEX('05基本'!J:J,MATCH(C5,'05基本'!C:C,0)) -> 0 | E5: =INDEX('05基本'!AA:AA,MATCH(C5,'05基本'!C:C,0)) -> 1497.5 | F5: =INDEX('05基本'!AB:AB,MATCH(C5,'05基本'!C:C,0)) -> 572 | G5: =INDEX('05基本'!AC:AC,MATCH(C5,'05基本'!C:C,0)) -> 117 | H5: =INDEX('05基本'!K:K,MATCH(C5,'05基本'!C:C,0))+INDEX('05基本'!L:L,MATCH(C5,'05基本'!C:C,0)) -> 1000 | I5: =INDEX('05基本'!P:P,MATCH(C5,'05基本'!C:C,0)) -> 8000 | J5: =INDEX('05基本'!M:M,MATCH(C5,'05基本'!C:C,0)) -> 1000 | K5: =INDEX('05月其他部门提成'!Q:Q,MATCH(C5,'05月其他部门提成'!C:C,0)) -> 8666.6667 | L5: =SUMIF(综合考核!A:A,'05月提成-武侯售后'!C5,综合考核!M:M) -> 0 | M5: =SUM(K5:L5) -> 8666.6667 | N5: =SUMIF(服装扣款!C:C,C5,服装扣款!N:N) -> 0 | O5: =M5-N5 -> 8666.6667 | P5: =SUMIF(超市公积金!C:C,'05月提成-武侯售后'!C5,超市公积金!I:I) -> 0 | Q5: =SUMIF(综合考核!A:A,'05月提成-武侯售后'!C5,综合考核!N:N) -> 0 | R5: =M5+I5+Q5 -> 16666.667 | S5: =INDEX(AC:AC,MATCH(C5,AB:AB,0)) -> 797.76 | U5: =S5-T5 -> 797.76 | V5: =INDEX('05基本'!AF:AF,MATCH(C5,'05基本'!C:C,0)) -> 0 | W5: =O5-P5-U5 -> 7868.9067 | Z5: 3566.67 | AB5: 曹磊 | AC5: 797.76 | AD5: =COUNTIF(C:C,C5) -> 1 | AE5: =INDEX('05基本'!P:P,MATCH(C5,'05基本'!C:C,0))-I5 -> 0 | AF5: =SUMIF('05月其他部门提成'!C:C,'05月提成-武侯售后'!C5,'05月其他部门提成'!Q:Q) -> 8666.6667 | AG5: =SUMIF('05月车间提成'!C:C,'05月提成-武侯售后'!C5,'05月车间提成'!W:W) -> 0 | AH5: =SUMIF('05月业务提成'!B:B,'05月提成-武侯售后'!C5,'05月业务提成'!BO:BO) -> 0 | AI5: =AF5+AG5+AH5 -> 8666.6667 | AJ5: =AI5-K5 -> 0
A6: 2 | C6: 曾吉斌 | D6: =INDEX('05基本'!I:I,MATCH(C6,'05基本'!C:C,0))+INDEX('05基本'!J:J,MATCH(C6,'05基本'!C:C,0)) -> 0 | E6: =INDEX('05基本'!AA:AA,MATCH(C6,'05基本'!C:C,0)) -> 1748.5 | F6: =INDEX('05基本'!AB:AB,MATCH(C6,'05基本'!C:C,0)) -> 676 | G6: =INDEX('05基本'!AC:AC,MATCH(C6,'05基本'!C:C,0)) -> 117 | H6: =INDEX('05基本'!K:K,MATCH(C6,'05基本'!C:C,0))+INDEX('05基本'!L:L,MATCH(C6,'05基本'!C:C,0)) -> 1000 | I6: =INDEX('05基本'!P:P,MATCH(C6,'05基本'!C:C,0)) -> 10000 | J6: =INDEX('05基本'!M:M,MATCH(C6,'05基本'!C:C,0)) -> 1000 | K6: =INDEX('05月其他部门提成'!Q:Q,MATCH(C6,'05月其他部门提成'!C:C,0)) -> 10833.33 | L6: =SUMIF(综合考核!A:A,'05月提成-武侯售后'!C6,综合考核!M:M) -> 0 | M6: =SUM(K6:L6) -> 10833.33 | N6: =SUMIF(服装扣款!C:C,C6,服装扣款!N:N) -> 0 | O6: =M6-N6 -> 10833.33 | P6: =SUMIF(超市公积金!C:C,'05月提成-武侯售后'!C6,超市公积金!I:I) -> 0 | Q6: =SUMIF(综合考核!A:A,'05月提成-武侯售后'!C6,综合考核!N:N) -> 0 | R6: =M6+I6+Q6 -> 20833.33 | S6: =INDEX(AC:AC,MATCH(C6,AB:AB,0)) -> 1504.03 | U6: =S6-T6 -> 1504.03 | V6: =INDEX('05基本'!AF:AF,MATCH(C6,'05基本'!C:C,0)) -> 0 | W6: =O6-P6-U6 -> 9329.3 | AB6: 曾吉斌 | AC6: 1504.03 | AD6: =COUNTIF(C:C,C6) -> 1 | AE6: =INDEX('05基本'!P:P,MATCH(C6,'05基本'!C:C,0))-I6 -> 0 | AF6: =SUMIF('05月其他部门提成'!C:C,'05月提成-武侯售后'!C6,'05月其他部门提成'!Q:Q) -> 10833.33 | AG6: =SUMIF('05月车间提成'!C:C,'05月提成-武侯售后'!C6,'05月车间提成'!W:W) -> 0 | AH6: =SUMIF('05月业务提成'!B:B,'05月提成-武侯售后'!C6,'05月业务提成'!BO:BO) -> 0 | AI6: =AF6+AG6+AH6 -> 10833.33 | AJ6: =AI6-K6 -> 0
A7: 3 | C7: 谢尧江 | D7: =INDEX('05基本'!I:I,MATCH(C7,'05基本'!C:C,0))+INDEX('05基本'!J:J,MATCH(C7,'05基本'!C:C,0)) -> 0 | E7: =INDEX('05基本'!AA:AA,MATCH(C7,'05基本'!C:C,0)) -> 1372 | F7: =INDEX('05基本'!AB:AB,MATCH(C7,'05基本'!C:C,0)) -> 520 | G7: =INDEX('05基本'!AC:AC,MATCH(C7,'05基本'!C:C,0)) -> 117 | H7: =INDEX('05基本'!K:K,MATCH(C7,'05基本'!C:C,0))+INDEX('05基本'!L:L,MATCH(C7,'05基本'!C:C,0)) -> 100 | I7: =INDEX('05基本'!P:P,MATCH(C7,'05基本'!C:C,0)) -> 1700 | J7: =INDEX('05基本'!M:M,MATCH(C7,'05基本'!C:C,0)) -> 0 | K7: =INDEX('05月其他部门提成'!Q:Q,MATCH(C7,'05月其他部门提成'!C:C,0)) -> 11763.001 | L7: =SUMIF(综合考核!A:A,'05月提成-武侯售后'!C7,综合考核!M:M) -> 0 | M7: =SUM(K7:L7) -> 11763.001 | N7: =SUMIF(服装扣款!C:C,C7,服装扣款!N:N) -> 0 | O7: =M7-N7 -> 11763.001 | P7: =SUMIF(超市公积金!C:C,'05月提成-武侯售后'!C7,超市公积金!I:I) -> 0 | Q7: =SUMIF(综合考核!A:A,'05月提成-武侯售后'!C7,综合考核!N:N) -> 0 | R7: =M7+I7+Q7 -> 13463.001 | S7: =INDEX(AC:AC,MATCH(C7,AB:AB,0)) -> 782.6 | U7: =S7-T7 -> 782.6 | V7: =INDEX('05基本'!AF:AF,MATCH(C7,'05基本'!C:C,0)) -> 0 | W7: =O7-P7-U7 -> 10980.401 | Z7: ='05月其他部门提成'!R9 -> 116.09792 | AB7: 谢尧江 | AC7: 782.6 | AD7: =COUNTIF(C:C,C7) -> 1 | AE7: =INDEX('05基本'!P:P,MATCH(C7,'05基本'!C:C,0))-I7 -> 0 | AF7: =SUMIF('05月其他部门提成'!C:C,'05月提成-武侯售后'!C7,'05月其他部门提成'!Q:Q) -> 11763.001 | AG7: =SUMIF('05月车间提成'!C:C,'05月提成-武侯售后'!C7,'05月车间提成'!W:W) -> 0 | AH7: =SUMIF('05月业务提成'!B:B,'05月提成-武侯售后'!C7,'05月业务提成'!BO:BO) -> 0 | AI7: =AF7+AG7+AH7 -> 11763.001 | AJ7: =AI7-K7 -> 0
C8: 小计 | D8: =SUM(D5:D7) -> 0 | E8: =SUM(E5:E7) -> 4618 | F8: =SUM(F5:F7) -> 1768 | G8: =SUM(G5:G7) -> 351 | H8: =SUM(H5:H7) -> 2100 | I8: =SUM(I5:I7) -> 19700 | J8: =SUM(J5:J7) -> 2000 | K8: =SUM(K5:K7) -> 31262.998 | ... AA8: =SUM(AA5:AA7) -> 0 | AB8: 张敏 | AC8: 0 | AD8: =COUNTIF(C:C,C8) -> 11 | AE8: =INDEX('05基本'!P:P,MATCH(C8,'05基本'!C:C,0))-I8 -> #N/A
A9: =A7+1 -> 4 | B9: 财务部 | C9: 张敏 | D9: =INDEX('05基本'!I:I,MATCH(C9,'05基本'!C:C,0))+INDEX('05基本'!J:J,MATCH(C9,'05基本'!C:C,0)) -> 200 | E9: =INDEX('05基本'!AA:AA,MATCH(C9,'05基本'!C:C,0)) -> 1268.59 | F9: =INDEX('05基本'!AB:AB,MATCH(C9,'05基本'!C:C,0)) -> 477.15 | G9: =INDEX('05基本'!AC:AC,MATCH(C9,'05基本'!C:C,0)) -> 117 | H9: =INDEX('05基本'!K:K,MATCH(C9,'05基本'!C:C,0))+INDEX('05基本'!L:L,MATCH(C9,'05基本'!C:C,0)) -> 0 | I9: =INDEX('05基本'!P:P,MATCH(C9,'05基本'!C:C,0)) -> 2200 | J9: =INDEX('05基本'!M:M,MATCH(C9,'05基本'!C:C,0)) -> 0 | K9: =INDEX('05月其他部门提成'!Q:Q,MATCH(C9,'05月其他部门提成'!C:C,0)) -> 6328.2846 | L9: =SUMIF(综合考核!A:A,'05月提成-武侯售后'!C9,综合考核!M:M) -> 0 | M9: =SUM(K9:L9) -> 6328.2846 | N9: =SUMIF(服装扣款!C:C,C9,服装扣款!N:N) -> 0 | O9: =M9-N9 -> 6328.2846 | P9: =SUMIF(超市公积金!C:C,'05月提成-武侯售后'!C9,超市公积金!I:I) -> 0 | Q9: =SUMIF(综合考核!A:A,'05月提成-武侯售后'!C9,综合考核!N:N) -> 0 | R9: =M9+I9+Q9 -> 8528.2846 | S9: =INDEX(AC:AC,MATCH(C9,AB:AB,0)) -> 0 | U9: =S9-T9 -> 0 | V9: =INDEX('05基本'!AF:AF,MATCH(C9,'05基本'!C:C,0)) -> 0 | W9: =O9-P9-U9 -> 6328.2846 | Y9: =SUM(Z9:AA9) -> 416.66667 | Z9: =INDEX('05月其他部门提成'!S:S,MATCH(C9,'05月其他部门提成'!C:C,0)) -> 416.66667 | AB9: 邱小艳 | AC9: 26.11 | AD9: =COUNTIF(C:C,C9) -> 1 | AE9: =INDEX('05基本'!P:P,MATCH(C9,'05基本'!C:C,0))-I9 -> 0 | AF9: =SUMIF('05月其他部门提成'!C:C,'05月提成-武侯售后'!C9,'05月其他部门提成'!Q:Q) -> 6328.2846 | AG9: =SUMIF('05月车间提成'!C:C,'05月提成-武侯售后'!C9,'05月车间提成'!W:W) -> 0 | AH9: =SUMIF('05月业务提成'!B:B,'05月提成-武侯售后'!C9,'05月业务提成'!BO:BO) -> 0 | AI9: =AF9+AG9+AH9 -> 6328.2846 | AJ9: =AI9-K9 -> 0
A10: =A9+1 -> 5 | C10: 邱小艳 | D10: =INDEX('05基本'!I:I,MATCH(C10,'05基本'!C:C,0))+INDEX('05基本'!J:J,MATCH(C10,'05基本'!C:C,0)) -> 0 | E10: =INDEX('05基本'!AA:AA,MATCH(C10,'05基本'!C:C,0)) -> 1268.59 | F10: =INDEX('05基本'!AB:AB,MATCH(C10,'05基本'!C:C,0)) -> 477.15 | G10: =INDEX('05基本'!AC:AC,MATCH(C10,'05基本'!C:C,0)) -> 117 | H10: =INDEX('05基本'!K:K,MATCH(C10,'05基本'!C:C,0))+INDEX('05基本'!L:L,MATCH(C10,'05基本'!C:C,0)) -> 0 | I10: =INDEX('05基本'!P:P,MATCH(C10,'05基本'!C:C,0)) -> 2000 | J10: =INDEX('05基本'!M:M,MATCH(C10,'05基本'!C:C,0)) -> 0 | K10: =INDEX('05月其他部门提成'!Q:Q,MATCH(C10,'05月其他部门提成'!C:C,0)) -> 4464.7607 | L10: =SUMIF(综合考核!A:A,'05月提成-武侯售后'!C10,综合考核!M:M) -> 0 | M10: =SUM(K10:L10) -> 4464.7607 | N10: =SUMIF(服装扣款!C:C,C10,服装扣款!N:N) -> 0 | O10: =M10-N10 -> 4464.7607 | P10: =SUMIF(超市公积金!C:C,'05月提成-武侯售后'!C10,超市公积金!I:I) -> 0 | Q10: =SUMIF(综合考核!A:A,'05月提成-武侯售后'!C10,综合考核!N:N) -> 0 | R10: =M10+I10+Q10 -> 6464.7607 | S10: =INDEX(AC:AC,MATCH(C10,AB:AB,0)) -> 26.11 | U10: =S10-T10 -> 26.11 | V10: =INDEX('05基本'!AF:AF,MATCH(C10,'05基本'!C:C,0)) -> 0 | W10: =O10-P10-U10 -> 4438.6507 | Y10: =SUM(Z10:AA10) -> 216.66667 | Z10: =INDEX('05月其他部门提成'!S:S,MATCH(C10,'05月其他部门提成'!C:C,0)) -> 216.66667 | AB10: 潘倩 | AC10: 18.71 | AD10: =COUNTIF(C:C,C10) -> 1 | AE10: =INDEX('05基本'!P:P,MATCH(C10,'05基本'!C:C,0))-I10 -> 0 | AF10: =SUMIF('05月其他部门提成'!C:C,'05月提成-武侯售后'!C10,'05月其他部门提成'!Q:Q) -> 4464.7607 | AG10: =SUMIF('05月车间提成'!C:C,'05月提成-武侯售后'!C10,'05月车间提成'!W:W) -> 0 | AH10: =SUMIF('05月业务提成'!B:B,'05月提成-武侯售后'!C10,'05月业务提成'!BO:BO) -> 0 | AI10: =AF10+AG10+AH10 -> 4464.7607 | AJ10: =AI10-K10 -> 0
A11: =A10+1 -> 6 | C11: 潘倩 | D11: =INDEX('05基本'!I:I,MATCH(C11,'05基本'!C:C,0))+INDEX('05基本'!J:J,MATCH(C11,'05基本'!C:C,0)) -> 0 | E11: =INDEX('05基本'!AA:AA,MATCH(C11,'05基本'!C:C,0)) -> 1268.59 | F11: =INDEX('05基本'!AB:AB,MATCH(C11,'05基本'!C:C,0)) -> 477.15 | G11: =INDEX('05基本'!AC:AC,MATCH(C11,'05基本'!C:C,0)) -> 117 | H11: =INDEX('05基本'!K:K,MATCH(C11,'05基本'!C:C,0))+INDEX('05基本'!L:L,MATCH(C11,'05基本'!C:C,0)) -> 0 | I11: =INDEX('05基本'!P:P,MATCH(C11,'05基本'!C:C,0)) -> 2000 | J11: =INDEX('05基本'!M:M,MATCH(C11,'05基本'!C:C,0)) -> 0 | K11: =INDEX('05月其他部门提成'!Q:Q,MATCH(C11,'05月其他部门提成'!C:C,0)) -> 4217.8873 | L11: =SUMIF(综合考核!A:A,'05月提成-武侯售后'!C11,综合考核!M:M) -> 0 | M11: =SUM(K11:L11) -> 4217.8873 | N11: =SUMIF(服装扣款!C:C,C11,服装扣款!N:N) -> 0 | O11: =M11-N11 -> 4217.8873 | P11: =SUMIF(超市公积金!C:C,'05月提成-武侯售后'!C11,超市公积金!I:I) -> 0 | Q11: =SUMIF(综合考核!A:A,'05月提成-武侯售后'!C11,综合考核!N:N) -> 0 | R11: =M11+I11+Q11 -> 6217.8873 | S11: =INDEX(AC:AC,MATCH(C11,AB:AB,0)) -> 18.71 | U11: =S11-T11 -> 18.71 | V11: =INDEX('05基本'!AF:AF,MATCH(C11,'05基本'!C:C,0)) -> 0 | W11: =O11-P11-U11 -> 4199.1773 | Y11: =SUM(Z11:AA11) -> 216.66667 | Z11: =INDEX('05月其他部门提成'!S:S,MATCH(C11,'05月其他部门提成'!C:C,0)) -> 216.66667 | AB11: 唐玉屏 | AC11: 28.46 | AD11: =COUNTIF(C:C,C11) -> 1 | AE11: =INDEX('05基本'!P:P,MATCH(C11,'05基本'!C:C,0))-I11 -> 0 | AF11: =SUMIF('05月其他部门提成'!C:C,'05月提成-武侯售后'!C11,'05月其他部门提成'!Q:Q) -> 4217.8873 | AG11: =SUMIF('05月车间提成'!C:C,'05月提成-武侯售后'!C11,'05月车间提成'!W:W) -> 0 | AH11: =SUMIF('05月业务提成'!B:B,'05月提成-武侯售后'!C11,'05月业务提成'!BO:BO) -> 0 | AI11: =AF11+AG11+AH11 -> 4217.8873 | AJ11: =AI11-K11 -> 0
A12: =A11+1 -> 7 | B12: 业务部 | C12: 唐玉屏 | D12: =INDEX('05基本'!I:I,MATCH(C12,'05基本'!C:C,0))+INDEX('05基本'!J:J,MATCH(C12,'05基本'!C:C,0)) -> 0 | E12: =INDEX('05基本'!AA:AA,MATCH(C12,'05基本'!C:C,0)) -> 1268.59 | F12: =INDEX('05基本'!AB:AB,MATCH(C12,'05基本'!C:C,0)) -> 477.15 | G12: =INDEX('05基本'!AC:AC,MATCH(C12,'05基本'!C:C,0)) -> 117 | H12: =INDEX('05基本'!K:K,MATCH(C12,'05基本'!C:C,0))+INDEX('05基本'!L:L,MATCH(C12,'05基本'!C:C,0)) -> 0 | I12: =INDEX('05基本'!P:P,MATCH(C12,'05基本'!C:C,0)) -> 1200 | J12: =INDEX('05基本'!M:M,MATCH(C12,'05基本'!C:C,0)) -> 0 | K12: =INDEX('05月其他部门提成'!Q:Q,MATCH(C12,'05月其他部门提成'!C:C,0)) -> 5342.8 | L12: =SUMIF(综合考核!A:A,'05月提成-武侯售后'!C12,综合考核!M:M) -> 0 | M12: =SUM(K12:L12) -> 5342.8 | N12: =SUMIF(服装扣款!C:C,C12,服装扣款!N:N) -> 0 | O12: =M12-N12 -> 5342.8 | P12: =SUMIF(超市公积金!C:C,'05月提成-武侯售后'!C12,超市公积金!I:I) -> 0 | Q12: =SUMIF(综合考核!A:A,'05月提成-武侯售后'!C12,综合考核!N:N) -> 0 | R12: =M12+I12+Q12 -> 6542.8 | S12: =INDEX(AC:AC,MATCH(C12,AB:AB,0)) -> 28.46 | U12: =S12-T12 -> 28.46 | V12: =INDEX('05基本'!AF:AF,MATCH(C12,'05基本'!C:C,0)) -> 0 | W12: =O12-P12-U12 -> 5314.34 | Y12: =SUM(Z12:AA12) -> 281.2 | Z12: =INDEX('05月其他部门提成'!S:S,MATCH(C12,'05月其他部门提成'!C:C,0)) -> 281.2 | AB12: 陈川蓉 | AC12: 62.65 | AD12: =COUNTIF(C:C,C12) -> 1 | AE12: =INDEX('05基本'!P:P,MATCH(C12,'05基本'!C:C,0))-I12 -> 0 | AF12: =SUMIF('05月其他部门提成'!C:C,'05月提成-武侯售后'!C12,'05月其他部门提成'!Q:Q) -> 5342.8 | AG12: =SUMIF('05月车间提成'!C:C,'05月提成-武侯售后'!C12,'05月车间提成'!W:W) -> 0 | AH12: =SUMIF('05月业务提成'!B:B,'05月提成-武侯售后'!C12,'05月业务提成'!BO:BO) -> 0 | AI12: =AF12+AG12+AH12 -> 5342.8 | AJ12: =AI12-K12 -> 0
A13: =A12+1 -> 8 | C13: 陈川蓉 | D13: =INDEX('05基本'!I:I,MATCH(C13,'05基本'!C:C,0))+INDEX('05基本'!J:J,MATCH(C13,'05基本'!C:C,0)) -> 0 | E13: =INDEX('05基本'!AA:AA,MATCH(C13,'05基本'!C:C,0)) -> 1268.59 | F13: =INDEX('05基本'!AB:AB,MATCH(C13,'05基本'!C:C,0)) -> 477.15 | G13: =INDEX('05基本'!AC:AC,MATCH(C13,'05基本'!C:C,0)) -> 117 | H13: =INDEX('05基本'!K:K,MATCH(C13,'05基本'!C:C,0))+INDEX('05基本'!L:L,MATCH(C13,'05基本'!C:C,0)) -> 0 | I13: =INDEX('05基本'!P:P,MATCH(C13,'05基本'!C:C,0)) -> 1200 | J13: =INDEX('05基本'!M:M,MATCH(C13,'05基本'!C:C,0)) -> 0 | K13: =INDEX('05月其他部门提成'!Q:Q,MATCH(C13,'05月其他部门提成'!C:C,0)) -> 6482.6133 | L13: =SUMIF(综合考核!A:A,'05月提成-武侯售后'!C13,综合考核!M:M) -> 0 | M13: =SUM(K13:L13) -> 6482.6133 | N13: =SUMIF(服装扣款!C:C,C13,服装扣款!N:N) -> 0 | O13: =M13-N13 -> 6482.6133 | P13: =SUMIF(超市公积金!C:C,'05月提成-武侯售后'!C13,超市公积金!I:I) -> 0 | Q13: =SUMIF(综合考核!A:A,'05月提成-武侯售后'!C13,综合考核!N:N) -> 0 | R13: =M13+I13+Q13 -> 7682.6133 | S13: =INDEX(AC:AC,MATCH(C13,AB:AB,0)) -> 62.65 | U13: =S13-T13 -> 62.65 | V13: =INDEX('05基本'!AF:AF,MATCH(C13,'05基本'!C:C,0)) -> 0 | W13: =O13-P13-U13 -> 6419.9633 | Y13: =SUM(Z13:AA13) -> 86.414327 | Z13: =INDEX('05月其他部门提成'!S:S,MATCH(C13,'05月其他部门提成'!C:C,0)) -> 86.414327 | AB13: 白影 | AC13: 0 | AD13: =COUNTIF(C:C,C13) -> 1 | AE13: =INDEX('05基本'!P:P,MATCH(C13,'05基本'!C:C,0))-I13 -> 0 | AF13: =SUMIF('05月其他部门提成'!C:C,'05月提成-武侯售后'!C13,'05月其他部门提成'!Q:Q) -> 6482.6133 | AG13: =SUMIF('05月车间提成'!C:C,'05月提成-武侯售后'!C13,'05月车间提成'!W:W) -> 0 | AH13: =SUMIF('05月业务提成'!B:B,'05月提成-武侯售后'!C13,'05月业务提成'!BO:BO) -> 0 | AI13: =AF13+AG13+AH13 -> 6482.6133 | AJ13: =AI13-K13 -> 0
C14: 小计 | D14: =SUM(D9:D13) -> 200 | E14: =SUM(E9:E13) -> 6342.95 | F14: =SUM(F9:F13) -> 2385.75 | G14: =SUM(G9:G13) -> 585 | H14: =SUM(H9:H13) -> 0 | I14: =SUM(I9:I13) -> 8600 | J14: =SUM(J9:J13) -> 0 | K14: =SUM(K9:K13) -> 26836.346 | ... AA14: =SUM(AA9:AA13) -> 0 | AB14: 曹青 | AC14: 0 | AD14: =COUNTIF(C:C,C14) -> 11 | AE14: =INDEX('05基本'!P:P,MATCH(C14,'05基本'!C:C,0))-I14 -> #N/A
A15: =A13+1 -> 9 | B15: 服务部 | C15: 白影 | D15: =INDEX('05基本'!I:I,MATCH(C15,'05基本'!C:C,0))+INDEX('05基本'!J:J,MATCH(C15,'05基本'!C:C,0)) -> 0 | E15: =INDEX('05基本'!AA:AA,MATCH(C15,'05基本'!C:C,0)) -> 1268.59 | F15: =INDEX('05基本'!AB:AB,MATCH(C15,'05基本'!C:C,0)) -> 477.15 | G15: =INDEX('05基本'!AC:AC,MATCH(C15,'05基本'!C:C,0)) -> 117 | H15: =INDEX('05基本'!K:K,MATCH(C15,'05基本'!C:C,0))+INDEX('05基本'!L:L,MATCH(C15,'05基本'!C:C,0)) -> 312 | I15: =INDEX('05基本'!P:P,MATCH(C15,'05基本'!C:C,0)) -> 1812 | J15: =INDEX('05基本'!M:M,MATCH(C15,'05基本'!C:C,0)) -> 0 | K15: =INDEX(吧台提成!M:M,MATCH(C15,吧台提成!B:B,0)) -> 3632.94 | L15: =SUMIF(综合考核!A:A,'05月提成-武侯售后'!C15,综合考核!M:M) -> 0 | M15: =SUM(K15:L15) -> 3632.94 | N15: =SUMIF(服装扣款!C:C,C15,服装扣款!N:N) -> 0 | O15: =M15-N15 -> 3632.94 | P15: =SUMIF(超市公积金!C:C,'05月提成-武侯售后'!C15,超市公积金!I:I) -> 0 | Q15: =SUMIF(综合考核!A:A,'05月提成-武侯售后'!C15,综合考核!N:N) -> 0 | R15: =M15+I15+Q15 -> 5444.94 | S15: =INDEX(AC:AC,MATCH(C15,AB:AB,0)) -> 0 | U15: =S15-T15 -> 0 | V15: =INDEX('05基本'!AF:AF,MATCH(C15,'05基本'!C:C,0)) -> 0 | W15: =O15-P15-U15 -> 3632.94 | Y15: =SUM(Z15:AA15) -> 83.33 | Z15: 83.33 | AB15: 陶纯玲 | AC15: 0 | AD15: =COUNTIF(C:C,C15) -> 1 | AE15: =INDEX('05基本'!P:P,MATCH(C15,'05基本'!C:C,0))-I15 -> 0 | AF15: =SUMIF('05月其他部门提成'!C:C,'05月提成-武侯售后'!C15,'05月其他部门提成'!Q:Q) -> 0 | AG15: =SUMIF('05月车间提成'!C:C,'05月提成-武侯售后'!C15,'05月车间提成'!W:W) -> 0 | AH15: =SUMIF('05月业务提成'!B:B,'05月提成-武侯售后'!C15,'05月业务提成'!BO:BO) -> 0 | AI15: =K15 -> 3632.94 | AJ15: =AI15-K15 -> 0
A16: =A15+1 -> 10 | C16: 曹青 | D16: =INDEX('05基本'!I:I,MATCH(C16,'05基本'!C:C,0))+INDEX('05基本'!J:J,MATCH(C16,'05基本'!C:C,0)) -> 0 | E16: =INDEX('05基本'!AA:AA,MATCH(C16,'05基本'!C:C,0)) -> 0 | F16: =INDEX('05基本'!AB:AB,MATCH(C16,'05基本'!C:C,0)) -> 0 | G16: =INDEX('05基本'!AC:AC,MATCH(C16,'05基本'!C:C,0)) -> 0 | H16: =INDEX('05基本'!K:K,MATCH(C16,'05基本'!C:C,0))+INDEX('05基本'!L:L,MATCH(C16,'05基本'!C:C,0)) -> 0 | I16: =INDEX('05基本'!P:P,MATCH(C16,'05基本'!C:C,0)) -> 500 | J16: =INDEX('05基本'!M:M,MATCH(C16,'05基本'!C:C,0)) -> 0 | K16: =INDEX(吧台提成!M:M,MATCH(C16,吧台提成!B:B,0)) -> 1210.98 | L16: =SUMIF(综合考核!A:A,'05月提成-武侯售后'!C16,综合考核!M:M) -> 0 | M16: =SUM(K16:L16) -> 1210.98 | N16: =SUMIF(服装扣款!C:C,C16,服装扣款!N:N) -> 0 | O16: =M16-N16 -> 1210.98 | P16: =SUMIF(超市公积金!C:C,'05月提成-武侯售后'!C16,超市公积金!I:I) -> 0 | Q16: =SUMIF(综合考核!A:A,'05月提成-武侯售后'!C16,综合考核!N:N) -> 0 | R16: =M16+I16+Q16 -> 1710.98 | S16: =INDEX(AC:AC,MATCH(C16,AB:AB,0)) -> 0 | U16: =S16-T16 -> 0 | V16: =INDEX('05基本'!AF:AF,MATCH(C16,'05基本'!C:C,0)) -> 0 | W16: =O16-P16-U16 -> 1210.98 | Y16: =SUM(Z16:AA16) -> 83.33 | Z16: 83.33 | AB16: 朱开莲 | AC16: 0 | AD16: =COUNTIF(C:C,C16) -> 1 | AE16: =INDEX('05基本'!P:P,MATCH(C16,'05基本'!C:C,0))-I16 -> 0 | AF16: =SUMIF('05月其他部门提成'!C:C,'05月提成-武侯售后'!C16,'05月其他部门提成'!Q:Q) -> 0 | AG16: =SUMIF('05月车间提成'!C:C,'05月提成-武侯售后'!C16,'05月车间提成'!W:W) -> 0 | AH16: =SUMIF('05月业务提成'!B:B,'05月提成-武侯售后'!C16,'05月业务提成'!BO:BO) -> 0 | AI16: =K16 -> 1210.98 | AJ16: =AI16-K16 -> 0
A17: =A16+1 -> 11 | C17: 陶纯玲 | D17: =INDEX('05基本'!I:I,MATCH(C17,'05基本'!C:C,0))+INDEX('05基本'!J:J,MATCH(C17,'05基本'!C:C,0)) -> 0 | E17: =INDEX('05基本'!AA:AA,MATCH(C17,'05基本'!C:C,0)) -> 1268.59 | F17: =INDEX('05基本'!AB:AB,MATCH(C17,'05基本'!C:C,0)) -> 477.15 | G17: =INDEX('05基本'!AC:AC,MATCH(C17,'05基本'!C:C,0)) -> 117 | H17: =INDEX('05基本'!K:K,MATCH(C17,'05基本'!C:C,0))+INDEX('05基本'!L:L,MATCH(C17,'05基本'!C:C,0)) -> 0 | I17: =INDEX('05基本'!P:P,MATCH(C17,'05基本'!C:C,0)) -> 1500 | J17: =INDEX('05基本'!M:M,MATCH(C17,'05基本'!C:C,0)) -> 0 | K17: =INDEX(吧台提成!M:M,MATCH(C17,吧台提成!B:B,0)) -> 1695.372 | L17: =SUMIF(综合考核!A:A,'05月提成-武侯售后'!C17,综合考核!M:M) -> 0 | M17: =SUM(K17:L17) -> 1695.372 | N17: =SUMIF(服装扣款!C:C,C17,服装扣款!N:N) -> 0 | O17: =M17-N17 -> 1695.372 | P17: =SUMIF(超市公积金!C:C,'05月提成-武侯售后'!C17,超市公积金!I:I) -> 0 | Q17: =SUMIF(综合考核!A:A,'05月提成-武侯售后'!C17,综合考核!N:N) -> 0 | R17: =M17+I17+Q17 -> 3195.372 | S17: =INDEX(AC:AC,MATCH(C17,AB:AB,0)) -> 0 | U17: =S17-T17 -> 0 | V17: =INDEX('05基本'!AF:AF,MATCH(C17,'05基本'!C:C,0)) -> 0 | W17: =O17-P17-U17 -> 1695.372 | Y17: =SUM(Z17:AA17) -> 83.33 | Z17: 83.33 | AB17: 唐梅 | AC17: 0 | AD17: =COUNTIF(C:C,C17) -> 1 | AE17: =INDEX('05基本'!P:P,MATCH(C17,'05基本'!C:C,0))-I17 -> 0 | AF17: =SUMIF('05月其他部门提成'!C:C,'05月提成-武侯售后'!C17,'05月其他部门提成'!Q:Q) -> 0 | AG17: =SUMIF('05月车间提成'!C:C,'05月提成-武侯售后'!C17,'05月车间提成'!W:W) -> 0 | AH17: =SUMIF('05月业务提成'!B:B,'05月提成-武侯售后'!C17,'05月业务提成'!BO:BO) -> 0 | AI17: =K17 -> 1695.372 | AJ17: =AI17-K17 -> 0
A18: =A17+1 -> 12 | C18: 朱开莲 | D18: =INDEX('05基本'!I:I,MATCH(C18,'05基本'!C:C,0))+INDEX('05基本'!J:J,MATCH(C18,'05基本'!C:C,0)) -> 0 | E18: =INDEX('05基本'!AA:AA,MATCH(C18,'05基本'!C:C,0)) -> 1268.59 | F18: =INDEX('05基本'!AB:AB,MATCH(C18,'05基本'!C:C,0)) -> 477.15 | G18: =INDEX('05基本'!AC:AC,MATCH(C18,'05基本'!C:C,0)) -> 117 | H18: =INDEX('05基本'!K:K,MATCH(C18,'05基本'!C:C,0))+INDEX('05基本'!L:L,MATCH(C18,'05基本'!C:C,0)) -> 312 | I18: =INDEX('05基本'!P:P,MATCH(C18,'05基本'!C:C,0)) -> 1812 | J18: =INDEX('05基本'!M:M,MATCH(C18,'05基本'!C:C,0)) -> 0 | K18: =INDEX(吧台提成!M:M,MATCH(C18,吧台提成!B:B,0)) -> 2664.156 | L18: =SUMIF(综合考核!A:A,'05月提成-武侯售后'!C18,综合考核!M:M) -> 0 | M18: =SUM(K18:L18) -> 2664.156 | N18: =SUMIF(服装扣款!C:C,C18,服装扣款!N:N) -> 0 | O18: =M18-N18 -> 2664.156 | P18: =SUMIF(超市公积金!C:C,'05月提成-武侯售后'!C18,超市公积金!I:I) -> 0 | Q18: =SUMIF(综合考核!A:A,'05月提成-武侯售后'!C18,综合考核!N:N) -> 0 | R18: =M18+I18+Q18 -> 4476.156 | S18: =INDEX(AC:AC,MATCH(C18,AB:AB,0)) -> 0 | U18: =S18-T18 -> 0 | V18: =INDEX('05基本'!AF:AF,MATCH(C18,'05基本'!C:C,0)) -> 0 | W18: =O18-P18-U18 -> 2664.156 | Y18: =SUM(Z18:AA18) -> 83.33 | Z18: 83.33 | AB18: 陈琳琳 | AC18: 0 | AD18: =COUNTIF(C:C,C18) -> 1 | AE18: =INDEX('05基本'!P:P,MATCH(C18,'05基本'!C:C,0))-I18 -> 0 | AF18: =SUMIF('05月其他部门提成'!C:C,'05月提成-武侯售后'!C18,'05月其他部门提成'!Q:Q) -> 0 | AG18: =SUMIF('05月车间提成'!C:C,'05月提成-武侯售后'!C18,'05月车间提成'!W:W) -> 0 | AH18: =SUMIF('05月业务提成'!B:B,'05月提成-武侯售后'!C18,'05月业务提成'!BO:BO) -> 0 | AI18: =K18 -> 2664.156 | AJ18: =AI18-K18 -> 0
C19: 小计 | D19: =SUM(D15:D18) -> 0 | E19: =SUM(E15:E18) -> 3805.77 | F19: =SUM(F15:F18) -> 1431.45 | G19: =SUM(G15:G18) -> 351 | H19: =SUM(H15:H18) -> 624 | I19: =SUM(I15:I18) -> 5624 | J19: =SUM(J15:J18) -> 0 | K19: =SUM(K15:K18) -> 9203.448 | ... AA19: =SUM(AA15:AA18) -> 0 | AB19: 邱昭丽 | AC19: 25.49 | AD19: =COUNTIF(C:C,C19) -> 11 | AE19: =INDEX('05基本'!P:P,MATCH(C19,'05基本'!C:C,0))-I19 -> #N/A
A20: =A18+1 -> 13 | B20: 回访部 | C20: 唐梅 | D20: =INDEX('05基本'!I:I,MATCH(C20,'05基本'!C:C,0))+INDEX('05基本'!J:J,MATCH(C20,'05基本'!C:C,0)) -> 0 | E20: =INDEX('05基本'!AA:AA,MATCH(C20,'05基本'!C:C,0)) -> 1268.59 | F20: =INDEX('05基本'!AB:AB,MATCH(C20,'05基本'!C:C,0)) -> 477.15 | G20: =INDEX('05基本'!AC:AC,MATCH(C20,'05基本'!C:C,0)) -> 117 | H20: =INDEX('05基本'!K:K,MATCH(C20,'05基本'!C:C,0))+INDEX('05基本'!L:L,MATCH(C20,'05基本'!C:C,0)) -> 0 | I20: =INDEX('05基本'!P:P,MATCH(C20,'05基本'!C:C,0)) -> 1200 | J20: =INDEX('05基本'!M:M,MATCH(C20,'05基本'!C:C,0)) -> 0 | K20: =INDEX('05月其他部门提成'!Q:Q,MATCH(C20,'05月其他部门提成'!C:C,0)) -> 4387 | L20: =SUMIF(综合考核!A:A,'05月提成-武侯售后'!C20,综合考核!M:M) -> 0 | M20: =SUM(K20:L20) -> 4387 | N20: =SUMIF(服装扣款!C:C,C20,服装扣款!N:N) -> 0 | O20: =M20-N20 -> 4387 | P20: =SUMIF(超市公积金!C:C,'05月提成-武侯售后'!C20,超市公积金!I:I) -> 0 | Q20: =SUMIF(综合考核!A:A,'05月提成-武侯售后'!C20,综合考核!N:N) -> 0 | R20: =M20+I20+Q20 -> 5587 | S20: =INDEX(AC:AC,MATCH(C20,AB:AB,0)) -> 0 | U20: =S20-T20 -> 0 | V20: =INDEX('05基本'!AF:AF,MATCH(C20,'05基本'!C:C,0)) -> 0 | W20: =O20-P20-U20 -> 4387 | Y20: =SUM(Z20:AA20) -> 83.333333 | Z20: =1000/12 -> 83.333333 | AB20: 黄雪梅 | AC20: 19.91 | AD20: =COUNTIF(C:C,C20) -> 1 | AE20: =INDEX('05基本'!P:P,MATCH(C20,'05基本'!C:C,0))-I20 -> 0 | AF20: =SUMIF('05月其他部门提成'!C:C,'05月提成-武侯售后'!C20,'05月其他部门提成'!Q:Q) -> 4387 | AG20: =SUMIF('05月车间提成'!C:C,'05月提成-武侯售后'!C20,'05月车间提成'!W:W) -> 0 | AH20: =SUMIF('05月业务提成'!B:B,'05月提成-武侯售后'!C20,'05月业务提成'!BO:BO) -> 0 | AI20: =AF20+AG20+AH20 -> 4387 | AJ20: =AI20-K20 -> 0
A21: =A20+1 -> 14 | C21: 陈琳琳 | D21: =INDEX('05基本'!I:I,MATCH(C21,'05基本'!C:C,0))+INDEX('05基本'!J:J,MATCH(C21,'05基本'!C:C,0)) -> 0 | E21: =INDEX('05基本'!AA:AA,MATCH(C21,'05基本'!C:C,0)) -> 1268.59 | F21: =INDEX('05基本'!AB:AB,MATCH(C21,'05基本'!C:C,0)) -> 477.15 | G21: =INDEX('05基本'!AC:AC,MATCH(C21,'05基本'!C:C,0)) -> 117 | H21: =INDEX('05基本'!K:K,MATCH(C21,'05基本'!C:C,0))+INDEX('05基本'!L:L,MATCH(C21,'05基本'!C:C,0)) -> 0 | I21: =INDEX('05基本'!P:P,MATCH(C21,'05基本'!C:C,0)) -> 1200 | J21: =INDEX('05基本'!M:M,MATCH(C21,'05基本'!C:C,0)) -> 0 | K21: =INDEX('05月其他部门提成'!Q:Q,MATCH(C21,'05月其他部门提成'!C:C,0)) -> 3868 | L21: =SUMIF(综合考核!A:A,'05月提成-武侯售后'!C21,综合考核!M:M) -> 0 | M21: =SUM(K21:L21) -> 3868 | N21: =SUMIF(服装扣款!C:C,C21,服装扣款!N:N) -> 0 | O21: =M21-N21 -> 3868 | P21: =SUMIF(超市公积金!C:C,'05月提成-武侯售后'!C21,超市公积金!I:I) -> 0 | Q21: =SUMIF(综合考核!A:A,'05月提成-武侯售后'!C21,综合考核!N:N) -> 0 | R21: =M21+I21+Q21 -> 5068 | S21: =INDEX(AC:AC,MATCH(C21,AB:AB,0)) -> 0 | U21: =S21-T21 -> 0 | V21: =INDEX('05基本'!AF:AF,MATCH(C21,'05基本'!C:C,0)) -> 0 | W21: =O21-P21-U21 -> 3868 | Y21: =SUM(Z21:AA21) -> 83.333333 | Z21: =1000/12 -> 83.333333 | AB21: 李彩琼 | AC21: 11.36 | AD21: =COUNTIF(C:C,C21) -> 1 | AE21: =INDEX('05基本'!P:P,MATCH(C21,'05基本'!C:C,0))-I21 -> 0 | AF21: =SUMIF('05月其他部门提成'!C:C,'05月提成-武侯售后'!C21,'05月其他部门提成'!Q:Q) -> 3868 | AG21: =SUMIF('05月车间提成'!C:C,'05月提成-武侯售后'!C21,'05月车间提成'!W:W) -> 0 | AH21: =SUMIF('05月业务提成'!B:B,'05月提成-武侯售后'!C21,'05月业务提成'!BO:BO) -> 0 | AI21: =AF21+AG21+AH21 -> 3868 | AJ21: =AI21-K21 -> 0
A22: =A21+1 -> 15 | C22: 邱昭丽 | D22: =INDEX('05基本'!I:I,MATCH(C22,'05基本'!C:C,0))+INDEX('05基本'!J:J,MATCH(C22,'05基本'!C:C,0)) -> 0 | E22: =INDEX('05基本'!AA:AA,MATCH(C22,'05基本'!C:C,0)) -> 1268.59 | F22: =INDEX('05基本'!AB:AB,MATCH(C22,'05基本'!C:C,0)) -> 477.15 | G22: =INDEX('05基本'!AC:AC,MATCH(C22,'05基本'!C:C,0)) -> 117 | H22: =INDEX('05基本'!K:K,MATCH(C22,'05基本'!C:C,0))+INDEX('05基本'!L:L,MATCH(C22,'05基本'!C:C,0)) -> 0 | I22: =INDEX('05基本'!P:P,MATCH(C22,'05基本'!C:C,0)) -> 1200 | J22: =INDEX('05基本'!M:M,MATCH(C22,'05基本'!C:C,0)) -> 0 | K22: =INDEX('05月其他部门提成'!Q:Q,MATCH(C22,'05月其他部门提成'!C:C,0)) -> 5244 | L22: =SUMIF(综合考核!A:A,'05月提成-武侯售后'!C22,综合考核!M:M) -> 0 | M22: =SUM(K22:L22) -> 5244 | N22: =SUMIF(服装扣款!C:C,C22,服装扣款!N:N) -> 0 | O22: =M22-N22 -> 5244 | P22: =SUMIF(超市公积金!C:C,'05月提成-武侯售后'!C22,超市公积金!I:I) -> 0 | Q22: =SUMIF(综合考核!A:A,'05月提成-武侯售后'!C22,综合考核!N:N) -> 0 | R22: =M22+I22+Q22 -> 6444 | S22: =INDEX(AC:AC,MATCH(C22,AB:AB,0)) -> 25.49 | U22: =S22-T22 -> 25.49 | V22: =INDEX('05基本'!AF:AF,MATCH(C22,'05基本'!C:C,0)) -> 0 | W22: =O22-P22-U22 -> 5218.51 | Y22: =SUM(Z22:AA22) -> 83.333333 | Z22: =1000/12 -> 83.333333 | AB22: 向阳 | AC22: 0 | AD22: =COUNTIF(C:C,C22) -> 1 | AE22: =INDEX('05基本'!P:P,MATCH(C22,'05基本'!C:C,0))-I22 -> 0 | AF22: =SUMIF('05月其他部门提成'!C:C,'05月提成-武侯售后'!C22,'05月其他部门提成'!Q:Q) -> 5244 | AG22: =SUMIF('05月车间提成'!C:C,'05月提成-武侯售后'!C22,'05月车间提成'!W:W) -> 0 | AH22: =SUMIF('05月业务提成'!B:B,'05月提成-武侯售后'!C22,'05月业务提成'!BO:BO) -> 0 | AI22: =AF22+AG22+AH22 -> 5244 | AJ22: =AI22-K22 -> 0
A23: =A22+1 -> 16 | C23: 黄雪梅 | D23: =INDEX('05基本'!I:I,MATCH(C23,'05基本'!C:C,0))+INDEX('05基本'!J:J,MATCH(C23,'05基本'!C:C,0)) -> 0 | E23: =INDEX('05基本'!AA:AA,MATCH(C23,'05基本'!C:C,0)) -> 1268.59 | F23: =INDEX('05基本'!AB:AB,MATCH(C23,'05基本'!C:C,0)) -> 477.15 | G23: =INDEX('05基本'!AC:AC,MATCH(C23,'05基本'!C:C,0)) -> 117 | H23: =INDEX('05基本'!K:K,MATCH(C23,'05基本'!C:C,0))+INDEX('05基本'!L:L,MATCH(C23,'05基本'!C:C,0)) -> 0 | I23: =INDEX('05基本'!P:P,MATCH(C23,'05基本'!C:C,0)) -> 1200 | J23: =INDEX('05基本'!M:M,MATCH(C23,'05基本'!C:C,0)) -> 0 | K23: =INDEX('05月其他部门提成'!Q:Q,MATCH(C23,'05月其他部门提成'!C:C,0)) -> 5058 | L23: =SUMIF(综合考核!A:A,'05月提成-武侯售后'!C23,综合考核!M:M) -> 0 | M23: =SUM(K23:L23) -> 5058 | N23: =SUMIF(服装扣款!C:C,C23,服装扣款!N:N) -> 0 | O23: =M23-N23 -> 5058 | P23: =SUMIF(超市公积金!C:C,'05月提成-武侯售后'!C23,超市公积金!I:I) -> 0 | Q23: =SUMIF(综合考核!A:A,'05月提成-武侯售后'!C23,综合考核!N:N) -> 0 | R23: =M23+I23+Q23 -> 6258 | S23: =INDEX(AC:AC,MATCH(C23,AB:AB,0)) -> 19.91 | U23: =S23-T23 -> 19.91 | V23: =INDEX('05基本'!AF:AF,MATCH(C23,'05基本'!C:C,0)) -> 0 | W23: =O23-P23-U23 -> 5038.09 | Y23: =SUM(Z23:AA23) -> 83.333333 | Z23: =1000/12 -> 83.333333 | AB23: 阳国华 | AC23: 709.53 | AD23: =COUNTIF(C:C,C23) -> 1 | AE23: =INDEX('05基本'!P:P,MATCH(C23,'05基本'!C:C,0))-I23 -> 0 | AF23: =SUMIF('05月其他部门提成'!C:C,'05月提成-武侯售后'!C23,'05月其他部门提成'!Q:Q) -> 5058 | AG23: =SUMIF('05月车间提成'!C:C,'05月提成-武侯售后'!C23,'05月车间提成'!W:W) -> 0 | AH23: =SUMIF('05月业务提成'!B:B,'05月提成-武侯售后'!C23,'05月业务提成'!BO:BO) -> 0 | AI23: =AF23+AG23+AH23 -> 5058 | AJ23: =AI23-K23 -> 0
A24: =A23+1 -> 17 | C24: 李彩琼 | D24: =INDEX('05基本'!I:I,MATCH(C24,'05基本'!C:C,0))+INDEX('05基本'!J:J,MATCH(C24,'05基本'!C:C,0)) -> 0 | E24: =INDEX('05基本'!AA:AA,MATCH(C24,'05基本'!C:C,0)) -> 1268.59 | F24: =INDEX('05基本'!AB:AB,MATCH(C24,'05基本'!C:C,0)) -> 477.15 | G24: =INDEX('05基本'!AC:AC,MATCH(C24,'05基本'!C:C,0)) -> 117 | H24: =INDEX('05基本'!K:K,MATCH(C24,'05基本'!C:C,0))+INDEX('05基本'!L:L,MATCH(C24,'05基本'!C:C,0)) -> 0 | I24: =INDEX('05基本'!P:P,MATCH(C24,'05基本'!C:C,0)) -> 1200 | J24: =INDEX('05基本'!M:M,MATCH(C24,'05基本'!C:C,0)) -> 0 | K24: =INDEX('05月其他部门提成'!Q:Q,MATCH(C24,'05月其他部门提成'!C:C,0)) -> 4773 | L24: =SUMIF(综合考核!A:A,'05月提成-武侯售后'!C24,综合考核!M:M) -> 0 | M24: =SUM(K24:L24) -> 4773 | N24: =SUMIF(服装扣款!C:C,C24,服装扣款!N:N) -> 0 | O24: =M24-N24 -> 4773 | P24: =SUMIF(超市公积金!C:C,'05月提成-武侯售后'!C24,超市公积金!I:I) -> 0 | Q24: =SUMIF(综合考核!A:A,'05月提成-武侯售后'!C24,综合考核!N:N) -> 0 | R24: =M24+I24+Q24 -> 5973 | S24: =INDEX(AC:AC,MATCH(C24,AB:AB,0)) -> 11.36 | U24: =S24-T24 -> 11.36 | V24: =INDEX('05基本'!AF:AF,MATCH(C24,'05基本'!C:C,0)) -> 0 | W24: =O24-P24-U24 -> 4761.64 | Y24: =SUM(Z24:AA24) -> 83.333333 | Z24: =1000/12 -> 83.333333 | AB24: 舒童强 | AC24: 56.79 | AD24: =COUNTIF(C:C,C24) -> 1 | AE24: =INDEX('05基本'!P:P,MATCH(C24,'05基本'!C:C,0))-I24 -> 0 | AF24: =SUMIF('05月其他部门提成'!C:C,'05月提成-武侯售后'!C24,'05月其他部门提成'!Q:Q) -> 4773 | AG24: =SUMIF('05月车间提成'!C:C,'05月提成-武侯售后'!C24,'05月车间提成'!W:W) -> 0 | AH24: =SUMIF('05月业务提成'!B:B,'05月提成-武侯售后'!C24,'05月业务提成'!BO:BO) -> 0 | AI24: =AF24+AG24+AH24 -> 4773 | AJ24: =AI24-K24 -> 0
A25: =A24+1 -> 18 | C25: 向阳 | D25: =INDEX('05基本'!I:I,MATCH(C25,'05基本'!C:C,0))+INDEX('05基本'!J:J,MATCH(C25,'05基本'!C:C,0)) -> 0 | E25: =INDEX('05基本'!AA:AA,MATCH(C25,'05基本'!C:C,0)) -> 1268.59 | F25: =INDEX('05基本'!AB:AB,MATCH(C25,'05基本'!C:C,0)) -> 477.15 | G25: =INDEX('05基本'!AC:AC,MATCH(C25,'05基本'!C:C,0)) -> 117 | H25: =INDEX('05基本'!K:K,MATCH(C25,'05基本'!C:C,0))+INDEX('05基本'!L:L,MATCH(C25,'05基本'!C:C,0)) -> 0 | I25: =INDEX('05基本'!P:P,MATCH(C25,'05基本'!C:C,0)) -> 1200 | K25: =INDEX('05月其他部门提成'!Q:Q,MATCH(C25,'05月其他部门提成'!C:C,0)) -> 4010 | L25: =SUMIF(综合考核!A:A,'05月提成-武侯售后'!C25,综合考核!M:M) -> 0 | M25: =SUM(K25:L25) -> 4010 | N25: =SUMIF(服装扣款!C:C,C25,服装扣款!N:N) -> 0 | O25: =M25-N25 -> 4010 | P25: =SUMIF(超市公积金!C:C,'05月提成-武侯售后'!C25,超市公积金!I:I) -> 0 | Q25: =SUMIF(综合考核!A:A,'05月提成-武侯售后'!C25,综合考核!N:N) -> 0 | R25: =M25+I25+Q25 -> 5210 | S25: =INDEX(AC:AC,MATCH(C25,AB:AB,0)) -> 0 | U25: =S25-T25 -> 0 | V25: =INDEX('05基本'!AF:AF,MATCH(C25,'05基本'!C:C,0)) -> 0 | W25: =O25-P25-U25 -> 4010 | Y25: =SUM(Z25:AA25) -> 83.333333 | Z25: =1000/12 -> 83.333333 | AB25: 罗义瑕 | AC25: 0 | AE25: =INDEX('05基本'!P:P,MATCH(C25,'05基本'!C:C,0))-I25 -> 0
C26: 小计 | D26: =SUM(D20:D25) -> 0 | E26: =SUM(E20:E25) -> 7611.54 | F26: =SUM(F20:F25) -> 2862.9 | G26: =SUM(G20:G25) -> 702 | H26: =SUM(H20:H25) -> 0 | I26: =SUM(I20:I25) -> 7200 | J26: =SUM(J20:J25) -> 0 | K26: =SUM(K20:K25) -> 27340 | ... AA26: =SUM(AA20:AA25) -> 0 | AB26: 段宝安 | AC26: 81.26 | AD26: =COUNTIF(C:C,C26) -> 11 | AE26: =INDEX('05基本'!P:P,MATCH(C26,'05基本'!C:C,0))-I26 -> #N/A
A27: =A25+1 -> 19 | C27: 阳国华 | D27: =INDEX('05基本'!I:I,MATCH(C27,'05基本'!C:C,0))+INDEX('05基本'!J:J,MATCH(C27,'05基本'!C:C,0)) -> 0 | E27: =INDEX('05基本'!AA:AA,MATCH(C27,'05基本'!C:C,0)) -> 1268.59 | F27: =INDEX('05基本'!AB:AB,MATCH(C27,'05基本'!C:C,0)) -> 477.15 | G27: =INDEX('05基本'!AC:AC,MATCH(C27,'05基本'!C:C,0)) -> 117 | H27: =INDEX('05基本'!K:K,MATCH(C27,'05基本'!C:C,0))+INDEX('05基本'!L:L,MATCH(C27,'05基本'!C:C,0)) -> 100 | I27: =INDEX('05基本'!P:P,MATCH(C27,'05基本'!C:C,0)) -> 1700 | J27: =INDEX('05基本'!M:M,MATCH(C27,'05基本'!C:C,0)) -> 0 | K27: =INDEX('05月其他部门提成'!Q:Q,MATCH(C27,'05月其他部门提成'!C:C,0)) -> 10989.415 | L27: =SUMIF(综合考核!A:A,'05月提成-武侯售后'!C27,综合考核!M:M) -> 0 | M27: =SUM(K27:L27) -> 10989.415 | N27: =SUMIF(服装扣款!C:C,C27,服装扣款!N:N) -> 0 | O27: =M27-N27 -> 10989.415 | P27: =SUMIF(超市公积金!C:C,'05月提成-武侯售后'!C27,超市公积金!I:I) -> 0 | Q27: =SUMIF(综合考核!A:A,'05月提成-武侯售后'!C27,综合考核!N:N) -> 0 | R27: =M27+I27+Q27 -> 12689.415 | S27: =INDEX(AC:AC,MATCH(C27,AB:AB,0)) -> 709.53 | U27: =S27-T27 -> 709.53 | V27: =INDEX('05基本'!AF:AF,MATCH(C27,'05基本'!C:C,0)) -> 0 | W27: =O27-P27-U27 -> 10279.885 | Y27: =SUM(Z27:AA27) -> 830.08647 | Z27: ='05月其他部门提成'!R8 -> 830.08647 | AB27: 张建 | AC27: 68.18 | AD27: =COUNTIF(C:C,C27) -> 1 | AE27: =INDEX('05基本'!P:P,MATCH(C27,'05基本'!C:C,0))-I27 -> 0 | AF27: =SUMIF('05月其他部门提成'!C:C,'05月提成-武侯售后'!C27,'05月其他部门提成'!Q:Q) -> 10989.415 | AG27: =SUMIF('05月车间提成'!C:C,'05月提成-武侯售后'!C27,'05月车间提成'!W:W) -> 0 | AH27: =SUMIF('05月业务提成'!B:B,'05月提成-武侯售后'!C27,'05月业务提成'!BO:BO) -> 0 | AI27: =AF27+AG27+AH27 -> 10989.415 | AJ27: =AI27-K27 -> 0
A28: =A27+1 -> 20 | B28: 业务部 | C28: 舒童强 | D28: =INDEX('05基本'!I:I,MATCH(C28,'05基本'!C:C,0))+INDEX('05基本'!J:J,MATCH(C28,'05基本'!C:C,0)) -> 32 | E28: =INDEX('05基本'!AA:AA,MATCH(C28,'05基本'!C:C,0)) -> 1268.59 | F28: =INDEX('05基本'!AB:AB,MATCH(C28,'05基本'!C:C,0)) -> 477.15 | G28: =INDEX('05基本'!AC:AC,MATCH(C28,'05基本'!C:C,0)) -> 117 | H28: =INDEX('05基本'!K:K,MATCH(C28,'05基本'!C:C,0))+INDEX('05基本'!L:L,MATCH(C28,'05基本'!C:C,0)) -> 0 | I28: =INDEX('05基本'!P:P,MATCH(C28,'05基本'!C:C,0)) -> 932 | J28: =INDEX('05基本'!M:M,MATCH(C28,'05基本'!C:C,0)) -> 0 | K28: =INDEX('05月业务提成'!BO:BO,MATCH(C28,'05月业务提成'!B:B,0)) -> 6555.1645 | L28: =SUMIF(综合考核!A:A,'05月提成-武侯售后'!C28,综合考核!M:M) -> 0 | M28: =SUM(K28:L28) -> 6555.1645 | N28: =SUMIF(服装扣款!C:C,C28,服装扣款!N:N) -> 0 | O28: =M28-N28 -> 6555.1645 | P28: =SUMIF(超市公积金!C:C,'05月提成-武侯售后'!C28,超市公积金!I:I) -> 0 | Q28: =SUMIF(综合考核!A:A,'05月提成-武侯售后'!C28,综合考核!N:N) -> 0 | R28: =M28+I28+Q28 -> 7487.1645 | S28: =INDEX(AC:AC,MATCH(C28,AB:AB,0)) -> 56.79 | U28: =S28-T28 -> 56.79 | V28: =INDEX('05基本'!AF:AF,MATCH(C28,'05基本'!C:C,0)) -> 0 | W28: =O28-P28-U28 -> 6498.3745 | Y28: =SUM(Z28:AA28) -> 479.10813 | Z28: =INDEX('05月业务提成'!C:C,MATCH(C28,'05月业务提成'!B:B,0))*1 -> 288 | AA28: =INDEX('05月业务提成'!F:F,MATCH(C28,'05月业务提成'!B:B,0))*0.05*2%+INDEX('05月业务提成'!J:J,MATCH(C28,'05月业务提成'!B:B,0))*0.05*1.6%+(INDEX('05月业务提成'!P:P,MATCH(C28,'05月业务提成'!B:B,0))/0.95)*0.05++(INDEX('05月业务提成'!V:V,MATCH(C28,'05月业务提成'!B:B,0))/0.95)*0.05+(INDEX('05月业务提成'!Z:Z,MATCH(C28,'05月业务提成'!B:B,0))/0.95)*0.05 -> 191.10813 | AB28: 贾文哲 | AC28: 33.7 | AD28: =COUNTIF(C:C,C28) -> 1 | AE28: =INDEX('05基本'!P:P,MATCH(C28,'05基本'!C:C,0))-I28 -> 0 | AF28: =SUMIF('05月其他部门提成'!C:C,'05月提成-武侯售后'!C28,'05月其他部门提成'!Q:Q) -> 0 | AG28: =SUMIF('05月车间提成'!C:C,'05月提成-武侯售后'!C28,'05月车间提成'!W:W) -> 0 | AH28: =SUMIF('05月业务提成'!B:B,'05月提成-武侯售后'!C28,'05月业务提成'!BO:BO) -> 6555.1645 | AI28: =AF28+AG28+AH28 -> 6555.1645 | AJ28: =AI28-K28 -> 0
A29: =A28+1 -> 21 | C29: 罗义瑕 | D29: =INDEX('05基本'!I:I,MATCH(C29,'05基本'!C:C,0))+INDEX('05基本'!J:J,MATCH(C29,'05基本'!C:C,0)) -> 32 | E29: =INDEX('05基本'!AA:AA,MATCH(C29,'05基本'!C:C,0)) -> 1268.59 | F29: =INDEX('05基本'!AB:AB,MATCH(C29,'05基本'!C:C,0)) -> 477.15 | G29: =INDEX('05基本'!AC:AC,MATCH(C29,'05基本'!C:C,0)) -> 117 | H29: =INDEX('05基本'!K:K,MATCH(C29,'05基本'!C:C,0))+INDEX('05基本'!L:L,MATCH(C29,'05基本'!C:C,0)) -> 0 | I29: =INDEX('05基本'!P:P,MATCH(C29,'05基本'!C:C,0)) -> 932 | J29: =INDEX('05基本'!M:M,MATCH(C29,'05基本'!C:C,0)) -> 0 | K29: =INDEX('05月业务提成'!BO:BO,MATCH(C29,'05月业务提成'!B:B,0)) -> 4175.6566 | L29: =SUMIF(综合考核!A:A,'05月提成-武侯售后'!C29,综合考核!M:M) -> 0 | M29: =SUM(K29:L29) -> 4175.6566 | N29: =SUMIF(服装扣款!C:C,C29,服装扣款!N:N) -> 0 | O29: =M29-N29 -> 4175.6566 | P29: =SUMIF(超市公积金!C:C,'05月提成-武侯售后'!C29,超市公积金!I:I) -> 0 | Q29: =SUMIF(综合考核!A:A,'05月提成-武侯售后'!C29,综合考核!N:N) -> 0 | R29: =M29+I29+Q29 -> 5107.6566 | S29: =INDEX(AC:AC,MATCH(C29,AB:AB,0)) -> 0 | U29: =S29-T29 -> 0 | V29: =INDEX('05基本'!AF:AF,MATCH(C29,'05基本'!C:C,0)) -> 0 | W29: =O29-P29-U29 -> 4175.6566 | Y29: =SUM(Z29:AA29) -> 294.04403 | Z29: =INDEX('05月业务提成'!C:C,MATCH(C29,'05月业务提成'!B:B,0))*1 -> 159 | AA29: =INDEX('05月业务提成'!F:F,MATCH(C29,'05月业务提成'!B:B,0))*0.05*2%+INDEX('05月业务提成'!J:J,MATCH(C29,'05月业务提成'!B:B,0))*0.05*1.6%+(INDEX('05月业务提成'!P:P,MATCH(C29,'05月业务提成'!B:B,0))/0.95)*0.05++(INDEX('05月业务提成'!V:V,MATCH(C29,'05月业务提成'!B:B,0))/0.95)*0.05+(INDEX('05月业务提成'!Z:Z,MATCH(C29,'05月业务提成'!B:B,0))/0.95)*0.05 -> 135.04403 | AB29: 黄小炼 | AC29: 22.15 | AD29: =COUNTIF(C:C,C29) -> 1 | AE29: =INDEX('05基本'!P:P,MATCH(C29,'05基本'!C:C,0))-I29 -> 0 | AF29: =SUMIF('05月其他部门提成'!C:C,'05月提成-武侯售后'!C29,'05月其他部门提成'!Q:Q) -> 0 | AG29: =SUMIF('05月车间提成'!C:C,'05月提成-武侯售后'!C29,'05月车间提成'!W:W) -> 0 | AH29: =SUMIF('05月业务提成'!B:B,'05月提成-武侯售后'!C29,'05月业务提成'!BO:BO) -> 4175.6566 | AI29: =AF29+AG29+AH29 -> 4175.6566 | AJ29: =AI29-K29 -> 0
A30: =A29+1 -> 22 | C30: 段宝安 | D30: =INDEX('05基本'!I:I,MATCH(C30,'05基本'!C:C,0))+INDEX('05基本'!J:J,MATCH(C30,'05基本'!C:C,0)) -> 0 | E30: =INDEX('05基本'!AA:AA,MATCH(C30,'05基本'!C:C,0)) -> 1268.59 | F30: =INDEX('05基本'!AB:AB,MATCH(C30,'05基本'!C:C,0)) -> 477.15 | G30: =INDEX('05基本'!AC:AC,MATCH(C30,'05基本'!C:C,0)) -> 117 | H30: =INDEX('05基本'!K:K,MATCH(C30,'05基本'!C:C,0))+INDEX('05基本'!L:L,MATCH(C30,'05基本'!C:C,0)) -> 0 | I30: =INDEX('05基本'!P:P,MATCH(C30,'05基本'!C:C,0)) -> 900 | J30: =INDEX('05基本'!M:M,MATCH(C30,'05基本'!C:C,0)) -> 0 | K30: =INDEX('05月业务提成'!BO:BO,MATCH(C30,'05月业务提成'!B:B,0)) -> 7182.7026 | L30: =SUMIF(综合考核!A:A,'05月提成-武侯售后'!C30,综合考核!M:M) -> 220 | M30: =SUM(K30:L30) -> 7402.7026 | N30: =SUMIF(服装扣款!C:C,C30,服装扣款!N:N) -> 0 | O30: =M30-N30 -> 7402.7026 | P30: =SUMIF(超市公积金!C:C,'05月提成-武侯售后'!C30,超市公积金!I:I) -> 0 | Q30: =SUMIF(综合考核!A:A,'05月提成-武侯售后'!C30,综合考核!N:N) -> 0 | R30: =M30+I30+Q30 -> 8302.7026 | S30: =INDEX(AC:AC,MATCH(C30,AB:AB,0)) -> 81.26 | U30: =S30-T30 -> 81.26 | V30: =INDEX('05基本'!AF:AF,MATCH(C30,'05基本'!C:C,0)) -> 0 | W30: =O30-P30-U30 -> 7321.4426 | Y30: =SUM(Z30:AA30) -> 461.30014 | Z30: =INDEX('05月业务提成'!C:C,MATCH(C30,'05月业务提成'!B:B,0))*1 -> 62 | AA30: =INDEX('05月业务提成'!F:F,MATCH(C30,'05月业务提成'!B:B,0))*0.05*2%+INDEX('05月业务提成'!J:J,MATCH(C30,'05月业务提成'!B:B,0))*0.05*1.6%+(INDEX('05月业务提成'!P:P,MATCH(C30,'05月业务提成'!B:B,0))/0.95)*0.05++(INDEX('05月业务提成'!V:V,MATCH(C30,'05月业务提成'!B:B,0))/0.95)*0.05+(INDEX('05月业务提成'!Z:Z,MATCH(C30,'05月业务提成'!B:B,0))/0.95)*0.05 -> 399.30014 | AB30: 陈昱良 | AC30: 50.13 | AD30: =COUNTIF(C:C,C30) -> 1 | AE30: =INDEX('05基本'!P:P,MATCH(C30,'05基本'!C:C,0))-I30 -> 0 | AF30: =SUMIF('05月其他部门提成'!C:C,'05月提成-武侯售后'!C30,'05月其他部门提成'!Q:Q) -> 0 | AG30: =SUMIF('05月车间提成'!C:C,'05月提成-武侯售后'!C30,'05月车间提成'!W:W) -> 0 | AH30: =SUMIF('05月业务提成'!B:B,'05月提成-武侯售后'!C30,'05月业务提成'!BO:BO) -> 7182.7026 | AI30: =AF30+AG30+AH30 -> 7182.7026 | AJ30: =AI30-K30 -> 0
A31: =A30+1 -> 23 | C31: 张建 | D31: =INDEX('05基本'!I:I,MATCH(C31,'05基本'!C:C,0))+INDEX('05基本'!J:J,MATCH(C31,'05基本'!C:C,0)) -> 32 | E31: =INDEX('05基本'!AA:AA,MATCH(C31,'05基本'!C:C,0)) -> 1268.59 | F31: =INDEX('05基本'!AB:AB,MATCH(C31,'05基本'!C:C,0)) -> 477.15 | G31: =INDEX('05基本'!AC:AC,MATCH(C31,'05基本'!C:C,0)) -> 117 | H31: =INDEX('05基本'!K:K,MATCH(C31,'05基本'!C:C,0))+INDEX('05基本'!L:L,MATCH(C31,'05基本'!C:C,0)) -> 0 | I31: =INDEX('05基本'!P:P,MATCH(C31,'05基本'!C:C,0)) -> 932 | J31: =INDEX('05基本'!M:M,MATCH(C31,'05基本'!C:C,0)) -> 0 | K31: =INDEX('05月业务提成'!BO:BO,MATCH(C31,'05月业务提成'!B:B,0)) -> 6934.8284 | L31: =SUMIF(综合考核!A:A,'05月提成-武侯售后'!C31,综合考核!M:M) -> 0 | M31: =SUM(K31:L31) -> 6934.8284 | N31: =SUMIF(服装扣款!C:C,C31,服装扣款!N:N) -> 0 | O31: =M31-N31 -> 6934.8284 | P31: =SUMIF(超市公积金!C:C,'05月提成-武侯售后'!C31,超市公积金!I:I) -> 0 | Q31: =SUMIF(综合考核!A:A,'05月提成-武侯售后'!C31,综合考核!N:N) -> 0 | R31: =M31+I31+Q31 -> 7866.8284 | S31: =INDEX(AC:AC,MATCH(C31,AB:AB,0)) -> 68.18 | U31: =S31-T31 -> 68.18 | V31: =INDEX('05基本'!AF:AF,MATCH(C31,'05基本'!C:C,0)) -> 0 | W31: =O31-P31-U31 -> 6866.6484 | Y31: =SUM(Z31:AA31) -> 441.89571 | Z31: =INDEX('05月业务提成'!C:C,MATCH(C31,'05月业务提成'!B:B,0))*1 -> 235 | AA31: =INDEX('05月业务提成'!F:F,MATCH(C31,'05月业务提成'!B:B,0))*0.05*2%+INDEX('05月业务提成'!J:J,MATCH(C31,'05月业务提成'!B:B,0))*0.05*1.6%+(INDEX('05月业务提成'!P:P,MATCH(C31,'05月业务提成'!B:B,0))/0.95)*0.05++(INDEX('05月业务提成'!V:V,MATCH(C31,'05月业务提成'!B:B,0))/0.95)*0.05+(INDEX('05月业务提成'!Z:Z,MATCH(C31,'05月业务提成'!B:B,0))/0.95)*0.05 -> 206.8957 | AB31: 张林 | AC31: 66.88 | AD31: =COUNTIF(C:C,C31) -> 1 | AE31: =INDEX('05基本'!P:P,MATCH(C31,'05基本'!C:C,0))-I31 -> 0 | AF31: =SUMIF('05月其他部门提成'!C:C,'05月提成-武侯售后'!C31,'05月其他部门提成'!Q:Q) -> 0 | AG31: =SUMIF('05月车间提成'!C:C,'05月提成-武侯售后'!C31,'05月车间提成'!W:W) -> 0 | AH31: =SUMIF('05月业务提成'!B:B,'05月提成-武侯售后'!C31,'05月业务提成'!BO:BO) -> 6934.8284 | AI31: =AF31+AG31+AH31 -> 6934.8284 | AJ31: =AI31-K31 -> 0
A32: =A31+1 -> 24 | C32: 贾文哲 | D32: =INDEX('05基本'!I:I,MATCH(C32,'05基本'!C:C,0))+INDEX('05基本'!J:J,MATCH(C32,'05基本'!C:C,0)) -> 32 | E32: =INDEX('05基本'!AA:AA,MATCH(C32,'05基本'!C:C,0)) -> 1268.59 | F32: =INDEX('05基本'!AB:AB,MATCH(C32,'05基本'!C:C,0)) -> 477.15 | G32: =INDEX('05基本'!AC:AC,MATCH(C32,'05基本'!C:C,0)) -> 117 | H32: =INDEX('05基本'!K:K,MATCH(C32,'05基本'!C:C,0))+INDEX('05基本'!L:L,MATCH(C32,'05基本'!C:C,0)) -> 0 | I32: =INDEX('05基本'!P:P,MATCH(C32,'05基本'!C:C,0)) -> 932 | J32: =INDEX('05基本'!M:M,MATCH(C32,'05基本'!C:C,0)) -> 0 | K32: =INDEX('05月业务提成'!BO:BO,MATCH(C32,'05月业务提成'!B:B,0)) -> 5785.5861 | L32: =SUMIF(综合考核!A:A,'05月提成-武侯售后'!C32,综合考核!M:M) -> 0 | M32: =SUM(K32:L32) -> 5785.5861 | N32: =SUMIF(服装扣款!C:C,C32,服装扣款!N:N) -> 0 | O32: =M32-N32 -> 5785.5861 | P32: =SUMIF(超市公积金!C:C,'05月提成-武侯售后'!C32,超市公积金!I:I) -> 0 | Q32: =SUMIF(综合考核!A:A,'05月提成-武侯售后'!C32,综合考核!N:N) -> 0 | R32: =M32+I32+Q32 -> 6717.5861 | S32: =INDEX(AC:AC,MATCH(C32,AB:AB,0)) -> 33.7 | U32: =S32-T32 -> 33.7 | V32: =INDEX('05基本'!AF:AF,MATCH(C32,'05基本'!C:C,0)) -> 0 | W32: =O32-P32-U32 -> 5751.8861 | Y32: =SUM(Z32:AA32) -> 385.18137 | Z32: =INDEX('05月业务提成'!C:C,MATCH(C32,'05月业务提成'!B:B,0))*1 -> 219 | AA32: =INDEX('05月业务提成'!F:F,MATCH(C32,'05月业务提成'!B:B,0))*0.05*2%+INDEX('05月业务提成'!J:J,MATCH(C32,'05月业务提成'!B:B,0))*0.05*1.6%+(INDEX('05月业务提成'!P:P,MATCH(C32,'05月业务提成'!B:B,0))/0.95)*0.05++(INDEX('05月业务提成'!V:V,MATCH(C32,'05月业务提成'!B:B,0))/0.95)*0.05+(INDEX('05月业务提成'!Z:Z,MATCH(C32,'05月业务提成'!B:B,0))/0.95)*0.05 -> 166.18137 | AB32: 王毅 | AC32: 125.15 | AD32: =COUNTIF(C:C,C32) -> 1 | AE32: =INDEX('05基本'!P:P,MATCH(C32,'05基本'!C:C,0))-I32 -> 0 | AF32: =SUMIF('05月其他部门提成'!C:C,'05月提成-武侯售后'!C32,'05月其他部门提成'!Q:Q) -> 0 | AG32: =SUMIF('05月车间提成'!C:C,'05月提成-武侯售后'!C32,'05月车间提成'!W:W) -> 0 | AH32: =SUMIF('05月业务提成'!B:B,'05月提成-武侯售后'!C32,'05月业务提成'!BO:BO) -> 5785.5861 | AI32: =AF32+AG32+AH32 -> 5785.5861 | AJ32: =AI32-K32 -> 0
A33: =A32+1 -> 25 | C33: 黄小炼 | D33: =INDEX('05基本'!I:I,MATCH(C33,'05基本'!C:C,0))+INDEX('05基本'!J:J,MATCH(C33,'05基本'!C:C,0)) -> 32 | E33: =INDEX('05基本'!AA:AA,MATCH(C33,'05基本'!C:C,0)) -> 1268.59 | F33: =INDEX('05基本'!AB:AB,MATCH(C33,'05基本'!C:C,0)) -> 477.15 | G33: =INDEX('05基本'!AC:AC,MATCH(C33,'05基本'!C:C,0)) -> 117 | H33: =INDEX('05基本'!K:K,MATCH(C33,'05基本'!C:C,0))+INDEX('05基本'!L:L,MATCH(C33,'05基本'!C:C,0)) -> 0 | I33: =INDEX('05基本'!P:P,MATCH(C33,'05基本'!C:C,0)) -> 932 | J33: =INDEX('05基本'!M:M,MATCH(C33,'05基本'!C:C,0)) -> 0 | K33: =INDEX('05月业务提成'!BO:BO,MATCH(C33,'05月业务提成'!B:B,0)) -> 8400.5975 | L33: =SUMIF(综合考核!A:A,'05月提成-武侯售后'!C33,综合考核!M:M) -> 0 | M33: =SUM(K33:L33) -> 8400.5975 | N33: =SUMIF(服装扣款!C:C,C33,服装扣款!N:N) -> 0 | O33: =M33-N33 -> 8400.5975 | P33: =SUMIF(超市公积金!C:C,'05月提成-武侯售后'!C33,超市公积金!I:I) -> 0 | Q33: =SUMIF(综合考核!A:A,'05月提成-武侯售后'!C33,综合考核!N:N) -> 0 | R33: =M33+I33+Q33 -> 9332.5975 | S33: =INDEX(AC:AC,MATCH(C33,AB:AB,0)) -> 22.15 | U33: =S33-T33 -> 22.15 | V33: =INDEX('05基本'!AF:AF,MATCH(C33,'05基本'!C:C,0)) -> 0 | W33: =O33-P33-U33 -> 8378.4475 | Y33: =SUM(Z33:AA33) -> 509.28303 | Z33: =INDEX('05月业务提成'!C:C,MATCH(C33,'05月业务提成'!B:B,0))*1 -> 292 | AA33: =INDEX('05月业务提成'!F:F,MATCH(C33,'05月业务提成'!B:B,0))*0.05*2%+INDEX('05月业务提成'!J:J,MATCH(C33,'05月业务提成'!B:B,0))*0.05*1.6%+(INDEX('05月业务提成'!P:P,MATCH(C33,'05月业务提成'!B:B,0))/0.95)*0.05++(INDEX('05月业务提成'!V:V,MATCH(C33,'05月业务提成'!B:B,0))/0.95)*0.05+(INDEX('05月业务提成'!Z:Z,MATCH(C33,'05月业务提成'!B:B,0))/0.95)*0.05 -> 217.28303 | AB33: 李国民 | AC33: 0 | AD33: =COUNTIF(C:C,C33) -> 1 | AE33: =INDEX('05基本'!P:P,MATCH(C33,'05基本'!C:C,0))-I33 -> 0 | AF33: =SUMIF('05月其他部门提成'!C:C,'05月提成-武侯售后'!C33,'05月其他部门提成'!Q:Q) -> 0 | AG33: =SUMIF('05月车间提成'!C:C,'05月提成-武侯售后'!C33,'05月车间提成'!W:W) -> 0 | AH33: =SUMIF('05月业务提成'!B:B,'05月提成-武侯售后'!C33,'05月业务提成'!BO:BO) -> 8400.5975 | AI33: =AF33+AG33+AH33 -> 8400.5975 | AJ33: =AI33-K33 -> 0
A34: =A33+1 -> 26 | C34: 陈昱良 | D34: =INDEX('05基本'!I:I,MATCH(C34,'05基本'!C:C,0))+INDEX('05基本'!J:J,MATCH(C34,'05基本'!C:C,0)) -> 0 | E34: =INDEX('05基本'!AA:AA,MATCH(C34,'05基本'!C:C,0)) -> 1268.59 | F34: =INDEX('05基本'!AB:AB,MATCH(C34,'05基本'!C:C,0)) -> 477.15 | G34: =INDEX('05基本'!AC:AC,MATCH(C34,'05基本'!C:C,0)) -> 117 | H34: =INDEX('05基本'!K:K,MATCH(C34,'05基本'!C:C,0))+INDEX('05基本'!L:L,MATCH(C34,'05基本'!C:C,0)) -> 0 | I34: =INDEX('05基本'!P:P,MATCH(C34,'05基本'!C:C,0)) -> 900 | J34: =INDEX('05基本'!M:M,MATCH(C34,'05基本'!C:C,0)) -> 0 | K34: =INDEX('05月业务提成'!BO:BO,MATCH(C34,'05月业务提成'!B:B,0)) -> 6015.3249 | L34: =SUMIF(综合考核!A:A,'05月提成-武侯售后'!C34,综合考核!M:M) -> 350 | M34: =SUM(K34:L34) -> 6365.3249 | N34: =SUMIF(服装扣款!C:C,C34,服装扣款!N:N) -> 0 | O34: =M34-N34 -> 6365.3249 | P34: =SUMIF(超市公积金!C:C,'05月提成-武侯售后'!C34,超市公积金!I:I) -> 0 | Q34: =SUMIF(综合考核!A:A,'05月提成-武侯售后'!C34,综合考核!N:N) -> 0 | R34: =M34+I34+Q34 -> 7265.3249 | S34: =INDEX(AC:AC,MATCH(C34,AB:AB,0)) -> 50.13 | U34: =S34-T34 -> 50.13 | V34: =INDEX('05基本'!AF:AF,MATCH(C34,'05基本'!C:C,0)) -> 0 | W34: =O34-P34-U34 -> 6315.1949 | Y34: =SUM(Z34:AA34) -> 409.12236 | Z34: =INDEX('05月业务提成'!C:C,MATCH(C34,'05月业务提成'!B:B,0))*1 -> 78 | AA34: =INDEX('05月业务提成'!F:F,MATCH(C34,'05月业务提成'!B:B,0))*0.05*2%+INDEX('05月业务提成'!J:J,MATCH(C34,'05月业务提成'!B:B,0))*0.05*1.6%+(INDEX('05月业务提成'!P:P,MATCH(C34,'05月业务提成'!B:B,0))/0.95)*0.05++(INDEX('05月业务提成'!V:V,MATCH(C34,'05月业务提成'!B:B,0))/0.95)*0.05+(INDEX('05月业务提成'!Z:Z,MATCH(C34,'05月业务提成'!B:B,0))/0.95)*0.05 -> 331.12236 | AB34: 金亮亮 | AC34: 1024.74 | AD34: =COUNTIF(C:C,C34) -> 1 | AE34: =INDEX('05基本'!P:P,MATCH(C34,'05基本'!C:C,0))-I34 -> 0 | AF34: =SUMIF('05月其他部门提成'!C:C,'05月提成-武侯售后'!C34,'05月其他部门提成'!Q:Q) -> 0 | AG34: =SUMIF('05月车间提成'!C:C,'05月提成-武侯售后'!C34,'05月车间提成'!W:W) -> 0 | AH34: =SUMIF('05月业务提成'!B:B,'05月提成-武侯售后'!C34,'05月业务提成'!BO:BO) -> 6015.3249 | AI34: =AF34+AG34+AH34 -> 6015.3249 | AJ34: =AI34-K34 -> 0
A35: =A34+1 -> 27 | C35: 张林 | D35: =INDEX('05基本'!I:I,MATCH(C35,'05基本'!C:C,0))+INDEX('05基本'!J:J,MATCH(C35,'05基本'!C:C,0)) -> 32 | E35: =INDEX('05基本'!AA:AA,MATCH(C35,'05基本'!C:C,0)) -> 1268.59 | F35: =INDEX('05基本'!AB:AB,MATCH(C35,'05基本'!C:C,0)) -> 477.15 | G35: =INDEX('05基本'!AC:AC,MATCH(C35,'05基本'!C:C,0)) -> 117 | H35: =INDEX('05基本'!K:K,MATCH(C35,'05基本'!C:C,0))+INDEX('05基本'!L:L,MATCH(C35,'05基本'!C:C,0)) -> 0 | I35: =INDEX('05基本'!P:P,MATCH(C35,'05基本'!C:C,0)) -> 932 | J35: =INDEX('05基本'!M:M,MATCH(C35,'05基本'!C:C,0)) -> 0 | K35: =INDEX('05月业务提成'!BO:BO,MATCH(C35,'05月业务提成'!B:B,0)) -> 6591.5185 | L35: =SUMIF(综合考核!A:A,'05月提成-武侯售后'!C35,综合考核!M:M) -> 0 | M35: =SUM(K35:L35) -> 6591.5185 | N35: =SUMIF(服装扣款!C:C,C35,服装扣款!N:N) -> 0 | O35: =M35-N35 -> 6591.5185 | P35: =SUMIF(超市公积金!C:C,'05月提成-武侯售后'!C35,超市公积金!I:I) -> 0 | Q35: =SUMIF(综合考核!A:A,'05月提成-武侯售后'!C35,综合考核!N:N) -> 300 | R35: =M35+I35+Q35 -> 7823.5185 | S35: =INDEX(AC:AC,MATCH(C35,AB:AB,0)) -> 66.88 | U35: =S35-T35 -> 66.88 | V35: =INDEX('05基本'!AF:AF,MATCH(C35,'05基本'!C:C,0)) -> 0 | W35: =O35-P35-U35 -> 6524.6385 | Y35: =SUM(Z35:AA35) -> 439.35519 | Z35: =INDEX('05月业务提成'!C:C,MATCH(C35,'05月业务提成'!B:B,0))*1 -> 250 | AA35: =INDEX('05月业务提成'!F:F,MATCH(C35,'05月业务提成'!B:B,0))*0.05*2%+INDEX('05月业务提成'!J:J,MATCH(C35,'05月业务提成'!B:B,0))*0.05*1.6%+(INDEX('05月业务提成'!P:P,MATCH(C35,'05月业务提成'!B:B,0))/0.95)*0.05++(INDEX('05月业务提成'!V:V,MATCH(C35,'05月业务提成'!B:B,0))/0.95)*0.05+(INDEX('05月业务提成'!Z:Z,MATCH(C35,'05月业务提成'!B:B,0))/0.95)*0.05 -> 189.35519 | AB35: 应文龙 | AC35: 55.55 | AD35: =COUNTIF(C:C,C35) -> 1 | AE35: =INDEX('05基本'!P:P,MATCH(C35,'05基本'!C:C,0))-I35 -> 0 | AF35: =SUMIF('05月其他部门提成'!C:C,'05月提成-武侯售后'!C35,'05月其他部门提成'!Q:Q) -> 0 | AG35: =SUMIF('05月车间提成'!C:C,'05月提成-武侯售后'!C35,'05月车间提成'!W:W) -> 0 | AH35: =SUMIF('05月业务提成'!B:B,'05月提成-武侯售后'!C35,'05月业务提成'!BO:BO) -> 6591.5185 | AI35: =AF35+AG35+AH35 -> 6591.5185 | AJ35: =AI35-K35 -> 0
A36: =A35+1 -> 28 | C36: 王毅 | D36: =INDEX('05基本'!I:I,MATCH(C36,'05基本'!C:C,0))+INDEX('05基本'!J:J,MATCH(C36,'05基本'!C:C,0)) -> 24 | E36: =INDEX('05基本'!AA:AA,MATCH(C36,'05基本'!C:C,0)) -> 1268.59 | F36: =INDEX('05基本'!AB:AB,MATCH(C36,'05基本'!C:C,0)) -> 477.15 | G36: =INDEX('05基本'!AC:AC,MATCH(C36,'05基本'!C:C,0)) -> 117 | H36: =INDEX('05基本'!K:K,MATCH(C36,'05基本'!C:C,0))+INDEX('05基本'!L:L,MATCH(C36,'05基本'!C:C,0)) -> 0 | I36: =INDEX('05基本'!P:P,MATCH(C36,'05基本'!C:C,0)) -> 924 | J36: =INDEX('05基本'!M:M,MATCH(C36,'05基本'!C:C,0)) -> 0 | K36: =INDEX('05月业务提成'!BO:BO,MATCH(C36,'05月业务提成'!B:B,0)) -> 8841.9309 | L36: =SUMIF(综合考核!A:A,'05月提成-武侯售后'!C36,综合考核!M:M) -> 0 | M36: =SUM(K36:L36) -> 8841.9309 | N36: =SUMIF(服装扣款!C:C,C36,服装扣款!N:N) -> 0 | O36: =M36-N36 -> 8841.9309 | P36: =SUMIF(超市公积金!C:C,'05月提成-武侯售后'!C36,超市公积金!I:I) -> 0 | Q36: =SUMIF(综合考核!A:A,'05月提成-武侯售后'!C36,综合考核!N:N) -> 0 | R36: =M36+I36+Q36 -> 9765.9309 | S36: =INDEX(AC:AC,MATCH(C36,AB:AB,0)) -> 125.15 | U36: =S36-T36 -> 125.15 | V36: =INDEX('05基本'!AF:AF,MATCH(C36,'05基本'!C:C,0)) -> 0 | W36: =O36-P36-U36 -> 8716.7809 | Y36: =SUM(Z36:AA36) -> 577.93163 | Z36: =INDEX('05月业务提成'!C:C,MATCH(C36,'05月业务提成'!B:B,0))*1 -> 319 | AA36: =INDEX('05月业务提成'!F:F,MATCH(C36,'05月业务提成'!B:B,0))*0.05*2%+INDEX('05月业务提成'!J:J,MATCH(C36,'05月业务提成'!B:B,0))*0.05*1.6%+(INDEX('05月业务提成'!P:P,MATCH(C36,'05月业务提成'!B:B,0))/0.95)*0.05++(INDEX('05月业务提成'!V:V,MATCH(C36,'05月业务提成'!B:B,0))/0.95)*0.05+(INDEX('05月业务提成'!Z:Z,MATCH(C36,'05月业务提成'!B:B,0))/0.95)*0.05 -> 258.93163 | AB36: 曾浩 | AC36: 145.59 | AD36: =COUNTIF(C:C,C36) -> 1 | AE36: =INDEX('05基本'!P:P,MATCH(C36,'05基本'!C:C,0))-I36 -> 0 | AF36: =SUMIF('05月其他部门提成'!C:C,'05月提成-武侯售后'!C36,'05月其他部门提成'!Q:Q) -> 0 | AG36: =SUMIF('05月车间提成'!C:C,'05月提成-武侯售后'!C36,'05月车间提成'!W:W) -> 0 | AH36: =SUMIF('05月业务提成'!B:B,'05月提成-武侯售后'!C36,'05月业务提成'!BO:BO) -> 8841.9309 | AI36: =AF36+AG36+AH36 -> 8841.9309 | AJ36: =AI36-K36 -> 0
A37: =A36+1 -> 29 | C37: 李国民 | D37: =INDEX('05基本'!I:I,MATCH(C37,'05基本'!C:C,0))+INDEX('05基本'!J:J,MATCH(C37,'05基本'!C:C,0)) -> 0 | E37: =INDEX('05基本'!AA:AA,MATCH(C37,'05基本'!C:C,0)) -> 1268.59 | F37: =INDEX('05基本'!AB:AB,MATCH(C37,'05基本'!C:C,0)) -> 477.15 | G37: =INDEX('05基本'!AC:AC,MATCH(C37,'05基本'!C:C,0)) -> 117 | H37: =INDEX('05基本'!K:K,MATCH(C37,'05基本'!C:C,0))+INDEX('05基本'!L:L,MATCH(C37,'05基本'!C:C,0)) -> 0 | I37: =INDEX('05基本'!P:P,MATCH(C37,'05基本'!C:C,0)) -> 900 | J37: =INDEX('05基本'!M:M,MATCH(C37,'05基本'!C:C,0)) -> 0 | K37: =INDEX('05月业务提成'!BO:BO,MATCH(C37,'05月业务提成'!B:B,0)) -> 3393.3366 | L37: =SUMIF(综合考核!A:A,'05月提成-武侯售后'!C37,综合考核!M:M) -> 190 | M37: =SUM(K37:L37) -> 3583.3366 | N37: =SUMIF(服装扣款!C:C,C37,服装扣款!N:N) -> 0 | O37: =M37-N37 -> 3583.3366 | P37: =SUMIF(超市公积金!C:C,'05月提成-武侯售后'!C37,超市公积金!I:I) -> 0 | Q37: =SUMIF(综合考核!A:A,'05月提成-武侯售后'!C37,综合考核!N:N) -> 0 | R37: =M37+I37+Q37 -> 4483.3366 | S37: =INDEX(AC:AC,MATCH(C37,AB:AB,0)) -> 0 | U37: =S37-T37 -> 0 | V37: =INDEX('05基本'!AF:AF,MATCH(C37,'05基本'!C:C,0)) -> 0 | W37: =O37-P37-U37 -> 3583.3366 | Y37: =SUM(Z37:AA37) -> 252.59667 | Z37: =INDEX('05月业务提成'!C:C,MATCH(C37,'05月业务提成'!B:B,0))*1 -> 46 | AA37: =INDEX('05月业务提成'!F:F,MATCH(C37,'05月业务提成'!B:B,0))*0.05*2%+INDEX('05月业务提成'!J:J,MATCH(C37,'05月业务提成'!B:B,0))*0.05*1.6%+(INDEX('05月业务提成'!P:P,MATCH(C37,'05月业务提成'!B:B,0))/0.95)*0.05++(INDEX('05月业务提成'!V:V,MATCH(C37,'05月业务提成'!B:B,0))/0.95)*0.05+(INDEX('05月业务提成'!Z:Z,MATCH(C37,'05月业务提成'!B:B,0))/0.95)*0.05 -> 206.59667 | AB37: 刘强 | AC37: 64.78 | AD37: =COUNTIF(C:C,C37) -> 1 | AE37: =INDEX('05基本'!P:P,MATCH(C37,'05基本'!C:C,0))-I37 -> 0 | AF37: =SUMIF('05月其他部门提成'!C:C,'05月提成-武侯售后'!C37,'05月其他部门提成'!Q:Q) -> 0 | AG37: =SUMIF('05月车间提成'!C:C,'05月提成-武侯售后'!C37,'05月车间提成'!W:W) -> 0 | AH37: =SUMIF('05月业务提成'!B:B,'05月提成-武侯售后'!C37,'05月业务提成'!BO:BO) -> 3393.3366 | AI37: =AF37+AG37+AH37 -> 3393.3366 | AJ37: =AI37-K37 -> 0
A38: =A37+1 -> 30 | C38: 金亮亮 | D38: =INDEX('05基本'!I:I,MATCH(C38,'05基本'!C:C,0))+INDEX('05基本'!J:J,MATCH(C38,'05基本'!C:C,0)) -> 0 | E38: =INDEX('05基本'!AA:AA,MATCH(C38,'05基本'!C:C,0)) -> 1268.59 | F38: =INDEX('05基本'!AB:AB,MATCH(C38,'05基本'!C:C,0)) -> 477.15 | G38: =INDEX('05基本'!AC:AC,MATCH(C38,'05基本'!C:C,0)) -> 117 | H38: =INDEX('05基本'!K:K,MATCH(C38,'05基本'!C:C,0))+INDEX('05基本'!L:L,MATCH(C38,'05基本'!C:C,0)) -> 0 | I38: =INDEX('05基本'!P:P,MATCH(C38,'05基本'!C:C,0)) -> 900 | J38: =INDEX('05基本'!M:M,MATCH(C38,'05基本'!C:C,0)) -> 0 | K38: =INDEX('05月业务提成'!BO:BO,MATCH(C38,'05月业务提成'!B:B,0)) -> 14651.612 | L38: =SUMIF(综合考核!A:A,'05月提成-武侯售后'!C38,综合考核!M:M) -> 290 | M38: =SUM(K38:L38) -> 14941.612 | N38: =SUMIF(服装扣款!C:C,C38,服装扣款!N:N) -> 0 | O38: =M38-N38 -> 14941.612 | P38: =SUMIF(超市公积金!C:C,'05月提成-武侯售后'!C38,超市公积金!I:I) -> 0 | Q38: =SUMIF(综合考核!A:A,'05月提成-武侯售后'!C38,综合考核!N:N) -> 0 | R38: =M38+I38+Q38 -> 15841.612 | S38: =INDEX(AC:AC,MATCH(C38,AB:AB,0)) -> 1024.74 | U38: =S38-T38 -> 1024.74 | V38: =INDEX('05基本'!AF:AF,MATCH(C38,'05基本'!C:C,0)) -> 0 | W38: =O38-P38-U38 -> 13916.872 | Y38: =SUM(Z38:AA38) -> 864.15855 | Z38: =INDEX('05月业务提成'!C:C,MATCH(C38,'05月业务提成'!B:B,0))*1 -> 83 | AA38: =INDEX('05月业务提成'!F:F,MATCH(C38,'05月业务提成'!B:B,0))*0.05*2%+INDEX('05月业务提成'!J:J,MATCH(C38,'05月业务提成'!B:B,0))*0.05*1.6%+(INDEX('05月业务提成'!P:P,MATCH(C38,'05月业务提成'!B:B,0))/0.95)*0.05++(INDEX('05月业务提成'!V:V,MATCH(C38,'05月业务提成'!B:B,0))/0.95)*0.05+(INDEX('05月业务提成'!Z:Z,MATCH(C38,'05月业务提成'!B:B,0))/0.95)*0.05 -> 781.15855 | AB38: 辜晓菲 | AC38: 214.65 | AD38: =COUNTIF(C:C,C38) -> 1 | AE38: =INDEX('05基本'!P:P,MATCH(C38,'05基本'!C:C,0))-I38 -> 0 | AF38: =SUMIF('05月其他部门提成'!C:C,'05月提成-武侯售后'!C38,'05月其他部门提成'!Q:Q) -> 0 | AG38: =SUMIF('05月车间提成'!C:C,'05月提成-武侯售后'!C38,'05月车间提成'!W:W) -> 0 | AH38: =SUMIF('05月业务提成'!B:B,'05月提成-武侯售后'!C38,'05月业务提成'!BO:BO) -> 14651.612 | AI38: =AF38+AG38+AH38 -> 14651.612 | AJ38: =AI38-K38 -> 0
A39: =A38+1 -> 31 | C39: 应文龙 | D39: =INDEX('05基本'!I:I,MATCH(C39,'05基本'!C:C,0))+INDEX('05基本'!J:J,MATCH(C39,'05基本'!C:C,0)) -> 0 | E39: =INDEX('05基本'!AA:AA,MATCH(C39,'05基本'!C:C,0)) -> 1268.59 | F39: =INDEX('05基本'!AB:AB,MATCH(C39,'05基本'!C:C,0)) -> 477.15 | G39: =INDEX('05基本'!AC:AC,MATCH(C39,'05基本'!C:C,0)) -> 117 | H39: =INDEX('05基本'!K:K,MATCH(C39,'05基本'!C:C,0))+INDEX('05基本'!L:L,MATCH(C39,'05基本'!C:C,0)) -> 0 | I39: =INDEX('05基本'!P:P,MATCH(C39,'05基本'!C:C,0)) -> 900 | J39: =INDEX('05基本'!M:M,MATCH(C39,'05基本'!C:C,0)) -> 0 | K39: =INDEX('05月业务提成'!BO:BO,MATCH(C39,'05月业务提成'!B:B,0)) -> 6275.8371 | L39: =SUMIF(综合考核!A:A,'05月提成-武侯售后'!C39,综合考核!M:M) -> 270 | M39: =SUM(K39:L39) -> 6545.8371 | N39: =SUMIF(服装扣款!C:C,C39,服装扣款!N:N) -> 0 | O39: =M39-N39 -> 6545.8371 | P39: =SUMIF(超市公积金!C:C,'05月提成-武侯售后'!C39,超市公积金!I:I) -> 0 | Q39: =SUMIF(综合考核!A:A,'05月提成-武侯售后'!C39,综合考核!N:N) -> 0 | R39: =M39+I39+Q39 -> 7445.8371 | S39: =INDEX(AC:AC,MATCH(C39,AB:AB,0)) -> 55.55 | U39: =S39-T39 -> 55.55 | V39: =INDEX('05基本'!AF:AF,MATCH(C39,'05基本'!C:C,0)) -> 0 | W39: =O39-P39-U39 -> 6490.287 | Y39: =SUM(Z39:AA39) -> 366.20195 | Z39: =INDEX('05月业务提成'!C:C,MATCH(C39,'05月业务提成'!B:B,0))*1 -> 62 | AA39: =INDEX('05月业务提成'!F:F,MATCH(C39,'05月业务提成'!B:B,0))*0.05*2%+INDEX('05月业务提成'!J:J,MATCH(C39,'05月业务提成'!B:B,0))*0.05*1.6%+(INDEX('05月业务提成'!P:P,MATCH(C39,'05月业务提成'!B:B,0))/0.95)*0.05++(INDEX('05月业务提成'!V:V,MATCH(C39,'05月业务提成'!B:B,0))/0.95)*0.05+(INDEX('05月业务提成'!Z:Z,MATCH(C39,'05月业务提成'!B:B,0))/0.95)*0.05 -> 304.20195 | AB39: 李超 | AC39: 1566.17 | AD39: =COUNTIF(C:C,C39) -> 1 | AE39: =INDEX('05基本'!P:P,MATCH(C39,'05基本'!C:C,0))-I39 -> 0 | AF39: =SUMIF('05月其他部门提成'!C:C,'05月提成-武侯售后'!C39,'05月其他部门提成'!Q:Q) -> 0 | AG39: =SUMIF('05月车间提成'!C:C,'05月提成-武侯售后'!C39,'05月车间提成'!W:W) -> 0 | AH39: =SUMIF('05月业务提成'!B:B,'05月提成-武侯售后'!C39,'05月业务提成'!BO:BO) -> 6275.8371 | AI39: =AF39+AG39+AH39 -> 6275.8371 | AJ39: =AI39-K39 -> 0
A40: =A39+1 -> 32 | C40: 曾浩 | D40: =INDEX('05基本'!I:I,MATCH(C40,'05基本'!C:C,0))+INDEX('05基本'!J:J,MATCH(C40,'05基本'!C:C,0)) -> 0 | E40: =INDEX('05基本'!AA:AA,MATCH(C40,'05基本'!C:C,0)) -> 1268.59 | F40: =INDEX('05基本'!AB:AB,MATCH(C40,'05基本'!C:C,0)) -> 477.15 | G40: =INDEX('05基本'!AC:AC,MATCH(C40,'05基本'!C:C,0)) -> 117 | H40: =INDEX('05基本'!K:K,MATCH(C40,'05基本'!C:C,0))+INDEX('05基本'!L:L,MATCH(C40,'05基本'!C:C,0)) -> 0 | I40: =INDEX('05基本'!P:P,MATCH(C40,'05基本'!C:C,0)) -> 900 | J40: =INDEX('05基本'!M:M,MATCH(C40,'05基本'!C:C,0)) -> 0 | K40: =INDEX('05月业务提成'!BO:BO,MATCH(C40,'05月业务提成'!B:B,0)) -> 9277.3472 | L40: =SUMIF(综合考核!A:A,'05月提成-武侯售后'!C40,综合考核!M:M) -> 270 | M40: =SUM(K40:L40) -> 9547.3472 | N40: =SUMIF(服装扣款!C:C,C40,服装扣款!N:N) -> 0 | O40: =M40-N40 -> 9547.3472 | P40: =SUMIF(超市公积金!C:C,'05月提成-武侯售后'!C40,超市公积金!I:I) -> 0 | Q40: =SUMIF(综合考核!A:A,'05月提成-武侯售后'!C40,综合考核!N:N) -> 0 | R40: =M40+I40+Q40 -> 10447.347 | S40: =INDEX(AC:AC,MATCH(C40,AB:AB,0)) -> 145.59 | U40: =S40-T40 -> 145.59 | V40: =INDEX('05基本'!AF:AF,MATCH(C40,'05基本'!C:C,0)) -> 0 | W40: =O40-P40-U40 -> 9401.7572 | Y40: =SUM(Z40:AA40) -> 591.2288 | Z40: =INDEX('05月业务提成'!C:C,MATCH(C40,'05月业务提成'!B:B,0))*1 -> 96 | AA40: =INDEX('05月业务提成'!F:F,MATCH(C40,'05月业务提成'!B:B,0))*0.05*2%+INDEX('05月业务提成'!J:J,MATCH(C40,'05月业务提成'!B:B,0))*0.05*1.6%+(INDEX('05月业务提成'!P:P,MATCH(C40,'05月业务提成'!B:B,0))/0.95)*0.05++(INDEX('05月业务提成'!V:V,MATCH(C40,'05月业务提成'!B:B,0))/0.95)*0.05+(INDEX('05月业务提成'!Z:Z,MATCH(C40,'05月业务提成'!B:B,0))/0.95)*0.05 -> 495.2288 | AB40: 黄意轩 | AC40: 188.28 | AD40: =COUNTIF(C:C,C40) -> 1 | AE40: =INDEX('05基本'!P:P,MATCH(C40,'05基本'!C:C,0))-I40 -> 0 | AF40: =SUMIF('05月其他部门提成'!C:C,'05月提成-武侯售后'!C40,'05月其他部门提成'!Q:Q) -> 0 | AG40: =SUMIF('05月车间提成'!C:C,'05月提成-武侯售后'!C40,'05月车间提成'!W:W) -> 0 | AH40: =SUMIF('05月业务提成'!B:B,'05月提成-武侯售后'!C40,'05月业务提成'!BO:BO) -> 9277.3472 | AI40: =AF40+AG40+AH40 -> 9277.3472 | AJ40: =AI40-K40 -> 0
A41: =A40+1 -> 33 | C41: 刘强 | D41: =INDEX('05基本'!I:I,MATCH(C41,'05基本'!C:C,0))+INDEX('05基本'!J:J,MATCH(C41,'05基本'!C:C,0)) -> 32 | E41: =INDEX('05基本'!AA:AA,MATCH(C41,'05基本'!C:C,0)) -> 1268.59 | F41: =INDEX('05基本'!AB:AB,MATCH(C41,'05基本'!C:C,0)) -> 477.15 | G41: =INDEX('05基本'!AC:AC,MATCH(C41,'05基本'!C:C,0)) -> 117 | H41: =INDEX('05基本'!K:K,MATCH(C41,'05基本'!C:C,0))+INDEX('05基本'!L:L,MATCH(C41,'05基本'!C:C,0)) -> 0 | I41: =INDEX('05基本'!P:P,MATCH(C41,'05基本'!C:C,0)) -> 932 | J41: =INDEX('05基本'!M:M,MATCH(C41,'05基本'!C:C,0)) -> 0 | K41: =INDEX('05月业务提成'!BO:BO,MATCH(C41,'05月业务提成'!B:B,0)) -> 6821.4486 | L41: =SUMIF(综合考核!A:A,'05月提成-武侯售后'!C41,综合考核!M:M) -> 0 | M41: =SUM(K41:L41) -> 6821.4486 | N41: =SUMIF(服装扣款!C:C,C41,服装扣款!N:N) -> 0 | O41: =M41-N41 -> 6821.4486 | P41: =SUMIF(超市公积金!C:C,'05月提成-武侯售后'!C41,超市公积金!I:I) -> 0 | Q41: =SUMIF(综合考核!A:A,'05月提成-武侯售后'!C41,综合考核!N:N) -> 0 | R41: =M41+I41+Q41 -> 7753.4486 | S41: =INDEX(AC:AC,MATCH(C41,AB:AB,0)) -> 64.78 | U41: =S41-T41 -> 64.78 | V41: =INDEX('05基本'!AF:AF,MATCH(C41,'05基本'!C:C,0)) -> 0 | W41: =O41-P41-U41 -> 6756.6686 | Y41: =SUM(Z41:AA41) -> 435.41309 | Z41: =INDEX('05月业务提成'!C:C,MATCH(C41,'05月业务提成'!B:B,0))*1 -> 264 | AA41: =INDEX('05月业务提成'!F:F,MATCH(C41,'05月业务提成'!B:B,0))*0.05*2%+INDEX('05月业务提成'!J:J,MATCH(C41,'05月业务提成'!B:B,0))*0.05*1.6%+(INDEX('05月业务提成'!P:P,MATCH(C41,'05月业务提成'!B:B,0))/0.95)*0.05++(INDEX('05月业务提成'!V:V,MATCH(C41,'05月业务提成'!B:B,0))/0.95)*0.05+(INDEX('05月业务提成'!Z:Z,MATCH(C41,'05月业务提成'!B:B,0))/0.95)*0.05 -> 171.41308 | AB41: 唐芳兰 | AC41: 83.72 | AD41: =COUNTIF(C:C,C41) -> 1 | AE41: =INDEX('05基本'!P:P,MATCH(C41,'05基本'!C:C,0))-I41 -> 0 | AF41: =SUMIF('05月其他部门提成'!C:C,'05月提成-武侯售后'!C41,'05月其他部门提成'!Q:Q) -> 0 | AG41: =SUMIF('05月车间提成'!C:C,'05月提成-武侯售后'!C41,'05月车间提成'!W:W) -> 0 | AH41: =SUMIF('05月业务提成'!B:B,'05月提成-武侯售后'!C41,'05月业务提成'!BO:BO) -> 6821.4486 | AI41: =AF41+AG41+AH41 -> 6821.4486 | AJ41: =AI41-K41 -> 0
C42: 小计 | D42: =SUM(D27:D41) -> 248 | E42: =SUM(E27:E41) -> 19028.85 | F42: =SUM(F27:F41) -> 7157.25 | G42: =SUM(G27:G41) -> 1755 | H42: =SUM(H27:H41) -> 100 | I42: =SUM(I27:I41) -> 14548 | J42: =SUM(J27:J41) -> 0 | K42: =SUM(K27:K41) -> 111892.31 | ... AA42: =SUM(AA27:AA41) -> 4053.8206 | AB42: 赵水仙 | AC42: 0 | AD42: =COUNTIF(C:C,C42) -> 11 | AE42: =INDEX('05基本'!P:P,MATCH(C42,'05基本'!C:C,0))-I42 -> #N/A
A43: =A41+1 -> 34 | C43: 辜晓菲 | D43: =INDEX('05基本'!I:I,MATCH(C43,'05基本'!C:C,0))+INDEX('05基本'!J:J,MATCH(C43,'05基本'!C:C,0)) -> 0 | E43: =INDEX('05基本'!AA:AA,MATCH(C43,'05基本'!C:C,0)) -> 1268.59 | F43: =INDEX('05基本'!AB:AB,MATCH(C43,'05基本'!C:C,0)) -> 477.15 | G43: =INDEX('05基本'!AC:AC,MATCH(C43,'05基本'!C:C,0)) -> 117 | H43: =INDEX('05基本'!K:K,MATCH(C43,'05基本'!C:C,0))+INDEX('05基本'!L:L,MATCH(C43,'05基本'!C:C,0)) -> 0 | I43: =INDEX('05基本'!P:P,MATCH(C43,'05基本'!C:C,0)) -> 825 | J43: =INDEX('05基本'!M:M,MATCH(C43,'05基本'!C:C,0)) -> 0 | K43: =INDEX(保险专员5月外拓!I:I,MATCH(C43,保险专员5月外拓!A:A,0)) -> 11924.22 | L43: =SUMIF(综合考核!A:A,'05月提成-武侯售后'!C43,综合考核!M:M) -> 0 | M43: =SUM(K43:L43) -> 11924.22 | N43: =SUMIF(服装扣款!C:C,C43,服装扣款!N:N) -> 0 | O43: =M43-N43 -> 11924.22 | P43: =SUMIF(超市公积金!C:C,'05月提成-武侯售后'!C43,超市公积金!I:I) -> 0 | Q43: =SUMIF(综合考核!A:A,'05月提成-武侯售后'!C43,综合考核!N:N) -> 0 | R43: =M43+I43+Q43 -> 12749.22 | S43: =INDEX(AC:AC,MATCH(C43,AB:AB,0)) -> 214.65 | U43: =S43-T43 -> 214.65 | V43: =INDEX('05基本'!AF:AF,MATCH(C43,'05基本'!C:C,0)) -> 0 | W43: =O43-P43-U43 -> 11709.57 | Y43: =SUM(Z43:AA43) -> 671.0116 | Z43: =保险专员5月外拓!J22 -> 671.0116 | AB43: 张琴 | AC43: 1077.9 | AD43: =COUNTIF(C:C,C43) -> 1 | AE43: =INDEX('05基本'!P:P,MATCH(C43,'05基本'!C:C,0))-I43 -> 0 | AF43: =SUMIF('05月其他部门提成'!C:C,'05月提成-武侯售后'!C43,'05月其他部门提成'!Q:Q) -> 0 | AG43: =SUMIF('05月车间提成'!C:C,'05月提成-武侯售后'!C43,'05月车间提成'!W:W) -> 0 | AH43: =SUMIF('05月业务提成'!B:B,'05月提成-武侯售后'!C43,'05月业务提成'!BO:BO) -> 0 | AI43: =K43 -> 11924.22 | AJ43: =AI43-K43 -> 0
A44: =A43+1 -> 35 | C44: 李超 | D44: =INDEX('05基本'!I:I,MATCH(C44,'05基本'!C:C,0))+INDEX('05基本'!J:J,MATCH(C44,'05基本'!C:C,0)) -> 0 | E44: =INDEX('05基本'!AA:AA,MATCH(C44,'05基本'!C:C,0)) -> 1268.59 | F44: =INDEX('05基本'!AB:AB,MATCH(C44,'05基本'!C:C,0)) -> 477.15 | G44: =INDEX('05基本'!AC:AC,MATCH(C44,'05基本'!C:C,0)) -> 117 | H44: =INDEX('05基本'!K:K,MATCH(C44,'05基本'!C:C,0))+INDEX('05基本'!L:L,MATCH(C44,'05基本'!C:C,0)) -> 0 | I44: =INDEX('05基本'!P:P,MATCH(C44,'05基本'!C:C,0)) -> 900 | J44: =INDEX('05基本'!M:M,MATCH(C44,'05基本'!C:C,0)) -> 0 | K44: =INDEX(保险专员5月外拓!I:I,MATCH(C44,保险专员5月外拓!A:A,0)) -> 20355.84 | L44: =SUMIF(综合考核!A:A,'05月提成-武侯售后'!C44,综合考核!M:M) -> 0 | M44: =SUM(K44:L44) -> 20355.84 | N44: =SUMIF(服装扣款!C:C,C44,服装扣款!N:N) -> 0 | O44: =M44-N44 -> 20355.84 | P44: =SUMIF(超市公积金!C:C,'05月提成-武侯售后'!C44,超市公积金!I:I) -> 0 | Q44: =SUMIF(综合考核!A:A,'05月提成-武侯售后'!C44,综合考核!N:N) -> 0 | R44: =M44+I44+Q44 -> 21255.84 | S44: =INDEX(AC:AC,MATCH(C44,AB:AB,0)) -> 1566.17 | U44: =S44-T44 -> 1566.17 | V44: =INDEX('05基本'!AF:AF,MATCH(C44,'05基本'!C:C,0)) -> 0 | W44: =O44-P44-U44 -> 18789.67 | Y44: =SUM(Z44:AA44) -> 1118.7284 | Z44: =保险专员5月外拓!J20 -> 1118.7284 | AB44: 刘林 | AC44: 0 | AD44: =COUNTIF(C:C,C44) -> 1 | AE44: =INDEX('05基本'!P:P,MATCH(C44,'05基本'!C:C,0))-I44 -> 0 | AF44: =SUMIF('05月其他部门提成'!C:C,'05月提成-武侯售后'!C44,'05月其他部门提成'!Q:Q) -> 0 | AG44: =SUMIF('05月车间提成'!C:C,'05月提成-武侯售后'!C44,'05月车间提成'!W:W) -> 0 | AH44: =SUMIF('05月业务提成'!B:B,'05月提成-武侯售后'!C44,'05月业务提成'!BO:BO) -> 0 | AI44: =K44 -> 20355.84 | AJ44: =AI44-K44 -> 0
C45: 小计 | D45: =SUM(D43:D44) -> 0 | E45: =SUM(E43:E44) -> 2537.18 | F45: =SUM(F43:F44) -> 954.3 | G45: =SUM(G43:G44) -> 234 | H45: =SUM(H43:H44) -> 0 | I45: =SUM(I43:I44) -> 1725 | J45: =SUM(J43:J44) -> 0 | K45: =SUM(K43:K44) -> 32280.06 | ... AA45: =SUM(AA43:AA44) -> 0 | AB45: 鄢雨濛 | AC45: 0 | AD45: =COUNTIF(C:C,C45) -> 11 | AE45: =INDEX('05基本'!P:P,MATCH(C45,'05基本'!C:C,0))-I45 -> #N/A
A46: =A44+1 -> 36 | B46: 续保 | C46: 黄意轩 | D46: =INDEX('05基本'!I:I,MATCH(C46,'05基本'!C:C,0))+INDEX('05基本'!J:J,MATCH(C46,'05基本'!C:C,0)) -> 0 | E46: =INDEX('05基本'!AA:AA,MATCH(C46,'05基本'!C:C,0)) -> 1268.59 | F46: =INDEX('05基本'!AB:AB,MATCH(C46,'05基本'!C:C,0)) -> 477.15 | G46: =INDEX('05基本'!AC:AC,MATCH(C46,'05基本'!C:C,0)) -> 117 | H46: =INDEX('05基本'!K:K,MATCH(C46,'05基本'!C:C,0))+INDEX('05基本'!L:L,MATCH(C46,'05基本'!C:C,0)) -> 0 | I46: =INDEX('05基本'!P:P,MATCH(C46,'05基本'!C:C,0)) -> 2000 | J46: =INDEX('05基本'!M:M,MATCH(C46,'05基本'!C:C,0)) -> 0 | K46: =INDEX('05月其他部门提成'!Q:Q,MATCH(C46,'05月其他部门提成'!C:C,0)) -> 9870 | L46: =SUMIF(综合考核!A:A,'05月提成-武侯售后'!C46,综合考核!M:M) -> 0 | M46: =SUM(K46:L46) -> 9870 | N46: =SUMIF(服装扣款!C:C,C46,服装扣款!N:N) -> 0 | O46: =M46-N46 -> 9870 | P46: =SUMIF(超市公积金!C:C,'05月提成-武侯售后'!C46,超市公积金!I:I) -> 0 | Q46: =SUMIF(综合考核!A:A,'05月提成-武侯售后'!C46,综合考核!N:N) -> 0 | R46: =M46+I46+Q46 -> 11870 | S46: =INDEX(AC:AC,MATCH(C46,AB:AB,0)) -> 188.28 | U46: =S46-T46 -> 188.28 | V46: =INDEX('05基本'!AF:AF,MATCH(C46,'05基本'!C:C,0)) -> 0 | W46: =O46-P46-U46 -> 9681.72 | Y46: =SUM(Z46:AA46) -> 333.33 | Z46: 333.33 | AB46: 刘尧梅 | AC46: 0 | AD46: =COUNTIF(C:C,C46) -> 1 | AE46: =INDEX('05基本'!P:P,MATCH(C46,'05基本'!C:C,0))-I46 -> 0 | AF46: =SUMIF('05月其他部门提成'!C:C,'05月提成-武侯售后'!C46,'05月其他部门提成'!Q:Q) -> 9870 | AG46: =SUMIF('05月车间提成'!C:C,'05月提成-武侯售后'!C46,'05月车间提成'!W:W) -> 0 | AH46: =SUMIF('05月业务提成'!B:B,'05月提成-武侯售后'!C46,'05月业务提成'!BO:BO) -> 0 | AI46: =AF46+AG46+AH46 -> 9870 | AJ46: =AI46-K46 -> 0
A47: =A46+1 -> 37 | C47: 唐芳兰 | D47: =INDEX('05基本'!I:I,MATCH(C47,'05基本'!C:C,0))+INDEX('05基本'!J:J,MATCH(C47,'05基本'!C:C,0)) -> 0 | E47: =INDEX('05基本'!AA:AA,MATCH(C47,'05基本'!C:C,0)) -> 1268.59 | F47: =INDEX('05基本'!AB:AB,MATCH(C47,'05基本'!C:C,0)) -> 477.15 | G47: =INDEX('05基本'!AC:AC,MATCH(C47,'05基本'!C:C,0)) -> 117 | H47: =INDEX('05基本'!K:K,MATCH(C47,'05基本'!C:C,0))+INDEX('05基本'!L:L,MATCH(C47,'05基本'!C:C,0)) -> 0 | I47: =INDEX('05基本'!P:P,MATCH(C47,'05基本'!C:C,0)) -> 900 | J47: =INDEX('05基本'!M:M,MATCH(C47,'05基本'!C:C,0)) -> 0 | K47: =INDEX('05月其他部门提成'!Q:Q,MATCH(C47,'05月其他部门提成'!C:C,0)) -> 7485 | L47: =SUMIF(综合考核!A:A,'05月提成-武侯售后'!C47,综合考核!M:M) -> 0 | M47: =SUM(K47:L47) -> 7485 | N47: =SUMIF(服装扣款!C:C,C47,服装扣款!N:N) -> 0 | O47: =M47-N47 -> 7485 | P47: =SUMIF(超市公积金!C:C,'05月提成-武侯售后'!C47,超市公积金!I:I) -> 0 | Q47: =SUMIF(综合考核!A:A,'05月提成-武侯售后'!C47,综合考核!N:N) -> 0 | R47: =M47+I47+Q47 -> 8385 | S47: =INDEX(AC:AC,MATCH(C47,AB:AB,0)) -> 83.72 | U47: =S47-T47 -> 83.72 | V47: =INDEX('05基本'!AF:AF,MATCH(C47,'05基本'!C:C,0)) -> 0 | W47: =O47-P47-U47 -> 7401.28 | Y47: =SUM(Z47:AA47) -> 83.34 | Z47: 83.34 | AB47: 冯桢 | AC47: 0 | AD47: =COUNTIF(C:C,C47) -> 1 | AE47: =INDEX('05基本'!P:P,MATCH(C47,'05基本'!C:C,0))-I47 -> 0 | AF47: =SUMIF('05月其他部门提成'!C:C,'05月提成-武侯售后'!C47,'05月其他部门提成'!Q:Q) -> 7485 | AG47: =SUMIF('05月车间提成'!C:C,'05月提成-武侯售后'!C47,'05月车间提成'!W:W) -> 0 | AH47: =SUMIF('05月业务提成'!B:B,'05月提成-武侯售后'!C47,'05月业务提成'!BO:BO) -> 0 | AI47: =AF47+AG47+AH47 -> 7485 | AJ47: =AI47-K47 -> 0
A48: =A47+1 -> 38 | C48: 赵水仙 | D48: =INDEX('05基本'!I:I,MATCH(C48,'05基本'!C:C,0))+INDEX('05基本'!J:J,MATCH(C48,'05基本'!C:C,0)) -> 0 | E48: =INDEX('05基本'!AA:AA,MATCH(C48,'05基本'!C:C,0)) -> 1268.59 | F48: =INDEX('05基本'!AB:AB,MATCH(C48,'05基本'!C:C,0)) -> 477.15 | G48: =INDEX('05基本'!AC:AC,MATCH(C48,'05基本'!C:C,0)) -> 117 | H48: =INDEX('05基本'!K:K,MATCH(C48,'05基本'!C:C,0))+INDEX('05基本'!L:L,MATCH(C48,'05基本'!C:C,0)) -> 0 | I48: =INDEX('05基本'!P:P,MATCH(C48,'05基本'!C:C,0)) -> 885 | J48: =INDEX('05基本'!M:M,MATCH(C48,'05基本'!C:C,0)) -> 0 | K48: =INDEX('05月其他部门提成'!Q:Q,MATCH(C48,'05月其他部门提成'!C:C,0)) -> 5820 | L48: =SUMIF(综合考核!A:A,'05月提成-武侯售后'!C48,综合考核!M:M) -> 0 | M48: =SUM(K48:L48) -> 5820 | N48: =SUMIF(服装扣款!C:C,C48,服装扣款!N:N) -> 0 | O48: =M48-N48 -> 5820 | P48: =SUMIF(超市公积金!C:C,'05月提成-武侯售后'!C48,超市公积金!I:I) -> 0 | Q48: =SUMIF(综合考核!A:A,'05月提成-武侯售后'!C48,综合考核!N:N) -> 0 | R48: =M48+I48+Q48 -> 6705 | S48: =INDEX(AC:AC,MATCH(C48,AB:AB,0)) -> 0 | U48: =S48-T48 -> 0 | V48: =INDEX('05基本'!AF:AF,MATCH(C48,'05基本'!C:C,0)) -> 0 | W48: =O48-P48-U48 -> 5820 | Y48: =SUM(Z48:AA48) -> 83.34 | Z48: 83.34 | AB48: 高梓绮 | AC48: 0 | AD48: =COUNTIF(C:C,C48) -> 1 | AE48: =INDEX('05基本'!P:P,MATCH(C48,'05基本'!C:C,0))-I48 -> 0 | AF48: =SUMIF('05月其他部门提成'!C:C,'05月提成-武侯售后'!C48,'05月其他部门提成'!Q:Q) -> 5820 | AG48: =SUMIF('05月车间提成'!C:C,'05月提成-武侯售后'!C48,'05月车间提成'!W:W) -> 0 | AH48: =SUMIF('05月业务提成'!B:B,'05月提成-武侯售后'!C48,'05月业务提成'!BO:BO) -> 0 | AI48: =AF48+AG48+AH48 -> 5820 | AJ48: =AI48-K48 -> 0
A49: =A48+1 -> 39 | C49: 张琴 | D49: =INDEX('05基本'!I:I,MATCH(C49,'05基本'!C:C,0))+INDEX('05基本'!J:J,MATCH(C49,'05基本'!C:C,0)) -> 0 | E49: =INDEX('05基本'!AA:AA,MATCH(C49,'05基本'!C:C,0)) -> 1268.59 | F49: =INDEX('05基本'!AB:AB,MATCH(C49,'05基本'!C:C,0)) -> 477.15 | G49: =INDEX('05基本'!AC:AC,MATCH(C49,'05基本'!C:C,0)) -> 117 | H49: =INDEX('05基本'!K:K,MATCH(C49,'05基本'!C:C,0))+INDEX('05基本'!L:L,MATCH(C49,'05基本'!C:C,0)) -> 0 | I49: =INDEX('05基本'!P:P,MATCH(C49,'05基本'!C:C,0)) -> 900 | J49: =INDEX('05基本'!M:M,MATCH(C49,'05基本'!C:C,0)) -> 0 | K49: =INDEX('05月其他部门提成'!Q:Q,MATCH(C49,'05月其他部门提成'!C:C,0)) -> 18235 | L49: =SUMIF(综合考核!A:A,'05月提成-武侯售后'!C49,综合考核!M:M) -> 0 | M49: =SUM(K49:L49) -> 18235 | N49: =SUMIF(服装扣款!C:C,C49,服装扣款!N:N) -> 0 | O49: =M49-N49 -> 18235 | P49: =SUMIF(超市公积金!C:C,'05月提成-武侯售后'!C49,超市公积金!I:I) -> 0 | Q49: =SUMIF(综合考核!A:A,'05月提成-武侯售后'!C49,综合考核!N:N) -> 0 | R49: =M49+I49+Q49 -> 19135 | S49: =INDEX(AC:AC,MATCH(C49,AB:AB,0)) -> 1077.9 | U49: =S49-T49 -> 1077.9 | V49: =INDEX('05基本'!AF:AF,MATCH(C49,'05基本'!C:C,0)) -> 0 | W49: =O49-P49-U49 -> 17157.1 | Y49: =SUM(Z49:AA49) -> 83.34 | Z49: 83.34 | AB49: 罗文琦 | AC49: 0 | AD49: =COUNTIF(C:C,C49) -> 1 | AE49: =INDEX('05基本'!P:P,MATCH(C49,'05基本'!C:C,0))-I49 -> 0 | AF49: =SUMIF('05月其他部门提成'!C:C,'05月提成-武侯售后'!C49,'05月其他部门提成'!Q:Q) -> 18235 | AG49: =SUMIF('05月车间提成'!C:C,'05月提成-武侯售后'!C49,'05月车间提成'!W:W) -> 0 | AH49: =SUMIF('05月业务提成'!B:B,'05月提成-武侯售后'!C49,'05月业务提成'!BO:BO) -> 0 | AI49: =AF49+AG49+AH49 -> 18235 | AJ49: =AI49-K49 -> 0
A50: =A49+1 -> 40 | C50: 刘林 | K50: =INDEX('05月其他部门提成'!Q:Q,MATCH(C50,'05月其他部门提成'!C:C,0)) -> 1980 | L50: =SUMIF(综合考核!A:A,'05月提成-武侯售后'!C50,综合考核!M:M) -> 0 | M50: =SUM(K50:L50) -> 1980 | N50: =SUMIF(服装扣款!C:C,C50,服装扣款!N:N) -> 0 | O50: =M50-N50 -> 1980 | P50: =SUMIF(超市公积金!C:C,'05月提成-武侯售后'!C50,超市公积金!I:I) -> 0 | Q50: =SUMIF(综合考核!A:A,'05月提成-武侯售后'!C50,综合考核!N:N) -> 0 | R50: =M50+I50+Q50 -> 1980 | S50: =INDEX(AC:AC,MATCH(C50,AB:AB,0)) -> 0 | U50: =S50-T50 -> 0 | W50: =O50-P50-U50 -> 1980 | Y50: =SUM(Z50:AA50) -> 0 | AB50: 周凤英 | AC50: 0 | AD50: =COUNTIF(C:C,C50) -> 1 | AE50: =INDEX('05基本'!P:P,MATCH(C50,'05基本'!C:C,0))-I50 -> #N/A | AF50: =SUMIF('05月其他部门提成'!C:C,'05月提成-武侯售后'!C50,'05月其他部门提成'!Q:Q) -> 1980 | AG50: =SUMIF('05月车间提成'!C:C,'05月提成-武侯售后'!C50,'05月车间提成'!W:W) -> 0 | AH50: =SUMIF('05月业务提成'!B:B,'05月提成-武侯售后'!C50,'05月业务提成'!BO:BO) -> 0 | AI50: =AF50+AG50+AH50 -> 1980 | AJ50: =AI50-K50 -> 0
A51: =A50+1 -> 41 | C51: 鄢雨濛 | K51: =INDEX('05月其他部门提成'!Q:Q,MATCH(C51,'05月其他部门提成'!C:C,0)) -> 615 | L51: =SUMIF(综合考核!A:A,'05月提成-武侯售后'!C51,综合考核!M:M) -> 0 | M51: =SUM(K51:L51) -> 615 | N51: =SUMIF(服装扣款!C:C,C51,服装扣款!N:N) -> 0 | O51: =M51-N51 -> 615 | P51: =SUMIF(超市公积金!C:C,'05月提成-武侯售后'!C51,超市公积金!I:I) -> 0 | Q51: =SUMIF(综合考核!A:A,'05月提成-武侯售后'!C51,综合考核!N:N) -> 0 | R51: =M51+I51+Q51 -> 615 | S51: =INDEX(AC:AC,MATCH(C51,AB:AB,0)) -> 0 | U51: =S51-T51 -> 0 | W51: =O51-P51-U51 -> 615 | Y51: =SUM(Z51:AA51) -> 0 | AB51: 孙茂梅 | AC51: 0 | AD51: =COUNTIF(C:C,C51) -> 1 | AE51: =INDEX('05基本'!P:P,MATCH(C51,'05基本'!C:C,0))-I51 -> #N/A | AF51: =SUMIF('05月其他部门提成'!C:C,'05月提成-武侯售后'!C51,'05月其他部门提成'!Q:Q) -> 615 | AG51: =SUMIF('05月车间提成'!C:C,'05月提成-武侯售后'!C51,'05月车间提成'!W:W) -> 0 | AH51: =SUMIF('05月业务提成'!B:B,'05月提成-武侯售后'!C51,'05月业务提成'!BO:BO) -> 0 | AI51: =AF51+AG51+AH51 -> 615 | AJ51: =AI51-K51 -> 0
A52: =A51+1 -> 42 | C52: 刘尧梅 | K52: =INDEX('05月其他部门提成'!Q:Q,MATCH(C52,'05月其他部门提成'!C:C,0)) -> 1913.3333 | L52: =SUMIF(综合考核!A:A,'05月提成-武侯售后'!C52,综合考核!M:M) -> 0 | M52: =SUM(K52:L52) -> 1913.3333 | N52: =SUMIF(服装扣款!C:C,C52,服装扣款!N:N) -> 0 | O52: =M52-N52 -> 1913.3333 | P52: =SUMIF(超市公积金!C:C,'05月提成-武侯售后'!C52,超市公积金!I:I) -> 0 | Q52: =SUMIF(综合考核!A:A,'05月提成-武侯售后'!C52,综合考核!N:N) -> 0 | R52: =M52+I52+Q52 -> 1913.3333 | S52: =INDEX(AC:AC,MATCH(C52,AB:AB,0)) -> 0 | U52: =S52-T52 -> 0 | V52: =INDEX('05基本'!AF:AF,MATCH(C52,'05基本'!C:C,0)) -> 0 | W52: =O52-P52-U52 -> 1913.3333 | Y52: =SUM(Z52:AA52) -> 0 | AB52: 雷维可 | AC52: 0 | AD52: =COUNTIF(C:C,C52) -> 1 | AE52: =INDEX('05基本'!P:P,MATCH(C52,'05基本'!C:C,0))-I52 -> 420 | AF52: =SUMIF('05月其他部门提成'!C:C,'05月提成-武侯售后'!C52,'05月其他部门提成'!Q:Q) -> 1913.3333 | AG52: =SUMIF('05月车间提成'!C:C,'05月提成-武侯售后'!C52,'05月车间提成'!W:W) -> 0 | AH52: =SUMIF('05月业务提成'!B:B,'05月提成-武侯售后'!C52,'05月业务提成'!BO:BO) -> 0 | AI52: =AF52+AG52+AH52 -> 1913.3333 | AJ52: =AI52-K52 -> 0
A53: =A52+1 -> 43 | C53: 冯桢 | K53: =INDEX('05月其他部门提成'!Q:Q,MATCH(C53,'05月其他部门提成'!C:C,0)) -> 956.66667 | L53: =SUMIF(综合考核!A:A,'05月提成-武侯售后'!C53,综合考核!M:M) -> 0 | M53: =SUM(K53:L53) -> 956.66667 | N53: =SUMIF(服装扣款!C:C,C53,服装扣款!N:N) -> 0 | O53: =M53-N53 -> 956.66667 | P53: =SUMIF(超市公积金!C:C,'05月提成-武侯售后'!C53,超市公积金!I:I) -> 0 | Q53: =SUMIF(综合考核!A:A,'05月提成-武侯售后'!C53,综合考核!N:N) -> 0 | R53: =M53+I53+Q53 -> 956.66667 | S53: =INDEX(AC:AC,MATCH(C53,AB:AB,0)) -> 0 | U53: =S53-T53 -> 0 | V53: =INDEX('05基本'!AF:AF,MATCH(C53,'05基本'!C:C,0)) -> 0 | W53: =O53-P53-U53 -> 956.66667 | Y53: =SUM(Z53:AA53) -> 0 | AB53: 梁宁 | AC53: 56.93 | AD53: =COUNTIF(C:C,C53) -> 1 | AE53: =INDEX('05基本'!P:P,MATCH(C53,'05基本'!C:C,0))-I53 -> 180 | AF53: =SUMIF('05月其他部门提成'!C:C,'05月提成-武侯售后'!C53,'05月其他部门提成'!Q:Q) -> 956.66667 | AG53: =SUMIF('05月车间提成'!C:C,'05月提成-武侯售后'!C53,'05月车间提成'!W:W) -> 0 | AH53: =SUMIF('05月业务提成'!B:B,'05月提成-武侯售后'!C53,'05月业务提成'!BO:BO) -> 0 | AI53: =AF53+AG53+AH53 -> 956.66667 | AJ53: =AI53-K53 -> 0
A54: =A53+1 -> 44 | C54: 高梓绮 | D54: =INDEX('05基本'!I:I,MATCH(C54,'05基本'!C:C,0))+INDEX('05基本'!J:J,MATCH(C54,'05基本'!C:C,0)) -> 0 | E54: =INDEX('05基本'!AA:AA,MATCH(C54,'05基本'!C:C,0)) -> 1268.59 | F54: =INDEX('05基本'!AB:AB,MATCH(C54,'05基本'!C:C,0)) -> 477.15 | G54: =INDEX('05基本'!AC:AC,MATCH(C54,'05基本'!C:C,0)) -> 117 | H54: =INDEX('05基本'!K:K,MATCH(C54,'05基本'!C:C,0))+INDEX('05基本'!L:L,MATCH(C54,'05基本'!C:C,0)) -> 0 | I54: =INDEX('05基本'!P:P,MATCH(C54,'05基本'!C:C,0)) -> 900 | J54: =INDEX('05基本'!M:M,MATCH(C54,'05基本'!C:C,0)) -> 0 | K54: =INDEX('05月其他部门提成'!Q:Q,MATCH(C54,'05月其他部门提成'!C:C,0)) -> 4010 | L54: =SUMIF(综合考核!A:A,'05月提成-武侯售后'!C54,综合考核!M:M) -> 0 | M54: =SUM(K54:L54) -> 4010 | N54: =SUMIF(服装扣款!C:C,C54,服装扣款!N:N) -> 0 | O54: =M54-N54 -> 4010 | P54: =SUMIF(超市公积金!C:C,'05月提成-武侯售后'!C54,超市公积金!I:I) -> 0 | Q54: =SUMIF(综合考核!A:A,'05月提成-武侯售后'!C54,综合考核!N:N) -> 0 | R54: =M54+I54+Q54 -> 4910 | S54: =INDEX(AC:AC,MATCH(C54,AB:AB,0)) -> 0 | U54: =S54-T54 -> 0 | V54: =INDEX('05基本'!AF:AF,MATCH(C54,'05基本'!C:C,0)) -> 0 | W54: =O54-P54-U54 -> 4010 | Y54: =SUM(Z54:AA54) -> 0 | AB54: 陈晓波 | AC54: 46.94 | AD54: =COUNTIF(C:C,C54) -> 1 | AE54: =INDEX('05基本'!P:P,MATCH(C54,'05基本'!C:C,0))-I54 -> 0 | AF54: =SUMIF('05月其他部门提成'!C:C,'05月提成-武侯售后'!C54,'05月其他部门提成'!Q:Q) -> 4010 | AG54: =SUMIF('05月车间提成'!C:C,'05月提成-武侯售后'!C54,'05月车间提成'!W:W) -> 0 | AH54: =SUMIF('05月业务提成'!B:B,'05月提成-武侯售后'!C54,'05月业务提成'!BO:BO) -> 0 | AI54: =AF54+AG54+AH54 -> 4010 | AJ54: =AI54-K54 -> 0
A55: =A54+1 -> 45 | C55: 罗文琦 | D55: =INDEX('05基本'!I:I,MATCH(C55,'05基本'!C:C,0))+INDEX('05基本'!J:J,MATCH(C55,'05基本'!C:C,0)) -> 0 | E55: =INDEX('05基本'!AA:AA,MATCH(C55,'05基本'!C:C,0)) -> 1268.59 | F55: =INDEX('05基本'!AB:AB,MATCH(C55,'05基本'!C:C,0)) -> 477.15 | G55: =INDEX('05基本'!AC:AC,MATCH(C55,'05基本'!C:C,0)) -> 117 | H55: =INDEX('05基本'!K:K,MATCH(C55,'05基本'!C:C,0))+INDEX('05基本'!L:L,MATCH(C55,'05基本'!C:C,0)) -> 0 | I55: =INDEX('05基本'!P:P,MATCH(C55,'05基本'!C:C,0)) -> 900 | J55: =INDEX('05基本'!M:M,MATCH(C55,'05基本'!C:C,0)) -> 0 | K55: =INDEX('05月其他部门提成'!Q:Q,MATCH(C55,'05月其他部门提成'!C:C,0)) -> 3770 | L55: =SUMIF(综合考核!A:A,'05月提成-武侯售后'!C55,综合考核!M:M) -> 0 | M55: =SUM(K55:L55) -> 3770 | N55: =SUMIF(服装扣款!C:C,C55,服装扣款!N:N) -> 0 | O55: =M55-N55 -> 3770 | P55: =SUMIF(超市公积金!C:C,'05月提成-武侯售后'!C55,超市公积金!I:I) -> 0 | Q55: =SUMIF(综合考核!A:A,'05月提成-武侯售后'!C55,综合考核!N:N) -> 0 | R55: =M55+I55+Q55 -> 4670 | S55: =INDEX(AC:AC,MATCH(C55,AB:AB,0)) -> 0 | U55: =S55-T55 -> 0 | V55: =INDEX('05基本'!AF:AF,MATCH(C55,'05基本'!C:C,0)) -> 0 | W55: =O55-P55-U55 -> 3770 | Y55: =SUM(Z55:AA55) -> 83.34 | Z55: 83.34 | AB55: 颜书琼 | AC55: 832.23 | AD55: =COUNTIF(C:C,C55) -> 1 | AE55: =INDEX('05基本'!P:P,MATCH(C55,'05基本'!C:C,0))-I55 -> 0 | AF55: =SUMIF('05月其他部门提成'!C:C,'05月提成-武侯售后'!C55,'05月其他部门提成'!Q:Q) -> 3770 | AG55: =SUMIF('05月车间提成'!C:C,'05月提成-武侯售后'!C55,'05月车间提成'!W:W) -> 0 | AH55: =SUMIF('05月业务提成'!B:B,'05月提成-武侯售后'!C55,'05月业务提成'!BO:BO) -> 0 | AI55: =AF55+AG55+AH55 -> 3770 | AJ55: =AI55-K55 -> 0
A56: =A55+1 -> 46 | C56: 周凤英 | K56: =INDEX('05月其他部门提成'!Q:Q,MATCH(C56,'05月其他部门提成'!C:C,0)) -> 2490 | L56: =SUMIF(综合考核!A:A,'05月提成-武侯售后'!C56,综合考核!M:M) -> 0 | M56: =SUM(K56:L56) -> 2490 | N56: =SUMIF(服装扣款!C:C,C56,服装扣款!N:N) -> 0 | O56: =M56-N56 -> 2490 | P56: =SUMIF(超市公积金!C:C,'05月提成-武侯售后'!C56,超市公积金!I:I) -> 0 | Q56: =SUMIF(综合考核!A:A,'05月提成-武侯售后'!C56,综合考核!N:N) -> 0 | R56: =M56+I56+Q56 -> 2490 | S56: =INDEX(AC:AC,MATCH(C56,AB:AB,0)) -> 0 | U56: =S56-T56 -> 0 | W56: =O56-P56-U56 -> 2490 | Y56: =SUM(Z56:AA56) -> 83.34 | Z56: 83.34 | AB56: 李波 | AC56: 0 | AD56: =COUNTIF(C:C,C56) -> 1 | AE56: =INDEX('05基本'!P:P,MATCH(C56,'05基本'!C:C,0))-I56 -> #N/A | AF56: =SUMIF('05月其他部门提成'!C:C,'05月提成-武侯售后'!C56,'05月其他部门提成'!Q:Q) -> 2490 | AG56: =SUMIF('05月车间提成'!C:C,'05月提成-武侯售后'!C56,'05月车间提成'!W:W) -> 0 | AH56: =SUMIF('05月业务提成'!B:B,'05月提成-武侯售后'!C56,'05月业务提成'!BO:BO) -> 0 | AI56: =AF56+AG56+AH56 -> 2490 | AJ56: =AI56-K56 -> 0
A57: =A56+1 -> 47 | C57: 孙茂梅 | D57: =INDEX('05基本'!I:I,MATCH(C57,'05基本'!C:C,0))+INDEX('05基本'!J:J,MATCH(C57,'05基本'!C:C,0)) -> 0 | E57: =INDEX('05基本'!AA:AA,MATCH(C57,'05基本'!C:C,0)) -> 0 | F57: =INDEX('05基本'!AB:AB,MATCH(C57,'05基本'!C:C,0)) -> 0 | G57: =INDEX('05基本'!AC:AC,MATCH(C57,'05基本'!C:C,0)) -> 0 | H57: =INDEX('05基本'!K:K,MATCH(C57,'05基本'!C:C,0))+INDEX('05基本'!L:L,MATCH(C57,'05基本'!C:C,0)) -> 0 | I57: =INDEX('05基本'!P:P,MATCH(C57,'05基本'!C:C,0)) -> 500 | J57: =INDEX('05基本'!M:M,MATCH(C57,'05基本'!C:C,0)) -> 0 | K57: =INDEX('05月其他部门提成'!Q:Q,MATCH(C57,'05月其他部门提成'!C:C,0)) -> 0 | L57: =SUMIF(综合考核!A:A,'05月提成-武侯售后'!C57,综合考核!M:M) -> 0 | M57: =SUM(K57:L57) -> 0 | N57: =SUMIF(服装扣款!C:C,C57,服装扣款!N:N) -> 0 | O57: =M57-N57 -> 0 | P57: =SUMIF(超市公积金!C:C,'05月提成-武侯售后'!C57,超市公积金!I:I) -> 0 | Q57: =SUMIF(综合考核!A:A,'05月提成-武侯售后'!C57,综合考核!N:N) -> 0 | R57: =M57+I57+Q57 -> 500 | S57: =INDEX(AC:AC,MATCH(C57,AB:AB,0)) -> 0 | U57: =S57-T57 -> 0 | V57: =INDEX('05基本'!AF:AF,MATCH(C57,'05基本'!C:C,0)) -> 0 | W57: =O57-P57-U57 -> 0 | Y57: =SUM(Z57:AA57) -> 83.34 | Z57: 83.34 | AB57: 肖伦容 | AC57: 49.98 | AD57: =COUNTIF(C:C,C57) -> 1 | AE57: =INDEX('05基本'!P:P,MATCH(C57,'05基本'!C:C,0))-I57 -> 0 | AF57: =SUMIF('05月其他部门提成'!C:C,'05月提成-武侯售后'!C57,'05月其他部门提成'!Q:Q) -> 0 | AG57: =SUMIF('05月车间提成'!C:C,'05月提成-武侯售后'!C57,'05月车间提成'!W:W) -> 0 | AH57: =SUMIF('05月业务提成'!B:B,'05月提成-武侯售后'!C57,'05月业务提成'!BO:BO) -> 0 | AI57: =AF57+AG57+AH57 -> 0 | AJ57: =AI57-K57 -> 0
C58: 小计 | D58: =SUM(D46:D57) -> 0 | E58: =SUM(E46:E57) -> 7611.54 | F58: =SUM(F46:F57) -> 2862.9 | G58: =SUM(G46:G57) -> 702 | H58: =SUM(H46:H57) -> 0 | I58: =SUM(I46:I57) -> 6985 | J58: =SUM(J46:J57) -> 0 | K58: =SUM(K46:K57) -> 57145 | ... AA58: =SUM(AA46:AA57) -> 0 | AB58: 李桃 | AC58: 66.82 | AD58: =COUNTIF(C:C,C58) -> 11 | AE58: =INDEX('05基本'!P:P,MATCH(C58,'05基本'!C:C,0))-I58 -> #N/A
A59: =A57+1 -> 48 | B59: 索赔部 | C59: 雷维可 | D59: =INDEX('05基本'!I:I,MATCH(C59,'05基本'!C:C,0))+INDEX('05基本'!J:J,MATCH(C59,'05基本'!C:C,0)) -> 0 | E59: =INDEX('05基本'!AA:AA,MATCH(C59,'05基本'!C:C,0)) -> 1268.59 | F59: =INDEX('05基本'!AB:AB,MATCH(C59,'05基本'!C:C,0)) -> 477.15 | G59: =INDEX('05基本'!AC:AC,MATCH(C59,'05基本'!C:C,0)) -> 117 | H59: =INDEX('05基本'!K:K,MATCH(C59,'05基本'!C:C,0))+INDEX('05基本'!L:L,MATCH(C59,'05基本'!C:C,0)) -> 0 | I59: =INDEX('05基本'!P:P,MATCH(C59,'05基本'!C:C,0)) -> 1700 | J59: =INDEX('05基本'!M:M,MATCH(C59,'05基本'!C:C,0)) -> 0 | K59: =INDEX('05月其他部门提成'!Q:Q,MATCH(C59,'05月其他部门提成'!C:C,0)) -> 9914.2025 | L59: =SUMIF(综合考核!A:A,'05月提成-武侯售后'!C59,综合考核!M:M) -> 0 | M59: =SUM(K59:L59) -> 9914.2025 | N59: =SUMIF(服装扣款!C:C,C59,服装扣款!N:N) -> 0 | O59: =M59-N59 -> 9914.2025 | P59: =SUMIF(超市公积金!C:C,'05月提成-武侯售后'!C59,超市公积金!I:I) -> 0 | Q59: =SUMIF(综合考核!A:A,'05月提成-武侯售后'!C59,综合考核!N:N) -> 0 | R59: =M59+I59+Q59 -> 11614.202 | S59: =INDEX(AC:AC,MATCH(C59,AB:AB,0)) -> 0 | T59: 0 | U59: =S59-T59 -> 0 | V59: =INDEX('05基本'!AF:AF,MATCH(C59,'05基本'!C:C,0)) -> 0 | W59: =O59-P59-U59 -> 9914.2025 | Y59: =SUM(Z59:AA59) -> 593.7602 | Z59: =INDEX('05月其他部门提成'!S:S,MATCH(C59,'05月其他部门提成'!C:C,0)) -> 593.7602 | AB59: 宋航 | AC59: 66.82 | AD59: =COUNTIF(C:C,C59) -> 1 | AE59: =INDEX('05基本'!P:P,MATCH(C59,'05基本'!C:C,0))-I59 -> 0 | AF59: =SUMIF('05月其他部门提成'!C:C,'05月提成-武侯售后'!C59,'05月其他部门提成'!Q:Q) -> 9914.2025 | AG59: =SUMIF('05月车间提成'!C:C,'05月提成-武侯售后'!C59,'05月车间提成'!W:W) -> 0 | AH59: =SUMIF('05月业务提成'!B:B,'05月提成-武侯售后'!C59,'05月业务提成'!BO:BO) -> 0 | AI59: =AF59+AG59+AH59 -> 9914.2025 | AJ59: =AI59-K59 -> 0
A60: =A59+1 -> 49 | C60: 梁宁 | D60: =INDEX('05基本'!I:I,MATCH(C60,'05基本'!C:C,0))+INDEX('05基本'!J:J,MATCH(C60,'05基本'!C:C,0)) -> 0 | E60: =INDEX('05基本'!AA:AA,MATCH(C60,'05基本'!C:C,0)) -> 9.18 | F60: =INDEX('05基本'!AB:AB,MATCH(C60,'05基本'!C:C,0)) -> 0 | G60: =INDEX('05基本'!AC:AC,MATCH(C60,'05基本'!C:C,0)) -> 0 | H60: =INDEX('05基本'!K:K,MATCH(C60,'05基本'!C:C,0))+INDEX('05基本'!L:L,MATCH(C60,'05基本'!C:C,0)) -> 0 | I60: =INDEX('05基本'!P:P,MATCH(C60,'05基本'!C:C,0)) -> 1700 | J60: =INDEX('05基本'!M:M,MATCH(C60,'05基本'!C:C,0)) -> 0 | K60: =INDEX('05月其他部门提成'!Q:Q,MATCH(C60,'05月其他部门提成'!C:C,0)) -> 5197.657 | L60: =SUMIF(综合考核!A:A,'05月提成-武侯售后'!C60,综合考核!M:M) -> 0 | M60: =SUM(K60:L60) -> 5197.657 | N60: =SUMIF(服装扣款!C:C,C60,服装扣款!N:N) -> 0 | O60: =M60-N60 -> 5197.657 | P60: =SUMIF(超市公积金!C:C,'05月提成-武侯售后'!C60,超市公积金!I:I) -> 0 | Q60: =SUMIF(综合考核!A:A,'05月提成-武侯售后'!C60,综合考核!N:N) -> 0 | R60: =M60+I60+Q60 -> 6897.657 | S60: =INDEX(AC:AC,MATCH(C60,AB:AB,0)) -> 56.93 | T60: 0 | U60: =S60-T60 -> 56.93 | V60: =INDEX('05基本'!AF:AF,MATCH(C60,'05基本'!C:C,0)) -> 0 | W60: =O60-P60-U60 -> 5140.727 | Y60: =SUM(Z60:AA60) -> 166.66667 | Z60: =INDEX('05月其他部门提成'!S:S,MATCH(C60,'05月其他部门提成'!C:C,0)) -> 166.66667 | AB60: 伍成勇 | AC60: 65.98 | AD60: =COUNTIF(C:C,C60) -> 1 | AE60: =INDEX('05基本'!P:P,MATCH(C60,'05基本'!C:C,0))-I60 -> 0 | AF60: =SUMIF('05月其他部门提成'!C:C,'05月提成-武侯售后'!C60,'05月其他部门提成'!Q:Q) -> 5197.657 | AG60: =SUMIF('05月车间提成'!C:C,'05月提成-武侯售后'!C60,'05月车间提成'!W:W) -> 0 | AH60: =SUMIF('05月业务提成'!B:B,'05月提成-武侯售后'!C60,'05月业务提成'!BO:BO) -> 0 | AI60: =AF60+AG60+AH60 -> 5197.657 | AJ60: =AI60-K60 -> 0
A61: =A60+1 -> 50 | C61: 陈晓波 | D61: =INDEX('05基本'!I:I,MATCH(C61,'05基本'!C:C,0))+INDEX('05基本'!J:J,MATCH(C61,'05基本'!C:C,0)) -> 0 | E61: =INDEX('05基本'!AA:AA,MATCH(C61,'05基本'!C:C,0)) -> 1268.59 | F61: =INDEX('05基本'!AB:AB,MATCH(C61,'05基本'!C:C,0)) -> 477.15 | G61: =INDEX('05基本'!AC:AC,MATCH(C61,'05基本'!C:C,0)) -> 117 | H61: =INDEX('05基本'!K:K,MATCH(C61,'05基本'!C:C,0))+INDEX('05基本'!L:L,MATCH(C61,'05基本'!C:C,0)) -> 0 | I61: =INDEX('05基本'!P:P,MATCH(C61,'05基本'!C:C,0)) -> 850 | J61: =INDEX('05基本'!M:M,MATCH(C61,'05基本'!C:C,0)) -> 0 | K61: =INDEX('05月其他部门提成'!Q:Q,MATCH(C61,'05月其他部门提成'!C:C,0)) -> 6309.0379 | L61: =SUMIF(综合考核!A:A,'05月提成-武侯售后'!C61,综合考核!M:M) -> 0 | M61: =SUM(K61:L61) -> 6309.0379 | N61: =SUMIF(服装扣款!C:C,C61,服装扣款!N:N) -> 0 | O61: =M61-N61 -> 6309.0379 | P61: =SUMIF(超市公积金!C:C,'05月提成-武侯售后'!C61,超市公积金!I:I) -> 0 | Q61: =SUMIF(综合考核!A:A,'05月提成-武侯售后'!C61,综合考核!N:N) -> 0 | R61: =M61+I61+Q61 -> 7159.0379 | S61: =INDEX(AC:AC,MATCH(C61,AB:AB,0)) -> 46.94 | T61: 0 | U61: =S61-T61 -> 46.94 | V61: =INDEX('05基本'!AF:AF,MATCH(C61,'05基本'!C:C,0)) -> 0 | W61: =O61-P61-U61 -> 6262.0979 | Y61: =SUM(Z61:AA61) -> 485.8038 | Z61: =INDEX('05月其他部门提成'!S:S,MATCH(C61,'05月其他部门提成'!C:C,0)) -> 485.8038 | AB61: 何毅 | AC61: 102.9 | AD61: =COUNTIF(C:C,C61) -> 1 | AE61: =INDEX('05基本'!P:P,MATCH(C61,'05基本'!C:C,0))-I61 -> 0 | AF61: =SUMIF('05月其他部门提成'!C:C,'05月提成-武侯售后'!C61,'05月其他部门提成'!Q:Q) -> 6309.0379 | AG61: =SUMIF('05月车间提成'!C:C,'05月提成-武侯售后'!C61,'05月车间提成'!W:W) -> 0 | AH61: =SUMIF('05月业务提成'!B:B,'05月提成-武侯售后'!C61,'05月业务提成'!BO:BO) -> 0 | AI61: =AF61+AG61+AH61 -> 6309.0379 | AJ61: =AI61-K61 -> 0
C62: 小计 | D62: =SUM(D59:D61) -> 0 | E62: =SUM(E59:E61) -> 2546.36 | F62: =SUM(F59:F61) -> 954.3 | G62: =SUM(G59:G61) -> 234 | H62: =SUM(H59:H61) -> 0 | I62: =SUM(I59:I61) -> 4250 | J62: =SUM(J59:J61) -> 0 | K62: =SUM(K59:K61) -> 21420.897 | ... AA62: =SUM(AA59:AA61) -> 0 | AB62: 王竹飞 | AC62: 102.91 | AD62: =COUNTIF(C:C,C62) -> 11 | AE62: =INDEX('05基本'!P:P,MATCH(C62,'05基本'!C:C,0))-I62 -> #N/A
A63: =A61+1 -> 51 | B63: 配件 | C63: 颜书琼 | D63: =INDEX('05基本'!I:I,MATCH(C63,'05基本'!C:C,0))+INDEX('05基本'!J:J,MATCH(C63,'05基本'!C:C,0)) -> 0 | E63: =INDEX('05基本'!AA:AA,MATCH(C63,'05基本'!C:C,0)) -> 1372 | F63: =INDEX('05基本'!AB:AB,MATCH(C63,'05基本'!C:C,0)) -> 520 | G63: =INDEX('05基本'!AC:AC,MATCH(C63,'05基本'!C:C,0)) -> 117 | H63: =INDEX('05基本'!K:K,MATCH(C63,'05基本'!C:C,0))+INDEX('05基本'!L:L,MATCH(C63,'05基本'!C:C,0)) -> 0 | I63: =INDEX('05基本'!P:P,MATCH(C63,'05基本'!C:C,0)) -> 1700 | J63: =INDEX('05基本'!M:M,MATCH(C63,'05基本'!C:C,0)) -> 0 | K63: =INDEX('05月其他部门提成'!Q:Q,MATCH(C63,'05月其他部门提成'!C:C,0)) -> 12259.303 | L63: =SUMIF(综合考核!A:A,'05月提成-武侯售后'!C63,综合考核!M:M) -> 0 | M63: =SUM(K63:L63) -> 12259.303 | N63: =SUMIF(服装扣款!C:C,C63,服装扣款!N:N) -> 0 | O63: =M63-N63 -> 12259.303 | P63: =SUMIF(超市公积金!C:C,'05月提成-武侯售后'!C63,超市公积金!I:I) -> 0 | Q63: =SUMIF(综合考核!A:A,'05月提成-武侯售后'!C63,综合考核!N:N) -> 0 | R63: =M63+I63+Q63 -> 13959.303 | S63: =INDEX(AC:AC,MATCH(C63,AB:AB,0)) -> 832.23 | U63: =S63-T63 -> 832.23 | V63: =INDEX('05基本'!AF:AF,MATCH(C63,'05基本'!C:C,0)) -> 0 | W63: =O63-P63-U63 -> 11427.073 | Y63: =SUM(Z63:AA63) -> 426.13951 | Z63: =INDEX('05月其他部门提成'!S:S,MATCH(C63,'05月其他部门提成'!C:C,0)) -> 426.13951 | AB63: 周劲松 | AC63: 0 | AD63: =COUNTIF(C:C,C63) -> 1 | AE63: =INDEX('05基本'!P:P,MATCH(C63,'05基本'!C:C,0))-I63 -> 0 | AF63: =SUMIF('05月其他部门提成'!C:C,'05月提成-武侯售后'!C63,'05月其他部门提成'!Q:Q) -> 12259.303 | AG63: =SUMIF('05月车间提成'!C:C,'05月提成-武侯售后'!C63,'05月车间提成'!W:W) -> 0 | AH63: =SUMIF('05月业务提成'!B:B,'05月提成-武侯售后'!C63,'05月业务提成'!BO:BO) -> 0 | AI63: =AF63+AG63+AH63 -> 12259.303 | AJ63: =AI63-K63 -> 0
A64: =A63+1 -> 52 | C64: 李波 | D64: =INDEX('05基本'!I:I,MATCH(C64,'05基本'!C:C,0))+INDEX('05基本'!J:J,MATCH(C64,'05基本'!C:C,0)) -> 0 | E64: =INDEX('05基本'!AA:AA,MATCH(C64,'05基本'!C:C,0)) -> 1268.59 | F64: =INDEX('05基本'!AB:AB,MATCH(C64,'05基本'!C:C,0)) -> 477.15 | G64: =INDEX('05基本'!AC:AC,MATCH(C64,'05基本'!C:C,0)) -> 117 | H64: =INDEX('05基本'!K:K,MATCH(C64,'05基本'!C:C,0))+INDEX('05基本'!L:L,MATCH(C64,'05基本'!C:C,0)) -> 0 | I64: =INDEX('05基本'!P:P,MATCH(C64,'05基本'!C:C,0)) -> 900 | J64: =INDEX('05基本'!M:M,MATCH(C64,'05基本'!C:C,0)) -> 0 | K64: =INDEX('05月其他部门提成'!Q:Q,MATCH(C64,'05月其他部门提成'!C:C,0)) -> 6438.2435 | L64: =SUMIF(综合考核!A:A,'05月提成-武侯售后'!C64,综合考核!M:M) -> 0 | M64: =SUM(K64:L64) -> 6438.2435 | N64: =SUMIF(服装扣款!C:C,C64,服装扣款!N:N) -> 0 | O64: =M64-N64 -> 6438.2435 | P64: =SUMIF(超市公积金!C:C,'05月提成-武侯售后'!C64,超市公积金!I:I) -> 0 | Q64: =SUMIF(综合考核!A:A,'05月提成-武侯售后'!C64,综合考核!N:N) -> 0 | R64: =M64+I64+Q64 -> 7338.2435 | S64: =INDEX(AC:AC,MATCH(C64,AB:AB,0)) -> 0 | U64: =S64-T64 -> 0 | V64: =INDEX('05基本'!AF:AF,MATCH(C64,'05基本'!C:C,0)) -> 0 | W64: =O64-P64-U64 -> 6438.2435 | Y64: =SUM(Z64:AA64) -> 2493.9553 | Z64: =INDEX('05月其他部门提成'!S:S,MATCH(C64,'05月其他部门提成'!C:C,0)) -> 2493.9553 | AB64: 田建勇 | AC64: 84.58 | AD64: =COUNTIF(C:C,C64) -> 1 | AE64: =INDEX('05基本'!P:P,MATCH(C64,'05基本'!C:C,0))-I64 -> 0 | AF64: =SUMIF('05月其他部门提成'!C:C,'05月提成-武侯售后'!C64,'05月其他部门提成'!Q:Q) -> 6438.2435 | AG64: =SUMIF('05月车间提成'!C:C,'05月提成-武侯售后'!C64,'05月车间提成'!W:W) -> 0 | AH64: =SUMIF('05月业务提成'!B:B,'05月提成-武侯售后'!C64,'05月业务提成'!BO:BO) -> 0 | AI64: =AF64+AG64+AH64 -> 6438.2435 | AJ64: =AI64-K64 -> 0
A65: =A64+1 -> 53 | C65: 肖伦容 | D65: =INDEX('05基本'!I:I,MATCH(C65,'05基本'!C:C,0))+INDEX('05基本'!J:J,MATCH(C65,'05基本'!C:C,0)) -> 0 | E65: =INDEX('05基本'!AA:AA,MATCH(C65,'05基本'!C:C,0)) -> 1268.59 | F65: =INDEX('05基本'!AB:AB,MATCH(C65,'05基本'!C:C,0)) -> 477.15 | G65: =INDEX('05基本'!AC:AC,MATCH(C65,'05基本'!C:C,0)) -> 117 | H65: =INDEX('05基本'!K:K,MATCH(C65,'05基本'!C:C,0))+INDEX('05基本'!L:L,MATCH(C65,'05基本'!C:C,0)) -> 0 | I65: =INDEX('05基本'!P:P,MATCH(C65,'05基本'!C:C,0)) -> 900 | J65: =INDEX('05基本'!M:M,MATCH(C65,'05基本'!C:C,0)) -> 0 | K65: =INDEX('05月其他部门提成'!Q:Q,MATCH(C65,'05月其他部门提成'!C:C,0)) -> 6360.0567 | L65: =SUMIF(综合考核!A:A,'05月提成-武侯售后'!C65,综合考核!M:M) -> 0 | M65: =SUM(K65:L65) -> 6360.0567 | N65: =SUMIF(服装扣款!C:C,C65,服装扣款!N:N) -> 0 | O65: =M65-N65 -> 6360.0567 | P65: =SUMIF(超市公积金!C:C,'05月提成-武侯售后'!C65,超市公积金!I:I) -> 0 | Q65: =SUMIF(综合考核!A:A,'05月提成-武侯售后'!C65,综合考核!N:N) -> 0 | R65: =M65+I65+Q65 -> 7260.0567 | S65: =INDEX(AC:AC,MATCH(C65,AB:AB,0)) -> 49.98 | U65: =S65-T65 -> 49.98 | V65: =INDEX('05基本'!AF:AF,MATCH(C65,'05基本'!C:C,0)) -> 0 | W65: =O65-P65-U65 -> 6310.0767 | Y65: =SUM(Z65:AA65) -> 0 | Z65: =INDEX('05月其他部门提成'!S:S,MATCH(C65,'05月其他部门提成'!C:C,0)) -> 0 | AB65: 宋虹冰 | AC65: 189.61 | AD65: =COUNTIF(C:C,C65) -> 1 | AE65: =INDEX('05基本'!P:P,MATCH(C65,'05基本'!C:C,0))-I65 -> 0 | AF65: =SUMIF('05月其他部门提成'!C:C,'05月提成-武侯售后'!C65,'05月其他部门提成'!Q:Q) -> 6360.0567 | AG65: =SUMIF('05月车间提成'!C:C,'05月提成-武侯售后'!C65,'05月车间提成'!W:W) -> 0 | AH65: =SUMIF('05月业务提成'!B:B,'05月提成-武侯售后'!C65,'05月业务提成'!BO:BO) -> 0 | AI65: =AF65+AG65+AH65 -> 6360.0567 | AJ65: =AI65-K65 -> 0
A66: =A65+1 -> 54 | C66: 李桃 | D66: =INDEX('05基本'!I:I,MATCH(C66,'05基本'!C:C,0))+INDEX('05基本'!J:J,MATCH(C66,'05基本'!C:C,0)) -> 0 | E66: =INDEX('05基本'!AA:AA,MATCH(C66,'05基本'!C:C,0)) -> 1268.59 | F66: =INDEX('05基本'!AB:AB,MATCH(C66,'05基本'!C:C,0)) -> 477.15 | G66: =INDEX('05基本'!AC:AC,MATCH(C66,'05基本'!C:C,0)) -> 117 | H66: =INDEX('05基本'!K:K,MATCH(C66,'05基本'!C:C,0))+INDEX('05基本'!L:L,MATCH(C66,'05基本'!C:C,0)) -> 0 | I66: =INDEX('05基本'!P:P,MATCH(C66,'05基本'!C:C,0)) -> 900 | J66: =INDEX('05基本'!M:M,MATCH(C66,'05基本'!C:C,0)) -> 0 | K66: =INDEX('05月其他部门提成'!Q:Q,MATCH(C66,'05月其他部门提成'!C:C,0)) -> 6921.4642 | L66: =SUMIF(综合考核!A:A,'05月提成-武侯售后'!C66,综合考核!M:M) -> 0 | M66: =SUM(K66:L66) -> 6921.4642 | N66: =SUMIF(服装扣款!C:C,C66,服装扣款!N:N) -> 0 | O66: =M66-N66 -> 6921.4642 | P66: =SUMIF(超市公积金!C:C,'05月提成-武侯售后'!C66,超市公积金!I:I) -> 0 | Q66: =SUMIF(综合考核!A:A,'05月提成-武侯售后'!C66,综合考核!N:N) -> 0 | R66: =M66+I66+Q66 -> 7821.4642 | S66: =INDEX(AC:AC,MATCH(C66,AB:AB,0)) -> 66.82 | U66: =S66-T66 -> 66.82 | V66: =INDEX('05基本'!AF:AF,MATCH(C66,'05基本'!C:C,0)) -> 0 | W66: =O66-P66-U66 -> 6854.6442 | Y66: =SUM(Z66:AA66) -> 0 | Z66: =INDEX('05月其他部门提成'!S:S,MATCH(C66,'05月其他部门提成'!C:C,0)) -> 0 | AB66: 冉维朗 | AC66: 48.08 | AD66: =COUNTIF(C:C,C66) -> 1 | AE66: =INDEX('05基本'!P:P,MATCH(C66,'05基本'!C:C,0))-I66 -> 0 | AF66: =SUMIF('05月其他部门提成'!C:C,'05月提成-武侯售后'!C66,'05月其他部门提成'!Q:Q) -> 6921.4642 | AG66: =SUMIF('05月车间提成'!C:C,'05月提成-武侯售后'!C66,'05月车间提成'!W:W) -> 0 | AH66: =SUMIF('05月业务提成'!B:B,'05月提成-武侯售后'!C66,'05月业务提成'!BO:BO) -> 0 | AI66: =AF66+AG66+AH66 -> 6921.4642 | AJ66: =AI66-K66 -> 0
A67: =A66+1 -> 55 | C67: 宋航 | D67: =INDEX('05基本'!I:I,MATCH(C67,'05基本'!C:C,0))+INDEX('05基本'!J:J,MATCH(C67,'05基本'!C:C,0)) -> 0 | E67: =INDEX('05基本'!AA:AA,MATCH(C67,'05基本'!C:C,0)) -> 1268.59 | F67: =INDEX('05基本'!AB:AB,MATCH(C67,'05基本'!C:C,0)) -> 477.15 | G67: =INDEX('05基本'!AC:AC,MATCH(C67,'05基本'!C:C,0)) -> 117 | H67: =INDEX('05基本'!K:K,MATCH(C67,'05基本'!C:C,0))+INDEX('05基本'!L:L,MATCH(C67,'05基本'!C:C,0)) -> 0 | I67: =INDEX('05基本'!P:P,MATCH(C67,'05基本'!C:C,0)) -> 900 | J67: =INDEX('05基本'!M:M,MATCH(C67,'05基本'!C:C,0)) -> 0 | K67: =INDEX('05月其他部门提成'!Q:Q,MATCH(C67,'05月其他部门提成'!C:C,0)) -> 6921.4642 | L67: =SUMIF(综合考核!A:A,'05月提成-武侯售后'!C67,综合考核!M:M) -> 0 | M67: =SUM(K67:L67) -> 6921.4642 | N67: =SUMIF(服装扣款!C:C,C67,服装扣款!N:N) -> 0 | O67: =M67-N67 -> 6921.4642 | P67: =SUMIF(超市公积金!C:C,'05月提成-武侯售后'!C67,超市公积金!I:I) -> 0 | Q67: =SUMIF(综合考核!A:A,'05月提成-武侯售后'!C67,综合考核!N:N) -> 0 | R67: =M67+I67+Q67 -> 7821.4642 | S67: =INDEX(AC:AC,MATCH(C67,AB:AB,0)) -> 66.82 | U67: =S67-T67 -> 66.82 | V67: =INDEX('05基本'!AF:AF,MATCH(C67,'05基本'!C:C,0)) -> 0 | W67: =O67-P67-U67 -> 6854.6442 | Y67: =SUM(Z67:AA67) -> 0 | Z67: =INDEX('05月其他部门提成'!S:S,MATCH(C67,'05月其他部门提成'!C:C,0)) -> 0 | AB67: 柳超 | AC67: 0 | AD67: =COUNTIF(C:C,C67) -> 1 | AE67: =INDEX('05基本'!P:P,MATCH(C67,'05基本'!C:C,0))-I67 -> 0 | AF67: =SUMIF('05月其他部门提成'!C:C,'05月提成-武侯售后'!C67,'05月其他部门提成'!Q:Q) -> 6921.4642 | AG67: =SUMIF('05月车间提成'!C:C,'05月提成-武侯售后'!C67,'05月车间提成'!W:W) -> 0 | AH67: =SUMIF('05月业务提成'!B:B,'05月提成-武侯售后'!C67,'05月业务提成'!BO:BO) -> 0 | AI67: =AF67+AG67+AH67 -> 6921.4642 | AJ67: =AI67-K67 -> 0
A68: =A67+1 -> 56 | C68: 伍成勇 | D68: =INDEX('05基本'!I:I,MATCH(C68,'05基本'!C:C,0))+INDEX('05基本'!J:J,MATCH(C68,'05基本'!C:C,0)) -> 0 | E68: =INDEX('05基本'!AA:AA,MATCH(C68,'05基本'!C:C,0)) -> 1268.59 | F68: =INDEX('05基本'!AB:AB,MATCH(C68,'05基本'!C:C,0)) -> 477.15 | G68: =INDEX('05基本'!AC:AC,MATCH(C68,'05基本'!C:C,0)) -> 117 | H68: =INDEX('05基本'!K:K,MATCH(C68,'05基本'!C:C,0))+INDEX('05基本'!L:L,MATCH(C68,'05基本'!C:C,0)) -> 0 | I68: =INDEX('05基本'!P:P,MATCH(C68,'05基本'!C:C,0)) -> 900 | J68: =INDEX('05基本'!M:M,MATCH(C68,'05基本'!C:C,0)) -> 0 | K68: =INDEX('05月其他部门提成'!Q:Q,MATCH(C68,'05月其他部门提成'!C:C,0)) -> 6893.2642 | L68: =SUMIF(综合考核!A:A,'05月提成-武侯售后'!C68,综合考核!M:M) -> 0 | M68: =SUM(K68:L68) -> 6893.2642 | N68: =SUMIF(服装扣款!C:C,C68,服装扣款!N:N) -> 0 | O68: =M68-N68 -> 6893.2642 | P68: =SUMIF(超市公积金!C:C,'05月提成-武侯售后'!C68,超市公积金!I:I) -> 0 | Q68: =SUMIF(综合考核!A:A,'05月提成-武侯售后'!C68,综合考核!N:N) -> 0 | R68: =M68+I68+Q68 -> 7793.2642 | S68: =INDEX(AC:AC,MATCH(C68,AB:AB,0)) -> 65.98 | U68: =S68-T68 -> 65.98 | V68: =INDEX('05基本'!AF:AF,MATCH(C68,'05基本'!C:C,0)) -> 0 | W68: =O68-P68-U68 -> 6827.2842 | Y68: =SUM(Z68:AA68) -> 0 | Z68: =INDEX('05月其他部门提成'!S:S,MATCH(C68,'05月其他部门提成'!C:C,0)) -> 0 | AB68: 杨洋 | AC68: 53.38 | AD68: =COUNTIF(C:C,C68) -> 1 | AE68: =INDEX('05基本'!P:P,MATCH(C68,'05基本'!C:C,0))-I68 -> 0 | AF68: =SUMIF('05月其他部门提成'!C:C,'05月提成-武侯售后'!C68,'05月其他部门提成'!Q:Q) -> 6893.2642 | AG68: =SUMIF('05月车间提成'!C:C,'05月提成-武侯售后'!C68,'05月车间提成'!W:W) -> 0 | AH68: =SUMIF('05月业务提成'!B:B,'05月提成-武侯售后'!C68,'05月业务提成'!BO:BO) -> 0 | AI68: =AF68+AG68+AH68 -> 6893.2642 | AJ68: =AI68-K68 -> 0
C69: 小计 | D69: =SUM(D63:D68) -> 0 | E69: =SUM(E63:E68) -> 7714.95 | F69: =SUM(F63:F68) -> 2905.75 | G69: =SUM(G63:G68) -> 702 | H69: =SUM(H63:H68) -> 0 | I69: =SUM(I63:I68) -> 6200 | J69: =SUM(J63:J68) -> 0 | K69: =SUM(K63:K68) -> 45793.796 | ... AA69: =SUM(AA63:AA68) -> 0 | AB69: 王华通 | AC69: 0 | AD69: =COUNTIF(C:C,C69) -> 11 | AE69: =INDEX('05基本'!P:P,MATCH(C69,'05基本'!C:C,0))-I69 -> #N/A
B70: 小计 | D70: =D8+D19+D45+D62+D69+D58+D26+D42+D14 -> 448 | E70: =E8+E19+E45+E62+E69+E58+E26+E42+E14 -> 61817.14 | F70: =F8+F19+F45+F62+F69+F58+F26+F42+F14 -> 23282.6 | G70: =G8+G19+G45+G62+G69+G58+G26+G42+G14 -> 5616 | H70: =H8+H19+H45+H62+H69+H58+H26+H42+H14 -> 2824 | I70: =I8+I19+I45+I62+I69+I58+I26+I42+I14 -> 74832 | J70: =J8+J19+J45+J62+J69+J58+J26+J42+J14 -> 2000 | K70: =K8+K19+K45+K62+K69+K58+K26+K42+K14 -> 363174.85 | ... AA70: =AA8+AA19+AA45+AA62+AA69+AA58+AA26+AA42+AA14 -> 4053.8206 | AB70: 谢波桃 | AC70: 72.39 | AD70: =COUNTIF(C:C,C70) -> 0 | AE70: =INDEX('05基本'!P:P,MATCH(C70,'05基本'!C:C,0))-I70 -> #N/A
A71: =A68+1 -> 57 | B71: 车间管理 | C71: 何毅 | D71: =INDEX('05基本'!I:I,MATCH(C71,'05基本'!C:C,0))+INDEX('05基本'!J:J,MATCH(C71,'05基本'!C:C,0)) -> 0 | E71: =INDEX('05基本'!AA:AA,MATCH(C71,'05基本'!C:C,0)) -> 1268.59 | F71: =INDEX('05基本'!AB:AB,MATCH(C71,'05基本'!C:C,0)) -> 477.15 | G71: =INDEX('05基本'!AC:AC,MATCH(C71,'05基本'!C:C,0)) -> 117 | H71: =INDEX('05基本'!K:K,MATCH(C71,'05基本'!C:C,0))+INDEX('05基本'!L:L,MATCH(C71,'05基本'!C:C,0)) -> 100 | I71: =INDEX('05基本'!P:P,MATCH(C71,'05基本'!C:C,0)) -> 1700 | J71: =INDEX('05基本'!M:M,MATCH(C71,'05基本'!C:C,0)) -> 0 | K71: =INDEX('05月其他部门提成'!Q:Q,MATCH(C71,'05月其他部门提成'!C:C,0)) -> 12324.34 | L71: =SUMIF(综合考核!A:A,'05月提成-武侯售后'!C71,综合考核!M:M) -> 0 | M71: =SUM(K71:L71) -> 12324.34 | N71: =SUMIF(服装扣款!C:C,C71,服装扣款!N:N) -> 0 | O71: =M71-N71 -> 12324.34 | P71: =SUMIF(超市公积金!C:C,'05月提成-武侯售后'!C71,超市公积金!I:I) -> 0 | Q71: =SUMIF(综合考核!A:A,'05月提成-武侯售后'!C71,综合考核!N:N) -> 0 | R71: =M71+I71+Q71 -> 14024.34 | S71: =INDEX(AC:AC,MATCH(C71,AB:AB,0)) -> 102.9 | U71: =S71-T71 -> 102.9 | V71: =INDEX('05基本'!AF:AF,MATCH(C71,'05基本'!C:C,0)) -> 0 | W71: =O71-P71-U71 -> 12221.44 | Y71: =SUM(Z71:AA71) -> 648.64949 | Z71: =INDEX('05月其他部门提成'!S:S,MATCH(C71,'05月其他部门提成'!C:C,0)) -> 648.64949 | AB71: 吴德亮 | AC71: 0 | AD71: =COUNTIF(C:C,C71) -> 1 | AE71: =INDEX('05基本'!P:P,MATCH(C71,'05基本'!C:C,0))-I71 -> 0 | AF71: =SUMIF('05月其他部门提成'!C:C,'05月提成-武侯售后'!C71,'05月其他部门提成'!Q:Q) -> 12324.34 | AG71: =SUMIF('05月车间提成'!C:C,'05月提成-武侯售后'!C71,'05月车间提成'!W:W) -> 0 | AH71: =SUMIF('05月业务提成'!B:B,'05月提成-武侯售后'!C71,'05月业务提成'!BO:BO) -> 0 | AI71: =AF71+AG71+AH71 -> 12324.34 | AJ71: =AI71-K71 -> 0
A72: =A71+1 -> 58 | C72: 王竹飞 | D72: =INDEX('05基本'!I:I,MATCH(C72,'05基本'!C:C,0))+INDEX('05基本'!J:J,MATCH(C72,'05基本'!C:C,0)) -> 0 | E72: =INDEX('05基本'!AA:AA,MATCH(C72,'05基本'!C:C,0)) -> 1268.59 | F72: =INDEX('05基本'!AB:AB,MATCH(C72,'05基本'!C:C,0)) -> 477.15 | G72: =INDEX('05基本'!AC:AC,MATCH(C72,'05基本'!C:C,0)) -> 117 | H72: =INDEX('05基本'!K:K,MATCH(C72,'05基本'!C:C,0))+INDEX('05基本'!L:L,MATCH(C72,'05基本'!C:C,0)) -> 100 | I72: =INDEX('05基本'!P:P,MATCH(C72,'05基本'!C:C,0)) -> 1700 | J72: =INDEX('05基本'!M:M,MATCH(C72,'05基本'!C:C,0)) -> 0 | K72: =INDEX('05月其他部门提成'!Q:Q,MATCH(C72,'05月其他部门提成'!C:C,0)) -> 12324.34 | L72: =SUMIF(综合考核!A:A,'05月提成-武侯售后'!C72,综合考核!M:M) -> 0 | M72: =SUM(K72:L72) -> 12324.34 | N72: =SUMIF(服装扣款!C:C,C72,服装扣款!N:N) -> 0 | O72: =M72-N72 -> 12324.34 | P72: =SUMIF(超市公积金!C:C,'05月提成-武侯售后'!C72,超市公积金!I:I) -> 0 | Q72: =SUMIF(综合考核!A:A,'05月提成-武侯售后'!C72,综合考核!N:N) -> 0 | R72: =M72+I72+Q72 -> 14024.34 | S72: =INDEX(AC:AC,MATCH(C72,AB:AB,0)) -> 102.91 | U72: =S72-T72 -> 102.91 | V72: =INDEX('05基本'!AF:AF,MATCH(C72,'05基本'!C:C,0)) -> 0 | W72: =O72-P72-U72 -> 12221.43 | Y72: =SUM(Z72:AA72) -> 648.64949 | Z72: =INDEX('05月其他部门提成'!S:S,MATCH(C72,'05月其他部门提成'!C:C,0)) -> 648.64949 | AB72: 蔡青山 | AC72: 99.98 | AD72: =COUNTIF(C:C,C72) -> 1 | AE72: =INDEX('05基本'!P:P,MATCH(C72,'05基本'!C:C,0))-I72 -> 0 | AF72: =SUMIF('05月其他部门提成'!C:C,'05月提成-武侯售后'!C72,'05月其他部门提成'!Q:Q) -> 12324.34 | AG72: =SUMIF('05月车间提成'!C:C,'05月提成-武侯售后'!C72,'05月车间提成'!W:W) -> 0 | AH72: =SUMIF('05月业务提成'!B:B,'05月提成-武侯售后'!C72,'05月业务提成'!BO:BO) -> 0 | AI72: =AF72+AG72+AH72 -> 12324.34 | AJ72: =AI72-K72 -> 0
A73: =A72+1 -> 59 | C73: 周劲松 | D73: =INDEX('05基本'!I:I,MATCH(C73,'05基本'!C:C,0))+INDEX('05基本'!J:J,MATCH(C73,'05基本'!C:C,0)) -> 0 | E73: =INDEX('05基本'!AA:AA,MATCH(C73,'05基本'!C:C,0)) -> 1268.59 | F73: =INDEX('05基本'!AB:AB,MATCH(C73,'05基本'!C:C,0)) -> 477.15 | G73: =INDEX('05基本'!AC:AC,MATCH(C73,'05基本'!C:C,0)) -> 117 | H73: =INDEX('05基本'!K:K,MATCH(C73,'05基本'!C:C,0))+INDEX('05基本'!L:L,MATCH(C73,'05基本'!C:C,0)) -> 0 | I73: =INDEX('05基本'!P:P,MATCH(C73,'05基本'!C:C,0)) -> 1200 | J73: =INDEX('05基本'!M:M,MATCH(C73,'05基本'!C:C,0)) -> 0 | K73: =INDEX('05月其他部门提成'!Q:Q,MATCH(C73,'05月其他部门提成'!C:C,0)) -> 8713.317 | L73: =SUMIF(综合考核!A:A,'05月提成-武侯售后'!C73,综合考核!M:M) -> 0 | M73: =SUM(K73:L73) -> 8713.317 | N73: =SUMIF(服装扣款!C:C,C73,服装扣款!N:N) -> 0 | O73: =M73-N73 -> 8713.317 | P73: =SUMIF(超市公积金!C:C,'05月提成-武侯售后'!C73,超市公积金!I:I) -> 0 | Q73: =SUMIF(综合考核!A:A,'05月提成-武侯售后'!C73,综合考核!N:N) -> 0 | R73: =M73+I73+Q73 -> 9913.317 | S73: =INDEX(AC:AC,MATCH(C73,AB:AB,0)) -> 0 | U73: =S73-T73 -> 0 | V73: =INDEX('05基本'!AF:AF,MATCH(C73,'05基本'!C:C,0)) -> 0 | W73: =O73-P73-U73 -> 8713.317 | Y73: =SUM(Z73:AA73) -> 614.14232 | Z73: =INDEX('05月其他部门提成'!S:S,MATCH(C73,'05月其他部门提成'!C:C,0)) -> 614.14232 | AB73: 廖君 | AC73: 51.33 | AD73: =COUNTIF(C:C,C73) -> 1 | AE73: =INDEX('05基本'!P:P,MATCH(C73,'05基本'!C:C,0))-I73 -> 0 | AF73: =SUMIF('05月其他部门提成'!C:C,'05月提成-武侯售后'!C73,'05月其他部门提成'!Q:Q) -> 8713.317 | AG73: =SUMIF('05月车间提成'!C:C,'05月提成-武侯售后'!C73,'05月车间提成'!W:W) -> 0 | AH73: =SUMIF('05月业务提成'!B:B,'05月提成-武侯售后'!C73,'05月业务提成'!BO:BO) -> 0 | AI73: =AF73+AG73+AH73 -> 8713.317 | AJ73: =AI73-K73 -> 0
A74: =A73+1 -> 60 | C74: 田建勇 | D74: =INDEX('05基本'!I:I,MATCH(C74,'05基本'!C:C,0))+INDEX('05基本'!J:J,MATCH(C74,'05基本'!C:C,0)) -> 0 | E74: =INDEX('05基本'!AA:AA,MATCH(C74,'05基本'!C:C,0)) -> 1268.59 | F74: =INDEX('05基本'!AB:AB,MATCH(C74,'05基本'!C:C,0)) -> 477.15 | G74: =INDEX('05基本'!AC:AC,MATCH(C74,'05基本'!C:C,0)) -> 117 | H74: =INDEX('05基本'!K:K,MATCH(C74,'05基本'!C:C,0))+INDEX('05基本'!L:L,MATCH(C74,'05基本'!C:C,0)) -> 0 | I74: =INDEX('05基本'!P:P,MATCH(C74,'05基本'!C:C,0)) -> 1200 | J74: =INDEX('05基本'!M:M,MATCH(C74,'05基本'!C:C,0)) -> 0 | K74: =INDEX('05月其他部门提成'!Q:Q,MATCH(C74,'05月其他部门提成'!C:C,0)) -> 8713.317 | L74: =SUMIF(综合考核!A:A,'05月提成-武侯售后'!C74,综合考核!M:M) -> 0 | M74: =SUM(K74:L74) -> 8713.317 | N74: =SUMIF(服装扣款!C:C,C74,服装扣款!N:N) -> 0 | O74: =M74-N74 -> 8713.317 | P74: =SUMIF(超市公积金!C:C,'05月提成-武侯售后'!C74,超市公积金!I:I) -> 0 | Q74: =SUMIF(综合考核!A:A,'05月提成-武侯售后'!C74,综合考核!N:N) -> 0 | R74: =M74+I74+Q74 -> 9913.317 | S74: =INDEX(AC:AC,MATCH(C74,AB:AB,0)) -> 84.58 | U74: =S74-T74 -> 84.58 | V74: =INDEX('05基本'!AF:AF,MATCH(C74,'05基本'!C:C,0)) -> 0 | W74: =O74-P74-U74 -> 8628.737 | Y74: =SUM(Z74:AA74) -> 614.14232 | Z74: =INDEX('05月其他部门提成'!S:S,MATCH(C74,'05月其他部门提成'!C:C,0)) -> 614.14232 | AB74: 李欢 | AC74: 0 | AD74: =COUNTIF(C:C,C74) -> 1 | AE74: =INDEX('05基本'!P:P,MATCH(C74,'05基本'!C:C,0))-I74 -> 0 | AF74: =SUMIF('05月其他部门提成'!C:C,'05月提成-武侯售后'!C74,'05月其他部门提成'!Q:Q) -> 8713.317 | AG74: =SUMIF('05月车间提成'!C:C,'05月提成-武侯售后'!C74,'05月车间提成'!W:W) -> 0 | AH74: =SUMIF('05月业务提成'!B:B,'05月提成-武侯售后'!C74,'05月业务提成'!BO:BO) -> 0 | AI74: =AF74+AG74+AH74 -> 8713.317 | AJ74: =AI74-K74 -> 0
A75: =A74+1 -> 61 | C75: 宋虹冰 | D75: =INDEX('05基本'!I:I,MATCH(C75,'05基本'!C:C,0))+INDEX('05基本'!J:J,MATCH(C75,'05基本'!C:C,0)) -> 0 | E75: =INDEX('05基本'!AA:AA,MATCH(C75,'05基本'!C:C,0)) -> 1268.59 | F75: =INDEX('05基本'!AB:AB,MATCH(C75,'05基本'!C:C,0)) -> 477.15 | G75: =INDEX('05基本'!AC:AC,MATCH(C75,'05基本'!C:C,0)) -> 117 | H75: =INDEX('05基本'!K:K,MATCH(C75,'05基本'!C:C,0))+INDEX('05基本'!L:L,MATCH(C75,'05基本'!C:C,0)) -> 0 | I75: =INDEX('05基本'!P:P,MATCH(C75,'05基本'!C:C,0)) -> 1200 | J75: =INDEX('05基本'!M:M,MATCH(C75,'05基本'!C:C,0)) -> 0 | K75: =INDEX('05月其他部门提成'!Q:Q,MATCH(C75,'05月其他部门提成'!C:C,0)) -> 10714.68 | L75: =SUMIF(综合考核!A:A,'05月提成-武侯售后'!C75,综合考核!M:M) -> 0 | M75: =SUM(K75:L75) -> 10714.68 | N75: =SUMIF(服装扣款!C:C,C75,服装扣款!N:N) -> 0 | O75: =M75-N75 -> 10714.68 | P75: =SUMIF(超市公积金!C:C,'05月提成-武侯售后'!C75,超市公积金!I:I) -> 0 | Q75: =SUMIF(综合考核!A:A,'05月提成-武侯售后'!C75,综合考核!N:N) -> 0 | R75: =M75+I75+Q75 -> 11914.68 | S75: =INDEX(AC:AC,MATCH(C75,AB:AB,0)) -> 189.61 | U75: =S75-T75 -> 189.61 | V75: =INDEX('05基本'!AF:AF,MATCH(C75,'05基本'!C:C,0)) -> 0 | W75: =O75-P75-U75 -> 10525.07 | Y75: =SUM(Z75:AA75) -> 563.93052 | Z75: =INDEX('05月其他部门提成'!S:S,MATCH(C75,'05月其他部门提成'!C:C,0)) -> 563.93052 | AB75: 李建国 | AC75: 0 | AD75: =COUNTIF(C:C,C75) -> 1 | AE75: =INDEX('05基本'!P:P,MATCH(C75,'05基本'!C:C,0))-I75 -> 0 | AF75: =SUMIF('05月其他部门提成'!C:C,'05月提成-武侯售后'!C75,'05月其他部门提成'!Q:Q) -> 10714.68 | AG75: =SUMIF('05月车间提成'!C:C,'05月提成-武侯售后'!C75,'05月车间提成'!W:W) -> 0 | AH75: =SUMIF('05月业务提成'!B:B,'05月提成-武侯售后'!C75,'05月业务提成'!BO:BO) -> 0 | AI75: =AF75+AG75+AH75 -> 10714.68 | AJ75: =AI75-K75 -> 0
C76: 小计 | D76: =SUM(D71:D75) -> 0 | E76: =SUM(E71:E75) -> 6342.95 | F76: =SUM(F71:F75) -> 2385.75 | G76: =SUM(G71:G75) -> 585 | H76: =SUM(H71:H75) -> 200 | I76: =SUM(I71:I75) -> 7000 | J76: =SUM(J71:J75) -> 0 | K76: =SUM(K71:K75) -> 52789.995 | ... AA76: =SUM(AA71:AA75) -> 0 | AB76: 左三明 | AC76: 38.59 | AD76: =COUNTIF(C:C,C76) -> 11 | AE76: =INDEX('05基本'!P:P,MATCH(C76,'05基本'!C:C,0))-I76 -> #N/A
A77: =A75+1 -> 62 | B77: 机一 | C77: 冉维朗 | D77: =INDEX('05基本'!I:I,MATCH(C77,'05基本'!C:C,0))+INDEX('05基本'!J:J,MATCH(C77,'05基本'!C:C,0)) -> 40 | E77: =INDEX('05基本'!AA:AA,MATCH(C77,'05基本'!C:C,0)) -> 1268.59 | F77: =INDEX('05基本'!AB:AB,MATCH(C77,'05基本'!C:C,0)) -> 477.15 | G77: =INDEX('05基本'!AC:AC,MATCH(C77,'05基本'!C:C,0)) -> 117 | H77: =INDEX('05基本'!K:K,MATCH(C77,'05基本'!C:C,0))+INDEX('05基本'!L:L,MATCH(C77,'05基本'!C:C,0)) -> 0 | I77: =INDEX('05基本'!P:P,MATCH(C77,'05基本'!C:C,0)) -> 1140 | J77: =INDEX('05基本'!M:M,MATCH(C77,'05基本'!C:C,0)) -> 0 | K77: =INDEX('05月车间提成'!W:W,MATCH(C77,'05月车间提成'!C:C,0)) -> 6056.6059 | L77: =SUMIF(综合考核!A:A,'05月提成-武侯售后'!C77,综合考核!M:M) -> 0 | M77: =SUM(K77:L77) -> 6056.6059 | N77: =SUMIF(服装扣款!C:C,C77,服装扣款!N:N) -> 0 | O77: =M77-N77 -> 6056.6059 | P77: =SUMIF(超市公积金!C:C,'05月提成-武侯售后'!C77,超市公积金!I:I) -> 0 | Q77: =SUMIF(综合考核!A:A,'05月提成-武侯售后'!C77,综合考核!N:N) -> 0 | R77: =M77+I77+Q77 -> 7196.6059 | S77: =INDEX(AC:AC,MATCH(C77,AB:AB,0)) -> 48.08 | U77: =S77-T77 -> 48.08 | V77: =INDEX('05基本'!AF:AF,MATCH(C77,'05基本'!C:C,0)) -> 0 | W77: =O77-P77-U77 -> 6008.5259 | Y77: =SUM(Z77:AA77) -> 647.89475 | Z77: =(INDEX('05月车间提成'!D:D,MATCH(C79,'05月车间提成'!C:C,0))-INDEX('05月车间提成'!F:F,MATCH('05月车间提成'!C7,'05月车间提成'!C:C,0)))*0.29*0.05+INDEX('05月车间提成'!E:E,MATCH(C79,'05月车间提成'!C:C,0))*0.33*0.05 -> 590.80975 | AA77: =INDEX('05月车间提成'!J:J,MATCH(C79,'05月车间提成'!C:C,0))*0.05*INDEX('05月车间提成'!K:K,MATCH(C79,'05月车间提成'!C:C,0)) -> 57.085 | AB77: 李伦伟 | AC77: 0 | AD77: =COUNTIF(C:C,C77) -> 1 | AE77: =INDEX('05基本'!P:P,MATCH(C77,'05基本'!C:C,0))-I77 -> 0 | AF77: =SUMIF('05月其他部门提成'!C:C,'05月提成-武侯售后'!C77,'05月其他部门提成'!Q:Q) -> 0 | AG77: =SUMIF('05月车间提成'!C:C,'05月提成-武侯售后'!C77,'05月车间提成'!W:W) -> 6056.6059 | AH77: =SUMIF('05月业务提成'!B:B,'05月提成-武侯售后'!C77,'05月业务提成'!BO:BO) -> 0 | AI77: =AF77+AG77+AH77 -> 6056.6059 | AJ77: =AI77-K77 -> 0
A78: =A77+1 -> 63 | C78: 柳超 | D78: =INDEX('05基本'!I:I,MATCH(C78,'05基本'!C:C,0))+INDEX('05基本'!J:J,MATCH(C78,'05基本'!C:C,0)) -> 40 | E78: =INDEX('05基本'!AA:AA,MATCH(C78,'05基本'!C:C,0)) -> 1268.59 | F78: =INDEX('05基本'!AB:AB,MATCH(C78,'05基本'!C:C,0)) -> 477.15 | G78: =INDEX('05基本'!AC:AC,MATCH(C78,'05基本'!C:C,0)) -> 117 | H78: =INDEX('05基本'!K:K,MATCH(C78,'05基本'!C:C,0))+INDEX('05基本'!L:L,MATCH(C78,'05基本'!C:C,0)) -> 0 | I78: =INDEX('05基本'!P:P,MATCH(C78,'05基本'!C:C,0)) -> 940 | J78: =INDEX('05基本'!M:M,MATCH(C78,'05基本'!C:C,0)) -> 0 | K78: =INDEX('05月车间提成'!W:W,MATCH(C78,'05月车间提成'!C:C,0)) -> 4467.4544 | L78: =SUMIF(综合考核!A:A,'05月提成-武侯售后'!C78,综合考核!M:M) -> 0 | M78: =SUM(K78:L78) -> 4467.4544 | N78: =SUMIF(服装扣款!C:C,C78,服装扣款!N:N) -> 0 | O78: =M78-N78 -> 4467.4544 | P78: =SUMIF(超市公积金!C:C,'05月提成-武侯售后'!C78,超市公积金!I:I) -> 0 | Q78: =SUMIF(综合考核!A:A,'05月提成-武侯售后'!C78,综合考核!N:N) -> 0 | R78: =M78+I78+Q78 -> 5407.4544 | S78: =INDEX(AC:AC,MATCH(C78,AB:AB,0)) -> 0 | U78: =S78-T78 -> 0 | V78: =INDEX('05基本'!AF:AF,MATCH(C78,'05基本'!C:C,0)) -> 0 | W78: =O78-P78-U78 -> 4467.4544 | Y78: =SUM(Z78:AA78) -> 647.89475 | Z78: =(INDEX('05月车间提成'!D:D,MATCH(C79,'05月车间提成'!C:C,0))-INDEX('05月车间提成'!F:F,MATCH('05月车间提成'!C7,'05月车间提成'!C:C,0)))*0.29*0.05+INDEX('05月车间提成'!E:E,MATCH(C79,'05月车间提成'!C:C,0))*0.33*0.05 -> 590.80975 | AA78: =INDEX('05月车间提成'!J:J,MATCH(C79,'05月车间提成'!C:C,0))*0.05*INDEX('05月车间提成'!K:K,MATCH(C79,'05月车间提成'!C:C,0)) -> 57.085 | AB78: 刘新宇 | AC78: 0 | AD78: =COUNTIF(C:C,C78) -> 1 | AE78: =INDEX('05基本'!P:P,MATCH(C78,'05基本'!C:C,0))-I78 -> 0 | AF78: =SUMIF('05月其他部门提成'!C:C,'05月提成-武侯售后'!C78,'05月其他部门提成'!Q:Q) -> 0 | AG78: =SUMIF('05月车间提成'!C:C,'05月提成-武侯售后'!C78,'05月车间提成'!W:W) -> 4467.4544 | AH78: =SUMIF('05月业务提成'!B:B,'05月提成-武侯售后'!C78,'05月业务提成'!BO:BO) -> 0 | AI78: =AF78+AG78+AH78 -> 4467.4544 | AJ78: =AI78-K78 -> 0
C79: 机修一组 | D79: =SUM(D77:D78) -> 80 | E79: =SUM(E77:E78) -> 2537.18 | F79: =SUM(F77:F78) -> 954.3 | G79: =SUM(G77:G78) -> 234 | H79: =SUM(H77:H78) -> 0 | I79: =SUM(I77:I78) -> 2080 | J79: =SUM(J77:J78) -> 0 | K79: =SUM(K77:K78) -> 10524.06 | ... P79: =SUM(P77:P78) -> 0 | Q79: =SUM(Q77:Q77) -> 0 | R79: =SUM(R77:R78) -> 12604.06 | S79: =SUM(S77:S78) -> 48.08 | T79: =SUM(T77:T78) -> 0 | U79: =SUM(U77:U78) -> 48.08 | V79: =SUM(V77:V78) -> 0 | W79: =SUM(W77:W78) -> 10475.98 | X79: =SUM(X77:X78) -> 0 | Y79: =SUM(Y77:Y78) -> 1295.7895 | ... AA79: =SUM(AA77:AA78) -> 114.17 | AB79: 章东 | AC79: 41.15 | AD79: =COUNTIF(C:C,C79) -> 1 | AE79: =INDEX('05基本'!P:P,MATCH(C79,'05基本'!C:C,0))-I79 -> #N/A
A80: =A78+1 -> 64 | B80: 机二 | C80: 杨洋 | D80: =INDEX('05基本'!I:I,MATCH(C80,'05基本'!C:C,0))+INDEX('05基本'!J:J,MATCH(C80,'05基本'!C:C,0)) -> 30 | E80: =INDEX('05基本'!AA:AA,MATCH(C80,'05基本'!C:C,0)) -> 1268.59 | F80: =INDEX('05基本'!AB:AB,MATCH(C80,'05基本'!C:C,0)) -> 477.15 | G80: =INDEX('05基本'!AC:AC,MATCH(C80,'05基本'!C:C,0)) -> 117 | H80: =INDEX('05基本'!K:K,MATCH(C80,'05基本'!C:C,0))+INDEX('05基本'!L:L,MATCH(C80,'05基本'!C:C,0)) -> 0 | I80: =INDEX('05基本'!P:P,MATCH(C80,'05基本'!C:C,0)) -> 1130 | J80: =INDEX('05基本'!M:M,MATCH(C80,'05基本'!C:C,0)) -> 0 | K80: =INDEX('05月车间提成'!W:W,MATCH(C80,'05月车间提成'!C:C,0)) -> 7243.5058 | L80: =SUMIF(综合考核!A:A,'05月提成-武侯售后'!C80,综合考核!M:M) -> 0 | M80: =SUM(K80:L80) -> 7243.5058 | N80: =SUMIF(服装扣款!C:C,C80,服装扣款!N:N) -> 0 | O80: =M80-N80 -> 7243.5058 | P80: =SUMIF(超市公积金!C:C,'05月提成-武侯售后'!C80,超市公积金!I:I) -> 0 | Q80: =SUMIF(综合考核!A:A,'05月提成-武侯售后'!C80,综合考核!N:N) -> 0 | R80: =M80+I80+Q80 -> 8373.5058 | S80: =INDEX(AC:AC,MATCH(C80,AB:AB,0)) -> 53.38 | U80: =S80-T80 -> 53.38 | V80: =INDEX('05基本'!AF:AF,MATCH(C80,'05基本'!C:C,0)) -> 0 | W80: =O80-P80-U80 -> 7190.1258 | Y80: =SUM(Z80:AA80) -> 704.233 | Z80: =(INDEX('05月车间提成'!D:D,MATCH(C82,'05月车间提成'!C:C,0))-INDEX('05月车间提成'!F:F,MATCH('05月车间提成'!C10,'05月车间提成'!C:C,0)))*0.29*0.05+INDEX('05月车间提成'!E:E,MATCH(C82,'05月车间提成'!C:C,0))*0.33*0.05 -> 654.588 | AA80: =INDEX('05月车间提成'!J:J,MATCH(C82,'05月车间提成'!C:C,0))*0.05*INDEX('05月车间提成'!K:K,MATCH(C82,'05月车间提成'!C:C,0)) -> 49.645 | AB80: 冯波 | AC80: 0 | AD80: =COUNTIF(C:C,C80) -> 1 | AE80: =INDEX('05基本'!P:P,MATCH(C80,'05基本'!C:C,0))-I80 -> 0 | AF80: =SUMIF('05月其他部门提成'!C:C,'05月提成-武侯售后'!C80,'05月其他部门提成'!Q:Q) -> 0 | AG80: =SUMIF('05月车间提成'!C:C,'05月提成-武侯售后'!C80,'05月车间提成'!W:W) -> 7243.5058 | AH80: =SUMIF('05月业务提成'!B:B,'05月提成-武侯售后'!C80,'05月业务提成'!BO:BO) -> 0 | AI80: =AF80+AG80+AH80 -> 7243.5058 | AJ80: =AI80-K80 -> 0
A81: =A80+1 -> 65 | C81: 王华通 | D81: =INDEX('05基本'!I:I,MATCH(C81,'05基本'!C:C,0))+INDEX('05基本'!J:J,MATCH(C81,'05基本'!C:C,0)) -> 30 | E81: =INDEX('05基本'!AA:AA,MATCH(C81,'05基本'!C:C,0)) -> 1268.59 | F81: =INDEX('05基本'!AB:AB,MATCH(C81,'05基本'!C:C,0)) -> 477.15 | G81: =INDEX('05基本'!AC:AC,MATCH(C81,'05基本'!C:C,0)) -> 117 | H81: =INDEX('05基本'!K:K,MATCH(C81,'05基本'!C:C,0))+INDEX('05基本'!L:L,MATCH(C81,'05基本'!C:C,0)) -> 0 | I81: =INDEX('05基本'!P:P,MATCH(C81,'05基本'!C:C,0)) -> 900 | J81: =INDEX('05基本'!M:M,MATCH(C81,'05基本'!C:C,0)) -> 0 | K81: =INDEX('05月车间提成'!W:W,MATCH(C81,'05月车间提成'!C:C,0)) -> 4303.4412 | L81: =SUMIF(综合考核!A:A,'05月提成-武侯售后'!C81,综合考核!M:M) -> 0 | M81: =SUM(K81:L81) -> 4303.4412 | N81: =SUMIF(服装扣款!C:C,C81,服装扣款!N:N) -> 0 | O81: =M81-N81 -> 4303.4412 | P81: =SUMIF(超市公积金!C:C,'05月提成-武侯售后'!C81,超市公积金!I:I) -> 0 | Q81: =SUMIF(综合考核!A:A,'05月提成-武侯售后'!C81,综合考核!N:N) -> 0 | R81: =M81+I81+Q81 -> 5203.4412 | S81: =INDEX(AC:AC,MATCH(C81,AB:AB,0)) -> 0 | U81: =S81-T81 -> 0 | V81: =INDEX('05基本'!AF:AF,MATCH(C81,'05基本'!C:C,0)) -> 0 | W81: =O81-P81-U81 -> 4303.4412 | Y81: =SUM(Z81:AA81) -> 0 | Z81: =(INDEX('05月车间提成'!D:D,MATCH(C83,'05月车间提成'!C:C,0))-INDEX('05月车间提成'!F:F,MATCH('05月车间提成'!C11,'05月车间提成'!C:C,0)))*0.29*0.05+INDEX('05月车间提成'!E:E,MATCH(C83,'05月车间提成'!C:C,0))*0.33*0.05 -> 0 | AA81: =INDEX('05月车间提成'!J:J,MATCH(C83,'05月车间提成'!C:C,0))*0.05*INDEX('05月车间提成'!K:K,MATCH(C83,'05月车间提成'!C:C,0)) -> 0 | AB81: 周俊宏 | AC81: 80.06 | AD81: =COUNTIF(C:C,C81) -> 1 | AE81: =INDEX('05基本'!P:P,MATCH(C81,'05基本'!C:C,0))-I81 -> 0 | AF81: =SUMIF('05月其他部门提成'!C:C,'05月提成-武侯售后'!C81,'05月其他部门提成'!Q:Q) -> 0 | AG81: =SUMIF('05月车间提成'!C:C,'05月提成-武侯售后'!C81,'05月车间提成'!W:W) -> 4303.4412 | AH81: =SUMIF('05月业务提成'!B:B,'05月提成-武侯售后'!C81,'05月业务提成'!BO:BO) -> 0 | AI81: =AF81+AG81+AH81 -> 4303.4412 | AJ81: =AI81-K81 -> 0
C82: 机修二组 | D82: =SUM(D80:D81) -> 60 | E82: =SUM(E80:E81) -> 2537.18 | F82: =SUM(F80:F81) -> 954.3 | G82: =SUM(G80:G81) -> 234 | H82: =SUM(H80:H80) -> 0 | I82: =SUM(I80:I81) -> 2030 | J82: =SUM(J80:J80) -> 0 | K82: =SUM(K80:K81) -> 11546.947 | L82: =SUM(L80:L81) -> 0 | M82: =SUM(M80:M81) -> 11546.947 | N82: =SUM(N80:N81) -> 0 | O82: =SUM(O80:O81) -> 11546.947 | P82: =SUM(P80:P81) -> 0 | Q82: =SUM(Q80:Q81) -> 0 | R82: =SUM(R80:R81) -> 13576.947 | ... AA82: =SUM(AA80:AA81) -> 49.645 | AB82: 易林江 | AC82: 103.32 | AD82: =COUNTIF(C:C,C82) -> 1 | AE82: =INDEX('05基本'!P:P,MATCH(C82,'05基本'!C:C,0))-I82 -> #N/A
A83: =A81+1 -> 66 | B83: 机三 | C83: 谢波桃 | D83: =INDEX('05基本'!I:I,MATCH(C83,'05基本'!C:C,0))+INDEX('05基本'!J:J,MATCH(C83,'05基本'!C:C,0)) -> 40 | E83: =INDEX('05基本'!AA:AA,MATCH(C83,'05基本'!C:C,0)) -> 1268.59 | F83: =INDEX('05基本'!AB:AB,MATCH(C83,'05基本'!C:C,0)) -> 477.15 | G83: =INDEX('05基本'!AC:AC,MATCH(C83,'05基本'!C:C,0)) -> 117 | H83: =INDEX('05基本'!K:K,MATCH(C83,'05基本'!C:C,0))+INDEX('05基本'!L:L,MATCH(C83,'05基本'!C:C,0)) -> 0 | I83: =INDEX('05基本'!P:P,MATCH(C83,'05基本'!C:C,0)) -> 1140 | J83: =INDEX('05基本'!M:M,MATCH(C83,'05基本'!C:C,0)) -> 0 | K83: =INDEX('05月车间提成'!W:W,MATCH(C83,'05月车间提成'!C:C,0)) -> 6867.0913 | L83: =SUMIF(综合考核!A:A,'05月提成-武侯售后'!C83,综合考核!M:M) -> 0 | M83: =SUM(K83:L83) -> 6867.0913 | N83: =SUMIF(服装扣款!C:C,C83,服装扣款!N:N) -> 0 | O83: =M83-N83 -> 6867.0913 | P83: =SUMIF(超市公积金!C:C,'05月提成-武侯售后'!C83,超市公积金!I:I) -> 0 | Q83: =SUMIF(综合考核!A:A,'05月提成-武侯售后'!C83,综合考核!N:N) -> 0 | R83: =M83+I83+Q83 -> 8007.0913 | S83: =INDEX(AC:AC,MATCH(C83,AB:AB,0)) -> 72.39 | U83: =S83-T83 -> 72.39 | V83: =INDEX('05基本'!AF:AF,MATCH(C83,'05基本'!C:C,0)) -> 0 | W83: =O83-P83-U83 -> 6794.7013 | Y83: =SUM(Z83:AA83) -> 675.3431 | Z83: =(INDEX('05月车间提成'!D:D,MATCH(C85,'05月车间提成'!C:C,0))-INDEX('05月车间提成'!F:F,MATCH('05月车间提成'!C13,'05月车间提成'!C:C,0)))*0.29*0.05+INDEX('05月车间提成'!E:E,MATCH(C85,'05月车间提成'!C:C,0))*0.33*0.05 -> 621.5541 | AA83: =INDEX('05月车间提成'!J:J,MATCH(C85,'05月车间提成'!C:C,0))*0.05*INDEX('05月车间提成'!K:K,MATCH(C85,'05月车间提成'!C:C,0)) -> 53.789 | AB83: 罗烽 | AC83: 0 | AD83: =COUNTIF(C:C,C83) -> 1 | AE83: =INDEX('05基本'!P:P,MATCH(C83,'05基本'!C:C,0))-I83 -> 0 | AF83: =SUMIF('05月其他部门提成'!C:C,'05月提成-武侯售后'!C83,'05月其他部门提成'!Q:Q) -> 0 | AG83: =SUMIF('05月车间提成'!C:C,'05月提成-武侯售后'!C83,'05月车间提成'!W:W) -> 6867.0913 | AH83: =SUMIF('05月业务提成'!B:B,'05月提成-武侯售后'!C83,'05月业务提成'!BO:BO) -> 0 | AI83: =AF83+AG83+AH83 -> 6867.0913 | AJ83: =AI83-K83 -> 0
A84: =A83+1 -> 67 | C84: 吴德亮 | D84: =INDEX('05基本'!I:I,MATCH(C84,'05基本'!C:C,0))+INDEX('05基本'!J:J,MATCH(C84,'05基本'!C:C,0)) -> 50 | E84: =INDEX('05基本'!AA:AA,MATCH(C84,'05基本'!C:C,0)) -> 1268.59 | F84: =INDEX('05基本'!AB:AB,MATCH(C84,'05基本'!C:C,0)) -> 477.15 | G84: =INDEX('05基本'!AC:AC,MATCH(C84,'05基本'!C:C,0)) -> 117 | H84: =INDEX('05基本'!K:K,MATCH(C84,'05基本'!C:C,0))+INDEX('05基本'!L:L,MATCH(C84,'05基本'!C:C,0)) -> 0 | I84: =INDEX('05基本'!P:P,MATCH(C84,'05基本'!C:C,0)) -> 850 | J84: =INDEX('05基本'!M:M,MATCH(C84,'05基本'!C:C,0)) -> 0 | K84: =INDEX('05月车间提成'!W:W,MATCH(C84,'05月车间提成'!C:C,0)) -> 4119.2676 | L84: =SUMIF(综合考核!A:A,'05月提成-武侯售后'!C84,综合考核!M:M) -> 0 | M84: =SUM(K84:L84) -> 4119.2676 | N84: =SUMIF(服装扣款!C:C,C84,服装扣款!N:N) -> 0 | O84: =M84-N84 -> 4119.2676 | P84: =SUMIF(超市公积金!C:C,'05月提成-武侯售后'!C84,超市公积金!I:I) -> 0 | Q84: =SUMIF(综合考核!A:A,'05月提成-武侯售后'!C84,综合考核!N:N) -> 0 | R84: =M84+I84+Q84 -> 4969.2676 | S84: =INDEX(AC:AC,MATCH(C84,AB:AB,0)) -> 0 | U84: =S84-T84 -> 0 | V84: =INDEX('05基本'!AF:AF,MATCH(C84,'05基本'!C:C,0)) -> 0 | W84: =O84-P84-U84 -> 4119.2676 | Y84: =SUM(Z84:AA84) -> 0 | AB84: 王浩宇 | AC84: 0 | AD84: =COUNTIF(C:C,C84) -> 1 | AE84: =INDEX('05基本'!P:P,MATCH(C84,'05基本'!C:C,0))-I84 -> 0 | AF84: =SUMIF('05月其他部门提成'!C:C,'05月提成-武侯售后'!C84,'05月其他部门提成'!Q:Q) -> 0 | AG84: =SUMIF('05月车间提成'!C:C,'05月提成-武侯售后'!C84,'05月车间提成'!W:W) -> 4119.2676 | AH84: =SUMIF('05月业务提成'!B:B,'05月提成-武侯售后'!C84,'05月业务提成'!BO:BO) -> 0 | AI84: =AF84+AG84+AH84 -> 4119.2676 | AJ84: =AI84-K84 -> 0
C85: 机修三组 | D85: =SUM(D83:D84) -> 90 | E85: =SUM(E83:E84) -> 2537.18 | F85: =SUM(F83:F84) -> 954.3 | G85: =SUM(G83:G84) -> 234 | H85: =SUM(H83:H84) -> 0 | I85: =SUM(I83:I84) -> 1990 | J85: =SUM(J83:J84) -> 0 | K85: =SUM(K83:K84) -> 10986.359 | ... AA85: =SUM(AA83:AA84) -> 53.789 | AB85: 王鹏 | AC85: 93.08 | AD85: =COUNTIF(C:C,C85) -> 1 | AE85: =INDEX('05基本'!P:P,MATCH(C85,'05基本'!C:C,0))-I85 -> #N/A
A86: =A84+1 -> 68 | B86: 机四 | C86: 蔡青山 | D86: =INDEX('05基本'!I:I,MATCH(C86,'05基本'!C:C,0))+INDEX('05基本'!J:J,MATCH(C86,'05基本'!C:C,0)) -> 20 | E86: =INDEX('05基本'!AA:AA,MATCH(C86,'05基本'!C:C,0)) -> 1268.59 | F86: =INDEX('05基本'!AB:AB,MATCH(C86,'05基本'!C:C,0)) -> 477.15 | G86: =INDEX('05基本'!AC:AC,MATCH(C86,'05基本'!C:C,0)) -> 117 | H86: =INDEX('05基本'!K:K,MATCH(C86,'05基本'!C:C,0))+INDEX('05基本'!L:L,MATCH(C86,'05基本'!C:C,0)) -> 0 | I86: =INDEX('05基本'!P:P,MATCH(C86,'05基本'!C:C,0)) -> 1120 | J86: =INDEX('05基本'!M:M,MATCH(C86,'05基本'!C:C,0)) -> 0 | K86: =INDEX('05月车间提成'!W:W,MATCH(C86,'05月车间提成'!C:C,0)) -> 7806.9899 | L86: =SUMIF(综合考核!A:A,'05月提成-武侯售后'!C86,综合考核!M:M) -> 0 | M86: =SUM(K86:L86) -> 7806.9899 | N86: =SUMIF(服装扣款!C:C,C86,服装扣款!N:N) -> 0 | O86: =M86-N86 -> 7806.9899 | P86: =SUMIF(超市公积金!C:C,'05月提成-武侯售后'!C86,超市公积金!I:I) -> 0 | Q86: =SUMIF(综合考核!A:A,'05月提成-武侯售后'!C86,综合考核!N:N) -> 0 | R86: =M86+I86+Q86 -> 8926.9899 | S86: =INDEX(AC:AC,MATCH(C86,AB:AB,0)) -> 99.98 | U86: =S86-T86 -> 99.98 | V86: =INDEX('05基本'!AF:AF,MATCH(C86,'05基本'!C:C,0)) -> 0 | W86: =O86-P86-U86 -> 7707.0099 | Y86: =SUM(Z86:AA86) -> 457.8321 | Z86: =(INDEX('05月车间提成'!D:D,MATCH(C87,'05月车间提成'!C:C,0))-INDEX('05月车间提成'!F:F,MATCH('05月车间提成'!C15,'05月车间提成'!C:C,0)))*0.29*0.05+INDEX('05月车间提成'!E:E,MATCH(C87,'05月车间提成'!C:C,0))*0.33*0.05 -> 411.7101 | AA86: =INDEX('05月车间提成'!J:J,MATCH(C87,'05月车间提成'!C:C,0))*0.05*INDEX('05月车间提成'!K:K,MATCH(C87,'05月车间提成'!C:C,0)) -> 46.122 | AB86: 刘玳琳 | AC86: 121.16 | AD86: =COUNTIF(C:C,C86) -> 1 | AE86: =INDEX('05基本'!P:P,MATCH(C86,'05基本'!C:C,0))-I86 -> 0 | AF86: =SUMIF('05月其他部门提成'!C:C,'05月提成-武侯售后'!C86,'05月其他部门提成'!Q:Q) -> 0 | AG86: =SUMIF('05月车间提成'!C:C,'05月提成-武侯售后'!C86,'05月车间提成'!W:W) -> 7806.9899 | AH86: =SUMIF('05月业务提成'!B:B,'05月提成-武侯售后'!C86,'05月业务提成'!BO:BO) -> 0 | AI86: =AF86+AG86+AH86 -> 7806.9899 | AJ86: =AI86-K86 -> 0
C87: 机修四组 | D87: =SUM(D86:D86) -> 20 | E87: =SUM(E86:E86) -> 1268.59 | F87: =SUM(F86:F86) -> 477.15 | G87: =SUM(G86:G86) -> 117 | H87: =SUM(H86:H86) -> 0 | I87: =SUM(I86:I86) -> 1120 | J87: =SUM(J86:J86) -> 0 | K87: =SUM(K86:K86) -> 7806.9899 | ... AA87: =SUM(AA86:AA86) -> 46.122 | AB87: 赵廷宇 | AC87: 5.32 | AD87: =COUNTIF(C:C,C87) -> 1 | AE87: =INDEX('05基本'!P:P,MATCH(C87,'05基本'!C:C,0))-I87 -> #N/A
A88: =A86+1 -> 69 | B88: 机五 | C88: 廖君 | D88: =INDEX('05基本'!I:I,MATCH(C88,'05基本'!C:C,0))+INDEX('05基本'!J:J,MATCH(C88,'05基本'!C:C,0)) -> 40 | E88: =INDEX('05基本'!AA:AA,MATCH(C88,'05基本'!C:C,0)) -> 1268.59 | F88: =INDEX('05基本'!AB:AB,MATCH(C88,'05基本'!C:C,0)) -> 477.15 | G88: =INDEX('05基本'!AC:AC,MATCH(C88,'05基本'!C:C,0)) -> 117 | H88: =INDEX('05基本'!K:K,MATCH(C88,'05基本'!C:C,0))+INDEX('05基本'!L:L,MATCH(C88,'05基本'!C:C,0)) -> 0 | I88: =INDEX('05基本'!P:P,MATCH(C88,'05基本'!C:C,0)) -> 1140 | J88: =INDEX('05基本'!M:M,MATCH(C88,'05基本'!C:C,0)) -> 0 | K88: =INDEX('05月车间提成'!W:W,MATCH(C88,'05月车间提成'!C:C,0)) -> 6165.0449 | L88: =SUMIF(综合考核!A:A,'05月提成-武侯售后'!C88,综合考核!M:M) -> 0 | M88: =SUM(K88:L88) -> 6165.0449 | N88: =SUMIF(服装扣款!C:C,C88,服装扣款!N:N) -> 0 | O88: =M88-N88 -> 6165.0449 | P88: =SUMIF(超市公积金!C:C,'05月提成-武侯售后'!C88,超市公积金!I:I) -> 0 | Q88: =SUMIF(综合考核!A:A,'05月提成-武侯售后'!C88,综合考核!N:N) -> 0 | R88: =M88+I88+Q88 -> 7305.0449 | S88: =INDEX(AC:AC,MATCH(C88,AB:AB,0)) -> 51.33 | U88: =S88-T88 -> 51.33 | V88: =INDEX('05基本'!AF:AF,MATCH(C88,'05基本'!C:C,0)) -> 0 | W88: =O88-P88-U88 -> 6113.7149 | Y88: =SUM(Z88:AA88) -> 636.3806 | Z88: =(INDEX('05月车间提成'!D:D,MATCH(C90,'05月车间提成'!C:C,0))-INDEX('05月车间提成'!F:F,MATCH('05月车间提成'!C15,'05月车间提成'!C:C,0)))*0.29*0.05+INDEX('05月车间提成'!E:E,MATCH(C90,'05月车间提成'!C:C,0))*0.33*0.05 -> 584.9416 | AA88: =INDEX('05月车间提成'!J:J,MATCH(C90,'05月车间提成'!C:C,0))*0.05*INDEX('05月车间提成'!K:K,MATCH(C90,'05月车间提成'!C:C,0)) -> 51.439 | AB88: 邓尚明 | AC88: 34.53 | AD88: =COUNTIF(C:C,C88) -> 1 | AE88: =INDEX('05基本'!P:P,MATCH(C88,'05基本'!C:C,0))-I88 -> 0 | AF88: =SUMIF('05月其他部门提成'!C:C,'05月提成-武侯售后'!C88,'05月其他部门提成'!Q:Q) -> 0 | AG88: =SUMIF('05月车间提成'!C:C,'05月提成-武侯售后'!C88,'05月车间提成'!W:W) -> 6165.0449 | AH88: =SUMIF('05月业务提成'!B:B,'05月提成-武侯售后'!C88,'05月业务提成'!BO:BO) -> 0 | AI88: =AF88+AG88+AH88 -> 6165.0449 | AJ88: =AI88-K88 -> 0
A89: =A88+1 -> 70 | C89: 李欢 | D89: =INDEX('05基本'!I:I,MATCH(C89,'05基本'!C:C,0))+INDEX('05基本'!J:J,MATCH(C89,'05基本'!C:C,0)) -> 50 | E89: =INDEX('05基本'!AA:AA,MATCH(C89,'05基本'!C:C,0)) -> 1268.59 | F89: =INDEX('05基本'!AB:AB,MATCH(C89,'05基本'!C:C,0)) -> 477.15 | G89: =INDEX('05基本'!AC:AC,MATCH(C89,'05基本'!C:C,0)) -> 117 | H89: =INDEX('05基本'!K:K,MATCH(C89,'05基本'!C:C,0))+INDEX('05基本'!L:L,MATCH(C89,'05基本'!C:C,0)) -> 0 | I89: =INDEX('05基本'!P:P,MATCH(C89,'05基本'!C:C,0)) -> 950 | J89: =INDEX('05基本'!M:M,MATCH(C89,'05基本'!C:C,0)) -> 0 | K89: =INDEX('05月车间提成'!W:W,MATCH(C89,'05月车间提成'!C:C,0)) -> 4185.5315 | L89: =SUMIF(综合考核!A:A,'05月提成-武侯售后'!C89,综合考核!M:M) -> 0 | M89: =SUM(K89:L89) -> 4185.5315 | N89: =SUMIF(服装扣款!C:C,C89,服装扣款!N:N) -> 0 | O89: =M89-N89 -> 4185.5315 | P89: =SUMIF(超市公积金!C:C,'05月提成-武侯售后'!C89,超市公积金!I:I) -> 0 | Q89: =SUMIF(综合考核!A:A,'05月提成-武侯售后'!C89,综合考核!N:N) -> 0 | R89: =M89+I89+Q89 -> 5135.5315 | S89: =INDEX(AC:AC,MATCH(C89,AB:AB,0)) -> 0 | U89: =S89-T89 -> 0 | V89: =INDEX('05基本'!AF:AF,MATCH(C89,'05基本'!C:C,0)) -> 0 | W89: =O89-P89-U89 -> 4185.5315 | Y89: =SUM(Z89:AA89) -> 0 | AB89: 刘石磊 | AC89: 134.1 | AD89: =COUNTIF(C:C,C89) -> 1 | AE89: =INDEX('05基本'!P:P,MATCH(C89,'05基本'!C:C,0))-I89 -> 0 | AF89: =SUMIF('05月其他部门提成'!C:C,'05月提成-武侯售后'!C89,'05月其他部门提成'!Q:Q) -> 0 | AG89: =SUMIF('05月车间提成'!C:C,'05月提成-武侯售后'!C89,'05月车间提成'!W:W) -> 4185.5315 | AH89: =SUMIF('05月业务提成'!B:B,'05月提成-武侯售后'!C89,'05月业务提成'!BO:BO) -> 0 | AI89: =AF89+AG89+AH89 -> 4185.5315 | AJ89: =AI89-K89 -> 0
C90: 机修五组 | D90: =SUM(D88:D89) -> 90 | E90: =SUM(E88:E89) -> 2537.18 | F90: =SUM(F88:F89) -> 954.3 | G90: =SUM(G88:G89) -> 234 | H90: =SUM(H88:H89) -> 0 | I90: =SUM(I88:I89) -> 2090 | J90: =SUM(J88:J89) -> 0 | K90: =SUM(K88:K89) -> 10350.576 | ... AA90: =SUM(AA88:AA89) -> 51.439 | AB90: 陈晓华 | AC90: 0 | AD90: =COUNTIF(C:C,C90) -> 1 | AE90: =INDEX('05基本'!P:P,MATCH(C90,'05基本'!C:C,0))-I90 -> #N/A
A91: =A89+1 -> 71 | B91: 机六 | C91: 李建国 | D91: =INDEX('05基本'!I:I,MATCH(C91,'05基本'!C:C,0))+INDEX('05基本'!J:J,MATCH(C91,'05基本'!C:C,0)) -> 20 | E91: =INDEX('05基本'!AA:AA,MATCH(C91,'05基本'!C:C,0)) -> 1268.59 | F91: =INDEX('05基本'!AB:AB,MATCH(C91,'05基本'!C:C,0)) -> 477.15 | G91: =INDEX('05基本'!AC:AC,MATCH(C91,'05基本'!C:C,0)) -> 117 | H91: =INDEX('05基本'!K:K,MATCH(C91,'05基本'!C:C,0))+INDEX('05基本'!L:L,MATCH(C91,'05基本'!C:C,0)) -> 0 | I91: =INDEX('05基本'!P:P,MATCH(C91,'05基本'!C:C,0)) -> 905 | J91: =INDEX('05基本'!M:M,MATCH(C91,'05基本'!C:C,0)) -> 0 | K91: =INDEX('05月车间提成'!W:W,MATCH(C91,'05月车间提成'!C:C,0)) -> 3373.344 | L91: =SUMIF(综合考核!A:A,'05月提成-武侯售后'!C91,综合考核!M:M) -> 0 | M91: =SUM(K91:L91) -> 3373.344 | N91: =SUMIF(服装扣款!C:C,C91,服装扣款!N:N) -> 0 | O91: =M91-N91 -> 3373.344 | P91: =SUMIF(超市公积金!C:C,'05月提成-武侯售后'!C91,超市公积金!I:I) -> 0 | Q91: =SUMIF(综合考核!A:A,'05月提成-武侯售后'!C91,综合考核!N:N) -> 0 | R91: =M91+I91+Q91 -> 4278.344 | S91: =INDEX(AC:AC,MATCH(C91,AB:AB,0)) -> 0 | U91: =S91-T91 -> 0 | V91: =INDEX('05基本'!AF:AF,MATCH(C91,'05基本'!C:C,0)) -> 0 | W91: =O91-P91-U91 -> 3373.344 | Y91: =SUM(Z91:AA91) -> 550.4026 | Z91: =(INDEX('05月车间提成'!D:D,MATCH(C93,'05月车间提成'!C:C,0))-INDEX('05月车间提成'!F:F,MATCH('05月车间提成'!C21,'05月车间提成'!C:C,0)))*0.29*0.05+INDEX('05月车间提成'!E:E,MATCH(C93,'05月车间提成'!C:C,0))*0.33*0.05 -> 503.5096 | AA91: =INDEX('05月车间提成'!J:J,MATCH(C93,'05月车间提成'!C:C,0))*0.05*INDEX('05月车间提成'!K:K,MATCH(C93,'05月车间提成'!C:C,0)) -> 46.893 | AB91: 王立勃 | AC91: 13.82 | AE91: =INDEX('05基本'!P:P,MATCH(C91,'05基本'!C:C,0))-I91 -> 0
A92: =A91+1 -> 72 | C92: 左三明 | D92: =INDEX('05基本'!I:I,MATCH(C92,'05基本'!C:C,0))+INDEX('05基本'!J:J,MATCH(C92,'05基本'!C:C,0)) -> 20 | E92: =INDEX('05基本'!AA:AA,MATCH(C92,'05基本'!C:C,0)) -> 1268.59 | F92: =INDEX('05基本'!AB:AB,MATCH(C92,'05基本'!C:C,0)) -> 477.15 | G92: =INDEX('05基本'!AC:AC,MATCH(C92,'05基本'!C:C,0)) -> 117 | H92: =INDEX('05基本'!K:K,MATCH(C92,'05基本'!C:C,0))+INDEX('05基本'!L:L,MATCH(C92,'05基本'!C:C,0)) -> 0 | I92: =INDEX('05基本'!P:P,MATCH(C92,'05基本'!C:C,0)) -> 1120 | J92: =INDEX('05基本'!M:M,MATCH(C92,'05基本'!C:C,0)) -> 0 | K92: =INDEX('05月车间提成'!W:W,MATCH(C92,'05月车间提成'!C:C,0)) -> 5760.6254 | L92: =SUMIF(综合考核!A:A,'05月提成-武侯售后'!C92,综合考核!M:M) -> 0 | M92: =SUM(K92:L92) -> 5760.6254 | N92: =SUMIF(服装扣款!C:C,C92,服装扣款!N:N) -> 0 | O92: =M92-N92 -> 5760.6254 | P92: =SUMIF(超市公积金!C:C,'05月提成-武侯售后'!C92,超市公积金!I:I) -> 0 | Q92: =SUMIF(综合考核!A:A,'05月提成-武侯售后'!C92,综合考核!N:N) -> 0 | R92: =M92+I92+Q92 -> 6880.6254 | S92: =INDEX(AC:AC,MATCH(C92,AB:AB,0)) -> 38.59 | U92: =S92-T92 -> 38.59 | V92: =INDEX('05基本'!AF:AF,MATCH(C92,'05基本'!C:C,0)) -> 0 | W92: =O92-P92-U92 -> 5722.0354 | Y92: =SUM(Z92:AA92) -> 0 | AB92: 陈志扬 | AC92: 0 | AD92: =COUNTIF(C:C,C92) -> 1 | AE92: =INDEX('05基本'!P:P,MATCH(C92,'05基本'!C:C,0))-I92 -> 0 | AF92: =SUMIF('05月其他部门提成'!C:C,'05月提成-武侯售后'!C92,'05月其他部门提成'!Q:Q) -> 0 | AG92: =SUMIF('05月车间提成'!C:C,'05月提成-武侯售后'!C92,'05月车间提成'!W:W) -> 5760.6254 | AH92: =SUMIF('05月业务提成'!B:B,'05月提成-武侯售后'!C92,'05月业务提成'!BO:BO) -> 0 | AI92: =AF92+AG92+AH92 -> 5760.6254 | AJ92: =AI92-K92 -> 0
C93: 机修六组 | D93: =SUM(D91:D92) -> 40 | E93: =SUM(E91:E92) -> 2537.18 | F93: =SUM(F91:F92) -> 954.3 | G93: =SUM(G91:G92) -> 234 | H93: =SUM(H91:H92) -> 0 | I93: =SUM(I91:I92) -> 2025 | J93: =SUM(J91:J92) -> 0 | K93: =SUM(K91:K92) -> 9133.9694 | ... AA93: =SUM(AA91:AA92) -> 46.893 | AB93: 朱小军 | AC93: 79.64 | AE93: =INDEX('05基本'!P:P,MATCH(C93,'05基本'!C:C,0))-I93 -> #N/A
A94: =A92+1 -> 73 | B94: 机七 | C94: 李伦伟 | D94: =INDEX('05基本'!I:I,MATCH(C94,'05基本'!C:C,0))+INDEX('05基本'!J:J,MATCH(C94,'05基本'!C:C,0)) -> 10 | E94: =INDEX('05基本'!AA:AA,MATCH(C94,'05基本'!C:C,0)) -> 117 | F94: =INDEX('05基本'!AB:AB,MATCH(C94,'05基本'!C:C,0)) -> 0 | G94: =INDEX('05基本'!AC:AC,MATCH(C94,'05基本'!C:C,0)) -> 117 | H94: =INDEX('05基本'!K:K,MATCH(C94,'05基本'!C:C,0))+INDEX('05基本'!L:L,MATCH(C94,'05基本'!C:C,0)) -> 0 | I94: =INDEX('05基本'!P:P,MATCH(C94,'05基本'!C:C,0)) -> 1110 | J94: =INDEX('05基本'!M:M,MATCH(C94,'05基本'!C:C,0)) -> 0 | K94: =INDEX('05月车间提成'!W:W,MATCH(C94,'05月车间提成'!C:C,0)) -> 8315.9309 | L94: =SUMIF(综合考核!A:A,'05月提成-武侯售后'!C94,综合考核!M:M) -> 0 | M94: =SUM(K94:L94) -> 8315.9309 | N94: =SUMIF(服装扣款!C:C,C94,服装扣款!N:N) -> 0 | O94: =M94-N94 -> 8315.9309 | P94: =SUMIF(超市公积金!C:C,'05月提成-武侯售后'!C94,超市公积金!I:I) -> 0 | Q94: =SUMIF(综合考核!A:A,'05月提成-武侯售后'!C94,综合考核!N:N) -> 0 | R94: =M94+I94+Q94 -> 9425.9309 | S94: =INDEX(AC:AC,MATCH(C94,AB:AB,0)) -> 0 | U94: =S94-T94 -> 0 | V94: =INDEX('05基本'!AF:AF,MATCH(C94,'05基本'!C:C,0)) -> 0 | W94: =O94-P94-U94 -> 8315.9309 | Y94: =SUM(Z94:AA94) -> 736.034 | Z94: =(INDEX('05月车间提成'!D:D,MATCH(C96,'05月车间提成'!C:C,0))-INDEX('05月车间提成'!F:F,MATCH('05月车间提成'!C25,'05月车间提成'!C:C,0)))*0.29*0.05+INDEX('05月车间提成'!E:E,MATCH(C96,'05月车间提成'!C:C,0))*0.33*0.05 -> 669.237 | AA94: =INDEX('05月车间提成'!J:J,MATCH(C96,'05月车间提成'!C:C,0))*0.05*INDEX('05月车间提成'!K:K,MATCH(C96,'05月车间提成'!C:C,0)) -> 66.797 | AB94: 王强 | AC94: 56.3 | AE94: =INDEX('05基本'!P:P,MATCH(C94,'05基本'!C:C,0))-I94 -> 0
A95: =A94+1 -> 74 | C95: 刘新宇 | D95: =INDEX('05基本'!I:I,MATCH(C95,'05基本'!C:C,0))+INDEX('05基本'!J:J,MATCH(C95,'05基本'!C:C,0)) -> 10 | E95: =INDEX('05基本'!AA:AA,MATCH(C95,'05基本'!C:C,0)) -> 0 | F95: =INDEX('05基本'!AB:AB,MATCH(C95,'05基本'!C:C,0)) -> 0 | G95: =INDEX('05基本'!AC:AC,MATCH(C95,'05基本'!C:C,0)) -> 0 | H95: =INDEX('05基本'!K:K,MATCH(C95,'05基本'!C:C,0))+INDEX('05基本'!L:L,MATCH(C95,'05基本'!C:C,0)) -> 0 | I95: =INDEX('05基本'!P:P,MATCH(C95,'05基本'!C:C,0)) -> 1010 | J95: =INDEX('05基本'!M:M,MATCH(C95,'05基本'!C:C,0)) -> 0 | K95: =INDEX('05月车间提成'!W:W,MATCH(C95,'05月车间提成'!C:C,0)) -> 4207.9655 | L95: =SUMIF(综合考核!A:A,'05月提成-武侯售后'!C95,综合考核!M:M) -> 0 | M95: =SUM(K95:L95) -> 4207.9655 | N95: =SUMIF(服装扣款!C:C,C95,服装扣款!N:N) -> 0 | O95: =M95-N95 -> 4207.9655 | P95: =SUMIF(超市公积金!C:C,'05月提成-武侯售后'!C95,超市公积金!I:I) -> 0 | Q95: =SUMIF(综合考核!A:A,'05月提成-武侯售后'!C95,综合考核!N:N) -> 0 | R95: =M95+I95+Q95 -> 5217.9655 | S95: =INDEX(AC:AC,MATCH(C95,AB:AB,0)) -> 0 | U95: =S95-T95 -> 0 | V95: =INDEX('05基本'!AF:AF,MATCH(C95,'05基本'!C:C,0)) -> 0 | W95: =O95-P95-U95 -> 4207.9655 | Y95: =SUM(Z95:AA95) -> 0 | AB95: 胡磊 | AC95: 0 | AD95: =COUNTIF(C:C,C95) -> 1 | AE95: =INDEX('05基本'!P:P,MATCH(C95,'05基本'!C:C,0))-I95 -> 0 | AF95: =SUMIF('05月其他部门提成'!C:C,'05月提成-武侯售后'!C95,'05月其他部门提成'!Q:Q) -> 0 | AG95: =SUMIF('05月车间提成'!C:C,'05月提成-武侯售后'!C95,'05月车间提成'!W:W) -> 4207.9655 | AH95: =SUMIF('05月业务提成'!B:B,'05月提成-武侯售后'!C95,'05月业务提成'!BO:BO) -> 0 | AI95: =AF95+AG95+AH95 -> 4207.9655 | AJ95: =AI95-K95 -> 0
C96: 机修七组 | D96: =SUM(D94:D95) -> 20 | E96: =SUM(E94:E95) -> 117 | F96: =SUM(F94:F95) -> 0 | G96: =SUM(G94:G95) -> 117 | H96: =SUM(H94:H95) -> 0 | I96: =SUM(I94:I95) -> 2120 | J96: =SUM(J94:J95) -> 0 | K96: =SUM(K94:K95) -> 12523.896 | ... AA96: =SUM(AA94:AA95) -> 66.797 | AB96: 李双权 | AC96: 49.72 | AE96: =INDEX('05基本'!P:P,MATCH(C96,'05基本'!C:C,0))-I96 -> #N/A
A97: =A95+1 -> 75 | B97: 快修1 | C97: 章东 | D97: =INDEX('05基本'!I:I,MATCH(C97,'05基本'!C:C,0))+INDEX('05基本'!J:J,MATCH(C97,'05基本'!C:C,0)) -> 20 | E97: =INDEX('05基本'!AA:AA,MATCH(C97,'05基本'!C:C,0)) -> 1268.59 | F97: =INDEX('05基本'!AB:AB,MATCH(C97,'05基本'!C:C,0)) -> 477.15 | G97: =INDEX('05基本'!AC:AC,MATCH(C97,'05基本'!C:C,0)) -> 117 | H97: =INDEX('05基本'!K:K,MATCH(C97,'05基本'!C:C,0))+INDEX('05基本'!L:L,MATCH(C97,'05基本'!C:C,0)) -> 0 | I97: =INDEX('05基本'!P:P,MATCH(C97,'05基本'!C:C,0)) -> 1120 | J97: =INDEX('05基本'!M:M,MATCH(C97,'05基本'!C:C,0)) -> 0 | K97: =INDEX('05月车间提成'!W:W,MATCH(C97,'05月车间提成'!C:C,0)) -> 6845.9485 | L97: =SUMIF(综合考核!A:A,'05月提成-武侯售后'!C97,综合考核!M:M) -> 0 | M97: =SUM(K97:L97) -> 6845.9485 | N97: =SUMIF(服装扣款!C:C,C97,服装扣款!N:N) -> 0 | O97: =M97-N97 -> 6845.9485 | P97: =SUMIF(超市公积金!C:C,'05月提成-武侯售后'!C97,超市公积金!I:I) -> 0 | Q97: =SUMIF(综合考核!A:A,'05月提成-武侯售后'!C97,综合考核!N:N) -> 0 | R97: =M97+I97+Q97 -> 7965.9485 | S97: =INDEX(AC:AC,MATCH(C97,AB:AB,0)) -> 41.15 | U97: =S97-T97 -> 41.15 | V97: =INDEX('05基本'!AF:AF,MATCH(C97,'05基本'!C:C,0)) -> 0 | W97: =O97-P97-U97 -> 6804.7985 | Y97: =SUM(Z97:AA97) -> 780.7702 | Z97: =(INDEX('05月车间提成'!D:D,MATCH(C99,'05月车间提成'!C:C,0))-INDEX('05月车间提成'!F:F,MATCH('05月车间提成'!C29,'05月车间提成'!C:C,0)))*0.29*0.05+INDEX('05月车间提成'!E:E,MATCH(C99,'05月车间提成'!C:C,0))*0.33*0.05 -> 728.5322 | AA97: =INDEX('05月车间提成'!J:J,MATCH(C99,'05月车间提成'!C:C,0))*0.05*INDEX('05月车间提成'!K:K,MATCH(C99,'05月车间提成'!C:C,0)) -> 52.238 | AB97: 李垚 | AC97: 0 | AD97: =COUNTIF(C:C,C97) -> 1 | AE97: =INDEX('05基本'!P:P,MATCH(C97,'05基本'!C:C,0))-I97 -> 0 | AF97: =SUMIF('05月其他部门提成'!C:C,'05月提成-武侯售后'!C97,'05月其他部门提成'!Q:Q) -> 0 | AG97: =SUMIF('05月车间提成'!C:C,'05月提成-武侯售后'!C97,'05月车间提成'!W:W) -> 6845.9485 | AH97: =SUMIF('05月业务提成'!B:B,'05月提成-武侯售后'!C97,'05月业务提成'!BO:BO) -> 0 | AI97: =AF97+AG97+AH97 -> 6845.9485 | AJ97: =AI97-K97 -> 0
A98: =A97+1 -> 76 | C98: 冯波 | D98: =INDEX('05基本'!I:I,MATCH(C98,'05基本'!C:C,0))+INDEX('05基本'!J:J,MATCH(C98,'05基本'!C:C,0)) -> 20 | E98: =INDEX('05基本'!AA:AA,MATCH(C98,'05基本'!C:C,0)) -> 1268.59 | F98: =INDEX('05基本'!AB:AB,MATCH(C98,'05基本'!C:C,0)) -> 477.15 | G98: =INDEX('05基本'!AC:AC,MATCH(C98,'05基本'!C:C,0)) -> 117 | H98: =INDEX('05基本'!K:K,MATCH(C98,'05基本'!C:C,0))+INDEX('05基本'!L:L,MATCH(C98,'05基本'!C:C,0)) -> 0 | I98: =INDEX('05基本'!P:P,MATCH(C98,'05基本'!C:C,0)) -> 920 | J98: =INDEX('05基本'!M:M,MATCH(C98,'05基本'!C:C,0)) -> 0 | K98: =INDEX('05月车间提成'!W:W,MATCH(C98,'05月车间提成'!C:C,0)) -> 3970.2717 | L98: =SUMIF(综合考核!A:A,'05月提成-武侯售后'!C98,综合考核!M:M) -> 0 | M98: =SUM(K98:L98) -> 3970.2717 | N98: =SUMIF(服装扣款!C:C,C98,服装扣款!N:N) -> 0 | O98: =M98-N98 -> 3970.2717 | P98: =SUMIF(超市公积金!C:C,'05月提成-武侯售后'!C98,超市公积金!I:I) -> 0 | Q98: =SUMIF(综合考核!A:A,'05月提成-武侯售后'!C98,综合考核!N:N) -> 0 | R98: =M98+I98+Q98 -> 4890.2717 | S98: =INDEX(AC:AC,MATCH(C98,AB:AB,0)) -> 0 | U98: =S98-T98 -> 0 | V98: =INDEX('05基本'!AF:AF,MATCH(C98,'05基本'!C:C,0)) -> 0 | W98: =O98-P98-U98 -> 3970.2717 | Y98: =SUM(Z98:AA98) -> 0 | AB98: 王柳毅 | AC98: 0 | AD98: =COUNTIF(C:C,C98) -> 1 | AE98: =INDEX('05基本'!P:P,MATCH(C98,'05基本'!C:C,0))-I98 -> 0 | AF98: =SUMIF('05月其他部门提成'!C:C,'05月提成-武侯售后'!C98,'05月其他部门提成'!Q:Q) -> 0 | AG98: =SUMIF('05月车间提成'!C:C,'05月提成-武侯售后'!C98,'05月车间提成'!W:W) -> 3970.2717 | AH98: =SUMIF('05月业务提成'!B:B,'05月提成-武侯售后'!C98,'05月业务提成'!BO:BO) -> 0 | AI98: =AF98+AG98+AH98 -> 3970.2717 | AJ98: =AI98-K98 -> 0
C99: 快修一组 | D99: =SUM(D97:D98) -> 40 | E99: =SUM(E97:E98) -> 2537.18 | F99: =SUM(F97:F98) -> 954.3 | G99: =SUM(G97:G98) -> 234 | H99: =SUM(H97:H98) -> 0 | I99: =SUM(I97:I98) -> 2040 | J99: =SUM(J97:J98) -> 0 | K99: =SUM(K97:K98) -> 10816.22 | ... AA99: =SUM(AA97:AA98) -> 52.238 | AB99: 李璐 | AC99: 44.04 | AD99: =COUNTIF(C:C,C99) -> 1 | AE99: =INDEX('05基本'!P:P,MATCH(C99,'05基本'!C:C,0))-I99 -> #N/A
A100: =A98+1 -> 77 | B100: 机电十组 | C100: 周俊宏 | D100: =INDEX('05基本'!I:I,MATCH(C100,'05基本'!C:C,0))+INDEX('05基本'!J:J,MATCH(C100,'05基本'!C:C,0)) -> 10 | E100: =INDEX('05基本'!AA:AA,MATCH(C100,'05基本'!C:C,0)) -> 1268.59 | F100: =INDEX('05基本'!AB:AB,MATCH(C100,'05基本'!C:C,0)) -> 477.15 | G100: =INDEX('05基本'!AC:AC,MATCH(C100,'05基本'!C:C,0)) -> 117 | H100: =INDEX('05基本'!K:K,MATCH(C100,'05基本'!C:C,0))+INDEX('05基本'!L:L,MATCH(C100,'05基本'!C:C,0)) -> 0 | I100: =INDEX('05基本'!P:P,MATCH(C100,'05基本'!C:C,0)) -> 1060 | J100: =INDEX('05基本'!M:M,MATCH(C100,'05基本'!C:C,0)) -> 0 | K100: =INDEX('05月车间提成'!W:W,MATCH(C100,'05月车间提成'!C:C,0)) -> 7203.0899 | L100: =SUMIF(综合考核!A:A,'05月提成-武侯售后'!C100,综合考核!M:M) -> 0 | M100: =SUM(K100:L100) -> 7203.0899 | N100: =SUMIF(服装扣款!C:C,C100,服装扣款!N:N) -> 0 | O100: =M100-N100 -> 7203.0899 | P100: =SUMIF(超市公积金!C:C,'05月提成-武侯售后'!C100,超市公积金!I:I) -> 0 | Q100: =SUMIF(综合考核!A:A,'05月提成-武侯售后'!C100,综合考核!N:N) -> 0 | R100: =M100+I100+Q100 -> 8263.0899 | S100: =INDEX(AC:AC,MATCH(C100,AB:AB,0)) -> 80.06 | U100: =S100-T100 -> 80.06 | V100: =INDEX('05基本'!AF:AF,MATCH(C100,'05基本'!C:C,0)) -> 0 | W100: =O100-P100-U100 -> 7123.0299 | Y100: =SUM(Z100:AA100) -> 428.1347 | Z100: =(INDEX('05月车间提成'!D:D,MATCH(C101,'05月车间提成'!C:C,0))-INDEX('05月车间提成'!F:F,MATCH('05月车间提成'!C29,'05月车间提成'!C:C,0)))*0.29*0.05+INDEX('05月车间提成'!E:E,MATCH(C101,'05月车间提成'!C:C,0))*0.33*0.05 -> 401.0267 | AA100: =INDEX('05月车间提成'!J:J,MATCH(C101,'05月车间提成'!C:C,0))*0.05*INDEX('05月车间提成'!K:K,MATCH(C101,'05月车间提成'!C:C,0)) -> 27.108 | AB100: 王成 | AC100: 3.63 | AD100: =COUNTIF(C:C,C100) -> 1 | AE100: =INDEX('05基本'!P:P,MATCH(C100,'05基本'!C:C,0))-I100 -> 0 | AF100: =SUMIF('05月其他部门提成'!C:C,'05月提成-武侯售后'!C100,'05月其他部门提成'!Q:Q) -> 0 | AG100: =SUMIF('05月车间提成'!C:C,'05月提成-武侯售后'!C100,'05月车间提成'!W:W) -> 7203.0899 | AH100: =SUMIF('05月业务提成'!B:B,'05月提成-武侯售后'!C100,'05月业务提成'!BO:BO) -> 0 | AI100: =AF100+AG100+AH100 -> 7203.0899 | AJ100: =AI100-K100 -> 0
...

Sheet 05月提成-机场售后
A1: 2026年05月成都西物汽车工资明细表-（机场售后）
A2: 编制：人事部
A3: 序号 | B3: 部门 | C3: 姓 名 | D3: 其他补贴 | E3: 单位社保 | F3: 个人社保 | G3: 个人公积金 | H3: 其它 | I3: 基本工资 | J3: 其中： 加班工资 | K3: 当月应计提绩效 | L3: 综合考核/其他 | M3: 应付提 成工资 | N3: 代扣社保 | O3: 实付提成 | P3: 其它 | Q3: 已发并税 | R3: 计税工资 | S3: 代扣个税 | V3: 其他(代扣项) | W3: 实发提成 | X3: 备注 | Y3: 留存 合计 | Z3: 留存1 | AA3: 留存2 | AF3: 其他部门 | AG3: 车间 | AH3: 业务
S4: 应扣税 | T4: 已扣税 | U4: 实际扣税 | Y4: 留存 | Z4: 留存 | AA4: 留存 | AB4: 姓名 | AC4: 累计应补(退)税额 | AF4: =SUMIF('05月其他部门提成'!C:C,'05月提成-机场售后'!C4,'05月其他部门提成'!Q:Q) -> 0 | AH4: =SUMIF('05月业务提成'!B:B,'05月提成-机场售后'!C4,'05月业务提成'!BO:BO) -> 0
A5: 1 | B5: 机场管理岗 | C5: 罗筱凡 | D5: =INDEX('05基本'!I:I,MATCH(C5,'05基本'!C:C,0))+INDEX('05基本'!J:J,MATCH(C5,'05基本'!C:C,0)) -> 0 | E5: =INDEX('05基本'!AA:AA,MATCH(C5,'05基本'!C:C,0)) -> 1497.5 | F5: =INDEX('05基本'!AB:AB,MATCH(C5,'05基本'!C:C,0)) -> 572 | G5: =INDEX('05基本'!AC:AC,MATCH(C5,'05基本'!C:C,0)) -> 117 | H5: =INDEX('05基本'!K:K,MATCH(C5,'05基本'!C:C,0))+INDEX('05基本'!L:L,MATCH(C5,'05基本'!C:C,0)) -> 0 | I5: =INDEX('05基本'!P:P,MATCH(C5,'05基本'!C:C,0)) -> 4000 | J5: =INDEX('05基本'!M:M,MATCH(C5,'05基本'!C:C,0)) -> 0 | K5: =INDEX('05月其他部门提成'!Q:Q,MATCH(C5,'05月其他部门提成'!C:C,0)) -> 6800 | L5: =SUMIF(综合考核!A:A,'05月提成-机场售后'!C5,综合考核!M:M) -> 0 | M5: =SUM(K5:L5) -> 6800 | N5: =SUMIF(服装扣款!C:C,C5,服装扣款!N:N) -> 0 | O5: =M5-N5 -> 6800 | P5: =SUMIF(西物公积金!C:C,C5,西物公积金!I:I) -> 0 | Q5: =SUMIF(综合考核!A:A,'05月提成-机场售后'!C5,综合考核!N:N) -> 0 | R5: =M5+I5+Q5 -> 10800 | S5: =INDEX(AC:AC,MATCH(C5,AB:AB,0)) -> 411.1 | U5: =S5-T5 -> 411.1 | V5: =INDEX('05基本'!AF:AF,MATCH(C5,'05基本'!C:C,0)) -> 0 | W5: =O5-P5-U5 -> 6388.9 | Y5: =SUM(Z5:AA5) -> 0 | Z5: =INDEX('05月其他部门提成'!S:S,MATCH(C5,'05月其他部门提成'!C:C,0)) -> 0 | AB5: 罗筱凡 | AC5: 411.1 | AD5: =COUNTIF(C:C,C5) -> 1 | AF5: =SUMIF('05月其他部门提成'!C:C,'05月提成-机场售后'!C5,'05月其他部门提成'!Q:Q) -> 6800 | AG5: =SUMIF('05月车间提成'!C:C,'05月提成-机场售后'!C5,'05月车间提成'!W:W) -> 0 | AH5: =SUMIF('05月业务提成'!B:B,'05月提成-机场售后'!C5,'05月业务提成'!BO:BO) -> 0 | AI5: =AF5+AG5+AH5 -> 6800 | AJ5: =AI5-K5 -> 0
A6: 2 | B6: 机场财务 | C6: 李佳语 | D6: =INDEX('05基本'!I:I,MATCH(C6,'05基本'!C:C,0))+INDEX('05基本'!J:J,MATCH(C6,'05基本'!C:C,0)) -> 0 | E6: =INDEX('05基本'!AA:AA,MATCH(C6,'05基本'!C:C,0)) -> 0 | F6: =INDEX('05基本'!AB:AB,MATCH(C6,'05基本'!C:C,0)) -> 0 | G6: =INDEX('05基本'!AC:AC,MATCH(C6,'05基本'!C:C,0)) -> 0 | H6: =INDEX('05基本'!K:K,MATCH(C6,'05基本'!C:C,0))+INDEX('05基本'!L:L,MATCH(C6,'05基本'!C:C,0)) -> 0 | I6: =INDEX('05基本'!P:P,MATCH(C6,'05基本'!C:C,0)) -> 1600 | J6: =INDEX('05基本'!M:M,MATCH(C6,'05基本'!C:C,0)) -> 0 | K6: =INDEX('05月其他部门提成'!Q:Q,MATCH(C6,'05月其他部门提成'!C:C,0)) -> 3855.4579 | L6: =SUMIF(综合考核!A:A,'05月提成-机场售后'!C6,综合考核!M:M) -> 0 | M6: =SUM(K6:L6) -> 3855.4579 | N6: =SUMIF(服装扣款!C:C,C6,服装扣款!N:N) -> 0 | O6: =M6-N6 -> 3855.4579 | P6: =SUMIF(西物公积金!C:C,C6,西物公积金!I:I) -> 0 | Q6: =SUMIF(综合考核!A:A,'05月提成-机场售后'!C6,综合考核!N:N) -> 0 | R6: =M6+I6+Q6 -> 5455.4579 | S6: =INDEX(AC:AC,MATCH(C6,AB:AB,0)) -> 13.66 | T6: 0 | U6: =S6-T6 -> 13.66 | V6: =INDEX('05基本'!AF:AF,MATCH(C6,'05基本'!C:C,0)) -> 0 | W6: =O6-P6-U6 -> 3841.7979 | Y6: =SUM(Z6:AA6) -> 216.66667 | Z6: =INDEX('05月其他部门提成'!S:S,MATCH(C6,'05月其他部门提成'!C:C,0)) -> 216.66667 | AB6: 李佳语 | AC6: 13.66 | AF6: =SUMIF('05月其他部门提成'!C:C,'05月提成-机场售后'!C6,'05月其他部门提成'!Q:Q) -> 3855.4579 | AG6: =SUMIF('05月车间提成'!C:C,'05月提成-机场售后'!C6,'05月车间提成'!W:W) -> 0 | AH6: =SUMIF('05月业务提成'!B:B,'05月提成-机场售后'!C6,'05月业务提成'!BO:BO) -> 0 | AI6: =AF6+AG6+AH6 -> 3855.4579 | AJ6: =AI6-K6 -> 0
A7: 3 | B7: 配件部 | C7: 古镇吉 | D7: =INDEX('05基本'!I:I,MATCH(C7,'05基本'!C:C,0))+INDEX('05基本'!J:J,MATCH(C7,'05基本'!C:C,0)) -> 0 | E7: =INDEX('05基本'!AA:AA,MATCH(C7,'05基本'!C:C,0)) -> 1268.59 | F7: =INDEX('05基本'!AB:AB,MATCH(C7,'05基本'!C:C,0)) -> 477.15 | G7: =INDEX('05基本'!AC:AC,MATCH(C7,'05基本'!C:C,0)) -> 117 | H7: =INDEX('05基本'!K:K,MATCH(C7,'05基本'!C:C,0))+INDEX('05基本'!L:L,MATCH(C7,'05基本'!C:C,0)) -> 100 | I7: =INDEX('05基本'!P:P,MATCH(C7,'05基本'!C:C,0)) -> 1700 | J7: =INDEX('05基本'!M:M,MATCH(C7,'05基本'!C:C,0)) -> 0 | K7: =INDEX('05月其他部门提成'!Q:Q,MATCH(C7,'05月其他部门提成'!C:C,0)) -> 9851.2332 | L7: =SUMIF(综合考核!A:A,'05月提成-机场售后'!C7,综合考核!M:M) -> 0 | M7: =SUM(K7:L7) -> 9851.2332 | N7: =SUMIF(服装扣款!C:C,C7,服装扣款!N:N) -> 0 | O7: =M7-N7 -> 9851.2332 | P7: =SUMIF(西物公积金!C:C,C7,西物公积金!I:I) -> 0 | Q7: =SUMIF(综合考核!A:A,'05月提成-机场售后'!C7,综合考核!N:N) -> 0 | R7: =M7+I7+Q7 -> 11551.233 | S7: =INDEX(AC:AC,MATCH(C7,AB:AB,0)) -> 118.72 | T7: 0 | U7: =S7-T7 -> 118.72 | V7: =INDEX('05基本'!AF:AF,MATCH(C7,'05基本'!C:C,0)) -> 0 | W7: =O7-P7-U7 -> 9732.5132 | Y7: =SUM(Z7:AA7) -> 518.48896 | Z7: =INDEX('05月其他部门提成'!S:S,MATCH(C7,'05月其他部门提成'!C:C,0)) -> 518.48896 | AB7: 古镇吉 | AC7: 118.72 | AF7: =SUMIF('05月其他部门提成'!C:C,'05月提成-机场售后'!C7,'05月其他部门提成'!Q:Q) -> 9851.2332 | AG7: =SUMIF('05月车间提成'!C:C,'05月提成-机场售后'!C7,'05月车间提成'!W:W) -> 0 | AH7: =SUMIF('05月业务提成'!B:B,'05月提成-机场售后'!C7,'05月业务提成'!BO:BO) -> 0 | AI7: =AF7+AG7+AH7 -> 9851.2332 | AJ7: =AI7-K7 -> 0
A8: 4 | C8: 孙俊杰 | D8: =INDEX('05基本'!I:I,MATCH(C8,'05基本'!C:C,0))+INDEX('05基本'!J:J,MATCH(C8,'05基本'!C:C,0)) -> 0 | E8: =INDEX('05基本'!AA:AA,MATCH(C8,'05基本'!C:C,0)) -> 1268.59 | F8: =INDEX('05基本'!AB:AB,MATCH(C8,'05基本'!C:C,0)) -> 477.15 | G8: =INDEX('05基本'!AC:AC,MATCH(C8,'05基本'!C:C,0)) -> 117 | H8: =INDEX('05基本'!K:K,MATCH(C8,'05基本'!C:C,0))+INDEX('05基本'!L:L,MATCH(C8,'05基本'!C:C,0)) -> 0 | I8: =INDEX('05基本'!P:P,MATCH(C8,'05基本'!C:C,0)) -> 900 | J8: =INDEX('05基本'!M:M,MATCH(C8,'05基本'!C:C,0)) -> 0 | K8: =INDEX('05月其他部门提成'!Q:Q,MATCH(C8,'05月其他部门提成'!C:C,0)) -> 4100 | L8: =SUMIF(综合考核!A:A,'05月提成-机场售后'!C8,综合考核!M:M) -> 0 | M8: =SUM(K8:L8) -> 4100 | N8: =SUMIF(服装扣款!C:C,C8,服装扣款!N:N) -> 0 | O8: =M8-N8 -> 4100 | P8: =SUMIF(西物公积金!C:C,C8,西物公积金!I:I) -> 0 | Q8: =SUMIF(综合考核!A:A,'05月提成-机场售后'!C8,综合考核!N:N) -> 0 | R8: =M8+I8+Q8 -> 5000 | S8: =INDEX(AC:AC,MATCH(C8,AB:AB,0)) -> 0 | T8: 0 | U8: =S8-T8 -> 0 | V8: =INDEX('05基本'!AF:AF,MATCH(C8,'05基本'!C:C,0)) -> 0 | W8: =O8-P8-U8 -> 4100 | Y8: =SUM(Z8:AA8) -> 83.34 | Z8: =INDEX('05月其他部门提成'!S:S,MATCH(C8,'05月其他部门提成'!C:C,0)) -> 83.34 | AB8: 孙俊杰 | AC8: 0 | AF8: =SUMIF('05月其他部门提成'!C:C,'05月提成-机场售后'!C8,'05月其他部门提成'!Q:Q) -> 4100 | AG8: =SUMIF('05月车间提成'!C:C,'05月提成-机场售后'!C8,'05月车间提成'!W:W) -> 0 | AH8: =SUMIF('05月业务提成'!B:B,'05月提成-机场售后'!C8,'05月业务提成'!BO:BO) -> 0 | AI8: =AF8+AG8+AH8 -> 4100 | AJ8: =AI8-K8 -> 0
A9: 5 | C9: 周毅 | D9: =INDEX('05基本'!I:I,MATCH(C9,'05基本'!C:C,0))+INDEX('05基本'!J:J,MATCH(C9,'05基本'!C:C,0)) -> 0 | E9: =INDEX('05基本'!AA:AA,MATCH(C9,'05基本'!C:C,0)) -> 1268.59 | F9: =INDEX('05基本'!AB:AB,MATCH(C9,'05基本'!C:C,0)) -> 477.15 | G9: =INDEX('05基本'!AC:AC,MATCH(C9,'05基本'!C:C,0)) -> 117 | H9: =INDEX('05基本'!K:K,MATCH(C9,'05基本'!C:C,0))+INDEX('05基本'!L:L,MATCH(C9,'05基本'!C:C,0)) -> 0 | I9: =INDEX('05基本'!P:P,MATCH(C9,'05基本'!C:C,0)) -> 900 | J9: =INDEX('05基本'!M:M,MATCH(C9,'05基本'!C:C,0)) -> 0 | K9: =INDEX('05月其他部门提成'!Q:Q,MATCH(C9,'05月其他部门提成'!C:C,0)) -> 5500 | L9: =SUMIF(综合考核!A:A,'05月提成-机场售后'!C9,综合考核!M:M) -> 0 | M9: =SUM(K9:L9) -> 5500 | N9: =SUMIF(服装扣款!C:C,C9,服装扣款!N:N) -> 0 | O9: =M9-N9 -> 5500 | P9: =SUMIF(西物公积金!C:C,C9,西物公积金!I:I) -> 0 | Q9: =SUMIF(综合考核!A:A,'05月提成-机场售后'!C9,综合考核!N:N) -> 0 | R9: =M9+I9+Q9 -> 6400 | S9: =INDEX(AC:AC,MATCH(C9,AB:AB,0)) -> 0 | T9: 0 | U9: =S9-T9 -> 0 | V9: =INDEX('05基本'!AF:AF,MATCH(C9,'05基本'!C:C,0)) -> 0 | W9: =O9-P9-U9 -> 5500 | Y9: =SUM(Z9:AA9) -> 83.34 | Z9: =INDEX('05月其他部门提成'!S:S,MATCH(C9,'05月其他部门提成'!C:C,0)) -> 83.34 | AB9: 周毅 | AC9: 0 | AF9: =SUMIF('05月其他部门提成'!C:C,'05月提成-机场售后'!C9,'05月其他部门提成'!Q:Q) -> 5500 | AG9: =SUMIF('05月车间提成'!C:C,'05月提成-机场售后'!C9,'05月车间提成'!W:W) -> 0 | AH9: =SUMIF('05月业务提成'!B:B,'05月提成-机场售后'!C9,'05月业务提成'!BO:BO) -> 0 | AI9: =AF9+AG9+AH9 -> 5500 | AJ9: =AI9-K9 -> 0
C10: 小计 | D10: =SUM(D5:D9) -> 0 | E10: =SUM(E5:E9) -> 5303.27 | F10: =SUM(F5:F9) -> 2003.45 | G10: =SUM(G5:G9) -> 468 | H10: =SUM(H5:H9) -> 100 | I10: =SUM(I5:I9) -> 9100 | J10: =SUM(J5:J9) -> 0 | K10: =SUM(K5:K9) -> 30106.691 | ... AA10: =SUM(AA5:AA9) -> 0 | AB10: 徐源 | AC10: 4.34 | AD10: =COUNTIF(C:C,C10) -> 7
A11: 6 | B11: 机场业务 | C11: 徐源 | D11: =INDEX('05基本'!I:I,MATCH(C11,'05基本'!C:C,0))+INDEX('05基本'!J:J,MATCH(C11,'05基本'!C:C,0)) -> 0 | E11: =INDEX('05基本'!AA:AA,MATCH(C11,'05基本'!C:C,0)) -> 1268.59 | F11: =INDEX('05基本'!AB:AB,MATCH(C11,'05基本'!C:C,0)) -> 477.15 | G11: =INDEX('05基本'!AC:AC,MATCH(C11,'05基本'!C:C,0)) -> 117 | H11: =INDEX('05基本'!K:K,MATCH(C11,'05基本'!C:C,0))+INDEX('05基本'!L:L,MATCH(C11,'05基本'!C:C,0)) -> 0 | I11: =INDEX('05基本'!P:P,MATCH(C11,'05基本'!C:C,0)) -> 900 | J11: =INDEX('05基本'!M:M,MATCH(C11,'05基本'!C:C,0)) -> 0 | K11: =INDEX('05月业务提成'!BO:BO,MATCH(C11,'05月业务提成'!B:B,0)) -> 4838.7984 | L11: =SUMIF(综合考核!A:A,'05月提成-机场售后'!C11,综合考核!M:M) -> 0 | M11: =SUM(K11:L11) -> 4838.7984 | N11: =SUMIF(服装扣款!C:C,C11,服装扣款!N:N) -> 0 | O11: =M11-N11 -> 4838.7984 | P11: =SUMIF(西物公积金!C:C,C11,西物公积金!I:I) -> 0 | Q11: =SUMIF(综合考核!A:A,'05月提成-机场售后'!C11,综合考核!N:N) -> 0 | R11: =M11+I11+Q11 -> 5738.7984 | S11: =INDEX(AC:AC,MATCH(C11,AB:AB,0)) -> 4.34 | T11: 0 | U11: =S11-T11 -> 4.34 | V11: =INDEX('05基本'!AF:AF,MATCH(C11,'05基本'!C:C,0)) -> 0 | W11: =O11-P11-U11 -> 4834.4584 | Y11: =SUM(Z11:AA11) -> 0 | AB11: 刘红 | AC11: 43.26 | AD11: =COUNTIF(C:C,C11) -> 1 | AF11: =SUMIF('05月其他部门提成'!C:C,'05月提成-机场售后'!C11,'05月其他部门提成'!Q:Q) -> 0 | AG11: =SUMIF('05月车间提成'!C:C,'05月提成-机场售后'!C11,'05月车间提成'!W:W) -> 0 | AH11: =SUMIF('05月业务提成'!B:B,'05月提成-机场售后'!C11,'05月业务提成'!BO:BO) -> 4838.7984 | AI11: =AF11+AG11+AH11 -> 4838.7984 | AJ11: =AI11-K11 -> 0
A12: 7 | C12: 刘红 | D12: =INDEX('05基本'!I:I,MATCH(C12,'05基本'!C:C,0))+INDEX('05基本'!J:J,MATCH(C12,'05基本'!C:C,0)) -> 0 | E12: =INDEX('05基本'!AA:AA,MATCH(C12,'05基本'!C:C,0)) -> 1268.59 | F12: =INDEX('05基本'!AB:AB,MATCH(C12,'05基本'!C:C,0)) -> 477.15 | G12: =INDEX('05基本'!AC:AC,MATCH(C12,'05基本'!C:C,0)) -> 117 | H12: =INDEX('05基本'!K:K,MATCH(C12,'05基本'!C:C,0))+INDEX('05基本'!L:L,MATCH(C12,'05基本'!C:C,0)) -> 0 | I12: =INDEX('05基本'!P:P,MATCH(C12,'05基本'!C:C,0)) -> 900 | J12: =INDEX('05基本'!M:M,MATCH(C12,'05基本'!C:C,0)) -> 0 | K12: =INDEX('05月业务提成'!BO:BO,MATCH(C12,'05月业务提成'!B:B,0)) -> 6136.0702 | L12: =SUMIF(综合考核!A:A,'05月提成-机场售后'!C12,综合考核!M:M) -> 0 | M12: =SUM(K12:L12) -> 6136.0702 | N12: =SUMIF(服装扣款!C:C,C12,服装扣款!N:N) -> 0 | O12: =M12-N12 -> 6136.0702 | P12: =SUMIF(西物公积金!C:C,C12,西物公积金!I:I) -> 0 | Q12: =SUMIF(综合考核!A:A,'05月提成-机场售后'!C12,综合考核!N:N) -> 0 | R12: =M12+I12+Q12 -> 7036.0702 | S12: =INDEX(AC:AC,MATCH(C12,AB:AB,0)) -> 43.26 | T12: 0 | U12: =S12-T12 -> 43.26 | V12: =INDEX('05基本'!AF:AF,MATCH(C12,'05基本'!C:C,0)) -> 0 | W12: =O12-P12-U12 -> 6092.8102 | Y12: =SUM(Z12:AA12) -> 424.33211 | Z12: =INDEX('05月业务提成'!C:C,MATCH(C12,'05月业务提成'!B:B,0))*1 -> 240 | AA12: =INDEX('05月业务提成'!F:F,MATCH(C12,'05月业务提成'!B:B,0))*0.05*2%+INDEX('05月业务提成'!J:J,MATCH(C12,'05月业务提成'!B:B,0))*0.05*1.6%+(INDEX('05月业务提成'!P:P,MATCH(C12,'05月业务提成'!B:B,0))/0.95)*0.05++(INDEX('05月业务提成'!V:V,MATCH(C12,'05月业务提成'!B:B,0))/0.95)*0.05+(INDEX('05月业务提成'!Z:Z,MATCH(C12,'05月业务提成'!B:B,0))/0.95)*0.05 -> 184.33211 | AB12: 何滔 | AC12: 20.8 | AD12: =COUNTIF(C:C,C12) -> 1 | AF12: =SUMIF('05月其他部门提成'!C:C,'05月提成-机场售后'!C12,'05月其他部门提成'!Q:Q) -> 0 | AG12: =SUMIF('05月车间提成'!C:C,'05月提成-机场售后'!C12,'05月车间提成'!W:W) -> 0 | AH12: =SUMIF('05月业务提成'!B:B,'05月提成-机场售后'!C12,'05月业务提成'!BO:BO) -> 6136.0702 | AI12: =AF12+AG12+AH12 -> 6136.0702 | AJ12: =AI12-K12 -> 0
A13: 8 | C13: 何滔 | D13: =INDEX('05基本'!I:I,MATCH(C13,'05基本'!C:C,0))+INDEX('05基本'!J:J,MATCH(C13,'05基本'!C:C,0)) -> 0 | E13: =INDEX('05基本'!AA:AA,MATCH(C13,'05基本'!C:C,0)) -> 1268.59 | F13: =INDEX('05基本'!AB:AB,MATCH(C13,'05基本'!C:C,0)) -> 477.15 | G13: =INDEX('05基本'!AC:AC,MATCH(C13,'05基本'!C:C,0)) -> 117 | H13: =INDEX('05基本'!K:K,MATCH(C13,'05基本'!C:C,0))+INDEX('05基本'!L:L,MATCH(C13,'05基本'!C:C,0)) -> 0 | I13: =INDEX('05基本'!P:P,MATCH(C13,'05基本'!C:C,0)) -> 900 | J13: =INDEX('05基本'!M:M,MATCH(C13,'05基本'!C:C,0)) -> 0 | K13: =INDEX('05月业务提成'!BO:BO,MATCH(C13,'05月业务提成'!B:B,0)) -> 5387.3341 | L13: =SUMIF(综合考核!A:A,'05月提成-机场售后'!C13,综合考核!M:M) -> 0 | M13: =SUM(K13:L13) -> 5387.3341 | N13: =SUMIF(服装扣款!C:C,C13,服装扣款!N:N) -> 0 | O13: =M13-N13 -> 5387.3341 | P13: =SUMIF(西物公积金!C:C,C13,西物公积金!I:I) -> 0 | Q13: =SUMIF(综合考核!A:A,'05月提成-机场售后'!C13,综合考核!N:N) -> 0 | R13: =M13+I13+Q13 -> 6287.3341 | S13: =INDEX(AC:AC,MATCH(C13,AB:AB,0)) -> 20.8 | T13: 0 | U13: =S13-T13 -> 20.8 | V13: =INDEX('05基本'!AF:AF,MATCH(C13,'05基本'!C:C,0)) -> 0 | W13: =O13-P13-U13 -> 5366.5341 | Y13: =SUM(Z13:AA13) -> 381.0039 | Z13: =INDEX('05月业务提成'!C:C,MATCH(C13,'05月业务提成'!B:B,0))*1 -> 236 | AA13: =INDEX('05月业务提成'!F:F,MATCH(C13,'05月业务提成'!B:B,0))*0.05*2%+INDEX('05月业务提成'!J:J,MATCH(C13,'05月业务提成'!B:B,0))*0.05*1.6%+(INDEX('05月业务提成'!P:P,MATCH(C13,'05月业务提成'!B:B,0))/0.95)*0.05++(INDEX('05月业务提成'!V:V,MATCH(C13,'05月业务提成'!B:B,0))/0.95)*0.05+(INDEX('05月业务提成'!Z:Z,MATCH(C13,'05月业务提成'!B:B,0))/0.95)*0.05 -> 145.0039 | AB13: 李东梅 | AC13: 30 | AD13: =COUNTIF(C:C,C13) -> 1 | AF13: =SUMIF('05月其他部门提成'!C:C,'05月提成-机场售后'!C13,'05月其他部门提成'!Q:Q) -> 0 | AG13: =SUMIF('05月车间提成'!C:C,'05月提成-机场售后'!C13,'05月车间提成'!W:W) -> 0 | AH13: =SUMIF('05月业务提成'!B:B,'05月提成-机场售后'!C13,'05月业务提成'!BO:BO) -> 5387.3341 | AI13: =AF13+AG13+AH13 -> 5387.3341 | AJ13: =AI13-K13 -> 0
A14: =A13+1 -> 9 | C14: 李东梅 | D14: =INDEX('05基本'!I:I,MATCH(C14,'05基本'!C:C,0))+INDEX('05基本'!J:J,MATCH(C14,'05基本'!C:C,0)) -> 0 | E14: =INDEX('05基本'!AA:AA,MATCH(C14,'05基本'!C:C,0)) -> 1268.59 | F14: =INDEX('05基本'!AB:AB,MATCH(C14,'05基本'!C:C,0)) -> 477.15 | G14: =INDEX('05基本'!AC:AC,MATCH(C14,'05基本'!C:C,0)) -> 117 | H14: =INDEX('05基本'!K:K,MATCH(C14,'05基本'!C:C,0))+INDEX('05基本'!L:L,MATCH(C14,'05基本'!C:C,0)) -> 0 | I14: =INDEX('05基本'!P:P,MATCH(C14,'05基本'!C:C,0)) -> 900 | J14: =INDEX('05基本'!M:M,MATCH(C14,'05基本'!C:C,0)) -> 0 | K14: =INDEX('05月业务提成'!BO:BO,MATCH(C14,'05月业务提成'!B:B,0)) -> 5693.9029 | L14: =SUMIF(综合考核!A:A,'05月提成-机场售后'!C14,综合考核!M:M) -> 0 | M14: =SUM(K14:L14) -> 5693.9029 | N14: =SUMIF(服装扣款!C:C,C14,服装扣款!N:N) -> 0 | O14: =M14-N14 -> 5693.9029 | P14: =SUMIF(西物公积金!C:C,C14,西物公积金!I:I) -> 0 | Q14: =SUMIF(综合考核!A:A,'05月提成-机场售后'!C14,综合考核!N:N) -> 0 | R14: =M14+I14+Q14 -> 6593.9029 | S14: =INDEX(AC:AC,MATCH(C14,AB:AB,0)) -> 30 | T14: 0 | U14: =S14-T14 -> 30 | V14: =INDEX('05基本'!AF:AF,MATCH(C14,'05基本'!C:C,0)) -> 0 | W14: =O14-P14-U14 -> 5663.9029 | Y14: =SUM(Z14:AA14) -> 452.25858 | Z14: =INDEX('05月业务提成'!C:C,MATCH(C14,'05月业务提成'!B:B,0))*1 -> 280 | AA14: =INDEX('05月业务提成'!F:F,MATCH(C14,'05月业务提成'!B:B,0))*0.05*2%+INDEX('05月业务提成'!J:J,MATCH(C14,'05月业务提成'!B:B,0))*0.05*1.6%+(INDEX('05月业务提成'!P:P,MATCH(C14,'05月业务提成'!B:B,0))/0.95)*0.05++(INDEX('05月业务提成'!V:V,MATCH(C14,'05月业务提成'!B:B,0))/0.95)*0.05+(INDEX('05月业务提成'!Z:Z,MATCH(C14,'05月业务提成'!B:B,0))/0.95)*0.05 -> 172.25858 | AB14: 刘辉玺 | AC14: 114.71 | AD14: =COUNTIF(C:C,C14) -> 1 | AF14: =SUMIF('05月其他部门提成'!C:C,'05月提成-机场售后'!C14,'05月其他部门提成'!Q:Q) -> 0 | AG14: =SUMIF('05月车间提成'!C:C,'05月提成-机场售后'!C14,'05月车间提成'!W:W) -> 0 | AH14: =SUMIF('05月业务提成'!B:B,'05月提成-机场售后'!C14,'05月业务提成'!BO:BO) -> 5693.9029 | AI14: =AF14+AG14+AH14 -> 5693.9029 | AJ14: =AI14-K14 -> 0
C15: 小计 | D15: =SUM(D11:D14) -> 0 | E15: =SUM(E11:E14) -> 5074.36 | F15: =SUM(F11:F14) -> 1908.6 | G15: =SUM(G11:G14) -> 468 | H15: =SUM(H11:H14) -> 0 | I15: =SUM(I11:I14) -> 3600 | J15: =SUM(J11:J14) -> 0 | K15: =SUM(K11:K14) -> 22056.106 | ... AA15: =SUM(AA11:AA14) -> 501.59459 | AB15: 贾兴卜 | AC15: 151.99 | AD15: =COUNTIF(C:C,C15) -> 7
A16: =A14+1 -> 10 | B16: 事故理赔 | C16: 刘辉玺 | D16: =INDEX('05基本'!I:I,MATCH(C16,'05基本'!C:C,0))+INDEX('05基本'!J:J,MATCH(C16,'05基本'!C:C,0)) -> 0 | E16: =INDEX('05基本'!AA:AA,MATCH(C16,'05基本'!C:C,0)) -> 1268.59 | F16: =INDEX('05基本'!AB:AB,MATCH(C16,'05基本'!C:C,0)) -> 477.15 | G16: =INDEX('05基本'!AC:AC,MATCH(C16,'05基本'!C:C,0)) -> 117 | H16: =INDEX('05基本'!K:K,MATCH(C16,'05基本'!C:C,0))+INDEX('05基本'!L:L,MATCH(C16,'05基本'!C:C,0)) -> 0 | I16: =INDEX('05基本'!P:P,MATCH(C16,'05基本'!C:C,0)) -> 900 | J16: =INDEX('05基本'!M:M,MATCH(C16,'05基本'!C:C,0)) -> 0 | K16: =INDEX(保险专员5月外拓!I:I,MATCH(C16,保险专员5月外拓!A:A,0)) -> 8518.0142 | L16: =SUMIF(综合考核!A:A,'05月提成-机场售后'!C16,综合考核!M:M) -> 0 | M16: =SUM(K16:L16) -> 8518.0142 | N16: =SUMIF(服装扣款!C:C,C16,服装扣款!N:N) -> 0 | O16: =M16-N16 -> 8518.0142 | P16: =SUMIF(西物公积金!C:C,C16,西物公积金!I:I) -> 0 | Q16: =SUMIF(综合考核!A:A,'05月提成-机场售后'!C16,综合考核!N:N) -> 0 | R16: =M16+I16+Q16 -> 9418.0142 | S16: =INDEX(AC:AC,MATCH(C16,AB:AB,0)) -> 114.71 | U16: =S16-T16 -> 114.71 | V16: =INDEX('05基本'!AF:AF,MATCH(C16,'05基本'!C:C,0)) -> 0 | W16: =O16-P16-U16 -> 8403.3042 | Y16: =SUM(Z16:AA16) -> 671.0116 | AA16: =保险专员5月外拓!J22 -> 671.0116 | AB16: 周兴强 | AC16: 142.69 | AD16: =COUNTIF(C:C,C16) -> 1 | AF16: =SUMIF('05月其他部门提成'!C:C,'05月提成-机场售后'!C16,'05月其他部门提成'!Q:Q) -> 0 | AG16: =SUMIF('05月车间提成'!C:C,'05月提成-机场售后'!C16,'05月车间提成'!W:W) -> 0 | AH16: =SUMIF('05月业务提成'!B:B,'05月提成-机场售后'!C16,'05月业务提成'!BO:BO) -> 0 | AI16: =AF16+AG16+AH16 -> 0 | AJ16: =AI16-K16 -> -8518.0142
A17: =A16+1 -> 11 | C17: 贾兴卜 | D17: =INDEX('05基本'!I:I,MATCH(C17,'05基本'!C:C,0))+INDEX('05基本'!J:J,MATCH(C17,'05基本'!C:C,0)) -> 0 | E17: =INDEX('05基本'!AA:AA,MATCH(C17,'05基本'!C:C,0)) -> 1268.59 | F17: =INDEX('05基本'!AB:AB,MATCH(C17,'05基本'!C:C,0)) -> 477.15 | G17: =INDEX('05基本'!AC:AC,MATCH(C17,'05基本'!C:C,0)) -> 117 | H17: =INDEX('05基本'!K:K,MATCH(C17,'05基本'!C:C,0))+INDEX('05基本'!L:L,MATCH(C17,'05基本'!C:C,0)) -> 0 | I17: =INDEX('05基本'!P:P,MATCH(C17,'05基本'!C:C,0)) -> 900 | J17: =INDEX('05基本'!M:M,MATCH(C17,'05基本'!C:C,0)) -> 0 | K17: =INDEX('05月业务提成'!BO:BO,MATCH(C17,'05月业务提成'!B:B,0)) -> 9660.3826 | L17: =SUMIF(综合考核!A:A,'05月提成-机场售后'!C17,综合考核!M:M) -> 100 | M17: =SUM(K17:L17) -> 9760.3826 | N17: =SUMIF(服装扣款!C:C,C17,服装扣款!N:N) -> 0 | O17: =M17-N17 -> 9760.3826 | P17: =SUMIF(西物公积金!C:C,C17,西物公积金!I:I) -> 0 | Q17: =SUMIF(综合考核!A:A,'05月提成-机场售后'!C17,综合考核!N:N) -> 0 | R17: =M17+I17+Q17 -> 10660.383 | S17: =INDEX(AC:AC,MATCH(C17,AB:AB,0)) -> 151.99 | T17: 0 | U17: =S17-T17 -> 151.99 | V17: =INDEX('05基本'!AF:AF,MATCH(C17,'05基本'!C:C,0)) -> 0 | W17: =O17-P17-U17 -> 9608.3926 | Y17: =SUM(Z17:AA17) -> 502.54645 | Z17: =INDEX('05月业务提成'!C:C,MATCH(C17,'05月业务提成'!B:B,0))*1 -> 92 | AA17: =INDEX('05月业务提成'!F:F,MATCH(C17,'05月业务提成'!B:B,0))*0.05*2%+INDEX('05月业务提成'!J:J,MATCH(C17,'05月业务提成'!B:B,0))*0.05*1.6%+(INDEX('05月业务提成'!P:P,MATCH(C17,'05月业务提成'!B:B,0))/0.95)*0.05++(INDEX('05月业务提成'!V:V,MATCH(C17,'05月业务提成'!B:B,0))/0.95)*0.05+(INDEX('05月业务提成'!Z:Z,MATCH(C17,'05月业务提成'!B:B,0))/0.95)*0.05 -> 410.54645 | AB17: 姚金东 | AC17: 243.47 | AD17: =COUNTIF(C:C,C17) -> 1 | AF17: =SUMIF('05月其他部门提成'!C:C,'05月提成-机场售后'!C17,'05月其他部门提成'!Q:Q) -> 0 | AG17: =SUMIF('05月车间提成'!C:C,'05月提成-机场售后'!C17,'05月车间提成'!W:W) -> 0 | AH17: =SUMIF('05月业务提成'!B:B,'05月提成-机场售后'!C17,'05月业务提成'!BO:BO) -> 9660.3826 | AI17: =AF17+AG17+AH17 -> 9660.3826 | AJ17: =AI17-K17 -> 0
A18: =A17+1 -> 12 | C18: 周兴强 | D18: =INDEX('05基本'!I:I,MATCH(C18,'05基本'!C:C,0))+INDEX('05基本'!J:J,MATCH(C18,'05基本'!C:C,0)) -> 0 | E18: =INDEX('05基本'!AA:AA,MATCH(C18,'05基本'!C:C,0)) -> 1268.59 | F18: =INDEX('05基本'!AB:AB,MATCH(C18,'05基本'!C:C,0)) -> 477.15 | G18: =INDEX('05基本'!AC:AC,MATCH(C18,'05基本'!C:C,0)) -> 117 | H18: =INDEX('05基本'!K:K,MATCH(C18,'05基本'!C:C,0))+INDEX('05基本'!L:L,MATCH(C18,'05基本'!C:C,0)) -> 0 | I18: =INDEX('05基本'!P:P,MATCH(C18,'05基本'!C:C,0)) -> 850 | J18: =INDEX('05基本'!M:M,MATCH(C18,'05基本'!C:C,0)) -> 0 | K18: =INDEX('05月业务提成'!BO:BO,MATCH(C18,'05月业务提成'!B:B,0)) -> 9260.4106 | L18: =SUMIF(综合考核!A:A,'05月提成-机场售后'!C18,综合考核!M:M) -> 240 | M18: =SUM(K18:L18) -> 9500.4106 | N18: =SUMIF(服装扣款!C:C,C18,服装扣款!N:N) -> 0 | O18: =M18-N18 -> 9500.4106 | P18: =SUMIF(西物公积金!C:C,C18,西物公积金!I:I) -> 0 | Q18: =SUMIF(综合考核!A:A,'05月提成-机场售后'!C18,综合考核!N:N) -> 0 | R18: =M18+I18+Q18 -> 10350.411 | S18: =INDEX(AC:AC,MATCH(C18,AB:AB,0)) -> 142.69 | T18: 0 | U18: =S18-T18 -> 142.69 | V18: =INDEX('05基本'!AF:AF,MATCH(C18,'05基本'!C:C,0)) -> 0 | W18: =O18-P18-U18 -> 9357.7206 | Y18: =SUM(Z18:AA18) -> 480.60056 | Z18: =INDEX('05月业务提成'!C:C,MATCH(C18,'05月业务提成'!B:B,0))*1 -> 89 | AA18: =INDEX('05月业务提成'!F:F,MATCH(C18,'05月业务提成'!B:B,0))*0.05*2%+INDEX('05月业务提成'!J:J,MATCH(C18,'05月业务提成'!B:B,0))*0.05*1.6%+(INDEX('05月业务提成'!P:P,MATCH(C18,'05月业务提成'!B:B,0))/0.95)*0.05++(INDEX('05月业务提成'!V:V,MATCH(C18,'05月业务提成'!B:B,0))/0.95)*0.05+(INDEX('05月业务提成'!Z:Z,MATCH(C18,'05月业务提成'!B:B,0))/0.95)*0.05 -> 391.60056 | AB18: 舒麒羽 | AC18: 50.99 | AD18: =COUNTIF(C:C,C18) -> 1 | AF18: =SUMIF('05月其他部门提成'!C:C,'05月提成-机场售后'!C18,'05月其他部门提成'!Q:Q) -> 0 | AG18: =SUMIF('05月车间提成'!C:C,'05月提成-机场售后'!C18,'05月车间提成'!W:W) -> 0 | AH18: =SUMIF('05月业务提成'!B:B,'05月提成-机场售后'!C18,'05月业务提成'!BO:BO) -> 9260.4106 | AI18: =AF18+AG18+AH18 -> 9260.4106 | AJ18: =AI18-K18 -> 0
A19: =A18+1 -> 13 | C19: 姚金东 | D19: =INDEX('05基本'!I:I,MATCH(C19,'05基本'!C:C,0))+INDEX('05基本'!J:J,MATCH(C19,'05基本'!C:C,0)) -> 0 | E19: =INDEX('05基本'!AA:AA,MATCH(C19,'05基本'!C:C,0)) -> 1268.59 | F19: =INDEX('05基本'!AB:AB,MATCH(C19,'05基本'!C:C,0)) -> 477.15 | G19: =INDEX('05基本'!AC:AC,MATCH(C19,'05基本'!C:C,0)) -> 117 | H19: =INDEX('05基本'!K:K,MATCH(C19,'05基本'!C:C,0))+INDEX('05基本'!L:L,MATCH(C19,'05基本'!C:C,0)) -> 100 | I19: =INDEX('05基本'!P:P,MATCH(C19,'05基本'!C:C,0)) -> 1700 | J19: =INDEX('05基本'!M:M,MATCH(C19,'05基本'!C:C,0)) -> 0 | K19: =INDEX('05月其他部门提成'!Q:Q,MATCH(C19,'05月其他部门提成'!C:C,0)) -> 10672.231 | L19: =SUMIF(综合考核!A:A,'05月提成-机场售后'!C19,综合考核!M:M) -> 0 | M19: =SUM(K19:L19) -> 10672.231 | N19: =SUMIF(服装扣款!C:C,C19,服装扣款!N:N) -> 0 | O19: =M19-N19 -> 10672.231 | P19: =SUMIF(西物公积金!C:C,C19,西物公积金!I:I) -> 0 | Q19: =SUMIF(综合考核!A:A,'05月提成-机场售后'!C19,综合考核!N:N) -> 0 | R19: =M19+I19+Q19 -> 12372.231 | S19: =INDEX(AC:AC,MATCH(C19,AB:AB,0)) -> 243.47 | T19: 0 | U19: =S19-T19 -> 243.47 | V19: =INDEX('05基本'!AF:AF,MATCH(C19,'05基本'!C:C,0)) -> 0 | W19: =O19-P19-U19 -> 10428.761 | Y19: =SUM(Z19:AA19) -> 0 | Z19: =INDEX('05月业务提成'!C:C,MATCH(C19,'05月业务提成'!B:B,0))*1 -> 0 | AA19: =INDEX('05月业务提成'!F:F,MATCH(C19,'05月业务提成'!B:B,0))*0.05*2%+INDEX('05月业务提成'!J:J,MATCH(C19,'05月业务提成'!B:B,0))*0.05*1.6%+(INDEX('05月业务提成'!P:P,MATCH(C19,'05月业务提成'!B:B,0))/0.95)*0.05++(INDEX('05月业务提成'!V:V,MATCH(C19,'05月业务提成'!B:B,0))/0.95)*0.05+(INDEX('05月业务提成'!Z:Z,MATCH(C19,'05月业务提成'!B:B,0))/0.95)*0.05 -> 0 | AB19: 苟艳 | AC19: 43.67 | AD19: =COUNTIF(C:C,C19) -> 1 | AF19: =SUMIF('05月其他部门提成'!C:C,'05月提成-机场售后'!C19,'05月其他部门提成'!Q:Q) -> 10672.231 | AG19: =SUMIF('05月车间提成'!C:C,'05月提成-机场售后'!C19,'05月车间提成'!W:W) -> 0 | AH19: =SUMIF('05月业务提成'!B:B,'05月提成-机场售后'!C19,'05月业务提成'!BO:BO) -> 141879.79 | AI19: =AF19+AG19+AH19 -> 152552.02 | AJ19: =AI19-K19 -> 141879.79
A20: =A19+1 -> 14 | C20: 舒麒羽 | D20: =INDEX('05基本'!I:I,MATCH(C20,'05基本'!C:C,0))+INDEX('05基本'!J:J,MATCH(C20,'05基本'!C:C,0)) -> 0 | E20: =INDEX('05基本'!AA:AA,MATCH(C20,'05基本'!C:C,0)) -> 1268.59 | F20: =INDEX('05基本'!AB:AB,MATCH(C20,'05基本'!C:C,0)) -> 477.15 | G20: =INDEX('05基本'!AC:AC,MATCH(C20,'05基本'!C:C,0)) -> 117 | H20: =INDEX('05基本'!K:K,MATCH(C20,'05基本'!C:C,0))+INDEX('05基本'!L:L,MATCH(C20,'05基本'!C:C,0)) -> 0 | I20: =INDEX('05基本'!P:P,MATCH(C20,'05基本'!C:C,0)) -> 1200 | J20: =INDEX('05基本'!M:M,MATCH(C20,'05基本'!C:C,0)) -> 0 | K20: =INDEX('05月其他部门提成'!Q:Q,MATCH(C20,'05月其他部门提成'!C:C,0)) -> 6232 | L20: =SUMIF(综合考核!A:A,'05月提成-机场售后'!C20,综合考核!M:M) -> 0 | M20: =SUM(K20:L20) -> 6232 | N20: =SUMIF(服装扣款!C:C,C20,服装扣款!N:N) -> 0 | O20: =M20-N20 -> 6232 | P20: =SUMIF(西物公积金!C:C,C20,西物公积金!I:I) -> 0 | Q20: =SUMIF(综合考核!A:A,'05月提成-机场售后'!C20,综合考核!N:N) -> 0 | R20: =M20+I20+Q20 -> 7432 | S20: =INDEX(AC:AC,MATCH(C20,AB:AB,0)) -> 50.99 | T20: 0 | U20: =S20-T20 -> 50.99 | V20: =INDEX('05基本'!AF:AF,MATCH(C20,'05基本'!C:C,0)) -> 0 | W20: =O20-P20-U20 -> 6181.01 | Y20: =SUM(Z20:AA20) -> 83.33 | Z20: 83.33 | AB20: 孙苗 | AC20: 0 | AD20: =COUNTIF(C:C,C20) -> 1 | AF20: =SUMIF('05月其他部门提成'!C:C,'05月提成-机场售后'!C20,'05月其他部门提成'!Q:Q) -> 6232 | AG20: =SUMIF('05月车间提成'!C:C,'05月提成-机场售后'!C20,'05月车间提成'!W:W) -> 0 | AH20: =SUMIF('05月业务提成'!B:B,'05月提成-机场售后'!C20,'05月业务提成'!BO:BO) -> 0 | AI20: =AF20+AG20+AH20 -> 6232 | AJ20: =AI20-K20 -> 0
C21: 小计 | D21: =SUM(D16:D20) -> 0 | E21: =SUM(E16:E20) -> 6342.95 | F21: =SUM(F16:F20) -> 2385.75 | G21: =SUM(G16:G20) -> 585 | H21: =SUM(H16:H20) -> 100 | I21: =SUM(I16:I20) -> 5550 | J21: =SUM(J16:J20) -> 0 | K21: =SUM(K16:K20) -> 44343.039 | ... AA21: =SUM(AA16:AA20) -> 1473.1586 | AB21: 翁林星 | AC21: 0 | AD21: =COUNTIF(C:C,C21) -> 7
A22: =A20+1 -> 15 | B22: 续保部 | C22: 苟艳 | D22: =INDEX('05基本'!I:I,MATCH(C22,'05基本'!C:C,0))+INDEX('05基本'!J:J,MATCH(C22,'05基本'!C:C,0)) -> 0 | E22: =INDEX('05基本'!AA:AA,MATCH(C22,'05基本'!C:C,0)) -> 1268.59 | F22: =INDEX('05基本'!AB:AB,MATCH(C22,'05基本'!C:C,0)) -> 477.15 | G22: =INDEX('05基本'!AC:AC,MATCH(C22,'05基本'!C:C,0)) -> 117 | H22: =INDEX('05基本'!K:K,MATCH(C22,'05基本'!C:C,0))+INDEX('05基本'!L:L,MATCH(C22,'05基本'!C:C,0)) -> 0 | I22: =INDEX('05基本'!P:P,MATCH(C22,'05基本'!C:C,0)) -> 900 | J22: =INDEX('05基本'!M:M,MATCH(C22,'05基本'!C:C,0)) -> 0 | K22: =INDEX('05月其他部门提成'!Q:Q,MATCH(C22,'05月其他部门提成'!C:C,0)) -> 6150 | L22: =SUMIF(综合考核!A:A,'05月提成-机场售后'!C22,综合考核!M:M) -> 0 | M22: =SUM(K22:L22) -> 6150 | N22: =SUMIF(服装扣款!C:C,C22,服装扣款!N:N) -> 0 | O22: =M22-N22 -> 6150 | P22: =SUMIF(西物公积金!C:C,C22,西物公积金!I:I) -> 0 | Q22: =SUMIF(综合考核!A:A,'05月提成-机场售后'!C22,综合考核!N:N) -> 0 | R22: =M22+I22+Q22 -> 7050 | S22: =INDEX(AC:AC,MATCH(C22,AB:AB,0)) -> 43.67 | T22: 0 | U22: =S22-T22 -> 43.67 | V22: =INDEX('05基本'!AF:AF,MATCH(C22,'05基本'!C:C,0)) -> 0 | W22: =O22-P22-U22 -> 6106.33 | Y22: =SUM(Z22:AA22) -> 246 | Z22: =SUMIF(机场续保中心!B:B,C22,机场续保中心!AM:AM) -> 246 | AB22: 曹锟 | AC22: 0 | AD22: =COUNTIF(C:C,C22) -> 1 | AF22: =SUMIF('05月其他部门提成'!C:C,'05月提成-机场售后'!C22,'05月其他部门提成'!Q:Q) -> 6150 | AG22: =SUMIF('05月车间提成'!C:C,'05月提成-机场售后'!C22,'05月车间提成'!W:W) -> 0 | AH22: =SUMIF('05月业务提成'!B:B,'05月提成-机场售后'!C22,'05月业务提成'!BO:BO) -> 0 | AI22: =AF22+AG22+AH22 -> 6150 | AJ22: =AI22-K22 -> 0
A23: =A22+1 -> 16 | C23: 孙苗 | E23: =INDEX('05基本'!AA:AA,MATCH(C23,'05基本'!C:C,0)) -> 1268.59 | F23: =INDEX('05基本'!AB:AB,MATCH(C23,'05基本'!C:C,0)) -> 477.15 | G23: =INDEX('05基本'!AC:AC,MATCH(C23,'05基本'!C:C,0)) -> 117 | I23: =INDEX('05基本'!P:P,MATCH(C23,'05基本'!C:C,0)) -> 850 | K23: =INDEX('05月其他部门提成'!Q:Q,MATCH(C23,'05月其他部门提成'!C:C,0)) -> 4240 | L23: =SUMIF(综合考核!A:A,'05月提成-机场售后'!C23,综合考核!M:M) -> 0 | M23: =SUM(K23:L23) -> 4240 | N23: =SUMIF(服装扣款!C:C,C23,服装扣款!N:N) -> 0 | O23: =M23-N23 -> 4240 | P23: =SUMIF(西物公积金!C:C,C23,西物公积金!I:I) -> 0 | Q23: =SUMIF(综合考核!A:A,'05月提成-机场售后'!C23,综合考核!N:N) -> 0 | R23: =M23+I23+Q23 -> 5090 | S23: =INDEX(AC:AC,MATCH(C23,AB:AB,0)) -> 0 | T23: 0 | U23: =S23-T23 -> 0 | W23: =O23-P23-U23 -> 4240 | Y23: =SUM(Z23:AA23) -> 141 | Z23: =SUMIF(机场续保中心!B:B,C23,机场续保中心!AM:AM) -> 141 | AB23: 况婷婷 | AC23: 46.43 | AD23: =COUNTIF(C:C,C23) -> 1 | AF23: =SUMIF('05月其他部门提成'!C:C,'05月提成-机场售后'!C23,'05月其他部门提成'!Q:Q) -> 4240 | AG23: =SUMIF('05月车间提成'!C:C,'05月提成-机场售后'!C23,'05月车间提成'!W:W) -> 0 | AH23: =SUMIF('05月业务提成'!B:B,'05月提成-机场售后'!C23,'05月业务提成'!BO:BO) -> 0 | AI23: =AF23+AG23+AH23 -> 4240 | AJ23: =AI23-K23 -> 0
A24: =A23+1 -> 17 | C24: 翁林星 | E24: =INDEX('05基本'!AA:AA,MATCH(C24,'05基本'!C:C,0)) -> 1268.59 | F24: =INDEX('05基本'!AB:AB,MATCH(C24,'05基本'!C:C,0)) -> 477.15 | G24: =INDEX('05基本'!AC:AC,MATCH(C24,'05基本'!C:C,0)) -> 117 | I24: =INDEX('05基本'!P:P,MATCH(C24,'05基本'!C:C,0)) -> 730 | K24: =INDEX('05月其他部门提成'!Q:Q,MATCH(C24,'05月其他部门提成'!C:C,0)) -> 0 | L24: =SUMIF(综合考核!A:A,'05月提成-机场售后'!C24,综合考核!M:M) -> 0 | M24: =SUM(K24:L24) -> 0 | N24: =SUMIF(服装扣款!C:C,C24,服装扣款!N:N) -> 0 | O24: =M24-N24 -> 0 | P24: =SUMIF(西物公积金!C:C,C24,西物公积金!I:I) -> 0 | Q24: =SUMIF(综合考核!A:A,'05月提成-机场售后'!C24,综合考核!N:N) -> 0 | R24: =M24+I24+Q24 -> 730 | S24: =INDEX(AC:AC,MATCH(C24,AB:AB,0)) -> 0 | T24: 0 | U24: =S24-T24 -> 0 | W24: =O24-P24-U24 -> 0 | Y24: =SUM(Z24:AA24) -> 0 | Z24: =SUMIF(机场续保中心!B:B,C24,机场续保中心!AM:AM) -> 0 | AB24: 谢婷 | AC24: 108.98 | AD24: =COUNTIF(C:C,C24) -> 1 | AF24: =SUMIF('05月其他部门提成'!C:C,'05月提成-机场售后'!C24,'05月其他部门提成'!Q:Q) -> 0 | AG24: =SUMIF('05月车间提成'!C:C,'05月提成-机场售后'!C24,'05月车间提成'!W:W) -> 0 | AH24: =SUMIF('05月业务提成'!B:B,'05月提成-机场售后'!C24,'05月业务提成'!BO:BO) -> 0 | AI24: =AF24+AG24+AH24 -> 0 | AJ24: =AI24-K24 -> 0
A25: =A24+1 -> 18 | C25: 曹锟 | E25: =INDEX('05基本'!AA:AA,MATCH(C25,'05基本'!C:C,0)) -> 1268.59 | F25: =INDEX('05基本'!AB:AB,MATCH(C25,'05基本'!C:C,0)) -> 477.15 | G25: =INDEX('05基本'!AC:AC,MATCH(C25,'05基本'!C:C,0)) -> 117 | I25: =INDEX('05基本'!P:P,MATCH(C25,'05基本'!C:C,0)) -> 900 | K25: =INDEX('05月其他部门提成'!Q:Q,MATCH(C25,'05月其他部门提成'!C:C,0)) -> 4590 | L25: =SUMIF(综合考核!A:A,'05月提成-机场售后'!C25,综合考核!M:M) -> 0 | M25: =SUM(K25:L25) -> 4590 | N25: =SUMIF(服装扣款!C:C,C25,服装扣款!N:N) -> 0 | O25: =M25-N25 -> 4590 | P25: =SUMIF(西物公积金!C:C,C25,西物公积金!I:I) -> 0 | Q25: =SUMIF(综合考核!A:A,'05月提成-机场售后'!C25,综合考核!N:N) -> 0 | R25: =M25+I25+Q25 -> 5490 | S25: =INDEX(AC:AC,MATCH(C25,AB:AB,0)) -> 0 | T25: 0 | U25: =S25-T25 -> 0 | W25: =O25-P25-U25 -> 4590 | Y25: =SUM(Z25:AA25) -> 159 | Z25: =SUMIF(机场续保中心!B:B,C25,机场续保中心!AM:AM) -> 159 | AB25: 鞠双双 | AC25: 0 | AD25: =COUNTIF(C:C,C25) -> 1 | AF25: =SUMIF('05月其他部门提成'!C:C,'05月提成-机场售后'!C25,'05月其他部门提成'!Q:Q) -> 4590 | AG25: =SUMIF('05月车间提成'!C:C,'05月提成-机场售后'!C25,'05月车间提成'!W:W) -> 0 | AH25: =SUMIF('05月业务提成'!B:B,'05月提成-机场售后'!C25,'05月业务提成'!BO:BO) -> 0 | AI25: =AF25+AG25+AH25 -> 4590 | AJ25: =AI25-K25 -> 0
C26: 小计 | D26: =SUM(D22:D25) -> 0 | E26: =SUM(E22:E25) -> 5074.36 | F26: =SUM(F22:F25) -> 1908.6 | G26: =SUM(G22:G25) -> 468 | H26: =SUM(H22:H25) -> 0 | I26: =SUM(I22:I25) -> 3380 | J26: =SUM(J22:J25) -> 0 | K26: =SUM(K22:K25) -> 14980 | ... AA26: =SUM(AA22:AA25) -> 0 | AB26: 陈浩 | AC26: 189.17 | AD26: =COUNTIF(C:C,C26) -> 7
A27: =A25+1 -> 19 | B27: 回访部 | C27: 况婷婷 | D27: =INDEX('05基本'!I:I,MATCH(C27,'05基本'!C:C,0))+INDEX('05基本'!J:J,MATCH(C27,'05基本'!C:C,0)) -> 0 | E27: =INDEX('05基本'!AA:AA,MATCH(C27,'05基本'!C:C,0)) -> 1268.59 | F27: =INDEX('05基本'!AB:AB,MATCH(C27,'05基本'!C:C,0)) -> 477.15 | G27: =INDEX('05基本'!AC:AC,MATCH(C27,'05基本'!C:C,0)) -> 117 | H27: =INDEX('05基本'!K:K,MATCH(C27,'05基本'!C:C,0))+INDEX('05基本'!L:L,MATCH(C27,'05基本'!C:C,0)) -> 0 | I27: =INDEX('05基本'!P:P,MATCH(C27,'05基本'!C:C,0)) -> 1200 | J27: =INDEX('05基本'!M:M,MATCH(C27,'05基本'!C:C,0)) -> 0 | K27: =INDEX('05月其他部门提成'!Q:Q,MATCH(C27,'05月其他部门提成'!C:C,0)) -> 5942 | L27: =SUMIF(综合考核!A:A,'05月提成-机场售后'!C27,综合考核!M:M) -> 0 | M27: =SUM(K27:L27) -> 5942 | N27: =SUMIF(服装扣款!C:C,C27,服装扣款!N:N) -> 0 | O27: =M27-N27 -> 5942 | P27: =SUMIF(西物公积金!C:C,C27,西物公积金!I:I) -> 0 | Q27: =SUMIF(综合考核!A:A,'05月提成-机场售后'!C27,综合考核!N:N) -> 0 | R27: =M27+I27+Q27 -> 7142 | S27: =INDEX(AC:AC,MATCH(C27,AB:AB,0)) -> 46.43 | T27: 0 | U27: =S27-T27 -> 46.43 | V27: =INDEX('05基本'!AF:AF,MATCH(C27,'05基本'!C:C,0)) -> 0 | W27: =O27-P27-U27 -> 5895.57 | Y27: =SUM(Z27:AA27) -> 83.33 | Z27: 83.33 | AB27: 刘志洪 | AC27: 188.57 | AD27: =COUNTIF(C:C,C27) -> 1 | AF27: =SUMIF('05月其他部门提成'!C:C,'05月提成-机场售后'!C27,'05月其他部门提成'!Q:Q) -> 5942 | AG27: =SUMIF('05月车间提成'!C:C,'05月提成-机场售后'!C27,'05月车间提成'!W:W) -> 0 | AH27: =SUMIF('05月业务提成'!B:B,'05月提成-机场售后'!C27,'05月业务提成'!BO:BO) -> 0 | AI27: =AF27+AG27+AH27 -> 5942 | AJ27: =AI27-K27 -> 0
A28: =A27+1 -> 20 | C28: 谢婷 | D28: =INDEX('05基本'!I:I,MATCH(C28,'05基本'!C:C,0))+INDEX('05基本'!J:J,MATCH(C28,'05基本'!C:C,0)) -> 0 | E28: =INDEX('05基本'!AA:AA,MATCH(C28,'05基本'!C:C,0)) -> 1268.59 | F28: =INDEX('05基本'!AB:AB,MATCH(C28,'05基本'!C:C,0)) -> 477.15 | G28: =INDEX('05基本'!AC:AC,MATCH(C28,'05基本'!C:C,0)) -> 117 | H28: =INDEX('05基本'!K:K,MATCH(C28,'05基本'!C:C,0))+INDEX('05基本'!L:L,MATCH(C28,'05基本'!C:C,0)) -> 0 | I28: =INDEX('05基本'!P:P,MATCH(C28,'05基本'!C:C,0)) -> 1200 | J28: =INDEX('05基本'!M:M,MATCH(C28,'05基本'!C:C,0)) -> 0 | K28: =INDEX('05月其他部门提成'!Q:Q,MATCH(C28,'05月其他部门提成'!C:C,0)) -> 8027 | L28: =SUMIF(综合考核!A:A,'05月提成-机场售后'!C28,综合考核!M:M) -> 0 | M28: =SUM(K28:L28) -> 8027 | N28: =SUMIF(服装扣款!C:C,C28,服装扣款!N:N) -> 0 | O28: =M28-N28 -> 8027 | P28: =SUMIF(西物公积金!C:C,C28,西物公积金!I:I) -> 0 | Q28: =SUMIF(综合考核!A:A,'05月提成-机场售后'!C28,综合考核!N:N) -> 0 | R28: =M28+I28+Q28 -> 9227 | S28: =INDEX(AC:AC,MATCH(C28,AB:AB,0)) -> 108.98 | T28: 0 | U28: =S28-T28 -> 108.98 | V28: =INDEX('05基本'!AF:AF,MATCH(C28,'05基本'!C:C,0)) -> 0 | W28: =O28-P28-U28 -> 7918.02 | Y28: =SUM(Z28:AA28) -> 83.33 | Z28: 83.33 | AB28: 严云中 | AC28: 122.08 | AD28: =COUNTIF(C:C,C28) -> 1 | AF28: =SUMIF('05月其他部门提成'!C:C,'05月提成-机场售后'!C28,'05月其他部门提成'!Q:Q) -> 8027 | AG28: =SUMIF('05月车间提成'!C:C,'05月提成-机场售后'!C28,'05月车间提成'!W:W) -> 0 | AH28: =SUMIF('05月业务提成'!B:B,'05月提成-机场售后'!C28,'05月业务提成'!BO:BO) -> 0 | AI28: =AF28+AG28+AH28 -> 8027 | AJ28: =AI28-K28 -> 0
C29: 小计 | D29: =SUM(D27:D28) -> 0 | E29: =SUM(E27:E28) -> 2537.18 | F29: =SUM(F27:F28) -> 954.3 | G29: =SUM(G27:G28) -> 234 | H29: =SUM(H27:H28) -> 0 | I29: =SUM(I27:I28) -> 2400 | J29: =SUM(J27:J28) -> 0 | K29: =SUM(K27:K28) -> 13969 | ... AA29: =SUM(AA27:AA28) -> 0 | AB29: 吴明洋 | AC29: 51.05 | AD29: =COUNTIF(C:C,C29) -> 7
A30: =A28+1 -> 21 | C30: 鞠双双 | D30: =INDEX('05基本'!I:I,MATCH(C30,'05基本'!C:C,0))+INDEX('05基本'!J:J,MATCH(C30,'05基本'!C:C,0)) -> 0 | E30: =INDEX('05基本'!AA:AA,MATCH(C30,'05基本'!C:C,0)) -> 1268.59 | F30: =INDEX('05基本'!AB:AB,MATCH(C30,'05基本'!C:C,0)) -> 477.15 | G30: =INDEX('05基本'!AC:AC,MATCH(C30,'05基本'!C:C,0)) -> 117 | H30: =INDEX('05基本'!K:K,MATCH(C30,'05基本'!C:C,0))+INDEX('05基本'!L:L,MATCH(C30,'05基本'!C:C,0)) -> 0 | I30: =INDEX('05基本'!P:P,MATCH(C30,'05基本'!C:C,0)) -> 1500 | J30: =INDEX('05基本'!M:M,MATCH(C30,'05基本'!C:C,0)) -> 0 | K30: =INDEX('05月其他部门提成'!Q:Q,MATCH(C30,'05月其他部门提成'!C:C,0)) -> 2000 | L30: =SUMIF(综合考核!A:A,'05月提成-机场售后'!C30,综合考核!M:M) -> 0 | M30: =SUM(K30:L30) -> 2000 | N30: =SUMIF(服装扣款!C:C,C30,服装扣款!N:N) -> 0 | O30: =M30-N30 -> 2000 | P30: =SUMIF(西物公积金!C:C,C30,西物公积金!I:I) -> 0 | Q30: =SUMIF(综合考核!A:A,'05月提成-机场售后'!C30,综合考核!N:N) -> 0 | R30: =M30+I30+Q30 -> 3500 | S30: =INDEX(AC:AC,MATCH(C30,AB:AB,0)) -> 0 | T30: 0 | U30: =S30-T30 -> 0 | V30: =INDEX('05基本'!AF:AF,MATCH(C30,'05基本'!C:C,0)) -> 0 | W30: =O30-P30-U30 -> 2000 | Y30: =SUM(Z30:AA30) -> 83.33 | Z30: 83.33 | AB30: 韩爱民 | AC30: 104.41 | AD30: =COUNTIF(C:C,C30) -> 1 | AF30: =SUMIF('05月其他部门提成'!C:C,'05月提成-机场售后'!C30,'05月其他部门提成'!Q:Q) -> 2000 | AG30: =SUMIF('05月车间提成'!C:C,'05月提成-机场售后'!C30,'05月车间提成'!W:W) -> 0 | AH30: =SUMIF('05月业务提成'!B:B,'05月提成-机场售后'!C30,'05月业务提成'!BO:BO) -> 0 | AI30: =AF30+AG30+AH30 -> 2000 | AJ30: =AI30-K30 -> 0
C31: 小计 | D31: =SUM(D30) -> 0 | E31: =SUM(E30) -> 1268.59 | F31: =SUM(F30) -> 477.15 | G31: =SUM(G30) -> 117 | H31: =SUM(H30) -> 0 | I31: =SUM(I30) -> 1500 | J31: =SUM(J30) -> 0 | K31: =SUM(K30) -> 2000 | ... AA31: =SUM(AA30) -> 0 | AB31: 蒋湘龙 | AC31: 0 | AD31: =COUNTIF(C:C,C31) -> 7
B32: 小计 | D32: =D10+D15+D21+D26+D29+D31 -> 0 | E32: =E10+E15+E21+E26+E29+E31 -> 25600.71 | F32: =F10+F15+F21+F26+F29+F31 -> 9637.85 | G32: =G10+G15+G21+G26+G29+G31 -> 2340 | H32: =H10+H15+H21+H26+H29+H31 -> 200 | I32: =I10+I15+I21+I26+I29+I31 -> 25530 | J32: =J10+J15+J21+J26+J29+J31 -> 0 | K32: =K10+K15+K21+K26+K29+K31 -> 127454.84 | ... AA32: =AA10+AA15+AA21+AA26+AA29+AA31 -> 1974.7532 | AB32: 张雨 | AC32: 171.82 | AD32: =COUNTIF(C:C,C32) -> 0
A33: =A30+1 -> 22 | B33: 机场车间 | C33: 陈浩 | D33: =INDEX('05基本'!I:I,MATCH(C33,'05基本'!C:C,0))+INDEX('05基本'!J:J,MATCH(C33,'05基本'!C:C,0)) -> 0 | E33: =INDEX('05基本'!AA:AA,MATCH(C33,'05基本'!C:C,0)) -> 1268.59 | F33: =INDEX('05基本'!AB:AB,MATCH(C33,'05基本'!C:C,0)) -> 477.15 | G33: =INDEX('05基本'!AC:AC,MATCH(C33,'05基本'!C:C,0)) -> 117 | H33: =INDEX('05基本'!K:K,MATCH(C33,'05基本'!C:C,0))+INDEX('05基本'!L:L,MATCH(C33,'05基本'!C:C,0)) -> 100 | I33: =INDEX('05基本'!P:P,MATCH(C33,'05基本'!C:C,0)) -> 1700 | J33: =INDEX('05基本'!M:M,MATCH(C33,'05基本'!C:C,0)) -> 0 | K33: =INDEX('05月其他部门提成'!Q:Q,MATCH(C33,'05月其他部门提成'!C:C,0)) -> 10179.667 | L33: =SUMIF(综合考核!A:A,'05月提成-机场售后'!C33,综合考核!M:M) -> 20 | M33: =SUM(K33:L33) -> 10199.667 | N33: =SUMIF(服装扣款!C:C,C33,服装扣款!N:N) -> 0 | O33: =M33-N33 -> 10199.667 | P33: =SUMIF(西物公积金!C:C,C33,西物公积金!I:I) -> 0 | Q33: =SUMIF(综合考核!A:A,'05月提成-机场售后'!C33,综合考核!N:N) -> 0 | R33: =M33+I33+Q33 -> 11899.667 | S33: =INDEX(AC:AC,MATCH(C33,AB:AB,0)) -> 189.17 | U33: =S33-T33 -> 189.17 | V33: =INDEX('05基本'!AF:AF,MATCH(C33,'05基本'!C:C,0)) -> 0 | W33: =O33-P33-U33 -> 10010.497 | Y33: =SUM(Z33:AA33) -> 691.31861 | Z33: =INDEX('05月其他部门提成'!S:S,MATCH(C33,'05月其他部门提成'!C:C,0)) -> 691.31861 | AB33: 郑晓龙 | AC33: 52.99 | AD33: =COUNTIF(C:C,C33) -> 1 | AF33: =SUMIF('05月其他部门提成'!C:C,'05月提成-机场售后'!C33,'05月其他部门提成'!Q:Q) -> 10179.667 | AG33: =SUMIF('05月车间提成'!C:C,'05月提成-机场售后'!C33,'05月车间提成'!W:W) -> 0 | AH33: =SUMIF('05月业务提成'!B:B,'05月提成-机场售后'!C33,'05月业务提成'!BO:BO) -> 0 | AI33: =AF33+AG33+AH33 -> 10179.667 | AJ33: =AI33-K33 -> 0
A34: =A33+1 -> 23 | C34: 刘志洪 | D34: =INDEX('05基本'!I:I,MATCH(C34,'05基本'!C:C,0))+INDEX('05基本'!J:J,MATCH(C34,'05基本'!C:C,0)) -> 0 | E34: =INDEX('05基本'!AA:AA,MATCH(C34,'05基本'!C:C,0)) -> 1268.59 | F34: =INDEX('05基本'!AB:AB,MATCH(C34,'05基本'!C:C,0)) -> 477.15 | G34: =INDEX('05基本'!AC:AC,MATCH(C34,'05基本'!C:C,0)) -> 117 | H34: =INDEX('05基本'!K:K,MATCH(C34,'05基本'!C:C,0))+INDEX('05基本'!L:L,MATCH(C34,'05基本'!C:C,0)) -> 100 | I34: =INDEX('05基本'!P:P,MATCH(C34,'05基本'!C:C,0)) -> 1700 | J34: =INDEX('05基本'!M:M,MATCH(C34,'05基本'!C:C,0)) -> 0 | K34: =INDEX('05月其他部门提成'!Q:Q,MATCH(C34,'05月其他部门提成'!C:C,0)) -> 10179.667 | L34: =SUMIF(综合考核!A:A,'05月提成-机场售后'!C34,综合考核!M:M) -> 0 | M34: =SUM(K34:L34) -> 10179.667 | N34: =SUMIF(服装扣款!C:C,C34,服装扣款!N:N) -> 0 | O34: =M34-N34 -> 10179.667 | P34: =SUMIF(西物公积金!C:C,C34,西物公积金!I:I) -> 0 | Q34: =SUMIF(综合考核!A:A,'05月提成-机场售后'!C34,综合考核!N:N) -> 0 | R34: =M34+I34+Q34 -> 11879.667 | S34: =INDEX(AC:AC,MATCH(C34,AB:AB,0)) -> 188.57 | U34: =S34-T34 -> 188.57 | V34: =INDEX('05基本'!AF:AF,MATCH(C34,'05基本'!C:C,0)) -> 0 | W34: =O34-P34-U34 -> 9991.0966 | Y34: =SUM(Z34:AA34) -> 267.88596 | Z34: =INDEX('05月其他部门提成'!S:S,MATCH(C34,'05月其他部门提成'!C:C,0)) -> 267.88596 | AB34: 刘杨 | AC34: 141.8
C35: 小计 | D35: =SUM(D33:D34) -> 0 | E35: =SUM(E33:E34) -> 2537.18 | F35: =SUM(F33:F34) -> 954.3 | G35: =SUM(G33:G34) -> 234 | H35: =SUM(H33:H34) -> 200 | I35: =SUM(I33:I34) -> 3400 | J35: =SUM(J33:J34) -> 0 | K35: =SUM(K33:K34) -> 20359.333 | ... AA35: =SUM(AA33:AA34) -> 0 | AB35: 陈超 | AC35: 104.34 | AD35: =COUNTIF(C:C,C35) -> 7
A36: =A34+1 -> 24 | B36: 机场店1组 | C36: 严云中 | D36: =INDEX('05基本'!I:I,MATCH(C36,'05基本'!C:C,0))+INDEX('05基本'!J:J,MATCH(C36,'05基本'!C:C,0)) -> 40 | E36: =INDEX('05基本'!AA:AA,MATCH(C36,'05基本'!C:C,0)) -> 1268.59 | F36: =INDEX('05基本'!AB:AB,MATCH(C36,'05基本'!C:C,0)) -> 477.15 | G36: =INDEX('05基本'!AC:AC,MATCH(C36,'05基本'!C:C,0)) -> 117 | H36: =INDEX('05基本'!K:K,MATCH(C36,'05基本'!C:C,0))+INDEX('05基本'!L:L,MATCH(C36,'05基本'!C:C,0)) -> 0 | I36: =INDEX('05基本'!P:P,MATCH(C36,'05基本'!C:C,0)) -> 1140 | J36: =INDEX('05基本'!M:M,MATCH(C36,'05基本'!C:C,0)) -> 0 | K36: =INDEX('05月车间提成'!W:W,MATCH(C36,'05月车间提成'!C:C,0)) -> 8523.3875 | L36: =SUMIF(综合考核!A:A,'05月提成-机场售后'!C36,综合考核!M:M) -> 0 | M36: =SUM(K36:L36) -> 8523.3875 | N36: =SUMIF(服装扣款!C:C,C36,服装扣款!N:N) -> 0 | O36: =M36-N36 -> 8523.3875 | P36: =SUMIF(西物公积金!C:C,C36,西物公积金!I:I) -> 0 | Q36: =SUMIF(综合考核!A:A,'05月提成-机场售后'!C36,综合考核!N:N) -> 0 | R36: =M36+I36+Q36 -> 9663.3875 | S36: =INDEX(AC:AC,MATCH(C36,AB:AB,0)) -> 122.08 | U36: =S36-T36 -> 122.08 | V36: =INDEX('05基本'!AF:AF,MATCH(C36,'05基本'!C:C,0)) -> 0 | W36: =O36-P36-U36 -> 8401.3075 | Y36: =SUM(Z36:AA36) -> 768.616 | Z36: ='05月车间提成'!D66*'05月车间提成'!G66*0.05 -> 768.616 | AB36: 陈凤平 | AC36: 53.15 | AD36: =COUNTIF(C:C,C36) -> 1 | AF36: =SUMIF('05月其他部门提成'!C:C,'05月提成-机场售后'!C36,'05月其他部门提成'!Q:Q) -> 0 | AG36: =SUMIF('05月车间提成'!C:C,'05月提成-机场售后'!C36,'05月车间提成'!W:W) -> 8523.3875 | AH36: =SUMIF('05月业务提成'!B:B,'05月提成-机场售后'!C36,'05月业务提成'!BO:BO) -> 0 | AI36: =AF36+AG36+AH36 -> 8523.3875 | AJ36: =AI36-K36 -> 0
A37: =A36+1 -> 25 | C37: 吴明洋 | D37: =INDEX('05基本'!I:I,MATCH(C37,'05基本'!C:C,0))+INDEX('05基本'!J:J,MATCH(C37,'05基本'!C:C,0)) -> 30 | E37: =INDEX('05基本'!AA:AA,MATCH(C37,'05基本'!C:C,0)) -> 1268.59 | F37: =INDEX('05基本'!AB:AB,MATCH(C37,'05基本'!C:C,0)) -> 477.15 | G37: =INDEX('05基本'!AC:AC,MATCH(C37,'05基本'!C:C,0)) -> 117 | H37: =INDEX('05基本'!K:K,MATCH(C37,'05基本'!C:C,0))+INDEX('05基本'!L:L,MATCH(C37,'05基本'!C:C,0)) -> 0 | I37: =INDEX('05基本'!P:P,MATCH(C37,'05基本'!C:C,0)) -> 930 | J37: =INDEX('05基本'!M:M,MATCH(C37,'05基本'!C:C,0)) -> 0 | K37: =INDEX('05月车间提成'!W:W,MATCH(C37,'05月车间提成'!C:C,0)) -> 6365.6575 | L37: =SUMIF(综合考核!A:A,'05月提成-机场售后'!C37,综合考核!M:M) -> 0 | M37: =SUM(K37:L37) -> 6365.6575 | N37: =SUMIF(服装扣款!C:C,C37,服装扣款!N:N) -> 0 | O37: =M37-N37 -> 6365.6575 | P37: =SUMIF(西物公积金!C:C,C37,西物公积金!I:I) -> 0 | Q37: =SUMIF(综合考核!A:A,'05月提成-机场售后'!C37,综合考核!N:N) -> 0 | R37: =M37+I37+Q37 -> 7295.6575 | S37: =INDEX(AC:AC,MATCH(C37,AB:AB,0)) -> 51.05 | U37: =S37-T37 -> 51.05 | V37: =INDEX('05基本'!AF:AF,MATCH(C37,'05基本'!C:C,0)) -> 0 | W37: =O37-P37-U37 -> 6314.6075 | AB37: 韩维 | AC37: 104.37 | AD37: =COUNTIF(C:C,C37) -> 1 | AF37: =SUMIF('05月其他部门提成'!C:C,'05月提成-机场售后'!C37,'05月其他部门提成'!Q:Q) -> 0 | AG37: =SUMIF('05月车间提成'!C:C,'05月提成-机场售后'!C37,'05月车间提成'!W:W) -> 6365.6575 | AH37: =SUMIF('05月业务提成'!B:B,'05月提成-机场售后'!C37,'05月业务提成'!BO:BO) -> 0 | AI37: =AF37+AG37+AH37 -> 6365.6575 | AJ37: =AI37-K37 -> 0
C38: 机场店1组合计 | D38: =SUM(D36:D37) -> 70 | E38: =SUM(E36:E37) -> 2537.18 | F38: =SUM(F36:F37) -> 954.3 | G38: =SUM(G36:G37) -> 234 | H38: =SUM(H36:H37) -> 0 | I38: =SUM(I36:I37) -> 2070 | J38: =SUM(J36:J37) -> 0 | K38: =SUM(K36:K37) -> 14889.045 | ... AA38: =SUM(AA36:AA37) -> 0 | AB38: 何辉 | AC38: 78.07 | AD38: =COUNTIF(C:C,C38) -> 1
A39: =A37+1 -> 26 | B39: 机场店2组 | C39: 韩爱民 | D39: =INDEX('05基本'!I:I,MATCH(C39,'05基本'!C:C,0))+INDEX('05基本'!J:J,MATCH(C39,'05基本'!C:C,0)) -> 30 | E39: =INDEX('05基本'!AA:AA,MATCH(C39,'05基本'!C:C,0)) -> 1268.59 | F39: =INDEX('05基本'!AB:AB,MATCH(C39,'05基本'!C:C,0)) -> 477.15 | G39: =INDEX('05基本'!AC:AC,MATCH(C39,'05基本'!C:C,0)) -> 117 | H39: =INDEX('05基本'!K:K,MATCH(C39,'05基本'!C:C,0))+INDEX('05基本'!L:L,MATCH(C39,'05基本'!C:C,0)) -> 0 | I39: =INDEX('05基本'!P:P,MATCH(C39,'05基本'!C:C,0)) -> 1130 | J39: =INDEX('05基本'!M:M,MATCH(C39,'05基本'!C:C,0)) -> 0 | K39: =INDEX('05月车间提成'!W:W,MATCH(C39,'05月车间提成'!C:C,0)) -> 7944.3827 | L39: =SUMIF(综合考核!A:A,'05月提成-机场售后'!C39,综合考核!M:M) -> 0 | M39: =SUM(K39:L39) -> 7944.3827 | N39: =SUMIF(服装扣款!C:C,C39,服装扣款!N:N) -> 0 | O39: =M39-N39 -> 7944.3827 | P39: =SUMIF(西物公积金!C:C,C39,西物公积金!I:I) -> 0 | Q39: =SUMIF(综合考核!A:A,'05月提成-机场售后'!C39,综合考核!N:N) -> 0 | R39: =M39+I39+Q39 -> 9074.3827 | S39: =INDEX(AC:AC,MATCH(C39,AB:AB,0)) -> 104.41 | U39: =S39-T39 -> 104.41 | V39: =INDEX('05基本'!AF:AF,MATCH(C39,'05基本'!C:C,0)) -> 0 | W39: =O39-P39-U39 -> 7839.9727 | Y39: =Z39 -> 671.814 | Z39: ='05月车间提成'!D69*'05月车间提成'!G69*0.05 -> 671.814 | AB39: 杨定安 | AC39: 95.12 | AD39: =COUNTIF(C:C,C39) -> 1 | AF39: =SUMIF('05月其他部门提成'!C:C,'05月提成-机场售后'!C39,'05月其他部门提成'!Q:Q) -> 0 | AG39: =SUMIF('05月车间提成'!C:C,'05月提成-机场售后'!C39,'05月车间提成'!W:W) -> 7944.3827 | AH39: =SUMIF('05月业务提成'!B:B,'05月提成-机场售后'!C39,'05月业务提成'!BO:BO) -> 0 | AI39: =AF39+AG39+AH39 -> 7944.3827 | AJ39: =AI39-K39 -> 0
A40: =A39+1 -> 27 | C40: 蒋湘龙 | D40: =INDEX('05基本'!I:I,MATCH(C40,'05基本'!C:C,0))+INDEX('05基本'!J:J,MATCH(C40,'05基本'!C:C,0)) -> 30 | E40: =INDEX('05基本'!AA:AA,MATCH(C40,'05基本'!C:C,0)) -> 1268.59 | F40: =INDEX('05基本'!AB:AB,MATCH(C40,'05基本'!C:C,0)) -> 477.15 | G40: =INDEX('05基本'!AC:AC,MATCH(C40,'05基本'!C:C,0)) -> 117 | H40: =INDEX('05基本'!K:K,MATCH(C40,'05基本'!C:C,0))+INDEX('05基本'!L:L,MATCH(C40,'05基本'!C:C,0)) -> 0 | I40: =INDEX('05基本'!P:P,MATCH(C40,'05基本'!C:C,0)) -> 930 | J40: =INDEX('05基本'!M:M,MATCH(C40,'05基本'!C:C,0)) -> 0 | K40: =INDEX('05月车间提成'!W:W,MATCH(C40,'05月车间提成'!C:C,0)) -> 4164.8543 | L40: =SUMIF(综合考核!A:A,'05月提成-机场售后'!C40,综合考核!M:M) -> 0 | M40: =SUM(K40:L40) -> 4164.8543 | N40: =SUMIF(服装扣款!C:C,C40,服装扣款!N:N) -> 0 | O40: =M40-N40 -> 4164.8543 | P40: =SUMIF(西物公积金!C:C,C40,西物公积金!I:I) -> 0 | Q40: =SUMIF(综合考核!A:A,'05月提成-机场售后'!C40,综合考核!N:N) -> 0 | R40: =M40+I40+Q40 -> 5094.8543 | S40: =INDEX(AC:AC,MATCH(C40,AB:AB,0)) -> 0 | U40: =S40-T40 -> 0 | V40: =INDEX('05基本'!AF:AF,MATCH(C40,'05基本'!C:C,0)) -> 0 | W40: =O40-P40-U40 -> 4164.8543 | Y40: =Z40 -> 0 | Z40: ='05月车间提成'!D70*'05月车间提成'!G70*0.05 -> 0 | AD40: =COUNTIF(C:C,C40) -> 1 | AF40: =SUMIF('05月其他部门提成'!C:C,'05月提成-机场售后'!C40,'05月其他部门提成'!Q:Q) -> 0 | AG40: =SUMIF('05月车间提成'!C:C,'05月提成-机场售后'!C40,'05月车间提成'!W:W) -> 4164.8543 | AH40: =SUMIF('05月业务提成'!B:B,'05月提成-机场售后'!C40,'05月业务提成'!BO:BO) -> 0 | AI40: =AF40+AG40+AH40 -> 4164.8543 | AJ40: =AI40-K40 -> 0
B41: 机场店3组 | C41: 机场店2组 | D41: =SUM(D39:D40) -> 60 | E41: =SUM(E39:E40) -> 2537.18 | F41: =SUM(F39:F40) -> 954.3 | G41: =SUM(G39:G40) -> 234 | H41: =SUM(H39:H40) -> 0 | I41: =SUM(I39:I40) -> 2060 | J41: =SUM(J39:J40) -> 0 | K41: =SUM(K39:K40) -> 12109.237 | ... AA41: =SUM(AA39:AA40) -> 0
A42: =$A$40+1 -> 28 | C42: 张雨 | D42: =INDEX('05基本'!I:I,MATCH(C42,'05基本'!C:C,0))+INDEX('05基本'!J:J,MATCH(C42,'05基本'!C:C,0)) -> 90 | E42: =INDEX('05基本'!AA:AA,MATCH(C42,'05基本'!C:C,0)) -> 1268.59 | F42: =INDEX('05基本'!AB:AB,MATCH(C42,'05基本'!C:C,0)) -> 477.15 | G42: =INDEX('05基本'!AC:AC,MATCH(C42,'05基本'!C:C,0)) -> 117 | H42: =INDEX('05基本'!K:K,MATCH(C42,'05基本'!C:C,0))+INDEX('05基本'!L:L,MATCH(C42,'05基本'!C:C,0)) -> 0 | I42: =INDEX('05基本'!P:P,MATCH(C42,'05基本'!C:C,0)) -> 1140 | J42: =INDEX('05基本'!M:M,MATCH(C42,'05基本'!C:C,0)) -> 0 | K42: =INDEX('05月车间提成'!W:W,MATCH(C42,'05月车间提成'!C:C,0)) -> 10181.37 | L42: =SUMIF(综合考核!A:A,'05月提成-机场售后'!C42,综合考核!M:M) -> 0 | M42: =SUM(K42:L42) -> 10181.37 | N42: =SUMIF(服装扣款!C:C,C42,服装扣款!N:N) -> 0 | O42: =M42-N42 -> 10181.37 | P42: =SUMIF(西物公积金!C:C,C42,西物公积金!I:I) -> 0 | Q42: =SUMIF(综合考核!A:A,'05月提成-机场售后'!C42,综合考核!N:N) -> 0 | R42: =M42+I42+Q42 -> 11321.37 | S42: =INDEX(AC:AC,MATCH(C42,AB:AB,0)) -> 171.82 | U42: =S42-T42 -> 171.82 | V42: =INDEX('05基本'!AF:AF,MATCH(C42,'05基本'!C:C,0)) -> 0 | W42: =O42-P42-U42 -> 10009.55 | Y42: =Z42 -> 0 | Z42: ='05月车间提成'!D72*'05月车间提成'!G72*0.05 -> 0 | AD42: =COUNTIF(C:C,C42) -> 1 | AF42: =SUMIF('05月其他部门提成'!C:C,'05月提成-机场售后'!C42,'05月其他部门提成'!Q:Q) -> 0 | AG42: =SUMIF('05月车间提成'!C:C,'05月提成-机场售后'!C42,'05月车间提成'!W:W) -> 10181.37 | AH42: =SUMIF('05月业务提成'!B:B,'05月提成-机场售后'!C42,'05月业务提成'!BO:BO) -> 0 | AI42: =AF42+AG42+AH42 -> 10181.37 | AJ42: =AI42-K42 -> 0
A43: 29 | C43: 郑晓龙 | D43: =INDEX('05基本'!I:I,MATCH(C43,'05基本'!C:C,0))+INDEX('05基本'!J:J,MATCH(C43,'05基本'!C:C,0)) -> 60 | E43: =INDEX('05基本'!AA:AA,MATCH(C43,'05基本'!C:C,0)) -> 1268.59 | F43: =INDEX('05基本'!AB:AB,MATCH(C43,'05基本'!C:C,0)) -> 477.15 | G43: =INDEX('05基本'!AC:AC,MATCH(C43,'05基本'!C:C,0)) -> 117 | H43: =INDEX('05基本'!K:K,MATCH(C43,'05基本'!C:C,0))+INDEX('05基本'!L:L,MATCH(C43,'05基本'!C:C,0)) -> 0 | I43: =INDEX('05基本'!P:P,MATCH(C43,'05基本'!C:C,0)) -> 960 | J43: =INDEX('05基本'!M:M,MATCH(C43,'05基本'!C:C,0)) -> 0 | K43: =INDEX('05月车间提成'!W:W,MATCH(C43,'05月车间提成'!C:C,0)) -> 6400.3902 | L43: =SUMIF(综合考核!A:A,'05月提成-机场售后'!C43,综合考核!M:M) -> 0 | M43: =SUM(K43:L43) -> 6400.3902 | N43: =SUMIF(服装扣款!C:C,C43,服装扣款!N:N) -> 0 | O43: =M43-N43 -> 6400.3902 | P43: =SUMIF(西物公积金!C:C,C43,西物公积金!I:I) -> 0 | Q43: =SUMIF(综合考核!A:A,'05月提成-机场售后'!C43,综合考核!N:N) -> 0 | R43: =M43+I43+Q43 -> 7360.3902 | S43: =INDEX(AC:AC,MATCH(C43,AB:AB,0)) -> 52.99 | U43: =S43-T43 -> 52.99 | V43: =INDEX('05基本'!AF:AF,MATCH(C43,'05基本'!C:C,0)) -> 0 | W43: =O43-P43-U43 -> 6347.4002 | Y43: =Z43 -> 0 | Z43: ='05月车间提成'!D72*'05月车间提成'!G72*0.05 -> 0 | AD43: =COUNTIF(C:C,C43) -> 1 | AF43: =SUMIF('05月其他部门提成'!C:C,'05月提成-机场售后'!C43,'05月其他部门提成'!Q:Q) -> 0 | AG43: =SUMIF('05月车间提成'!C:C,'05月提成-机场售后'!C43,'05月车间提成'!W:W) -> 6400.3902 | AH43: =SUMIF('05月业务提成'!B:B,'05月提成-机场售后'!C43,'05月业务提成'!BO:BO) -> 0 | AI43: =AF43+AG43+AH43 -> 6400.3902 | AJ43: =AI43-K43 -> 0
A44: 30 | C44: 刘杨 | D44: =INDEX('05基本'!I:I,MATCH(C44,'05基本'!C:C,0))+INDEX('05基本'!J:J,MATCH(C44,'05基本'!C:C,0)) -> 100 | E44: =INDEX('05基本'!AA:AA,MATCH(C44,'05基本'!C:C,0)) -> 1268.59 | F44: =INDEX('05基本'!AB:AB,MATCH(C44,'05基本'!C:C,0)) -> 477.15 | G44: =INDEX('05基本'!AC:AC,MATCH(C44,'05基本'!C:C,0)) -> 117 | H44: =INDEX('05基本'!K:K,MATCH(C44,'05基本'!C:C,0))+INDEX('05基本'!L:L,MATCH(C44,'05基本'!C:C,0)) -> 0 | I44: =INDEX('05基本'!P:P,MATCH(C44,'05基本'!C:C,0)) -> 1000 | J44: =INDEX('05基本'!M:M,MATCH(C44,'05基本'!C:C,0)) -> 0 | K44: =INDEX('05月车间提成'!W:W,MATCH(C44,'05月车间提成'!C:C,0)) -> 9320.5463 | L44: =SUMIF(综合考核!A:A,'05月提成-机场售后'!C44,综合考核!M:M) -> 0 | M44: =SUM(K44:L44) -> 9320.5463 | N44: =SUMIF(服装扣款!C:C,C44,服装扣款!N:N) -> 0 | O44: =M44-N44 -> 9320.5463 | P44: =SUMIF(西物公积金!C:C,C44,西物公积金!I:I) -> 0 | Q44: =SUMIF(综合考核!A:A,'05月提成-机场售后'!C44,综合考核!N:N) -> 0 | R44: =M44+I44+Q44 -> 10320.546 | S44: =INDEX(AC:AC,MATCH(C44,AB:AB,0)) -> 141.8 | U44: =S44-T44 -> 141.8 | V44: =INDEX('05基本'!AF:AF,MATCH(C44,'05基本'!C:C,0)) -> 0 | W44: =O44-P44-U44 -> 9178.7463 | Y44: =Z44 -> 990.466 | Z44: ='05月车间提成'!D73*'05月车间提成'!G73*0.05 -> 990.466 | AD44: =COUNTIF(C:C,C44) -> 1 | AF44: =SUMIF('05月其他部门提成'!C:C,'05月提成-机场售后'!C44,'05月其他部门提成'!Q:Q) -> 0 | AG44: =SUMIF('05月车间提成'!C:C,'05月提成-机场售后'!C44,'05月车间提成'!W:W) -> 9320.5463 | AH44: =SUMIF('05月业务提成'!B:B,'05月提成-机场售后'!C44,'05月业务提成'!BO:BO) -> 0 | AI44: =AF44+AG44+AH44 -> 9320.5463 | AJ44: =AI44-K44 -> 0
C45: 机场店3组 | D45: =SUM(D42:D44) -> 250 | E45: =SUM(E42:E44) -> 3805.77 | F45: =SUM(F42:F44) -> 1431.45 | G45: =SUM(G42:G44) -> 351 | H45: =SUM(H42:H44) -> 0 | I45: =SUM(I42:I44) -> 3100 | J45: =SUM(J42:J44) -> 0 | K45: =SUM(K42:K44) -> 25902.306 | ... AA45: =SUM(AA42:AA44) -> 0
A46: =$A$44+1 -> 31 | B46: 机场-钣喷中心 | C46: 陈超 | D46: =INDEX('05基本'!I:I,MATCH(C46,'05基本'!C:C,0))+INDEX('05基本'!J:J,MATCH(C46,'05基本'!C:C,0)) -> 0 | E46: =INDEX('05基本'!AA:AA,MATCH(C46,'05基本'!C:C,0)) -> 1268.59 | F46: =INDEX('05基本'!AB:AB,MATCH(C46,'05基本'!C:C,0)) -> 477.15 | G46: =INDEX('05基本'!AC:AC,MATCH(C46,'05基本'!C:C,0)) -> 117 | H46: =INDEX('05基本'!K:K,MATCH(C46,'05基本'!C:C,0))+INDEX('05基本'!L:L,MATCH(C46,'05基本'!C:C,0)) -> 0 | I46: =INDEX('05基本'!P:P,MATCH(C46,'05基本'!C:C,0)) -> 1500 | J46: =INDEX('05基本'!M:M,MATCH(C46,'05基本'!C:C,0)) -> 0 | K46: =SUMIF(钣喷中心!C:C,C46,钣喷中心!N:N) -> 7572.39 | L46: =SUMIF(综合考核!A:A,'05月提成-机场售后'!C46,综合考核!M:M) -> 0 | M46: =SUM(K46:L46) -> 7572.39 | N46: =SUMIF(服装扣款!C:C,C46,服装扣款!N:N) -> 0 | O46: =M46-N46 -> 7572.39 | P46: =SUMIF(西物公积金!C:C,C46,西物公积金!I:I) -> 0 | Q46: =SUMIF(综合考核!A:A,'05月提成-机场售后'!C46,综合考核!N:N) -> 0 | R46: =M46+I46+Q46 -> 9072.39 | S46: =INDEX(AC:AC,MATCH(C46,AB:AB,0)) -> 104.34 | U46: =S46-T46 -> 104.34 | V46: =INDEX('05基本'!AF:AF,MATCH(C46,'05基本'!C:C,0)) -> 0 | W46: =O46-P46-U46 -> 7468.05 | Y46: =Z46 -> 83.34 | Z46: 83.34 | AD46: =COUNTIF(C:C,C46) -> 1 | AF46: =SUMIF('05月其他部门提成'!C:C,'05月提成-机场售后'!C46,'05月其他部门提成'!Q:Q) -> 0 | AG46: =SUMIF('05月车间提成'!C:C,'05月提成-机场售后'!C46,'05月车间提成'!W:W) -> 0 | AH46: =SUMIF('05月业务提成'!B:B,'05月提成-机场售后'!C46,'05月业务提成'!BO:BO) -> 0 | AI46: =AF46+AG46+AH46 -> 0 | AJ46: =AI46-K46 -> -7572.39
A47: =A46+1 -> 32 | C47: 陈凤平 | D47: =INDEX('05基本'!I:I,MATCH(C47,'05基本'!C:C,0))+INDEX('05基本'!J:J,MATCH(C47,'05基本'!C:C,0)) -> 0 | E47: =INDEX('05基本'!AA:AA,MATCH(C47,'05基本'!C:C,0)) -> 1268.59 | F47: =INDEX('05基本'!AB:AB,MATCH(C47,'05基本'!C:C,0)) -> 477.15 | G47: =INDEX('05基本'!AC:AC,MATCH(C47,'05基本'!C:C,0)) -> 117 | H47: =INDEX('05基本'!K:K,MATCH(C47,'05基本'!C:C,0))+INDEX('05基本'!L:L,MATCH(C47,'05基本'!C:C,0)) -> 0 | I47: =INDEX('05基本'!P:P,MATCH(C47,'05基本'!C:C,0)) -> 1500 | J47: =INDEX('05基本'!M:M,MATCH(C47,'05基本'!C:C,0)) -> 0 | K47: =SUMIF(钣喷中心!C:C,C47,钣喷中心!N:N) -> 7866 | L47: =SUMIF(综合考核!A:A,'05月提成-机场售后'!C47,综合考核!M:M) -> 0 | M47: =SUM(K47:L47) -> 7866 | N47: =SUMIF(服装扣款!C:C,C47,服装扣款!N:N) -> 0 | O47: =M47-N47 -> 7866 | P47: =SUMIF(西物公积金!C:C,C47,西物公积金!I:I) -> 0 | Q47: =SUMIF(综合考核!A:A,'05月提成-机场售后'!C47,综合考核!N:N) -> 0 | R47: =M47+I47+Q47 -> 9366 | S47: =INDEX(AC:AC,MATCH(C47,AB:AB,0)) -> 53.15 | U47: =S47-T47 -> 53.15 | V47: =INDEX('05基本'!AF:AF,MATCH(C47,'05基本'!C:C,0)) -> 0 | W47: =O47-P47-U47 -> 7812.85 | Y47: =Z47 -> 83.34 | Z47: 83.34 | AD47: =COUNTIF(C:C,C47) -> 1 | AF47: =SUMIF('05月其他部门提成'!C:C,'05月提成-机场售后'!C47,'05月其他部门提成'!Q:Q) -> 0 | AG47: =SUMIF('05月车间提成'!C:C,'05月提成-机场售后'!C47,'05月车间提成'!W:W) -> 0 | AH47: =SUMIF('05月业务提成'!B:B,'05月提成-机场售后'!C47,'05月业务提成'!BO:BO) -> 0 | AI47: =AF47+AG47+AH47 -> 0 | AJ47: =AI47-K47 -> -7866
A48: =A47+1 -> 33 | C48: 韩维 | D48: =INDEX('05基本'!I:I,MATCH(C48,'05基本'!C:C,0))+INDEX('05基本'!J:J,MATCH(C48,'05基本'!C:C,0)) -> 0 | E48: =INDEX('05基本'!AA:AA,MATCH(C48,'05基本'!C:C,0)) -> 1268.59 | F48: =INDEX('05基本'!AB:AB,MATCH(C48,'05基本'!C:C,0)) -> 477.15 | G48: =INDEX('05基本'!AC:AC,MATCH(C48,'05基本'!C:C,0)) -> 117 | H48: =INDEX('05基本'!K:K,MATCH(C48,'05基本'!C:C,0))+INDEX('05基本'!L:L,MATCH(C48,'05基本'!C:C,0)) -> 0 | I48: =INDEX('05基本'!P:P,MATCH(C48,'05基本'!C:C,0)) -> 1500 | J48: =INDEX('05基本'!M:M,MATCH(C48,'05基本'!C:C,0)) -> 0 | K48: =SUMIF(钣喷中心!C:C,C48,钣喷中心!N:N) -> 7573.39 | L48: =SUMIF(综合考核!A:A,'05月提成-机场售后'!C48,综合考核!M:M) -> 0 | M48: =SUM(K48:L48) -> 7573.39 | N48: =SUMIF(服装扣款!C:C,C48,服装扣款!N:N) -> 0 | O48: =M48-N48 -> 7573.39 | P48: =SUMIF(西物公积金!C:C,C48,西物公积金!I:I) -> 0 | Q48: =SUMIF(综合考核!A:A,'05月提成-机场售后'!C48,综合考核!N:N) -> 0 | R48: =M48+I48+Q48 -> 9073.39 | S48: =INDEX(AC:AC,MATCH(C48,AB:AB,0)) -> 104.37 | U48: =S48-T48 -> 104.37 | V48: =INDEX('05基本'!AF:AF,MATCH(C48,'05基本'!C:C,0)) -> 0 | W48: =O48-P48-U48 -> 7469.02 | Y48: =Z48 -> 83.34 | Z48: 83.34 | AD48: =COUNTIF(C:C,C48) -> 1 | AF48: =SUMIF('05月其他部门提成'!C:C,'05月提成-机场售后'!C48,'05月其他部门提成'!Q:Q) -> 0 | AG48: =SUMIF('05月车间提成'!C:C,'05月提成-机场售后'!C48,'05月车间提成'!W:W) -> 0 | AH48: =SUMIF('05月业务提成'!B:B,'05月提成-机场售后'!C48,'05月业务提成'!BO:BO) -> 0 | AI48: =AF48+AG48+AH48 -> 0 | AJ48: =AI48-K48 -> -7573.39
A49: =A48+1 -> 34 | C49: 何辉 | D49: =INDEX('05基本'!I:I,MATCH(C49,'05基本'!C:C,0))+INDEX('05基本'!J:J,MATCH(C49,'05基本'!C:C,0)) -> 0 | E49: =INDEX('05基本'!AA:AA,MATCH(C49,'05基本'!C:C,0)) -> 1268.59 | F49: =INDEX('05基本'!AB:AB,MATCH(C49,'05基本'!C:C,0)) -> 477.15 | G49: =INDEX('05基本'!AC:AC,MATCH(C49,'05基本'!C:C,0)) -> 117 | H49: =INDEX('05基本'!K:K,MATCH(C49,'05基本'!C:C,0))+INDEX('05基本'!L:L,MATCH(C49,'05基本'!C:C,0)) -> 0 | I49: =INDEX('05基本'!P:P,MATCH(C49,'05基本'!C:C,0)) -> 1500 | J49: =INDEX('05基本'!M:M,MATCH(C49,'05基本'!C:C,0)) -> 0 | K49: =SUMIF(钣喷中心!C:C,C49,钣喷中心!N:N) -> 6696.4333 | L49: =SUMIF(综合考核!A:A,'05月提成-机场售后'!C49,综合考核!M:M) -> 0 | M49: =SUM(K49:L49) -> 6696.4333 | N49: =SUMIF(服装扣款!C:C,C49,服装扣款!N:N) -> 0 | O49: =M49-N49 -> 6696.4333 | P49: =SUMIF(西物公积金!C:C,C49,西物公积金!I:I) -> 0 | Q49: =SUMIF(综合考核!A:A,'05月提成-机场售后'!C49,综合考核!N:N) -> 0 | R49: =M49+I49+Q49 -> 8196.4333 | S49: =INDEX(AC:AC,MATCH(C49,AB:AB,0)) -> 78.07 | U49: =S49-T49 -> 78.07 | V49: =INDEX('05基本'!AF:AF,MATCH(C49,'05基本'!C:C,0)) -> 0 | W49: =O49-P49-U49 -> 6618.3633 | Y49: =Z49 -> 83.34 | Z49: 83.34 | AD49: =COUNTIF(C:C,C49) -> 1 | AF49: =SUMIF('05月其他部门提成'!C:C,'05月提成-机场售后'!C49,'05月其他部门提成'!Q:Q) -> 0 | AG49: =SUMIF('05月车间提成'!C:C,'05月提成-机场售后'!C49,'05月车间提成'!W:W) -> 0 | AH49: =SUMIF('05月业务提成'!B:B,'05月提成-机场售后'!C49,'05月业务提成'!BO:BO) -> 0 | AI49: =AF49+AG49+AH49 -> 0 | AJ49: =AI49-K49 -> -6696.4333
A50: =A49+1 -> 35 | C50: 杨定安 | D50: =INDEX('05基本'!I:I,MATCH(C50,'05基本'!C:C,0))+INDEX('05基本'!J:J,MATCH(C50,'05基本'!C:C,0)) -> 0 | E50: =INDEX('05基本'!AA:AA,MATCH(C50,'05基本'!C:C,0)) -> 1268.59 | F50: =INDEX('05基本'!AB:AB,MATCH(C50,'05基本'!C:C,0)) -> 477.15 | G50: =INDEX('05基本'!AC:AC,MATCH(C50,'05基本'!C:C,0)) -> 117 | H50: =INDEX('05基本'!K:K,MATCH(C50,'05基本'!C:C,0))+INDEX('05基本'!L:L,MATCH(C50,'05基本'!C:C,0)) -> 0 | I50: =INDEX('05基本'!P:P,MATCH(C50,'05基本'!C:C,0)) -> 1500 | J50: =INDEX('05基本'!M:M,MATCH(C50,'05基本'!C:C,0)) -> 0 | K50: =SUMIF(钣喷中心!C:C,C50,钣喷中心!N:N) -> 7264.9 | L50: =SUMIF(综合考核!A:A,'05月提成-机场售后'!C50,综合考核!M:M) -> 0 | M50: =SUM(K50:L50) -> 7264.9 | N50: =SUMIF(服装扣款!C:C,C50,服装扣款!N:N) -> 0 | O50: =M50-N50 -> 7264.9 | P50: =SUMIF(西物公积金!C:C,C50,西物公积金!I:I) -> 0 | Q50: =SUMIF(综合考核!A:A,'05月提成-机场售后'!C50,综合考核!N:N) -> 0 | R50: =M50+I50+Q50 -> 8764.9 | S50: =INDEX(AC:AC,MATCH(C50,AB:AB,0)) -> 95.12 | U50: =S50-T50 -> 95.12 | V50: =INDEX('05基本'!AF:AF,MATCH(C50,'05基本'!C:C,0)) -> 0 | W50: =O50-P50-U50 -> 7169.78 | Y50: =Z50 -> 83.34 | Z50: 83.34 | AD50: =COUNTIF(C:C,C50) -> 1 | AF50: =SUMIF('05月其他部门提成'!C:C,'05月提成-机场售后'!C50,'05月其他部门提成'!Q:Q) -> 0 | AG50: =SUMIF('05月车间提成'!C:C,'05月提成-机场售后'!C50,'05月车间提成'!W:W) -> 0 | AH50: =SUMIF('05月业务提成'!B:B,'05月提成-机场售后'!C50,'05月业务提成'!BO:BO) -> 0 | AI50: =AF50+AG50+AH50 -> 0 | AJ50: =AI50-K50 -> -7264.9
C51: 机场店钣喷 | D51: =SUM(D46:D50) -> 0 | E51: =SUM(E46:E50) -> 6342.95 | F51: =SUM(F46:F50) -> 2385.75 | G51: =SUM(G46:G50) -> 585 | H51: =SUM(H46:H50) -> 0 | I51: =SUM(I46:I50) -> 7500 | J51: =SUM(J46:J50) -> 0 | K51: =SUM(K46:K50) -> 36973.113 | ... AA51: =SUM(AA46:AA50) -> 0 | AD51: =COUNTIF(C:C,C51) -> 1
C52: 机场店合计 | D52: =D35+D38+D41+D45+D51 -> 380 | E52: =E35+E38+E41+E45+E51 -> 17760.26 | F52: =F35+F38+F41+F45+F51 -> 6680.1 | G52: =G35+G38+G41+G45+G51 -> 1638 | H52: =H35+H38+H41+H45+H51 -> 200 | I52: =I35+I38+I41+I45+I51 -> 18130 | J52: =J35+J38+J41+J45+J51 -> 0 | K52: =K35+K38+K41+K45+K51 -> 110233.03 | ... AA52: =AA35+AA38+AA41+AA45+AA51 -> 0
A53: =A50 -> 35 | B53: 总计 | D53: =SUM(D32,D52) -> 380 | E53: =SUM(E32,E52) -> 43360.97 | F53: =SUM(F32,F52) -> 16317.95 | G53: =SUM(G32,G52) -> 3978 | H53: =SUM(H32,H52) -> 400 | I53: =SUM(I32,I52) -> 43660 | J53: =SUM(J32,J52) -> 0 | K53: =SUM(K32,K52) -> 237687.87 | ... AA53: =SUM(AA32,AA52) -> 1974.7532
A54: 附： | B54: 1、维修业务统计月报表 | E54: ='05基本'!AA163 -> 43360.97 | F54: ='05基本'!AB163 -> 16317.95 | G54: ='05基本'!AC163 -> 3978 | I54: ='05基本'!P163 -> 43660 | L54: =L53 -> 360 | M54: 3、加装提成统计表 | P54: =P53*2 -> 0 | R54: =R53/A53 -> 8048.7963
B55: 2、生产人员提成分配明细表 | E55: =E53-E54 -> 0 | F55: =F54-F53 -> 0 | G55: =G54-G53 -> 0 | I55: =I54-I53 -> 0 | L55: =L54-L53 -> 0 | M55: 4、旧车续保返利统计表 | P55: =P53-P54 -> 0
A56: 事业部总经理： | F56: 事业部审核： | G56: 事业部审核： | L56: 财务审核： | R56: 直属领导审核： | V56: 制表：
O57: =R53/A53 -> 8048.7963

Sheet 05月业务提成
A1: 2月业务提成
A2: 职 务 | B2: 姓名 | C2: 当月产值提成 | BK2: 当月基本 | BO2: 当月应提绩效
C3: 台次提成 | F3: 维修产值提成（不含保险，养护，精品，美容） | J3: 保险提成 | N3: 索赔提成 | Q3: 养护提成 | W3: 精品提成 | AA3: 美容提成 | AE3: 福袋提成 | AN3: 续保提成 | AR3: LED灯完成考核 | AW3: 车机奖励 | AX3: 美容奖励 | AY3: 轻小损提成 | AZ3: 续保提成 | BA3: 推荐事故 | BB3: 延保提成 | BG3: 小计 | BH3: 综合考核 | BJ3: 小计
C4: 台次 | D4: 单台/元 | E4: 台次提成 | F4: 提成产值 | G4: 完成率 | H4: 提成系数 | I4: 产值提成 | J4: 提成产值 | K4: 完成率 | L4: 提成系数 | M4: 保险提成 | N4: 索赔产值 | O4: 提成系数 | P4: 索赔提成 | Q4: 养护用品产值 | R4: 完成率 | S4: 提成系数 | T4: 首保赠送养护/变速箱保护剂 | U4: 提成系数 | V4: 养护提成 | W4: 精品产值 | X4: 完成率 | Y4: 提成系数 | Z4: 精品提成 | AA4: 美容产值 | AB4: 完成率 | AC4: 提成系数 | AD4: 美容提成 | AE4: 首保福袋卡 | AF4: 保养福袋卡 | AG4: DMS保养套餐（实际） | AH4: DMS保养套餐（目标） | AI4: 完成率 | AJ4: 首保单台/元 | AK4: 保养单台/元 | AL4: DMS套餐单台/元 | AM4: 福袋&保养提成 | AN4: 续保台次 | AO4: 完成率 | AP4: 单台/元 | AQ4: 续保提成 | AR4: LED灯未完成数 | AS4: LED灯完成数 | AT4: 完成率 | AU4: 单台/元 | AV4: LED灯考核 | AW4: 车机提成 | AX4: 美容 | AY4: 推介成功0.5个面25元/1个面以上50元 | AZ4: 推介成功25元一个 | BA4: 续保推荐事故 | BB4: 延保台次 | BC4: 完成率 | BD4: 单台/元 | BE4: 有技师参与 | BF4: 延保提成 | BH4: 固定绩效 | BI4: 其它 | BK4: 基本工资 | BL4: 其中： 加班工资 | BM4: 其中： 特殊津贴 | BN4: 其中：病假、事假、缺勤、罚款 | BP4: 备注
B5: 总计 | BS5: =F5/C5 -> #DIV/0! | BT5: 维修产值 | BU5: shuo | BV5: 养护 | BW5: 精品
A6: 武侯服务前台 | B6: 台次 | C6: =INDEX('2026-5任务'!C:C,MATCH(B6,'2026-5任务'!A:A,0))+INDEX('2026-5任务'!D:D,MATCH(B6,'2026-5任务'!A:A,0))+INDEX('2026-5任务'!G:G,MATCH(B6,'2026-5任务'!A:A,0))+INDEX('2026-5任务'!E:E,MATCH(B6,'2026-5任务'!A:A,0)) -> 0 | E6: =C6*D6 -> 0 | F6: =INDEX('2026-5任务'!X:X,MATCH(B6,'2026-5任务'!A:A,0))-INDEX('2026-5任务'!R:R,MATCH(B6,'2026-5任务'!A:A,0))-INDEX('2026-5任务'!U:U,MATCH(B6,'2026-5任务'!A:A,0)) -> 0 | G6: =INDEX('2026-5任务'!W:W,MATCH(B6,'2026-5任务'!A:A,0)) -> 0 | H6: 0.02 | I6: =F6*H6*0.95 -> 0 | J6: =INDEX('2026-5任务'!R:R,MATCH(B6,'2026-5任务'!A:A,0))+INDEX('2026-5任务'!U:U,MATCH(B6,'2026-5任务'!A:A,0)) -> 0 | L6: 0.016 | M6: =J6*L6*0.95 -> 0 | N6: =INDEX('2026-5任务'!AN:AN,MATCH(B6,'2026-5任务'!A:A,0))+INDEX('2026-5任务'!AO:AO,MATCH(B6,'2026-5任务'!A:A,0)) -> 0 | O6: 0.005 | P6: =(N6*O6)*0.95 -> 0 | Q6: =INDEX('2026-5任务'!Z:Z,MATCH(B6,'2026-5任务'!A:A,0)) -> 0 | R6: =INDEX('2026-5任务'!AB:AB,MATCH(B6,'2026-5任务'!A:A,0)) -> 0 | S6: 0.06 | T6: =INDEX('2026-5任务'!AA:AA,MATCH(B6,'2026-5任务'!A:A,0)) -> 0 | U6: 0.1 | V6: =(Q6*S6)*0.95+T6*U6 -> 0 | W6: =INDEX('2026-5任务'!AD:AD,MATCH(B6,'2026-5任务'!A:A,0)) -> 0 | X6: =INDEX('2026-5任务'!AF:AF,MATCH(B6,'2026-5任务'!A:A,0)) -> 0 | Y6: 0.08 | Z6: =(W6*Y6)*0.95 -> 0 | AA6: =INDEX('2026-5任务'!AF:AF,MATCH(F6,'2026-5任务'!E:E,0)) -> 0 | AB6: =INDEX('2026-5任务'!AK:AK,MATCH(F6,'2026-5任务'!E:E,0)) -> 0 | AC6: 0.1 | AD6: =(AA6*AC6)*0.95 -> 0 | AE6: =INDEX('2026-5任务'!AV:AV,MATCH($B6,'2026-5任务'!A:A,0)) -> 0 | AF6: =INDEX('2026-5任务'!AU:AU,MATCH('05月业务提成'!B6,'2026-5任务'!A:A,0)) -> 0 | AG6: 0 | AH6: 0 | AI6: =INDEX('2026-5任务'!AW:AW,MATCH(B6,'2026-5任务'!A:A,0)) -> 0 | AJ6: 35 | AK6: 25 | AL6: 50 | AM6: =(AE6*AJ6+AF6*AK6)+IF(AG6=AH6,AG6*AL6,IF(AG6>AH6,(AG6*50+(AG6-AH6)*30),IF(AG6<AH6,AG6*AL6-(AH6-AG6)*50))) -> 0 | AN6: =INDEX('2026-5任务'!BJ:BJ,MATCH(B6,'2026-5任务'!A:A,0)) -> 0 | AP6: 25 | AQ6: =AN6*AP6 -> 0 | AR6: =INDEX('2026-5任务'!BN:BN,MATCH(B6,'2026-5任务'!A:A,0)) -> 0 | AS6: =INDEX('2026-5任务'!BM:BM,MATCH(B6,'2026-5任务'!A:A,0)) -> 0 | AT6: =INDEX('2026-5任务'!BO:BO,MATCH(B6,'2026-5任务'!A:A,0)) -> 0 | AU6: 20 | AV6: =IF(AT6>=0.8,AS6*AU6,AS6*AU6+AR6*AU6) -> 0 | AW6: =INDEX('2026-5任务'!BA:BA,MATCH(B6,'2026-5任务'!A:A,0)) -> 0 | AX6: =INDEX('2026-5任务'!BB:BB,MATCH(B6,'2026-5任务'!A:A,0)) -> 0 | AY6: =INDEX('2026-5任务'!BG:BG,MATCH(B6,'2026-5任务'!A:A,0)) -> 0 | AZ6: =INDEX('2026-5任务'!BE:BE,MATCH(B6,'2026-5任务'!A:A,0)) -> 0 | BA6: =SUMIF('4月续保推荐事故'!I:I,'05月业务提成'!B6,'4月续保推荐事故'!L:L) -> 0 | BF6: =BB6*BD6 -> 0 | BG6: =(E6+I6+M6+P6+V6+Z6+AM6+AQ6+AW6+AX6+AY6+BF6+AV6+AZ6+BA6) -> 0 | BJ6: =BG6+BH6+BI6 -> 0 | BN6: =SUMIF('05月业务提成'!C:C,'05月业务提成'!B6,'05月业务提成'!O:O)+SUMIF('05基本'!C:C,'05月业务提成'!B6,'05基本'!N:N) -> 0 | BO6: =BJ6-BK6+BL6+BM6 -> 0 | BP6: =SUMIF('05月提成-武侯售后'!C:C,'05月业务提成'!B6,'05月提成-武侯售后'!K:K) -> 0 | BQ6: =BP6-BO6 -> 0
B7: 舒童强 | C7: =INDEX('2026-5任务'!C:C,MATCH(B7,'2026-5任务'!A:A,0))+INDEX('2026-5任务'!D:D,MATCH(B7,'2026-5任务'!A:A,0))+INDEX('2026-5任务'!G:G,MATCH(B7,'2026-5任务'!A:A,0))+INDEX('2026-5任务'!E:E,MATCH(B7,'2026-5任务'!A:A,0)) -> 288 | D7: 4 | E7: =C7*D7 -> 1152 | F7: =INDEX('2026-5任务'!X:X,MATCH(B7,'2026-5任务'!A:A,0))-J7 -> 64872.61 | G7: =INDEX('2026-5任务'!W:W,MATCH(B7,'2026-5任务'!A:A,0)) -> 1.2240115 | H7: 0.02 | I7: =F7*H7*0.95 -> 1232.5796 | J7: =INDEX('2026-5任务'!R:R,MATCH(B7,'2026-5任务'!A:A,0))+INDEX('2026-5任务'!U:U,MATCH(B7,'2026-5任务'!A:A,0)) -> 0 | L7: 0.016 | M7: =J7*L7*0.95 -> 0 | N7: =INDEX('2026-5任务'!AN:AN,MATCH(B7,'2026-5任务'!A:A,0))+INDEX('2026-5任务'!AO:AO,MATCH(B7,'2026-5任务'!A:A,0)) -> 137639.85 | O7: 0.005 | P7: =(N7*O7)*0.95 -> 653.78929 | Q7: =INDEX('2026-5任务'!Z:Z,MATCH(B7,'2026-5任务'!A:A,0))+INDEX('2026-5任务'!AA:AA,MATCH(B7,'2026-5任务'!A:A,0)) -> 18046 | R7: =INDEX('2026-5任务'!AB:AB,MATCH(B7,'2026-5任务'!A:A,0)) -> 0.76791489 | S7: 0.06 | T7: =INDEX('2026-5任务'!AA:AA,MATCH(B7,'2026-5任务'!A:A,0)) -> 0 | U7: 0.1 | V7: =(Q7*S7)*0.95+T7*U7 -> 1028.622 | W7: =INDEX('2026-5任务'!AD:AD,MATCH(B7,'2026-5任务'!A:A,0)) -> 9421.89 | X7: =INDEX('2026-5任务'!AF:AF,MATCH(B7,'2026-5任务'!A:A,0)) -> 0.67554944 | Y7: 0.08 | Z7: =(W7*Y7)*0.95 -> 716.06364 | AA7: =INDEX('2026-5任务'!AJ:AJ,MATCH(B7,'2026-5任务'!A:A,0)) -> 12938 | AB7: =INDEX('2026-5任务'!AK:AK,MATCH(B7,'2026-5任务'!A:A,0)) -> 0.99523077 | AC7: 0.1 | AD7: =(AA7*AC7)*0.95 -> 1229.11 | AE7: =INDEX('2026-5任务'!AV:AV,MATCH($B7,'2026-5任务'!A:A,0)) -> 2 | AF7: =INDEX('2026-5任务'!AU:AU,MATCH('05月业务提成'!B7,'2026-5任务'!A:A,0)) -> 7 | AG7: =INDEX('2026-5任务'!AR:AR,MATCH('05月业务提成'!B7,'2026-5任务'!A:A,0)) -> 18 | AH7: =INDEX('2026-5任务'!AQ:AQ,MATCH('05月业务提成'!B7,'2026-5任务'!A:A,0)) -> 12 | AI7: =INDEX('2026-5任务'!AW:AW,MATCH(B7,'2026-5任务'!A:A,0)) -> 0.45 | AJ7: 35 | AK7: 25 | AL7: 50 | AM7: =(AE7*AJ7+AF7*AK7)+IF(AG7=AH7,AG7*AL7,IF(AG7>AH7,(AG7*50+(AG7-AH7)*30),IF(AG7<AH7,AG7*AL7-(AH7-AG7)*50))) -> 1325 | AP7: 25 | AQ7: =AN7*AP7 -> 0 | AR7: =INDEX('2026-5任务'!BN:BN,MATCH(B7,'2026-5任务'!A:A,0)) -> 0 | AS7: =INDEX('2026-5任务'!BM:BM,MATCH(B7,'2026-5任务'!A:A,0)) -> 0 | AT7: =INDEX('2026-5任务'!BO:BO,MATCH(B7,'2026-5任务'!A:A,0)) -> 0 | AU7: 20 | AV7: =IF(AT7>=0.8,AS7*AU7,AS7*AU7+AR7*AU7) -> 0 | AW7: =INDEX('2026-5任务'!BA:BA,MATCH(B7,'2026-5任务'!A:A,0)) -> 0 | AY7: =INDEX('2026-5任务'!BG:BG,MATCH(B7,'2026-5任务'!A:A,0)) -> 100 | AZ7: =INDEX('2026-5任务'!BE:BE,MATCH(B7,'2026-5任务'!A:A,0)) -> 50 | BA7: =SUMIF('4月续保推荐事故'!I:I,'05月业务提成'!B7,'4月续保推荐事故'!L:L) -> 0 | BB7: =INDEX('2026-5任务'!BC:BC,MATCH('05月业务提成'!B7,'2026-5任务'!A:A,0)) -> 0 | BD7: 200 | BF7: =BB7*BD7 -> 0 | BG7: =(E7+I7+M7+P7+V7+Z7+AM7+AQ7+AW7+AX7+AY7+BF7+AV7+AZ7+BA7+AD7) -> 7487.1645 | BJ7: =BG7+BH7+BI7 -> 7487.1645 | BK7: =INDEX('05月提成-武侯售后'!I:I,MATCH(B7,'05月提成-武侯售后'!C:C,0)) -> 932 | BL7: =INDEX('05月提成-武侯售后'!J:J,MATCH(B7,'05月提成-武侯售后'!C:C,0)) -> 0 | BN7: =SUMIF('05月业务提成'!C:C,'05月业务提成'!B7,'05月业务提成'!O:O)+SUMIF('05基本'!C:C,'05月业务提成'!B7,'05基本'!N:N) -> 0 | BO7: =BJ7-BK7+BL7+BM7 -> 6555.1645 | BP7: =SUMIF('05月提成-武侯售后'!C:C,'05月业务提成'!B7,'05月提成-武侯售后'!K:K) -> 6555.1645 | BQ7: =BP7-BO7 -> 0 | BR7: =BO7/C7 -> 22.760988 | BS7: =F7/C7 -> 225.25212 | BT7: =F7/C7 -> 225.25212 | BU7: =N7/C7 -> 477.91615 | BV7: =Q7/C7 -> 62.659722 | BW7: =W7/C7 -> 32.714896
B8: 罗义瑕 | C8: =INDEX('2026-5任务'!C:C,MATCH(B8,'2026-5任务'!A:A,0))+INDEX('2026-5任务'!D:D,MATCH(B8,'2026-5任务'!A:A,0))+INDEX('2026-5任务'!G:G,MATCH(B8,'2026-5任务'!A:A,0))+INDEX('2026-5任务'!E:E,MATCH(B8,'2026-5任务'!A:A,0)) -> 159 | D8: 4 | E8: =C8*D8 -> 636 | F8: =INDEX('2026-5任务'!X:X,MATCH(B8,'2026-5任务'!A:A,0))-J8 -> 40928.32 | G8: =INDEX('2026-5任务'!W:W,MATCH(B8,'2026-5任务'!A:A,0)) -> 0.77223245 | H8: 0.02 | I8: =F8*H8*0.95 -> 777.63808 | J8: =INDEX('2026-5任务'!R:R,MATCH(B8,'2026-5任务'!A:A,0))+INDEX('2026-5任务'!U:U,MATCH(B8,'2026-5任务'!A:A,0)) -> 0 | L8: 0.016 | M8: =J8*L8*0.95 -> 0 | N8: =INDEX('2026-5任务'!AN:AN,MATCH(B8,'2026-5任务'!A:A,0))+INDEX('2026-5任务'!AO:AO,MATCH(B8,'2026-5任务'!A:A,0)) -> 81171.97 | O8: 0.005 | P8: =(N8*O8)*0.95 -> 385.56686 | Q8: =INDEX('2026-5任务'!Z:Z,MATCH(B8,'2026-5任务'!A:A,0))+INDEX('2026-5任务'!AA:AA,MATCH(B8,'2026-5任务'!A:A,0)) -> 15196 | R8: =INDEX('2026-5任务'!AB:AB,MATCH(B8,'2026-5任务'!A:A,0)) -> 0.6466383 | S8: 0.06 | T8: =INDEX('2026-5任务'!AA:AA,MATCH(B8,'2026-5任务'!A:A,0)) -> 0 | U8: 0.1 | V8: =(Q8*S8)*0.95+T8*U8 -> 866.172 | W8: =INDEX('2026-5任务'!AD:AD,MATCH(B8,'2026-5任务'!A:A,0)) -> 7058.68 | X8: =INDEX('2026-5任务'!AF:AF,MATCH(B8,'2026-5任务'!A:A,0)) -> 0.40737111 | Y8: 0.08 | Z8: =(W8*Y8)*0.95 -> 536.45968 | AA8: =INDEX('2026-5任务'!AJ:AJ,MATCH(B8,'2026-5任务'!A:A,0)) -> 7956 | AB8: =INDEX('2026-5任务'!AK:AK,MATCH(B8,'2026-5任务'!A:A,0)) -> 0.612 | AC8: 0.1 | AD8: =(AA8*AC8)*0.95 -> 755.82 | AE8: =INDEX('2026-5任务'!AV:AV,MATCH($B8,'2026-5任务'!A:A,0)) -> 0 | AF8: =INDEX('2026-5任务'!AU:AU,MATCH('05月业务提成'!B8,'2026-5任务'!A:A,0)) -> 6 | AG8: =INDEX('2026-5任务'!AR:AR,MATCH('05月业务提成'!B8,'2026-5任务'!A:A,0)) -> 17 | AH8: =INDEX('2026-5任务'!AQ:AQ,MATCH('05月业务提成'!B8,'2026-5任务'!A:A,0)) -> 12 | AI8: =INDEX('2026-5任务'!AW:AW,MATCH(B8,'2026-5任务'!A:A,0)) -> 0.3 | AJ8: 35 | AK8: 25 | AL8: 50 | AM8: =(AE8*AJ8+AF8*AK8)+IF(AG8=AH8,AG8*AL8,IF(AG8>AH8,(AG8*50+(AG8-AH8)*30),IF(AG8<AH8,AG8*AL8-(AH8-AG8)*50))) -> 1150 | AN8: =INDEX('2026-5任务'!BJ:BJ,MATCH(B8,'2026-5任务'!A:A,0)) -> 0 | AP8: 25 | AQ8: =AN8*AP8 -> 0 | AR8: =INDEX('2026-5任务'!BN:BN,MATCH(B8,'2026-5任务'!A:A,0)) -> 0 | AS8: =INDEX('2026-5任务'!BM:BM,MATCH(B8,'2026-5任务'!A:A,0)) -> 0 | AT8: =INDEX('2026-5任务'!BO:BO,MATCH(B8,'2026-5任务'!A:A,0)) -> 0 | AU8: 20 | AV8: =IF(AT8>=0.8,AS8*AU8,AS8*AU8+AR8*AU8) -> 0 | AW8: =INDEX('2026-5任务'!BA:BA,MATCH(B8,'2026-5任务'!A:A,0)) -> 0 | AY8: =INDEX('2026-5任务'!BG:BG,MATCH(B8,'2026-5任务'!A:A,0)) -> 0 | AZ8: =INDEX('2026-5任务'!BE:BE,MATCH(B8,'2026-5任务'!A:A,0)) -> 0 | BA8: =SUMIF('4月续保推荐事故'!I:I,'05月业务提成'!B8,'4月续保推荐事故'!L:L) -> 0 | BB8: =INDEX('2026-5任务'!BC:BC,MATCH('05月业务提成'!B8,'2026-5任务'!A:A,0)) -> 0 | BD8: 200 | BF8: =BB8*BD8 -> 0 | BG8: =(E8+I8+M8+P8+V8+Z8+AM8+AQ8+AW8+AX8+AY8+BF8+AV8+AZ8+BA8+AD8) -> 5107.6566 | BJ8: =BG8+BH8+BI8 -> 5107.6566 | BK8: =INDEX('05月提成-武侯售后'!I:I,MATCH(B8,'05月提成-武侯售后'!C:C,0)) -> 932 | BL8: =INDEX('05月提成-武侯售后'!J:J,MATCH(B8,'05月提成-武侯售后'!C:C,0)) -> 0 | BN8: =SUMIF('05月业务提成'!C:C,'05月业务提成'!B8,'05月业务提成'!O:O)+SUMIF('05基本'!C:C,'05月业务提成'!B8,'05基本'!N:N) -> 0 | BO8: =BJ8-BK8+BL8+BM8 -> 4175.6566 | BP8: =SUMIF('05月提成-武侯售后'!C:C,'05月业务提成'!B8,'05月提成-武侯售后'!K:K) -> 4175.6566 | BQ8: =BP8-BO8 -> 0 | BR8: =BO8/C8 -> 26.261991 | BS8: =F8/C8 -> 257.41082 | BT8: =F8/C8 -> 257.41082 | BU8: =N8/C8 -> 510.51553 | BV8: =Q8/C8 -> 95.572327 | BW8: =W8/C8 -> 44.394214
B9: 刘强 | C9: =INDEX('2026-5任务'!C:C,MATCH(B9,'2026-5任务'!A:A,0))+INDEX('2026-5任务'!D:D,MATCH(B9,'2026-5任务'!A:A,0))+INDEX('2026-5任务'!G:G,MATCH(B9,'2026-5任务'!A:A,0))+INDEX('2026-5任务'!E:E,MATCH(B9,'2026-5任务'!A:A,0)) -> 264 | D9: 4 | E9: =C9*D9 -> 1056 | F9: =INDEX('2026-5任务'!X:X,MATCH(B9,'2026-5任务'!A:A,0))-J9 -> 40106.15 | G9: =INDEX('2026-5任务'!W:W,MATCH(B9,'2026-5任务'!A:A,0)) -> 0.75671981 | H9: 0.02 | I9: =F9*H9*0.95 -> 762.01685 | J9: =INDEX('2026-5任务'!R:R,MATCH(B9,'2026-5任务'!A:A,0))+INDEX('2026-5任务'!U:U,MATCH(B9,'2026-5任务'!A:A,0)) -> 0 | L9: 0.016 | M9: =J9*L9*0.95 -> 0 | N9: =INDEX('2026-5任务'!AN:AN,MATCH(B9,'2026-5任务'!A:A,0))+INDEX('2026-5任务'!AO:AO,MATCH(B9,'2026-5任务'!A:A,0)) -> 147294.14 | O9: 0.005 | P9: =(N9*O9)*0.95 -> 699.64716 | Q9: =INDEX('2026-5任务'!Z:Z,MATCH(B9,'2026-5任务'!A:A,0))+INDEX('2026-5任务'!AA:AA,MATCH(B9,'2026-5任务'!A:A,0)) -> 19368 | R9: =INDEX('2026-5任务'!AB:AB,MATCH(B9,'2026-5任务'!A:A,0)) -> 0.82417021 | S9: 0.06 | U9: 0.1 | V9: =(Q9*S9)*0.95+T9*U9 -> 1103.976 | W9: =INDEX('2026-5任务'!AD:AD,MATCH(B9,'2026-5任务'!A:A,0)) -> 9094.85 | X9: =INDEX('2026-5任务'!AF:AF,MATCH(B9,'2026-5任务'!A:A,0)) -> 0.67154722 | Y9: 0.08 | Z9: =(W9*Y9)*0.95 -> 691.2086 | AA9: =INDEX('2026-5任务'!AJ:AJ,MATCH(B9,'2026-5任务'!A:A,0)) -> 13480 | AB9: =INDEX('2026-5任务'!AK:AK,MATCH(B9,'2026-5任务'!A:A,0)) -> 1.0369231 | AC9: 0.1 | AD9: =(AA9*AC9)*0.95 -> 1280.6 | AE9: =INDEX('2026-5任务'!AV:AV,MATCH($B9,'2026-5任务'!A:A,0)) -> 0 | AF9: =INDEX('2026-5任务'!AU:AU,MATCH('05月业务提成'!B9,'2026-5任务'!A:A,0)) -> 3 | AG9: =INDEX('2026-5任务'!AR:AR,MATCH('05月业务提成'!B9,'2026-5任务'!A:A,0)) -> 30 | AH9: =INDEX('2026-5任务'!AQ:AQ,MATCH('05月业务提成'!B9,'2026-5任务'!A:A,0)) -> 12 | AI9: =INDEX('2026-5任务'!AW:AW,MATCH(B9,'2026-5任务'!A:A,0)) -> 0.15 | AJ9: 35 | AK9: 25 | AL9: 50 | AM9: =(AE9*AJ9+AF9*AK9)+IF(AG9=AH9,AG9*AL9,IF(AG9>AH9,(AG9*50+(AG9-AH9)*30),IF(AG9<AH9,AG9*AL9-(AH9-AG9)*50))) -> 2115 | AP9: 25 | AQ9: =AN9*AP9 -> 0 | AR9: =INDEX('2026-5任务'!BN:BN,MATCH(B9,'2026-5任务'!A:A,0)) -> 0 | AS9: =INDEX('2026-5任务'!BM:BM,MATCH(B9,'2026-5任务'!A:A,0)) -> 0 | AT9: =INDEX('2026-5任务'!BO:BO,MATCH(B9,'2026-5任务'!A:A,0)) -> 0 | AU9: 20 | AV9: =IF(AT9>=0.8,AS9*AU9,AS9*AU9+AR9*AU9) -> 0 | AW9: =INDEX('2026-5任务'!BA:BA,MATCH(B9,'2026-5任务'!A:A,0)) -> 0 | AY9: =INDEX('2026-5任务'!BG:BG,MATCH(B9,'2026-5任务'!A:A,0)) -> 20 | AZ9: =INDEX('2026-5任务'!BE:BE,MATCH(B9,'2026-5任务'!A:A,0)) -> 25 | BA9: =SUMIF('4月续保推荐事故'!I:I,'05月业务提成'!B9,'4月续保推荐事故'!L:L) -> 0 | BB9: =INDEX('2026-5任务'!BC:BC,MATCH('05月业务提成'!B9,'2026-5任务'!A:A,0)) -> 0 | BD9: 200 | BF9: =BB9*BD9 -> 0 | BG9: =(E9+I9+M9+P9+V9+Z9+AM9+AQ9+AW9+AX9+AY9+BF9+AV9+AZ9+BA9+AD9) -> 7753.4486 | BJ9: =BG9+BH9+BI9 -> 7753.4486 | BK9: =INDEX('05月提成-武侯售后'!I:I,MATCH(B9,'05月提成-武侯售后'!C:C,0)) -> 932 | BL9: =INDEX('05月提成-武侯售后'!J:J,MATCH(B9,'05月提成-武侯售后'!C:C,0)) -> 0 | BN9: =SUMIF('05月业务提成'!C:C,'05月业务提成'!B9,'05月业务提成'!O:O)+SUMIF('05基本'!C:C,'05月业务提成'!B9,'05基本'!N:N) -> 0 | BO9: =BJ9-BK9+BL9+BM9 -> 6821.4486 | BP9: =SUMIF('05月提成-武侯售后'!C:C,'05月业务提成'!B9,'05月提成-武侯售后'!K:K) -> 6821.4486 | BQ9: =BP9-BO9 -> 0 | BR9: =BO9/C9 -> 25.838821 | BS9: =F9/C9 -> 151.91723 | BT9: =F9/C9 -> 151.91723 | BU9: =N9/C9 -> 557.93235 | BV9: =Q9/C9 -> 73.363636 | BW9: =W9/C9 -> 34.450189
